Workbook
Name 操火: #REF!
Name 传心: #REF!
Name 活力: #REF!
Name 遥感: #REF!
Name 预言: #REF!
Name 预言: 灵能大全!$C$64:$I$73
Name 次级灵能: 灵能大全!$C$3:$I$50
Name 文研员: 职业数据!$K$2:$K$13
Name 杀手: 职业数据!$M$2:$M$12
Name 牧师: 职业数据!$N$2:$N$12
Name 卫队士兵: 职业数据!$O$2:$O$15
Name 帝国灵能者: 职业数据!$P$2:$P$14
Name 流氓: 职业数据!$Q$2:$Q$12
Name 技术神甫: 职业数据!$R$2:$R$12
Name 法务官: 职业数据!$L$2:$L$12
Name 战斗修女背景包: 职业数据!$R$19:$R$30
Name 牧师背景包: 职业数据!$M$19:$M$37
Name 卫队士兵背景包: 职业数据!$N$19:$N$37
Name 帝国灵能者背景包: 职业数据!$O$19:$O$31
Name 技术神甫背景包: 职业数据!$Q$19:$Q$34
Name 杀手背景包: 职业数据!$L$19:$L$36
Name 法务官背景包: 职业数据!$K$19:$K$37
Name 文研员背景包: 职业数据!$J$19:$J$39
Name 流氓背景包: 职业数据!$P$19:$P$39

Sheet 人物
AC1: =".st"&"格斗"&K10&"射击"&K11&"力量"&K12&"坚韧"&K13&"敏捷"&K14&"智力"&K15&"感知"&K16&"意志"&K17&"交际"&K18&"生命值"&R28&"生命值上限"&P28&"命运点"&M17&"命运点上限"&M12&"威胁"&I42&"恐吓"&I42&"攀爬"&I43&"运动"&I43&B44&I44&"酗酒"&I45&"狂欢"&I45&B46&I46&B47&I47&B48&I48&B49&I49&B50&I50&B51&I51&B52&I52&"搜查"&I53&"搜索"&I53&B54&I54&B55&I55&B56&I56&B57&I57&B58&I58&B59&I59&B60&I60&B61&I61&A65&A68&A70&A72&A75&A78&A80&A82&A87&A89 -> .st格斗0射击0力量0坚韧0敏捷0智力0感知0意志0交际0生命值生命值上限0命运点命运点上限威胁0恐吓0攀爬0运动0游泳0酗酒0狂欢0躲藏0闪避0潜行0估价0逻辑0赌博0警觉0搜查0搜索0察言观色0交易0欺诈0搜集信息0伪装0吸引0扯淡0指挥0 | AD1: 审判庭汇款单（自动计算工资小工具）
B2: 玩家 | H2: 角色 | J2: 填入角色名称 | T2: 资金 | U2: 是否启用月工资 | X2: 否 | Z2: 每月 | AA2: =IFERROR(IF(X2="是",AR3,0),"") -> 0 | AD2: 社会阶级 | AI2: 当前等级 | AK2: 等级提升 | AM2: 当月工资 | AO2: 已发放工资月数 | AR2: 工资总额
B3: 生涯职业 | H3: 生日 | L3: 月 | N3: 日 | P3: 年龄 | U3: 行动经费 | Z3: 已用 | AA3: =SUM(武备!AB4:AB7)+SUM(武备!T4:T7)+SUM(武备!AB10:AB17)+SUM(武备!AB20:AB25)+SUM(武备!AB28:AB32)+SUM(武备!AB35:AB40)+SUM(武备!AB43:AB56)+SUM(武备!I75:I92)+SUM(武备!AJ65:AJ104)+SUM(武备!AO65:AO104)-SUM(武备!AJ22:AJ61)-SUM(武备!AO22:AO61) -> 0 | AI3: =IF(AD3="","",IF(N4>=10000,8,IF(N4>=8000,7,IF(N4>=6000,6,IF(N4>=3000,5,IF(N4>=2000,4,IF(N4>=1000,3,IF(N4>=500,2,IF(N4>=1,1,""))))))))) | AK3: =IF(AD3="","",VLOOKUP(AD3,职业数据!E:G,3,FALSE)) | AM3: =IF(AD3="","",VLOOKUP(AD3,职业数据!E2:G8,2,FALSE)+(AI3-1)*VLOOKUP(AD3,职业数据!E2:G8,3,FALSE)) | AO3: =IF(AD3="","",MAX(0,INT((MIN(N4,15000)-400)/400))) | AR3: {=IF(AD3="","",IF(AO3=0,0,SUMPRODUCT(--((ROW(INDEX(职业数据!E:E,1):INDEX(职业数据!E:E,AO3))*400+400)<=MIN(N4,15000)),VLOOKUP(AD3,职业数据!E2:G8,2,FALSE)+(LOOKUP(ROW(INDEX(职业数据!E:E,1):INDEX(职业数据!E:E,AO3))*400+400,{0,500,1000,2000,3000,6000,8000,10000},{0,1,2,3,4,5,6,7})*VLOOKUP(AD3,职业数据!E2:G8,3,FALSE)))))}
B4: 当前阶级 | H4: 等级 | L4: 经验 | M4: 持有 | P4: 已用 | Q4: =I19+R62+Z65+Z80+R91+AA120 -> 0 | U4: 其他收入 | Z4: 剩下 | AA4: =IFERROR(W4+W3+AR7-AA3,"")
AD5: 起始资金
B6: 状态 | D6: 身高 | G6: 虹膜 | J6: 发色 | M6: 预言 | N6: 投掷 | O6: 预言 | X6: 影响 | AD6: 生涯职业 | AI6: 起始资金骰点 | AR6: 总金额
D7: 体重 | G7: 肤色 | J7: 发型 | O7: =IF(N7="","",VLOOKUP(N7,人物数据!A:C,2,FALSE)) | X7: =IF(N7="","",VLOOKUP(N7,人物数据!A:C,3,FALSE)) | AI7: =IF(AD7="","",VLOOKUP(AD7,职业数据!A:D,2,FALSE)) | AK7: + | AL7: =IF(AD7="","",VLOOKUP(AD7,职业数据!A:D,3,FALSE)) | AM7: =IF(AD7="","",VLOOKUP(AD7,职业数据!A:D,4,FALSE)) | AN7: （ | AO7: 1 | AP7: ） | AQ7: = | AR7: =IF(AD7="","",AI7+AL7*AO7)
AN8: ↑↑↑骰子自己丢
B9: 属性情况 | D9: 基础 | E9: 超然 | F9: 备注 | G9: 加成 | H9: 训练 | I9: 消耗XP | J9: 减值 | K9: 最终 | L9: 加值 | M9: 命 运 点 | N9: 失心 | Q9: 堕落 | T9: 角色头像 | V9: 这里可以有头像
B10: 格斗 WS | E10: 1 | K10: =D10+G10+H10-J10 -> 0 | L10: =INT(K10/10)*E10 -> 0 | S10: 80 | AD10: 颅骨记账（不并入自动化，可用可不用）
B11: 射击 BS | E11: 1 | K11: =D11+G11+H11-J11 -> 0 | L11: =INT(K11/10)*E11 -> 0 | S11: 81 | AD11: 购买 | AF11: 花费 | AH11: 备注 | AJ11: 售出 | AL11: 收入 | AN11: 备注 | AP11: 额外收入 | AR11: 备注
B12: 力量 S | E12: 1 | K12: =D12+G12+H12-J12 -> 0 | L12: =INT(K12/10)*E12 -> 0 | S12: 82
B13: 坚韧 T | E13: 1 | K13: =D13+G13+H13-J13 -> 0 | L13: =INT(K13/10)*E13 -> 0 | S13: 83
B14: 敏捷 Ag | E14: 1 | K14: =D14+G14+H14-J14 -> 0 | L14: =INT(K14/10)*E14 -> 0 | M14: 剩 余 | S14: 84
B15: 智力 Int | E15: 1 | K15: =D15+G15+H15-J15 -> 0 | L15: =INT(K15/10)*E15 -> 0 | S15: 85
B16: 感知 Per | E16: 1 | K16: =D16+G16+H16-J16 -> 0 | L16: =INT(K16/10)*E16 -> 0 | S16: 86
B17: 意志 WP | E17: 1 | K17: =D17+G17+H17-J17 -> 0 | L17: =INT(K17/10)*E17 -> 0 | S17: 87
B18: 交际 Fel | E18: 1 | K18: =D18+G18+H18-J18 -> 0 | L18: =INT(K18/10)*E18 -> 0 | S18: 88
I19: =SUM(I10:I18) -> 0 | W19: 角色
B20: 移动 | D20: 部分 | F20: 完整 | H20: 冲锋 | J20: 奔跑 | L20: 每分钟 | N20: 每小时 | P20: 每天 | R20: 备注 | T20: 致命伤情况
B21: 徒步 | D21: =L14 -> 0 | F21: =D21*2 -> 0 | H21: =D21*3 -> 0 | J21: =D21*6 -> 0 | L21: =VLOOKUP(L14,人物数据!I2:P12,6,FALSE) -> 12m | N21: =VLOOKUP(L14,人物数据!I2:P12,7,FALSE) -> 0.75km | P21: =VLOOKUP(L14,人物数据!I2:P12,8,FALSE) -> 7km | R21: — | T21: 头部 0-1 | Y21: 躯干 31-70
B22: 飞跑 | D22: —— | F22: —— | H22: —— | J22: =J21*2 -> 0 | L22: —— | N22: —— | P22: —— | R22: — | T22: 右手 11-20 | Y22: 左手 21-30
T23: 左腿 86-00 | Y23: 左腿 71-85
B24: 先攻 | D24: 基础 | F24: 谨小慎微 | H24: 闪电反射 | J24: 巢都出身 | L24: 其他 | N24: 最终 | T24: 其他 | Y24: 其他
D25: =L14 -> 0 | F25: 否 | H25: 否 | J25: 否 | L25: 暂无 | N25: ="1D10+"&(IF(H25="是",D25*2,D25)+IF(F25="是",2,0)+IF(J25="是",1,0)) -> 1D10+0
T26: 负重（单位：kg）
B27: 承伤和防护情况（简） | T27: 负重上限 | V27: =VLOOKUP(V29,人物数据!D2:G22,2,FALSE) -> 0.9 | X27: 当前负重 | Z27: =SUM(武备!S4:S7)+SUM(武备!Z11:Z17)+SUM(武备!AA20:AA25)+SUM(武备!AA28:AA32)+SUM(武备!AA35:AA40)+SUM(武备!AA43:AA56) -> 0
B28: 承伤 | D28: 基础 | F28: 加成 | H28: 备注 | J28: 减值 | L28: 备注 | N28: 最终承伤 | P28: =E28+G28-K28 -> 0 | Q28: 剩余 | T28: 参考值 | V28: SB+TB | X28: 举起 | Z28: 拖拽
B29: 装备数值 | D29: 头部 0-1 | F29: 右臂 11-20 | H29: 左臂 21-30 | J29: 躯干 31-70 | L29: 右腿 71-85 | N29: 左腿 86-00 | P29: 血肉苦弱 | R29: 0 | V29: =L12+L13 -> 0 | X29: =VLOOKUP(V29,人物数据!D2:G22,3,FALSE) -> 2.25 | Z29: =VLOOKUP(V29,人物数据!D2:G22,4,FALSE) -> 4.5
B30: 额外护甲 | P30: 特殊护甲 | R30: 无
B31: 额外坚韧 | P31: 坚韧加值 | R31: =L13 -> 0 | T31: 武器训练
B32: 最终数值 | E32: =+E29+E30+E31+R31 -> 0 | G32: =+G29+G30+G31+R31 -> 0 | I32: =+I29+I30+I31+R31 -> 0 | K32: =+K29+K30+K31+R31 -> 0 | M32: =+M29+M30+M31+R31 -> 0 | O32: =+O29+O30+O31+R31 -> 0 | T32: 基础 | V32: 例如：基本武器训练（原始）
T33: 格斗
B34: 防护立场（简） | T34: 手枪
B35: 名称 | E35: 防护类型 | G35: 减伤数值 | I35: 完全失效 | L35: 过载 | O35: 持续时间/充能 | T35: 重型
T36: 异种/特种 | AF36: =SUM(AF12:AG35) -> 0 | AL36: =SUM(AL12:AM35) -> 0 | AP36: =SUM(AP12:AQ35) -> 0
T37: 其他
AD38: 最好使用excel或wps打开本卡
T39: 影响力天赋
B40: 基础技能 | T40: 平等待遇 | V40: 例如：平等待遇（国教） | AD40: 使用ALT+ENTER换行
B41: 名称 | D41: 属性 | E41: 受训 | F41: +10 | G41: +20 | H41: 天赋 | I41: 数值 | J41: 其他加成情况 | R41: 花费
B42: 威胁/恐吓 | D42: S | I42: =IF(E42<>"",K12,ROUNDUP(K12/2,0))+IF(F42<>"",10,0)+IF(G42<>"",10,0)+IF(H42<>"",10,0) -> 0 | R42: =E42+F42+G42+H42 -> 0 | T42: 有口皆碑 | AD42: 快速录入请见数据导入
B43: 攀爬/运动 | D43: S | I43: =IF(E43<>"",K12,ROUNDUP(K12/2,0))+IF(F43<>"",10,0)+IF(G43<>"",10,0)+IF(H43<>"",10,0) -> 0 | R43: =E43+F43+G43+H43 -> 0
B44: 游泳 | D44: S | I44: =IF(E44<>"",K12,ROUNDUP(K12/2,0))+IF(F44<>"",10,0)+IF(G44<>"",10,0)+IF(H44<>"",10,0) -> 0 | R44: =E44+F44+G44+H44 -> 0 | T44: 对手
B45: 酗酒/狂欢 | D45: T | I45: =IF(E45<>"",K13,ROUNDUP(K13/2,0))+IF(F45<>"",10,0)+IF(G45<>"",10,0)+IF(H45<>"",10,0) -> 0 | R45: =E45+F45+G45+H45 -> 0 | AD45: 经验开销计算(需手动填写)
B46: 躲藏 | D46: AG | I46: =IF(E46<>"",K14,ROUNDUP(K14/2,0))+IF(F46<>"",10,0)+IF(G46<>"",10,0)+IF(H46<>"",10,0) -> 0 | R46: =E46+F46+G46+H46 -> 0 | T46: 不共戴天 | AD46: 等级 | AE46: 1 | AG46: 2 | AI46: 3 | AK46: 4 | AM46: 5 | AO46: 6 | AQ46: 7 | AS46: 8 | AU46: 扬升
B47: 闪避 | D47: AG | I47: =IF(E47<>"",K14,ROUNDUP(K14/2,0))+IF(F47<>"",10,0)+IF(G47<>"",10,0)+IF(H47<>"",10,0) -> 0 | R47: =E47+F47+G47+H47 -> 0 | AD47: 总计 | AE47: =SUM(AE48:AF50) -> 0 | AF47: /499 | AG47: =SUM(AG48:AH50) -> 0 | AH47: /999 | AI47: =SUM(AI48:AJ50) -> 0 | AJ47: /1999 | AK47: =SUM(AK48:AL50) -> 0 | AL47: /2999 | AM47: =SUM(AM48:AN50) -> 0 | AN47: /5999 | AO47: =SUM(AO48:AP50) -> 0 | AP47: /7999 | AQ47: =SUM(AQ48:AR50) -> 0 | AR47: /9999 | AS47: =SUM(AS48:AT50) -> 0 | AT47: /14999 | AU47: =SUM(AU48:AV50) -> 0
B48: 潜行 | D48: AG | I48: =IF(E48<>"",K14,ROUNDUP(K14/2,0))+IF(F48<>"",10,0)+IF(G48<>"",10,0)+IF(H48<>"",10,0) -> 0 | R48: =E48+F48+G48+H48 -> 0 | AD48: 属性
B49: 估价 | D49: INT | I49: =IF(E49<>"",K15,ROUNDUP(K15/2,0))+IF(F49<>"",10,0)+IF(G49<>"",10,0)+IF(H49<>"",10,0) -> 0 | R49: =E49+F49+G49+H49 -> 0 | T49: 起源 | X49: 母星 | AD49: 技能
B50: 逻辑 | D50: INT | I50: =IF(E50<>"",K15,ROUNDUP(K15/2,0))+IF(F50<>"",10,0)+IF(G50<>"",10,0)+IF(H50<>"",10,0) -> 0 | R50: =E50+F50+G50+H50 -> 0 | AD50: 天赋
B51: 赌博 | D51: INT | I51: =IF(E51<>"",K15,ROUNDUP(K15/2,0))+IF(F51<>"",10,0)+IF(G51<>"",10,0)+IF(H51<>"",10,0) -> 0 | R51: =E51+F51+G51+H51 -> 0 | T51: 此处填入出身世界描述。
B52: 警觉 | D52: PER | I52: =IF(E52<>"",K16,ROUNDUP(K16/2,0))+IF(F52<>"",10,0)+IF(G52<>"",10,0)+IF(H52<>"",10,0) -> 0 | R52: =E52+F52+G52+H52 -> 0
B53: 搜查/搜索 | D53: PER | I53: =IF(E53<>"",K16,ROUNDUP(K16/2,0))+IF(F53<>"",10,0)+IF(G53<>"",10,0)+IF(H53<>"",10,0) -> 0 | R53: =E53+F53+G53+H53 -> 0
B54: 察言观色 | D54: PER | I54: =IF(E54<>"",K16,ROUNDUP(K16/2,0))+IF(F54<>"",10,0)+IF(G54<>"",10,0)+IF(H54<>"",10,0) -> 0 | R54: =E54+F54+G54+H54 -> 0
B55: 交易 | D55: FEL | I55: =IF(E55<>"",K18,ROUNDUP(K18/2,0))+IF(F55<>"",10,0)+IF(G55<>"",10,0)+IF(H55<>"",10,0) -> 0 | R55: =E55+F55+G55+H55 -> 0
B56: 欺诈 | D56: FEL | I56: =IF(E56<>"",K18,ROUNDUP(K18/2,0))+IF(F56<>"",10,0)+IF(G56<>"",10,0)+IF(H56<>"",10,0) -> 0 | R56: =E56+F56+G56+H56 -> 0
B57: 搜集信息 | D57: FEL | I57: =IF(E57<>"",K18,ROUNDUP(K18/2,0))+IF(F57<>"",10,0)+IF(G57<>"",10,0)+IF(H57<>"",10,0) -> 0 | R57: =E57+F57+G57+H57 -> 0
B58: 伪装 | D58: FEL | I58: =IF(E58<>"",K18,ROUNDUP(K18/2,0))+IF(F58<>"",10,0)+IF(G58<>"",10,0)+IF(H58<>"",10,0) -> 0 | R58: =E58+F58+G58+H58 -> 0
B59: 吸引 | D59: FEL | I59: =IF(E59<>"",K18,ROUNDUP(K18/2,0))+IF(F59<>"",10,0)+IF(G59<>"",10,0)+IF(H59<>"",10,0) -> 0 | R59: =E59+F59+G59+H59 -> 0
B60: 扯淡 | D60: FEL | I60: =IF(E60<>"",K18,ROUNDUP(K18/2,0))+IF(F60<>"",10,0)+IF(G60<>"",10,0)+IF(H60<>"",10,0) -> 0 | R60: =E60+F60+G60+H60 -> 0
B61: 指挥 | D61: FEL | I61: =IF(E61<>"",K18,ROUNDUP(K18/2,0))+IF(F61<>"",10,0)+IF(G61<>"",10,0)+IF(H61<>"",10,0) -> 0 | R61: =E61+F61+G61+H61 -> 0
R62: =SUM(R42:R61) -> 0
B63: 高级技能 | T63: 详细情况
B64: 名称 | F64: 属性 | G64: 受训 | H64: +10 | I64: +20 | J64: 天赋 | K64: 数值 | L64: 其他加成情况 | R64: 花费 | T64: 背景包
A65: {=IFERROR(_xlfn.TEXTJOIN("",TRUE,_xlfn._xlws.FILTER("听说语言_"&C65:C67&ROUNDUP(K65:K67,0),C65:C67<>"")),"")} | B65: 听说语言 | K65: {=IF(F65="S",IF(G65<>"",$K$12,$K$12/2),)+IF(F65="T",IF(G65<>"",$K$13,$K$13/2),)+IF(F65="Ag",IF(G65<>"",$K$14,$K$14/2),)+IF(F65="Int",IF(G65<>"",$K$15,_xlfn.ANCHORARRAY($K$15)/2),)+IF(F65="Per",IF(G65<>"",$K$16,$K$16/2),)+IF(F65="WP",IF(G65<>"",$K$17,_xlfn.ANCHORARRAY($K$17)/2),)+IF(F65="Fel",IF(G65<>"",$K$18,$K$18/2),)+IF(H65<>"",10,0)+IF(I65<>"",10,0)+IF(J65<>"",10,0)} -> 0 | R65: =G65+H65+I65+J65 -> 0 | Y65: 花费
F66: - | K66: {=IF(F66="S",IF(G66<>"",$K$12,$K$12/2),)+IF(F66="T",IF(G66<>"",$K$13,$K$13/2),)+IF(F66="Ag",IF(G66<>"",$K$14,$K$14/2),)+IF(F66="Int",IF(G66<>"",$K$15,_xlfn.ANCHORARRAY($K$15)/2),)+IF(F66="Per",IF(G66<>"",$K$16,$K$16/2),)+IF(F66="WP",IF(G66<>"",$K$17,_xlfn.ANCHORARRAY($K$17)/2),)+IF(F66="Fel",IF(G66<>"",$K$18,$K$18/2),)+IF(H66<>"",10,0)+IF(I66<>"",10,0)+IF(J66<>"",10,0)} -> 0 | R66: =G66+H66+I66+J66 -> 0 | T66: 此处填入背景包详情。
F67: - | K67: {=IF(F67="S",IF(G67<>"",$K$12,$K$12/2),)+IF(F67="T",IF(G67<>"",$K$13,$K$13/2),)+IF(F67="Ag",IF(G67<>"",$K$14,$K$14/2),)+IF(F67="Int",IF(G67<>"",$K$15,_xlfn.ANCHORARRAY($K$15)/2),)+IF(F67="Per",IF(G67<>"",$K$16,$K$16/2),)+IF(F67="WP",IF(G67<>"",$K$17,_xlfn.ANCHORARRAY($K$17)/2),)+IF(F67="Fel",IF(G67<>"",$K$18,$K$18/2),)+IF(H67<>"",10,0)+IF(I67<>"",10,0)+IF(J67<>"",10,0)} -> 0 | R67: =G67+H67+I67+J67 -> 0
A68: {=IFERROR(_xlfn.TEXTJOIN("",TRUE,_xlfn._xlws.FILTER("密语_"&C68:C69&ROUNDUP(K68:K69,0),C68:C69<>"")),"")} | B68: 密语 | F68: - | K68: {=IF(F68="S",IF(G68<>"",$K$12,$K$12/2),)+IF(F68="T",IF(G68<>"",$K$13,$K$13/2),)+IF(F68="Ag",IF(G68<>"",$K$14,$K$14/2),)+IF(F68="Int",IF(G68<>"",$K$15,_xlfn.ANCHORARRAY($K$15)/2),)+IF(F68="Per",IF(G68<>"",$K$16,$K$16/2),)+IF(F68="WP",IF(G68<>"",$K$17,_xlfn.ANCHORARRAY($K$17)/2),)+IF(F68="Fel",IF(G68<>"",$K$18,$K$18/2),)+IF(H68<>"",10,0)+IF(I68<>"",10,0)+IF(J68<>"",10,0)} -> 0 | R68: =G68+H68+I68+J68 -> 0
F69: - | K69: {=IF(F69="S",IF(G69<>"",$K$12,$K$12/2),)+IF(F69="T",IF(G69<>"",$K$13,$K$13/2),)+IF(F69="Ag",IF(G69<>"",$K$14,$K$14/2),)+IF(F69="Int",IF(G69<>"",$K$15,_xlfn.ANCHORARRAY($K$15)/2),)+IF(F69="Per",IF(G69<>"",$K$16,$K$16/2),)+IF(F69="WP",IF(G69<>"",$K$17,_xlfn.ANCHORARRAY($K$17)/2),)+IF(F69="Fel",IF(G69<>"",$K$18,$K$18/2),)+IF(H69<>"",10,0)+IF(I69<>"",10,0)+IF(J69<>"",10,0)} -> 0 | R69: =G69+H69+I69+J69 -> 0
A70: {=IFERROR(_xlfn.TEXTJOIN("",TRUE,_xlfn._xlws.FILTER("暗号_"&C70:C71&ROUNDUP(K70:K71,0),C70:C71<>"")),"")} | B70: 暗号 | F70: - | K70: {=IF(F70="S",IF(G70<>"",$K$12,$K$12/2),)+IF(F70="T",IF(G70<>"",$K$13,$K$13/2),)+IF(F70="Ag",IF(G70<>"",$K$14,$K$14/2),)+IF(F70="Int",IF(G70<>"",$K$15,_xlfn.ANCHORARRAY($K$15)/2),)+IF(F70="Per",IF(G70<>"",$K$16,$K$16/2),)+IF(F70="WP",IF(G70<>"",$K$17,_xlfn.ANCHORARRAY($K$17)/2),)+IF(F70="Fel",IF(G70<>"",$K$18,$K$18/2),)+IF(H70<>"",10,0)+IF(I70<>"",10,0)+IF(J70<>"",10,0)} -> 0 | R70: =G70+H70+I70+J70 -> 0
F71: - | K71: {=IF(F71="S",IF(G71<>"",$K$12,$K$12/2),)+IF(F71="T",IF(G71<>"",$K$13,$K$13/2),)+IF(F71="Ag",IF(G71<>"",$K$14,$K$14/2),)+IF(F71="Int",IF(G71<>"",$K$15,_xlfn.ANCHORARRAY($K$15)/2),)+IF(F71="Per",IF(G71<>"",$K$16,$K$16/2),)+IF(F71="WP",IF(G71<>"",$K$17,_xlfn.ANCHORARRAY($K$17)/2),)+IF(F71="Fel",IF(G71<>"",$K$18,$K$18/2),)+IF(H71<>"",10,0)+IF(I71<>"",10,0)+IF(J71<>"",10,0)} -> 0 | R71: =G71+H71+I71+J71 -> 0
A72: {=IFERROR(_xlfn.TEXTJOIN("",TRUE,_xlfn._xlws.FILTER("常识_"&C72:C74&ROUNDUP(K72:K74,0),C72:C74<>"")),"")} | B72: 常识 | F72: - | K72: {=IF(F72="S",IF(G72<>"",$K$12,$K$12/2),)+IF(F72="T",IF(G72<>"",$K$13,$K$13/2),)+IF(F72="Ag",IF(G72<>"",$K$14,$K$14/2),)+IF(F72="Int",IF(G72<>"",$K$15,_xlfn.ANCHORARRAY($K$15)/2),)+IF(F72="Per",IF(G72<>"",$K$16,$K$16/2),)+IF(F72="WP",IF(G72<>"",$K$17,_xlfn.ANCHORARRAY($K$17)/2),)+IF(F72="Fel",IF(G72<>"",$K$18,$K$18/2),)+IF(H72<>"",10,0)+IF(I72<>"",10,0)+IF(J72<>"",10,0)} -> 0 | R72: =G72+H72+I72+J72 -> 0
F73: - | K73: {=IF(F73="S",IF(G73<>"",$K$12,$K$12/2),)+IF(F73="T",IF(G73<>"",$K$13,$K$13/2),)+IF(F73="Ag",IF(G73<>"",$K$14,$K$14/2),)+IF(F73="Int",IF(G73<>"",$K$15,_xlfn.ANCHORARRAY($K$15)/2),)+IF(F73="Per",IF(G73<>"",$K$16,$K$16/2),)+IF(F73="WP",IF(G73<>"",$K$17,_xlfn.ANCHORARRAY($K$17)/2),)+IF(F73="Fel",IF(G73<>"",$K$18,$K$18/2),)+IF(H73<>"",10,0)+IF(I73<>"",10,0)+IF(J73<>"",10,0)} -> 0 | R73: =G73+H73+I73+J73 -> 0
F74: - | K74: {=IF(F74="S",IF(G74<>"",$K$12,$K$12/2),)+IF(F74="T",IF(G74<>"",$K$13,$K$13/2),)+IF(F74="Ag",IF(G74<>"",$K$14,$K$14/2),)+IF(F74="Int",IF(G74<>"",$K$15,_xlfn.ANCHORARRAY($K$15)/2),)+IF(F74="Per",IF(G74<>"",$K$16,$K$16/2),)+IF(F74="WP",IF(G74<>"",$K$17,_xlfn.ANCHORARRAY($K$17)/2),)+IF(F74="Fel",IF(G74<>"",$K$18,$K$18/2),)+IF(H74<>"",10,0)+IF(I74<>"",10,0)+IF(J74<>"",10,0)} -> 0 | R74: =G74+H74+I74+J74 -> 0
A75: {=IFERROR(_xlfn.TEXTJOIN("",TRUE,_xlfn._xlws.FILTER("学术知识_"&C75:C77&ROUNDUP(K75:K77,0),C75:C77<>"")),"")} | B75: 学术知识 | F75: - | K75: {=IF(F75="S",IF(G75<>"",$K$12,$K$12/2),)+IF(F75="T",IF(G75<>"",$K$13,$K$13/2),)+IF(F75="Ag",IF(G75<>"",$K$14,$K$14/2),)+IF(F75="Int",IF(G75<>"",$K$15,_xlfn.ANCHORARRAY($K$15)/2),)+IF(F75="Per",IF(G75<>"",$K$16,$K$16/2),)+IF(F75="WP",IF(G75<>"",$K$17,_xlfn.ANCHORARRAY($K$17)/2),)+IF(F75="Fel",IF(G75<>"",$K$18,$K$18/2),)+IF(H75<>"",10,0)+IF(I75<>"",10,0)+IF(J75<>"",10,0)} -> 0 | R75: =G75+H75+I75+J75 -> 0
F76: - | K76: {=IF(F76="S",IF(G76<>"",$K$12,$K$12/2),)+IF(F76="T",IF(G76<>"",$K$13,$K$13/2),)+IF(F76="Ag",IF(G76<>"",$K$14,$K$14/2),)+IF(F76="Int",IF(G76<>"",$K$15,_xlfn.ANCHORARRAY($K$15)/2),)+IF(F76="Per",IF(G76<>"",$K$16,$K$16/2),)+IF(F76="WP",IF(G76<>"",$K$17,_xlfn.ANCHORARRAY($K$17)/2),)+IF(F76="Fel",IF(G76<>"",$K$18,$K$18/2),)+IF(H76<>"",10,0)+IF(I76<>"",10,0)+IF(J76<>"",10,0)} -> 0 | R76: =G76+H76+I76+J76 -> 0
F77: - | K77: {=IF(F77="S",IF(G77<>"",$K$12,$K$12/2),)+IF(F77="T",IF(G77<>"",$K$13,$K$13/2),)+IF(F77="Ag",IF(G77<>"",$K$14,$K$14/2),)+IF(F77="Int",IF(G77<>"",$K$15,_xlfn.ANCHORARRAY($K$15)/2),)+IF(F77="Per",IF(G77<>"",$K$16,$K$16/2),)+IF(F77="WP",IF(G77<>"",$K$17,_xlfn.ANCHORARRAY($K$17)/2),)+IF(F77="Fel",IF(G77<>"",$K$18,$K$18/2),)+IF(H77<>"",10,0)+IF(I77<>"",10,0)+IF(J77<>"",10,0)} -> 0 | R77: =G77+H77+I77+J77 -> 0
A78: {=IFERROR(_xlfn.TEXTJOIN("",TRUE,_xlfn._xlws.FILTER("禁忌知识_"&C78:C79&ROUNDUP(K78:K79,0),C78:C79<>"")),"")} | B78: 禁忌知识 | F78: - | K78: {=IF(F78="S",IF(G78<>"",$K$12,$K$12/2),)+IF(F78="T",IF(G78<>"",$K$13,$K$13/2),)+IF(F78="Ag",IF(G78<>"",$K$14,$K$14/2),)+IF(F78="Int",IF(G78<>"",$K$15,_xlfn.ANCHORARRAY($K$15)/2),)+IF(F78="Per",IF(G78<>"",$K$16,$K$16/2),)+IF(F78="WP",IF(G78<>"",$K$17,_xlfn.ANCHORARRAY($K$17)/2),)+IF(F78="Fel",IF(G78<>"",$K$18,$K$18/2),)+IF(H78<>"",10,0)+IF(I78<>"",10,0)+IF(J78<>"",10,0)} -> 0 | R78: =G78+H78+I78+J78 -> 0 | Y78: 花费
F79: - | K79: {=IF(F79="S",IF(G79<>"",$K$12,$K$12/2),)+IF(F79="T",IF(G79<>"",$K$13,$K$13/2),)+IF(F79="Ag",IF(G79<>"",$K$14,$K$14/2),)+IF(F79="Int",IF(G79<>"",$K$15,_xlfn.ANCHORARRAY($K$15)/2),)+IF(F79="Per",IF(G79<>"",$K$16,$K$16/2),)+IF(F79="WP",IF(G79<>"",$K$17,_xlfn.ANCHORARRAY($K$17)/2),)+IF(F79="Fel",IF(G79<>"",$K$18,$K$18/2),)+IF(H79<>"",10,0)+IF(I79<>"",10,0)+IF(J79<>"",10,0)} -> 0 | R79: =G79+H79+I79+J79 -> 0
A80: {=IFERROR(_xlfn.TEXTJOIN("",TRUE,_xlfn._xlws.FILTER("生计_"&C80:C81&ROUNDUP(K80:K81,0),C80:C81<>"")),"")} | B80: 生计 | F80: - | K80: {=IF(F80="S",IF(G80<>"",$K$12,$K$12/2),)+IF(F80="T",IF(G80<>"",$K$13,$K$13/2),)+IF(F80="Ag",IF(G80<>"",$K$14,$K$14/2),)+IF(F80="Int",IF(G80<>"",$K$15,_xlfn.ANCHORARRAY($K$15)/2),)+IF(F80="Per",IF(G80<>"",$K$16,$K$16/2),)+IF(F80="WP",IF(G80<>"",$K$17,_xlfn.ANCHORARRAY($K$17)/2),)+IF(F80="Fel",IF(G80<>"",$K$18,$K$18/2),)+IF(H80<>"",10,0)+IF(I80<>"",10,0)+IF(J80<>"",10,0)} -> 0 | R80: =G80+H80+I80+J80 -> 0
F81: - | K81: {=IF(F81="S",IF(G81<>"",$K$12,$K$12/2),)+IF(F81="T",IF(G81<>"",$K$13,$K$13/2),)+IF(F81="Ag",IF(G81<>"",$K$14,$K$14/2),)+IF(F81="Int",IF(G81<>"",$K$15,_xlfn.ANCHORARRAY($K$15)/2),)+IF(F81="Per",IF(G81<>"",$K$16,$K$16/2),)+IF(F81="WP",IF(G81<>"",$K$17,_xlfn.ANCHORARRAY($K$17)/2),)+IF(F81="Fel",IF(G81<>"",$K$18,$K$18/2),)+IF(H81<>"",10,0)+IF(I81<>"",10,0)+IF(J81<>"",10,0)} -> 0 | R81: =G81+H81+I81+J81 -> 0
A82: {=IFERROR(_xlfn.TEXTJOIN("",TRUE,_xlfn._xlws.FILTER(B82:B86&ROUNDUP(K82:K86,0),B82:B86<>"")),"")} | F82: - | K82: {=IF(F82="S",IF(G82<>"",$K$12,$K$12/2),)+IF(F82="T",IF(G82<>"",$K$13,$K$13/2),)+IF(F82="Ag",IF(G82<>"",$K$14,$K$14/2),)+IF(F82="Int",IF(G82<>"",$K$15,_xlfn.ANCHORARRAY($K$15)/2),)+IF(F82="Per",IF(G82<>"",$K$16,$K$16/2),)+IF(F82="WP",IF(G82<>"",$K$17,_xlfn.ANCHORARRAY($K$17)/2),)+IF(F82="Fel",IF(G82<>"",$K$18,$K$18/2),)+IF(H82<>"",10,0)+IF(I82<>"",10,0)+IF(J82<>"",10,0)} -> 0 | R82: =G82+H82+I82+J82 -> 0
F83: - | K83: {=IF(F83="S",IF(G83<>"",$K$12,$K$12/2),)+IF(F83="T",IF(G83<>"",$K$13,$K$13/2),)+IF(F83="Ag",IF(G83<>"",$K$14,$K$14/2),)+IF(F83="Int",IF(G83<>"",$K$15,_xlfn.ANCHORARRAY($K$15)/2),)+IF(F83="Per",IF(G83<>"",$K$16,$K$16/2),)+IF(F83="WP",IF(G83<>"",$K$17,_xlfn.ANCHORARRAY($K$17)/2),)+IF(F83="Fel",IF(G83<>"",$K$18,$K$18/2),)+IF(H83<>"",10,0)+IF(I83<>"",10,0)+IF(J83<>"",10,0)} -> 0 | R83: =G83+H83+I83+J83 -> 0
F84: - | K84: {=IF(F84="S",IF(G84<>"",$K$12,$K$12/2),)+IF(F84="T",IF(G84<>"",$K$13,$K$13/2),)+IF(F84="Ag",IF(G84<>"",$K$14,$K$14/2),)+IF(F84="Int",IF(G84<>"",$K$15,_xlfn.ANCHORARRAY($K$15)/2),)+IF(F84="Per",IF(G84<>"",$K$16,$K$16/2),)+IF(F84="WP",IF(G84<>"",$K$17,_xlfn.ANCHORARRAY($K$17)/2),)+IF(F84="Fel",IF(G84<>"",$K$18,$K$18/2),)+IF(H84<>"",10,0)+IF(I84<>"",10,0)+IF(J84<>"",10,0)} -> 0 | R84: =G84+H84+I84+J84 -> 0
F85: - | K85: {=IF(F85="S",IF(G85<>"",$K$12,$K$12/2),)+IF(F85="T",IF(G85<>"",$K$13,$K$13/2),)+IF(F85="Ag",IF(G85<>"",$K$14,$K$14/2),)+IF(F85="Int",IF(G85<>"",$K$15,_xlfn.ANCHORARRAY($K$15)/2),)+IF(F85="Per",IF(G85<>"",$K$16,$K$16/2),)+IF(F85="WP",IF(G85<>"",$K$17,_xlfn.ANCHORARRAY($K$17)/2),)+IF(F85="Fel",IF(G85<>"",$K$18,$K$18/2),)+IF(H85<>"",10,0)+IF(I85<>"",10,0)+IF(J85<>"",10,0)} -> 0 | R85: =G85+H85+I85+J85 -> 0
K86: {=IF(F86="S",IF(G86<>"",$K$12,$K$12/2),)+IF(F86="T",IF(G86<>"",$K$13,$K$13/2),)+IF(F86="Ag",IF(G86<>"",$K$14,$K$14/2),)+IF(F86="Int",IF(G86<>"",$K$15,_xlfn.ANCHORARRAY($K$15)/2),)+IF(F86="Per",IF(G86<>"",$K$16,$K$16/2),)+IF(F86="WP",IF(G86<>"",$K$17,_xlfn.ANCHORARRAY($K$17)/2),)+IF(F86="Fel",IF(G86<>"",$K$18,$K$18/2),)+IF(H86<>"",10,0)+IF(I86<>"",10,0)+IF(J86<>"",10,0)} -> 0 | R86: =G86+H86+I86+J86 -> 0
A87: {=IFERROR(_xlfn.TEXTJOIN("",TRUE,_xlfn._xlws.FILTER("导航_"&C87:C88&ROUNDUP(K87:K88,0),C87:C88<>"")),"")} | B87: 导航 | F87: - | K87: {=IF(F87="S",IF(G87<>"",$K$12,$K$12/2),)+IF(F87="T",IF(G87<>"",$K$13,$K$13/2),)+IF(F87="Ag",IF(G87<>"",$K$14,$K$14/2),)+IF(F87="Int",IF(G87<>"",$K$15,_xlfn.ANCHORARRAY($K$15)/2),)+IF(F87="Per",IF(G87<>"",$K$16,$K$16/2),)+IF(F87="WP",IF(G87<>"",$K$17,_xlfn.ANCHORARRAY($K$17)/2),)+IF(F87="Fel",IF(G87<>"",$K$18,$K$18/2),)+IF(H87<>"",10,0)+IF(I87<>"",10,0)+IF(J87<>"",10,0)} -> 0 | R87: =G87+H87+I87+J87 -> 0
F88: - | K88: {=IF(F88="S",IF(G88<>"",$K$12,$K$12/2),)+IF(F88="T",IF(G88<>"",$K$13,$K$13/2),)+IF(F88="Ag",IF(G88<>"",$K$14,$K$14/2),)+IF(F88="Int",IF(G88<>"",$K$15,_xlfn.ANCHORARRAY($K$15)/2),)+IF(F88="Per",IF(G88<>"",$K$16,$K$16/2),)+IF(F88="WP",IF(G88<>"",$K$17,_xlfn.ANCHORARRAY($K$17)/2),)+IF(F88="Fel",IF(G88<>"",$K$18,$K$18/2),)+IF(H88<>"",10,0)+IF(I88<>"",10,0)+IF(J88<>"",10,0)} -> 0 | R88: =G88+H88+I88+J88 -> 0
A89: {=IFERROR(_xlfn.TEXTJOIN("",TRUE,_xlfn._xlws.FILTER("驾驶_"&C89:C90&ROUNDUP(K89:K90,0),C89:C90<>"")),"")} | B89: 驾驶 | F89: - | K89: {=IF(F89="S",IF(G89<>"",$K$12,$K$12/2),)+IF(F89="T",IF(G89<>"",$K$13,$K$13/2),)+IF(F89="Ag",IF(G89<>"",$K$14,$K$14/2),)+IF(F89="Int",IF(G89<>"",$K$15,_xlfn.ANCHORARRAY($K$15)/2),)+IF(F89="Per",IF(G89<>"",$K$16,$K$16/2),)+IF(F89="WP",IF(G89<>"",$K$17,_xlfn.ANCHORARRAY($K$17)/2),)+IF(F89="Fel",IF(G89<>"",$K$18,$K$18/2),)+IF(H89<>"",10,0)+IF(I89<>"",10,0)+IF(J89<>"",10,0)} -> 0 | R89: =G89+H89+I89+J89 -> 0
F90: - | K90: {=IF(F90="S",IF(G90<>"",$K$12,$K$12/2),)+IF(F90="T",IF(G90<>"",$K$13,$K$13/2),)+IF(F90="Ag",IF(G90<>"",$K$14,$K$14/2),)+IF(F90="Int",IF(G90<>"",$K$15,_xlfn.ANCHORARRAY($K$15)/2),)+IF(F90="Per",IF(G90<>"",$K$16,$K$16/2),)+IF(F90="WP",IF(G90<>"",$K$17,_xlfn.ANCHORARRAY($K$17)/2),)+IF(F90="Fel",IF(G90<>"",$K$18,$K$18/2),)+IF(H90<>"",10,0)+IF(I90<>"",10,0)+IF(J90<>"",10,0)} -> 0 | R90: =G90+H90+I90+J90 -> 0
R91: =SUM(R65:R90) -> 0
B92: 天 赋 记 录
B93: 名称 | G93: 具体 | Z93: R | AA93: 花费
B94: 起始技能 | G94: 按照职业生涯，填入起始技能，例如：听说语言（低哥特语）（Int），技术应用（Int），阅读（Int），密语（科技类）（Int），生计（雕刻师）（Ag）或者生计（抄写员）（Int）。
B96: 起始武器训练 | G96: 填入生涯（职业）的起始武器训练，并按照类型填入上方的武器训练表中。
AA120: =SUM(AA94:AA119) -> 0
B121: 出 身 特 性
B122: 名称 | G122: 描述
B127: 其 余 特 性
B128: 名称 | G128: 描述
...

Sheet 武备
B2: 近 战 武 器 | AD2: 武器改装/升级效果
B3: 名称 | F3: 类型 | H3: 射程 | J3: 伤害 | L3: 破甲 | N3: 特性 | S3: 重量 | T3: 花费 | U3: 品质 | W3: 改装/升级 | AB3: 花费 | AD3: 改装名称 | AH3: 效果描述
AH4: =_xlfn.IFNA(IF(AD4=0,"",VLOOKUP(AD4,附表!$AJ$65:$AK$73,2,FALSE)),"")
AH6: =_xlfn.IFNA(IF(AD6=0,"",VLOOKUP(AD6,附表!$AJ$65:$AK$73,2,FALSE)),"")
B8: 远程武器 | AH8: =_xlfn.IFNA(IF(AD8=0,"",VLOOKUP(AD8,附表!$AJ$65:$AK$73,2,FALSE)),"")
B9: 名称 | F9: 类型 | H9: 射程 | J9: 射速 | L9: 伤害 | N9: 破甲 | O9: 弹容 | Q9: 装填 | S9: 特性 | Y9: 品质 | AA9: 重量 | AB9: 花费
AH10: =_xlfn.IFNA(IF(AD10=0,"",VLOOKUP(AD10,附表!$AJ$65:$AK$73,2,FALSE)),"")
F11: 弹药 | O11: 弹夹 | S11: 改装
O12: 5 | AH12: =_xlfn.IFNA(IF(AD12=0,"",VLOOKUP(AD12,附表!$AJ$65:$AK$73,2,FALSE)),"")
F13: 弹药 | O13: 弹夹 | S13: 改装
O14: 6 | AH14: =_xlfn.IFNA(IF(AD14=0,"",VLOOKUP(AD14,附表!$AJ$65:$AK$73,2,FALSE)),"")
F15: 弹药 | O15: 弹夹 | S15: 改装
O16: 40 | AH16: =_xlfn.IFNA(IF(AD16=0,"",VLOOKUP(AD16,附表!$AJ$65:$AK$73,2,FALSE)),"")
F17: 弹药 | O17: 弹夹 | S17: 改装
B18: 弹药和榴弹等
B19: 名称 | F19: 类型/数量 | H19: 伤害 | J19: 破甲 | L19: 特性/适配/描述 | X19: 基重 | Y19: 单费 | Z19: 数量 | AA19: 重量 | AB19: 花费 | AD19: 购买物品资金自填减费配平/已并入已用经费
AA20: =IFERROR(IF(OR(ISBLANK(X20),ISBLANK(Z20),X20=0,Z20=0),"",X20*Z20),"") | AB20: =IF(OR(Y20=0,ISNUMBER(Z20)=FALSE,Z20=""),"",IFERROR(Y20*Z20,"")) | AD20: 多个相同物品减费配平 | AK20: 单个物品配平
AA21: =IFERROR(IF(OR(ISBLANK(X21),ISBLANK(Z21),X21=0,Z21=0),"",X21*Z21),"") | AB21: =IF(OR(Y21=0,ISNUMBER(Z21)=FALSE,Z21=""),"",IFERROR(Y21*Z21,"")) | AD21: 名称 | AH21: 单减费 | AI21: 数量 | AJ21: 总减费 | AK21: 名称 | AO21: 减费数
AA22: =IFERROR(IF(OR(ISBLANK(X22),ISBLANK(Z22),X22=0,Z22=0),"",X22*Z22),"") | AB22: =IF(OR(Y22=0,ISNUMBER(Z22)=FALSE,Z22=""),"",IFERROR(Y22*Z22,"")) | AJ22: =IFERROR(IF(OR(ISBLANK(AH22),ISBLANK(AI22),AH22=0,AI22=0),"",AH22*AI22),"")
AA23: =IFERROR(IF(OR(ISBLANK(X23),ISBLANK(Z23),X23=0,Z23=0),"",X23*Z23),"") | AB23: =IF(OR(Y23=0,ISNUMBER(Z23)=FALSE,Z23=""),"",IFERROR(Y23*Z23,"")) | AJ23: =IFERROR(IF(OR(ISBLANK(AH23),ISBLANK(AI23),AH23=0,AI23=0),"",AH23*AI23),"")
AA24: =IFERROR(IF(OR(ISBLANK(X24),ISBLANK(Z24),X24=0,Z24=0),"",X24*Z24),"") | AB24: =IF(OR(Y24=0,ISNUMBER(Z24)=FALSE,Z24=""),"",IFERROR(Y24*Z24,"")) | AJ24: =IFERROR(IF(OR(ISBLANK(AH24),ISBLANK(AI24),AH24=0,AI24=0),"",AH24*AI24),"")
AA25: =IFERROR(IF(OR(ISBLANK(X25),ISBLANK(Z25),X25=0,Z25=0),"",X25*Z25),"") | AB25: =IF(OR(Y25=0,ISNUMBER(Z25)=FALSE,Z25=""),"",IFERROR(Y25*Z25,"")) | AJ25: =IFERROR(IF(OR(ISBLANK(AH25),ISBLANK(AI25),AH25=0,AI25=0),"",AH25*AI25),"")
B26: 防护立场&饰品&其他 | AJ26: =IFERROR(IF(OR(ISBLANK(AH26),ISBLANK(AI26),AH26=0,AI26=0),"",AH26*AI26),"")
B27: 名称 | F27: 效果描述 | AA27: 重量 | AB27: 花费 | AJ27: =IFERROR(IF(OR(ISBLANK(AH27),ISBLANK(AI27),AH27=0,AI27=0),"",AH27*AI27),"")
AJ28: =IFERROR(IF(OR(ISBLANK(AH28),ISBLANK(AI28),AH28=0,AI28=0),"",AH28*AI28),"")
AJ29: =IFERROR(IF(OR(ISBLANK(AH29),ISBLANK(AI29),AH29=0,AI29=0),"",AH29*AI29),"")
AJ30: =IFERROR(IF(OR(ISBLANK(AH30),ISBLANK(AI30),AH30=0,AI30=0),"",AH30*AI30),"")
AJ31: =IFERROR(IF(OR(ISBLANK(AH31),ISBLANK(AI31),AH31=0,AI31=0),"",AH31*AI31),"")
AJ32: =IFERROR(IF(OR(ISBLANK(AH32),ISBLANK(AI32),AH32=0,AI32=0),"",AH32*AI32),"")
B33: 护甲 | AJ33: =IFERROR(IF(OR(ISBLANK(AH33),ISBLANK(AI33),AH33=0,AI33=0),"",AH33*AI33),"")
B34: 名称 | F34: 防护部位 | H34: AP | J34: 效果描述 | AA34: 重量 | AB34: 花费 | AJ34: =IFERROR(IF(OR(ISBLANK(AH34),ISBLANK(AI34),AH34=0,AI34=0),"",AH34*AI34),"")
AJ35: =IFERROR(IF(OR(ISBLANK(AH35),ISBLANK(AI35),AH35=0,AI35=0),"",AH35*AI35),"")
AJ36: =IFERROR(IF(OR(ISBLANK(AH36),ISBLANK(AI36),AH36=0,AI36=0),"",AH36*AI36),"")
AJ37: =IFERROR(IF(OR(ISBLANK(AH37),ISBLANK(AI37),AH37=0,AI37=0),"",AH37*AI37),"")
AJ38: =IFERROR(IF(OR(ISBLANK(AH38),ISBLANK(AI38),AH38=0,AI38=0),"",AH38*AI38),"")
AJ39: =IFERROR(IF(OR(ISBLANK(AH39),ISBLANK(AI39),AH39=0,AI39=0),"",AH39*AI39),"")
AJ40: =IFERROR(IF(OR(ISBLANK(AH40),ISBLANK(AI40),AH40=0,AI40=0),"",AH40*AI40),"")
B41: 物品 | AJ41: =IFERROR(IF(OR(ISBLANK(AH41),ISBLANK(AI41),AH41=0,AI41=0),"",AH41*AI41),"")
B42: 名称 | F42: 具体 | X42: 基重 | Y42: 单费 | Z42: 数量 | AA42: 重量 | AB42: 花费 | AJ42: =IFERROR(IF(OR(ISBLANK(AH42),ISBLANK(AI42),AH42=0,AI42=0),"",AH42*AI42),"")
B43: 背 包 | AA43: =IFERROR(IF(OR(ISBLANK(X43),ISBLANK(Z43),X43=0,Z43=0),"",X43*Z43),"") | AB43: =IF(OR(Y43=0,ISNUMBER(Z43)=FALSE,Z43=""),"",IFERROR(Y43*Z43,"")) | AJ43: =IFERROR(IF(OR(ISBLANK(AH43),ISBLANK(AI43),AH43=0,AI43=0),"",AH43*AI43),"")
AA44: =IFERROR(IF(OR(ISBLANK(X44),ISBLANK(Z44),X44=0,Z44=0),"",X44*Z44),"") | AB44: =IF(OR(Y44=0,ISNUMBER(Z44)=FALSE,Z44=""),"",IFERROR(Y44*Z44,"")) | AJ44: =IFERROR(IF(OR(ISBLANK(AH44),ISBLANK(AI44),AH44=0,AI44=0),"",AH44*AI44),"")
AA45: =IFERROR(IF(OR(ISBLANK(X45),ISBLANK(Z45),X45=0,Z45=0),"",X45*Z45),"") | AB45: =IF(OR(Y45=0,ISNUMBER(Z45)=FALSE,Z45=""),"",IFERROR(Y45*Z45,"")) | AJ45: =IFERROR(IF(OR(ISBLANK(AH45),ISBLANK(AI45),AH45=0,AI45=0),"",AH45*AI45),"")
AA46: =IFERROR(IF(OR(ISBLANK(X46),ISBLANK(Z46),X46=0,Z46=0),"",X46*Z46),"") | AB46: =IF(OR(Y46=0,ISNUMBER(Z46)=FALSE,Z46=""),"",IFERROR(Y46*Z46,"")) | AJ46: =IFERROR(IF(OR(ISBLANK(AH46),ISBLANK(AI46),AH46=0,AI46=0),"",AH46*AI46),"")
AA47: =IFERROR(IF(OR(ISBLANK(X47),ISBLANK(Z47),X47=0,Z47=0),"",X47*Z47),"") | AB47: =IF(OR(Y47=0,ISNUMBER(Z47)=FALSE,Z47=""),"",IFERROR(Y47*Z47,"")) | AJ47: =IFERROR(IF(OR(ISBLANK(AH47),ISBLANK(AI47),AH47=0,AI47=0),"",AH47*AI47),"")
AA48: =IFERROR(IF(OR(ISBLANK(X48),ISBLANK(Z48),X48=0,Z48=0),"",X48*Z48),"") | AB48: =IF(OR(Y48=0,ISNUMBER(Z48)=FALSE,Z48=""),"",IFERROR(Y48*Z48,"")) | AJ48: =IFERROR(IF(OR(ISBLANK(AH48),ISBLANK(AI48),AH48=0,AI48=0),"",AH48*AI48),"")
AA49: =IFERROR(IF(OR(ISBLANK(X49),ISBLANK(Z49),X49=0,Z49=0),"",X49*Z49),"") | AB49: =IF(OR(Y49=0,ISNUMBER(Z49)=FALSE,Z49=""),"",IFERROR(Y49*Z49,"")) | AJ49: =IFERROR(IF(OR(ISBLANK(AH49),ISBLANK(AI49),AH49=0,AI49=0),"",AH49*AI49),"")
AA50: =IFERROR(IF(OR(ISBLANK(X50),ISBLANK(Z50),X50=0,Z50=0),"",X50*Z50),"") | AB50: =IF(OR(Y50=0,ISNUMBER(Z50)=FALSE,Z50=""),"",IFERROR(Y50*Z50,"")) | AJ50: =IFERROR(IF(OR(ISBLANK(AH50),ISBLANK(AI50),AH50=0,AI50=0),"",AH50*AI50),"")
AA51: =IFERROR(IF(OR(ISBLANK(X51),ISBLANK(Z51),X51=0,Z51=0),"",X51*Z51),"") | AB51: =IF(OR(Y51=0,ISNUMBER(Z51)=FALSE,Z51=""),"",IFERROR(Y51*Z51,"")) | AJ51: =IFERROR(IF(OR(ISBLANK(AH51),ISBLANK(AI51),AH51=0,AI51=0),"",AH51*AI51),"")
AA52: =IFERROR(IF(OR(ISBLANK(X52),ISBLANK(Z52),X52=0,Z52=0),"",X52*Z52),"") | AB52: =IF(OR(Y52=0,ISNUMBER(Z52)=FALSE,Z52=""),"",IFERROR(Y52*Z52,"")) | AJ52: =IFERROR(IF(OR(ISBLANK(AH52),ISBLANK(AI52),AH52=0,AI52=0),"",AH52*AI52),"")
AA53: =IFERROR(IF(OR(ISBLANK(X53),ISBLANK(Z53),X53=0,Z53=0),"",X53*Z53),"") | AB53: =IF(OR(Y53=0,ISNUMBER(Z53)=FALSE,Z53=""),"",IFERROR(Y53*Z53,"")) | AJ53: =IFERROR(IF(OR(ISBLANK(AH53),ISBLANK(AI53),AH53=0,AI53=0),"",AH53*AI53),"")
AA54: =IFERROR(IF(OR(ISBLANK(X54),ISBLANK(Z54),X54=0,Z54=0),"",X54*Z54),"") | AB54: =IF(OR(Y54=0,ISNUMBER(Z54)=FALSE,Z54=""),"",IFERROR(Y54*Z54,"")) | AJ54: =IFERROR(IF(OR(ISBLANK(AH54),ISBLANK(AI54),AH54=0,AI54=0),"",AH54*AI54),"")
AA55: =IFERROR(IF(OR(ISBLANK(X55),ISBLANK(Z55),X55=0,Z55=0),"",X55*Z55),"") | AB55: =IF(OR(Y55=0,ISNUMBER(Z55)=FALSE,Z55=""),"",IFERROR(Y55*Z55,"")) | AJ55: =IFERROR(IF(OR(ISBLANK(AH55),ISBLANK(AI55),AH55=0,AI55=0),"",AH55*AI55),"")
AA56: =IFERROR(IF(OR(ISBLANK(X56),ISBLANK(Z56),X56=0,Z56=0),"",X56*Z56),"") | AB56: =IF(OR(Y56=0,ISNUMBER(Z56)=FALSE,Z56=""),"",IFERROR(Y56*Z56,"")) | AJ56: =IFERROR(IF(OR(ISBLANK(AH56),ISBLANK(AI56),AH56=0,AI56=0),"",AH56*AI56),"")
B57: 同伴 | AJ57: =IFERROR(IF(OR(ISBLANK(AH57),ISBLANK(AI57),AH57=0,AI57=0),"",AH57*AI57),"")
B58: 种类/型号 | G58: 属性情况 | I58: 基础 | J58: 超然 | K58: 备注 | L58: 加成 | M58: 最终 | N58: 加值 | O58: 体型 | Q58: 修正 | R58: =IFERROR(VLOOKUP(P58,人物数据!Q2:R8,2,FALSE),"") | T58: 移动 | W58: 护甲 | Z58: 承伤 | AJ58: =IFERROR(IF(OR(ISBLANK(AH58),ISBLANK(AI58),AH58=0,AI58=0),"",AH58*AI58),"")
G59: 格斗 WS | J59: 1 | L59: 0 | M59: =L59+I59+K59 -> 0 | N59: =INT(M59/10)*J59 -> 0 | T59: 技能 | W59: 天赋 | Z59: 特性 | AJ59: =IFERROR(IF(OR(ISBLANK(AH59),ISBLANK(AI59),AH59=0,AI59=0),"",AH59*AI59),"")
B60: 名字/绰号 | G60: 射击 BS | J60: 1 | L60: 0 | M60: =L60+I60+K60 -> 0 | N60: =INT(M60/10)*J60 -> 0 | AJ60: =IFERROR(IF(OR(ISBLANK(AH60),ISBLANK(AI60),AH60=0,AI60=0),"",AH60*AI60),"")
G61: 力量 S | J61: 1 | L61: 0 | M61: =L61+I61+K61 -> 0 | N61: =INT(M61/10)*J61 -> 0 | AJ61: =IFERROR(IF(OR(ISBLANK(AH61),ISBLANK(AI61),AH61=0,AI61=0),"",AH61*AI61),"")
B62: 伙伴样貌 | G62: 坚韧 T | J62: 1 | L62: 0 | M62: =L62+I62+K62 -> 0 | N62: =INT(M62/10)*J62 -> 0 | AD62: 购买物品资金：自填加费配平/已并入已用经费
G63: 敏捷 Ag | J63: 1 | L63: 0 | M63: =L63+I63+K63 -> 0 | N63: =INT(M63/10)*J63 -> 0 | AD63: 多个相同物品减费配平 | AK63: 单个物品配平
G64: 智力 Int | J64: 1 | L64: 0 | M64: =L64+I64+K64 -> 0 | N64: =INT(M64/10)*J64 -> 0 | AD64: 名称 | AH64: 单加费 | AI64: 数量 | AJ64: 总加费 | AK64: 名称 | AO64: 加费数
G65: 感知 Per | J65: 1 | L65: 0 | M65: =L65+I65+K65 -> 0 | N65: =INT(M65/10)*J65 -> 0 | AJ65: =IFERROR(IF(OR(ISBLANK(AH65),ISBLANK(AI65),AH65=0,AI65=0),"",AH65*AI65),"")
G66: 意志 WP | J66: 1 | L66: 0 | M66: =L66+I66+K66 -> 0 | N66: =INT(M66/10)*J66 -> 0 | AJ66: =IFERROR(IF(OR(ISBLANK(AH66),ISBLANK(AI66),AH66=0,AI66=0),"",AH66*AI66),"")
G67: 交际 Fel | J67: 1 | L67: 0 | M67: =L67+I67+K67 -> 0 | N67: =INT(M67/10)*J67 -> 0 | AJ67: =IFERROR(IF(OR(ISBLANK(AH67),ISBLANK(AI67),AH67=0,AI67=0),"",AH67*AI67),"")
G68: 武 器 | H68: 名称 | L68: 类型 | N68: 射程 | P68: 伤害 | S68: 破甲 | U68: 特性 | AJ68: =IFERROR(IF(OR(ISBLANK(AH68),ISBLANK(AI68),AH68=0,AI68=0),"",AH68*AI68),"")
AJ69: =IFERROR(IF(OR(ISBLANK(AH69),ISBLANK(AI69),AH69=0,AI69=0),"",AH69*AI69),"")
AJ70: =IFERROR(IF(OR(ISBLANK(AH70),ISBLANK(AI70),AH70=0,AI70=0),"",AH70*AI70),"")
B71: 装备 | AJ71: =IFERROR(IF(OR(ISBLANK(AH71),ISBLANK(AI71),AH71=0,AI71=0),"",AH71*AI71),"")
AJ72: =IFERROR(IF(OR(ISBLANK(AH72),ISBLANK(AI72),AH72=0,AI72=0),"",AH72*AI72),"")
B73: 假肢/神经反馈设备等情况 | AJ73: =IFERROR(IF(OR(ISBLANK(AH73),ISBLANK(AI73),AH73=0,AI73=0),"",AH73*AI73),"")
B74: 类型 | C74: 名称 | F74: 位置 | G74: 装配 | H74: 品质 | I74: 花费 | J74: 具 体 植 入 | K74: 名称 | O74: 效果 | AJ74: =IFERROR(IF(OR(ISBLANK(AH74),ISBLANK(AI74),AH74=0,AI74=0),"",AH74*AI74),"")
B75: 假肢 | C75: 生化手臂 | F75: 左臂 | G75: - | AJ75: =IFERROR(IF(OR(ISBLANK(AH75),ISBLANK(AI75),AH75=0,AI75=0),"",AH75*AI75),"")
C76: 仿生肌肉移植 | F76: 全身 | G76: - | AJ76: =IFERROR(IF(OR(ISBLANK(AH76),ISBLANK(AI76),AH76=0,AI76=0),"",AH76*AI76),"")
B77: 植 入 设 备 | C77: 机械装殖 | F77: 全身 | G77: - | AJ77: =IFERROR(IF(OR(ISBLANK(AH77),ISBLANK(AI77),AH77=0,AI77=0),"",AH77*AI77),"")
C78: 机械外壳 | F78: 背部 | G78: - | AJ78: =IFERROR(IF(OR(ISBLANK(AH78),ISBLANK(AI78),AH78=0,AI78=0),"",AH78*AI78),"")
C79: 思维刺激设备MIU | F79: 头部 | G79: - | AJ79: =IFERROR(IF(OR(ISBLANK(AH79),ISBLANK(AI79),AH79=0,AI79=0),"",AH79*AI79),"")
C80: 电子接口 | F80: 头部 | G80: - | AJ80: =IFERROR(IF(OR(ISBLANK(AH80),ISBLANK(AI80),AH80=0,AI80=0),"",AH80*AI80),"")
C81: 循环呼吸面罩 | F81: 头部 | G81: - | AJ81: =IFERROR(IF(OR(ISBLANK(AH81),ISBLANK(AI81),AH81=0,AI81=0),"",AH81*AI81),"")
C82: 脑皮层植入物 | F82: 头部 | G82: - | AJ82: =IFERROR(IF(OR(ISBLANK(AH82),ISBLANK(AI82),AH82=0,AI82=0),"",AH82*AI82),"")
C83: 电感组织 | F83: 左手 | G83: - | AJ83: =IFERROR(IF(OR(ISBLANK(AH83),ISBLANK(AI83),AH83=0,AI83=0),"",AH83*AI83),"")
B84: 附 肢 | C84: 多功能附肢 | F84: 背部 | G84: - | AJ84: =IFERROR(IF(OR(ISBLANK(AH84),ISBLANK(AI84),AH84=0,AI84=0),"",AH84*AI84),"")
C85: 构造阵列 | F85: 背部 | G85: - | AJ85: =IFERROR(IF(OR(ISBLANK(AH85),ISBLANK(AI85),AH85=0,AI85=0),"",AH85*AI85),"")
C86: 医疗附肢 | F86: 背部 | G86: - | AJ86: =IFERROR(IF(OR(ISBLANK(AH86),ISBLANK(AI86),AH86=0,AI86=0),"",AH86*AI86),"")
C87: 光学附肢 | F87: 背部 | G87: - | AJ87: =IFERROR(IF(OR(ISBLANK(AH87),ISBLANK(AI87),AH87=0,AI87=0),"",AH87*AI87),"")
C88: 多功能附肢 | F88: 背部 | G88: - | AJ88: =IFERROR(IF(OR(ISBLANK(AH88),ISBLANK(AI88),AH88=0,AI88=0),"",AH88*AI88),"")
B89: 扩 展 | G89: - | AJ89: =IFERROR(IF(OR(ISBLANK(AH89),ISBLANK(AI89),AH89=0,AI89=0),"",AH89*AI89),"")
G90: - | AJ90: =IFERROR(IF(OR(ISBLANK(AH90),ISBLANK(AI90),AH90=0,AI90=0),"",AH90*AI90),"")
G91: - | AJ91: =IFERROR(IF(OR(ISBLANK(AH91),ISBLANK(AI91),AH91=0,AI91=0),"",AH91*AI91),"")
G92: - | AJ92: =IFERROR(IF(OR(ISBLANK(AH92),ISBLANK(AI92),AH92=0,AI92=0),"",AH92*AI92),"")
B93: 杂物 | AJ93: =IFERROR(IF(OR(ISBLANK(AH93),ISBLANK(AI93),AH93=0,AI93=0),"",AH93*AI93),"")
B94: 名称 | F94: 描述 | AJ94: =IFERROR(IF(OR(ISBLANK(AH94),ISBLANK(AI94),AH94=0,AI94=0),"",AH94*AI94),"")
F95: 填入不计入花费的随身杂物 | AJ95: =IFERROR(IF(OR(ISBLANK(AH95),ISBLANK(AI95),AH95=0,AI95=0),"",AH95*AI95),"")
AJ96: =IFERROR(IF(OR(ISBLANK(AH96),ISBLANK(AI96),AH96=0,AI96=0),"",AH96*AI96),"")
AJ97: =IFERROR(IF(OR(ISBLANK(AH97),ISBLANK(AI97),AH97=0,AI97=0),"",AH97*AI97),"")
AJ98: =IFERROR(IF(OR(ISBLANK(AH98),ISBLANK(AI98),AH98=0,AI98=0),"",AH98*AI98),"")
AJ99: =IFERROR(IF(OR(ISBLANK(AH99),ISBLANK(AI99),AH99=0,AI99=0),"",AH99*AI99),"")
AJ100: =IFERROR(IF(OR(ISBLANK(AH100),ISBLANK(AI100),AH100=0,AI100=0),"",AH100*AI100),"")
AJ101: =IFERROR(IF(OR(ISBLANK(AH101),ISBLANK(AI101),AH101=0,AI101=0),"",AH101*AI101),"")
AJ102: =IFERROR(IF(OR(ISBLANK(AH102),ISBLANK(AI102),AH102=0,AI102=0),"",AH102*AI102),"")
AJ103: =IFERROR(IF(OR(ISBLANK(AH103),ISBLANK(AI103),AH103=0,AI103=0),"",AH103*AI103),"")
...

Sheet 数据导入
B2: 人物导入，但是作者只用过海豹，别的骰娘行不行暂时不知道！ | O2: 表格制作者们 | S2: 1.3 | X2: 1.6
B3: 右键下格，点击“复制”，并在下方的TXT栏“粘贴”就可以导出文本，然后再选中文本，复制到最上方显示框，然后再剪切进QQ可以避免黏贴的是图片的问题。 也可以直接复制下格，复制进一个TXT文本。 | O3: （排名不分前后） | S3: 武器自动化！ | X3: 完善自动化，添加了改装描述简要查找，购买资金配平功能，并更改了武器的自动化逻辑。
O4: 勒
O5: 迮越
B6: =人物!AC1 -> .st格斗0射击0力量0坚韧0敏捷0智力0感知0意志0交际0生命值生命值上限0命运点命运点上限威胁0恐吓0攀爬0运动0游泳0酗酒0狂欢0躲藏0闪避0潜行0估价0逻辑0赌博0警觉0搜查0搜索0察言观色0交易0欺诈0搜集信息0伪装0吸引0扯淡0指挥0 | O6: 晨星
O7: 一壶
O8: 五三点九
O9: IAN
O10: 浣熊旅記
S11: 1.31 | X11: 1.61
S12: 添加了更多弹药并并入自动化中。 优化了1.3版本更新后，弹药计算总数时只填充数量会导致总数显示错误的bug | X12: 修复一些bug并优化
X20: 1.62
S21: 1.4 | X21: 修复一些bug并优化，完善自动化并更改了天赋与物品的自动化逻辑。
S22: 添加了机机风味美化，修复了角色卡没有纯洁印记的漏洞 | U22: 增加了天赋及技能详情速查表，购物表并加入了自动化，添加住宿和医疗表，以及添加了机械神甫晋升表。
X29: 1.63
X30: 更新了资金方面，更新了自动计算目前等级，更改了武器的自动化逻辑，添加了一些标注，新增内置了车卡战斗指南 小幅调整了‘人物’中的排版，增加了每个部位自动计算护甲+坚韧加值得出每个部位最终都有多少甲的功能，邀请了没被邀请的修女的钱包
S31: 1.5 | U31: 分版：半自动
S32: 优化并微调了排版，完善了并新增了更多自动化，对齐了半自动灵能最新版本，新增了可以自己填入非自动化内的内容并入自动化的功能，修复了一些bug | U32: 浣熊旅記接手并制作了半自动姐妹卡，重构优化了灵能相关，并制作了新版美化
X38: 1.64
X39: 同步更新了一些老旧翻译问题，自动化添加了有关背景包的自动功能。

Sheet 灵能
B2: 持有情况 | K2: 灵能相关速查 | Q2: 施法聚焦
B3: 类别 | C3: 次级 | D3: 生化 | E3: 预言 | F3: 操火 | G3: 遥感 | H3: 传心 | I3: 巫术 | J3: 其他 | K3: 优异灵能 | M3: 灵能等级 | O3: 房规加成 | Q3: DH施法
B4: 数量 | Q4: 束缚 | R4: 自由 | S4: 引导
B5: 精通 | K5: 专注/法器 | M5: 灵能感应 | O5: WP | P5: WB | Q5: =ROUND(R5/2,0) -> 0 | R5: =M4 -> 0 | S5: =R5+3 -> 3
B6: 专攻 | O6: =人物!K17 -> 0 | P6: =人物!L17 -> 0 | Q6: RT施法
B7: 额外 | K7: 其他天赋 | Q7: 束缚 | R7: 自由 | S7: 引导
B8: 共计 | C8: =IF(M4="","",IF(C6="√",2,0)+P6+K4+C7) | D8: =IF(M4="","",IF(D6="√",2,0)+P6+K4+D7) | E8: =IF(M4="","",IF(E6="√",2,0)+P6+K4+E7) | F8: =IF(M4="","",IF(F6="√",2,0)+P6+K4+F7) | G8: =IF(M4="","",IF(G6="√",2,0)+P6+K4+G7) | H8: =IF(M4="","",IF(H6="√",2,0)+P6+K4+H7) | I8: =IF(M4="","",IF(I6="√",2,0)+P6+K4+I7) | J8: =IF(M4="","",IF(J6="√",2,0)+P6+K4+J7) | Q8: =Q5*5+O6 -> 0 | R8: =R5*5+O6 -> 0 | S8: =S5*5+O6 -> 15
B10: ↓搜索框
B11: 灵能类别 | H11: 灵能名称 | N11: 加值 | P11: 束缚 | Q11: {=IF(M4="","",Q5&"D10+"&_xlfn.SWITCH(E11,"次级灵能",C8,"生化学科",D8,"预言学科",E8,"操火学科",F8,"遥感学科",G8,"传心学科",H8,"高阶秘仪",I8,"其他灵能",J8,P6+K4))}
P12: 自由 | Q12: {=IF(M4="","",R5&"D10+"&_xlfn.SWITCH(E11,"次级灵能",C8,"生化学科",D8,"预言学科",E8,"操火学科",F8,"遥感学科",G8,"传心学科",H8,"高阶秘仪",I8,"其他灵能",J8,P6+K4))}
P13: 引导 | Q13: {=IF(M4="","",S5&"D10+"&_xlfn.SWITCH(E11,"次级灵能",C8,"生化学科",D8,"预言学科",E8,"操火学科",F8,"遥感学科",G8,"传心学科",H8,"高阶秘仪",I8,"其他灵能",J8,P6+K4))}
B14: Ps：可以在灵能大全表最末自己手动添加房规灵能，会自动同步
B15: 灵 能 详 情
B16: 灵能名称 | E16: 灵能类别 | H16: 阈值 | K16: 聚焦 | N16: 维持 | Q16: 范围
B17: =IFERROR(VLOOKUP(K11,灵能表[],1,0),"") | E17: =IFERROR(VLOOKUP(K11,灵能表[],2,0),"") | H17: =IFERROR(VLOOKUP(K11,灵能表[],3,0),"") | K17: =IFERROR(VLOOKUP(K11,灵能表[],4,0),"") | N17: =IFERROR(VLOOKUP(K11,灵能表[],5,0),"") | Q17: =IFERROR(VLOOKUP(K11,灵能表[],6,0),"")
B18: =IFERROR(VLOOKUP(K11,灵能表[],7,0),"")
B30: 超量释放 | E30: =IFERROR(VLOOKUP(K11,灵能表[],8,0),"")
B35: 次 级 灵 能
B36: 次级灵能
B43: 次级秘仪
B46: 学 科 灵 能
B57: 其 他 灵 能

Sheet 灵能大全
B2: 灵能名称 | C2: 灵能类别 | D2: 阈值 | E2: 聚焦 | F2: 维持 | G2: 范围 | H2: 能力 | I2: 超量释放
B3: 鼓舞氛围 | C3: 次级灵能 | D3: 6 | E3: 完整动作 | F3: 可 | G3: 自身 | H3: 这是个好的灵能，它让你看上去很好，所有看到你的人都会忍不住想对你说好话，这很好。另外，看到你的人会觉得充满自信，以至于对抗恐惧和压制的检定 +20。 | I3: /
B4: 减缓痛苦 | C4: 次级灵能 | D4: 8 | E4: 部分动作 | F4: 否 | G4: 10m | H4: 范围内你指定的一个生物（也可以是你自己）移除 1 级虚弱。 | I4: 每超过阀值 5 点，额外移除 1 级虚弱。
B5: 痉挛 | C5: 次级灵能 | D5: 7 | E5: 部分动作 | F5: 否 | G5: 50m | H5: 你可以瞬间使目标肌肉痉挛。目标可以进行意志检定抵抗此效果，失败会全身发痒，陷入一阵无法控制的痉挛，并立刻倒地。如果目标持有射击武器，该武器会走火，目标正常进行 BS 检定并击中最接近的人。 | I5: 每超过阀值 5 点，你可以多指定一个目标，或者将意志检定难度提高一级。
B6: 武器故障 | C6: 次级灵能 | D6: 8 | E6: 完整动作 | F6: 否 | G6: 50m | H6: 用你的意志干扰机魂，范围内你指定的一件不具有原始特性的武器自动发生故障。武器故障可以通过正常方法排除。注意机械神教对这种做法很反感，对这种灵能者往往持不信任态度。 | I6: 每超过阀值 5 点，影响范围增加10m，或者多指定一件武器。
B7: 医疗者 | C7: 次级灵能 | D7: 7 | E7: 完整动作 | F7: 否 | G7: 10m | H7: 该灵能只能作用于范围内的一个自愿目标（包括你自己），并使其恢复 1d5 点伤害（优先恢复致命伤害）。但是反复使用这种治疗手段存在危险，人体会开始抵制亚空间的能量。如果目标在六小时之内再次被施以此灵能，他必须进行坚韧检定，否则会受到而不是恢复1d5 伤害，该伤害无视坚韧加值和护甲防护。 | I7: /
B8: 把戏 | C8: 次级灵能 | D8: 5 | E8: 部分动作 | F8: 可 | G8: 自身 | H8: 你巧妙地影响身边的“场”，让自己在游戏中作弊的技巧更为高超。灵能生效期间，赌博技能将变为你的基本技能，且得到二级精通（+20）。如果你已经掌握了赌博技能，则该技能检定 +20。但如果你在赌博技能上已经有任何一级精通，该灵能无效，因为你已经达到这个水准了。 | I8: /
B9: 白噪音 | C9: 次级灵能 | D9: 8 | E9: 完整动作 | F9: 可 | G9: 10m | H9: 让区域内充满亚空间干扰，使区域内的任何目标都难以被侦测。尝试用灵能手段或技术手段对该区域内任何目标进行侦测的检定变为艰难(-20)。如果侦测手段不需要检定，那么侦测者需要进行一个常规(+10)意志检定(使用灵能手段)或常规(+10)智力检定(使用科技手段)。 | I9: 每超过阀值 5 点，影响范围增加10m。
B10: 爆炸闪光 | C10: 次级灵能 | D10: 6 | E10: 部分动作 | F10: 否 | G10: 20m | H10: 你制造出一阵闪光爆炸，范围内的任何人都要进行一次常规（+20）意志检定，失败则眩晕 1 轮。 | I10: 每超过阀值 10 点，检定难度提升一级。
B11: 变色龙 | C11: 次级灵能 | D11: 7 | E11: 部分动作 | F11: 可 | G11: 自身 | H11: 让自己身体颜色与环境一致。躲藏+30，针对你的射击 BS-20。 | I11: /
B12: 抵抗附身 | C12: 次级灵能 | D12: 6 | E12: 反射动作 | F12: 否 | G12: 自身 | H12: 建立精神守护保卫自己的意志。接下来的一小时之内，抵抗恶魔的附身时，你可以重投任何失败的意志检定。 | I12: /
B13: 凋零 | C13: 次级灵能 | D13: 6 | E13: 完整动作 | F13: 否 | G13: 3d10m | H13: 你引发一阵恶毒的波动席卷四周，使范围内的所有“正常”植物凋零死亡。 | I13: 每超过阀值 5 点，影响范围增加1d10m。
B14: 非凡精准 | C14: 次级灵能 | D14: 8 | E14: 部分动作 | F14: 否 | G14: 自身 | H14: 用亚空间的力量引导自己瞄准。到你的下一回合结束，你所做的任何 BS 检定 +30。 | I14: /
... B112: 恶魔咒阵 | C112: 高阶秘仪 | D112: 23 | E112: 完整动作 | F112: 否 | G112: 50m | H112: 通过编织亚空间能量的术式，巫师可以尝试驱退、困缚并夺取对恶魔实体的控制权。 施展成功后，巫师可与目标恶魔生物进行意志对抗检定，以此对其施加厄咒。或者，如果目标恶魔的意志属性为 50 或更低，则巫师可改为强制进行一次恶魔掌控检定来支配它。 特殊：这项能力仅能影响同时具有恶魔特性和亚空间不稳定特性的实体。 | I112: 每超过阈值 5 点，巫师在意志对抗和恶魔掌控检定上便获得 +10 加值。
B113: 恶毒诅咒 | C113: 高阶秘仪 | D113: 特殊 | E113: 完整动作 | F113: 否 | G113: 视线范围内 | H113: 阈值：祸祟 16；致盲 20；催命 23 你祈求扭曲交缠的恶性能量，为受害者带去灾祸与诅咒。此处列出了三种不同的诅咒形式，当然，世上的诅咒形式显然不止于此。无论面对何种诅咒，受害者均可尝试通过一次难度为挑战（+0）的意志检定，以此抵抗诅咒效果。 祸祟 Hex：受害者饱受厄运缠身、蚀骨寒意与超自然的恐惧折磨。在接下来的 1d5 小时内，受害者的所有属性检定与技能检定均承受 -10 减值。若抵抗此能力的检定失败度为 3 及以上，受害者还必须额外在表 8-4：震惊（Shock）上掷骰（见《黑暗异端》第 233 页），此情形被视作亚空间惊吓。 致盲 Blindness：受害者的双眼被白内障填满，泣出血泪，陷入失明状态，持续 1d5 小时。若抵抗此巫术的检定失败度为 3 及以上，受害者的双眼会在血雨飞溅中被摧毁，对头部造成 1d10 R 伤害，并且会永久失明（若其幸存，则需更换假眼）。双眼被摧毁还会带给受害者 1d10 点失心。 催命 Death：通过遏停心跳、引爆血管、撕裂内脏以及其他种种可怖方式，此诅咒的威力足以使人丧失行动能力，甚至致人死亡。受害者遭受 3d10+10 点坚韧伤害（若其具有超自然坚韧（x2）等特性，则伤害减半）。受害者的坚韧降至 0 点时，其立即死亡。若此诅咒的受害者存活下来，则坚韧伤害可如常治疗。 注意：因诅咒而死时，受害者可以燃烧 1 命运点来避免暴毙，并恢复 1d5 坚韧。但受害者会陷入昏迷状态，亟需紧急救治。 特殊：每次施展诅咒时，巫师必须通过一次难度为挑战（+0）的意志检定，否则其获得 1d5 点堕落。 | I113: 每超过阈值 5 点，受害者抵抗诅咒的检定难度便提高一级，最高难度为艰巨（-30）。
B114: 地狱爆破 | C114: 高阶秘仪 | D114: 22 | E114: 部分动作 | F114: 否 | G114: 5m x 意志加值 | H114: 使用此能力时，你可以从亚空间引导能量，向受害者投掷一团纯粹的毁灭性爆流，将其点燃并炸成碎片。如同远程攻击一般，你进行一次远程技巧（BS）检定以命中目标。检定成功时，你的攻击造成 1d10+WB E 伤害。这次伤害视为具备亚空间武器特性，因此可以穿透大多数护甲与防御。 | I114: 每超过阈值 10 点，便额外造成 1d10 点伤害。
B115: 黑暗导能 | C115: 高阶秘仪 | D115: 25 | E115: 完整动作 | F115: 可 | G115: 20 米半径 | H115: 巫师从亚空间中汲取扭曲力量，用以增强和维系范围内的恶魔生物，巩固恶魔在现实世界的存在，并强化其力量。 作用范围内，任何拥有恶魔特性的生物获得再生特性，其先攻 +1，并在抵抗亚空间不稳定时获得 +10 加值。 特殊：巫师需要为引导这些邪恶能量支付代价。维持灵能的每一轮，施术者都必须通过一次难度为困难（-10）的坚韧检定，否则将失去 1 点承伤。 | I115: 每超过阈值 10 点，范围半径增加 10 米。
B116: 恶意风暴 | C116: 高阶秘仪 | D116: 18 | E116: 完整动作 | F116: 可 | G116: 50 米半径 | H116: 巫师借助亚空间中那些经由灵能回响而传播开的恶意、偏执与仇恨，将突如其来的狂怒、恐慌与杀意，灌注进毫无防备之人的心智中去，并由此引发致命后果。这股情绪浪潮足以将一群普通人变成施暴的狂徒，引起大规模的群体癫狂与血腥暴乱。在能力生效期间，身处范围内的所有活物，每轮必须通过一次难度为挑战（+0）的意志检定，否则便会陷入极度危险且充满暴力的狂怒状态。依据其各自的心智状况，他们要么会疯狂攻击任何触手可及的人，要么会因极度恐惧而四散奔逃。如果受害者屈从于这项能力，其所带来的直接影响将持续到维持结束，再加上额外 1d10 轮。 这项能力属于灵能攻击，同时也被视为恐惧效果，因此能够抵抗恐惧的天赋和特性，对这项能力同样有效。 | I116: 每超过阈值 10 点，范围半径翻倍。
B117: 时间扭曲 | C117: 高阶秘仪 | D117: 20 | E117: 完整动作 | F117: 可 | G117: 自身 | H117: 巫师使自己与周围现实及时间的流动略微错相。巫师的身形变得模糊且飘忽不定，其过去与未来各种可能行动的阴影相互重叠，如幽灵般环绕其身周。 能力生效期间，巫师变得极难被击中，任何对其发起的攻击检定承受 -20 减值。此外，如果巫师在 1d10 中掷出奇数结果（即1、3、5、7、9），则任何成功命中将被抵消，除非该次攻击使用灵能、来自受祝（Blessed）或神圣（Holy）武器，或是具备亚空间武器特性。 特殊：如果巫师遭受亚空间危险，则时间反冲将撕裂巫师自身，对其造成 3d10 E 伤害。 | I117: 每超过阈值 5 点，此能力在维持中断后，效果额外持续 1 轮。
B118: 创造门扉 | C118: 高阶秘仪 | D118: 28 | E118: 完整动作 | F118: 否 | G118: 5m | H118: 巫师凭空召唤出一道燃烧的门扉。这道门扉可用于将巫师传送至他脑海中能清晰回忆起的任何地方。巫师的玩家必须告知游戏主持人他希望门扉通向何处；游戏主持人随后会根据巫师上次身处该地的时间、其心智状态、周遭环境及专注程度，设定一个适当的难度等级。巫师随后可迈步穿过门扉，并基于该难度等级进行智力检定。若检定通过，则一切顺利。若未通过，游戏主持人将决定一个合适的替代目的地——通常是一个巫师宁愿避开的地方。 特殊：穿越如此亵渎的门户，会让使用者比安全限度更接近亚空间的恐怖。任何穿过门扉者都必须通过一个难度为艰难（-20）的意志检定。若检定失败，该角色必须在亚空间危险表上掷骰。 10 米–100 米：常规（+20）；101 米–1000 米：普通（+10）；星球内的任意地点：挑战（+ 0）；星系内的任意地点：困难（-10）；次星区内的任意地点：艰难（-20）；星区内的任意地点：艰巨（-30） | I118: /
B119: 疫病 | C119: 高阶秘仪 | D119: 20 | E119: 部分动作 | F119: 否 | G119: 5m | H119: 巫师轻蔑地一挥手，便将一场瘟疫降于目标身上。目标开始呕出胆汁与鲜血，皮肤上隆起脓包。此疫病持续轮数等于 1d10 减去目标的坚韧加值。目标在染疫期间，全部属性每轮降低 10 点。若其坚韧降低至零，则目标死亡。 超量释放：每超过阈值 5 点，疫病的持续时间增加 1 轮。 特殊：若一名角色死于疫病，其灵魂将归于瘟疫之主纳垢。倒下的尸体会进一步腐烂，并在 5 轮后作为一只瘟疫使者（Plaguebearer）站起（见《黑暗异端》规则书第 354 页）。瘟疫使者会立即攻击附近的任何生物。 | I119: /
B120: 失血术 | C120: 高阶秘仪 | D120: 18 | E120: 部分动作 | F120: 否 | G120: 10m | H120: 巫师朝目标打个响指并吼出一段咒文，使目标的血液沸腾、涌出体外。巫师用意志与目标的坚韧对抗。若对抗成功，目标承受等同于巫师意志加值两倍的伤害（坚韧加值与护甲无法减免此伤害），并会陷入失血状态（见《黑暗异端》规则书第 211 页）。 | I120: /
B121: 颅骨连枷 | C121: 高阶秘仪 | D121: 14 | E121: 部分动作 | F121: 可 | G121: 自身 | H121: 巫师以亚空间为索，将亡者的颅骨束缚在一起，打造出一把燃烧着恶意的颅骨连枷。颅骨连枷显现后，其数据与普通连枷相同（见《黑暗异端》规则书第 139 页），但具有亚空间武器特性，能够绕过大多数护甲与防御。任何受到颅骨连枷伤害的目标将获得 1d10 点失心，并且从第二颗颅骨之后算起，每多使用一颗颅骨打造此连枷，便额外造成 1 点失心。 特殊：显然，使用此能力需要巫师拥有至少一颗颅骨。 | I121: /
B122: 燃烧之语 | C122: 高阶秘仪 | D122: 18 | E122: 部分动作 | F122: 否 | G122: 自身 | H122: 巫师张开嘴巴，将其作为亚空间烈焰的门户。此能力造成 1d10+4 E 伤害，并具有 3 点破甲。其效果范围可延伸至 20 米，并具有火焰特性。此外，由于这些火焰的超自然本质，任何被此能力效果影响的目标都会自动着火（on fire）（见《黑暗异端》规则书第 210 页）。 特殊：在此能力施展期间，巫师无法进行口头交流；这可能会阻止巫师施放某些其他能力。 | I122: /
B123: 免疫冲击 | C123: 高阶秘仪 | D123: 24 | E123: 部分动作 | F123: 否 | G123: 自身 | H123: 巫师吞下一颗实弹弹药，以此强化自身躯体，抵御投射物与粗制武器的攻击。巫师必须通过一次坚韧检定。若检定成功，巫师在 1d5 轮内免疫任何冲击伤害（Impact Type Damage）。 | I123: /
B124: 汲食生命 | C124: 高阶秘仪 | D124: 21 | E124: 完整动作 | F124: 否 | G124: 接触 | H124: 巫师将手指插入目标的血肉，吸收其生命力，直至目标仅剩一具干枯的躯壳。这一能力仅能作用于处在眩晕状态或其他无力反抗的目标。每超过阈值 5 点，巫师便恢复 1 点承伤，同时目标的承伤减少 1 点。巫师恢复的承伤数不能超过其原本的承伤上限。如果目标的承伤降低至零，则目标死亡。 | I124: /
B125: 活体武器 | C125: 高阶秘仪 | D125: 24 | E125: 完整动作 | F125: 可 | G125: 自身 | H125: 巫师将混沌的邪秽符号刻入自己的血肉之中，呼唤亚空间重塑其肉身以应对战斗。在能力生效期间，巫师的属性获得以下提升：近战技巧 +20、力量 +20、坚韧 +10、敏捷 +10。此外，巫师在所有先攻检定中获得 +3 加值，获得天生武器特性，且其所有近战攻击均获得撕裂特性。在此等兽性状态下，他的交际降低 10 点。 | I125: /
... B135: 苦痛浩劫 | C135: 其他灵能 | D135: 28 | E135: 完整动作 | F135: 可 | G135: 以苦痛之拥为中心，10 米半径内 | H135: 苦痛之拥（见第 131 页）的受害者每时每刻承受着难以想象的剧痛与绝望。他们在生与死间遭受不死的折磨，一边是恶魔对其灵魂的啃噬，一边是肉体永无止境的消亡。经由亚空间的回响与放大，苦痛之拥的受害者能将这种难耐的折磨施加于他人，产生粉碎性的效果。他们能撕裂其周围的现实，将实体物质、血肉与心智一并击溃。 爆炸范围内的一切事物都将承受 2d10 R 伤害。该伤害无视除力场防护或护符（Field effects or wards）之外的任何护甲，且受创者将被巨大的力量向后击飞（与凶猛投掷灵能等效）。任何在此攻击下幸存的生物都必须通过一次难度为艰难（-20）的恐惧检定，否则将遭受亚空间惊吓。 | I135: 每超过阈值 10 点，范围半径增加 10 米。

Sheet 武器与防具与弹药
A1: 武器表 | O1: 武器类型 | U1: 武器特性注释 | AH1: 防具表 | AP1: 防具类型
A4: 近 战 武 器 | K4: 格斗武器 †代表该武器需要双手使用 | O4: 格斗 | P4: 格斗武器包括了近战使用的武器， 当你使用这些武器时，在伤害检定上加上你的力量调整值 | U4: 原始 | V4: 原始且基础的设计，这种类型的武器，虽然依然致命，但对更高水平的护甲意义不大。 护甲的所有防护值在对抗原始武器时会加倍，除非护甲也具有原始属性。 | AA4: 充能 | AB4: 因为武器的弹药由不稳定物质构成，或是射击方式所限，这种武器在两次射击间需要时间进行充能。 具有充能特性的武器在开火之后必须花费一轮对武器进行充电并且无法再次使用，实际上你使用这种武器的时候只能隔一轮开火一次。 | AH4: 护甲 | AP4: 原始 | AQ4: 主要使用原始材料制做，例如兽皮和软金属，相较于抵挡子弹，这种护甲更擅长偏折锋刃。 具有原始特性的护甲在对抗不具有原始特性的武器时，只能计算一半的护甲防护（向上取整）。武器破甲在护甲防护取半之后计算。
B5: 名称 | C5: 类型 | D5: 射程 | E5: 伤害 | F5: 破甲 | G5: 特性 | H5: 重量 | I5: 花费 | J5: 原始 | AI5: 名称 | AJ5: 特性 | AK5: AP | AL5: 重量 | AM5: 花费 | AN5: 原始
B6: 斧 | C6: 格斗 | D6: — | E6: 1d10+1 R | F6: 0 | G6: 原始，失衡 | H6: 4 | I6: 20 | AI6: 皮夹克 | AJ6: 手臂 躯干 腿 | AK6: 1 | AL6: 5 | AM6: 25
B7: 黄铜指虎 | C7: 格斗 | D7: — | E7: 1d5−1 I | F7: 0 | G7: 原始 | H7: 0.5 | I7: 5 | AI7: 重皮甲 | AJ7: 手臂 躯干 腿 | AK7: 2 | AL7: 7 | AM7: 100
B8: 棍棒 | C8: 格斗 | D8: — | E8: 1d10 I | F8: 0 | G8: 原始 | H8: 2 | I8: 5 | AI8: 棉布背心 | AJ8: 躯干 | AK8: 2 | AL8: 2 | AM8: 10
B9: 链枷 | C9: 格斗† | D9: — | E9: 1d10+2 I | F9: 0 | G9: 原始，柔韧 | H9: 4 | I9: 20 | AI9: 戈洛兽革甲 | AJ9: 手臂 躯干 腿 | AK9: 3 | AL9: 14 | AM9: 60
B10: 加重武器 | C10: 格斗† | D10: — | E10: 2d10 R | F10: 2 | G10: 原始，笨重 | H10: 7 | I10: 70 | K10: 掷弹筒武器 †代表该武器的伤害，破甲，及特性取决于它们发射的榴弹种类 | O10: 投掷 | P10: 投掷武器包括了所有依靠臂力投掷的武器，像飞刀，斧子，短矛等等 除非它们同时具有格斗武器类型，否则不能进行近战（或者在近战中被视为临时武器） 使用投掷武器时，在伤害检定上加上你的力量调整值（手榴弹类武器例外） | U10: 失衡 | V10: 由于沉重并且在攻击后难以控制，这种类型武器在进行格档的时候会受到 −10 惩罚。 | AA10: 过热 | AB10: 某些武器容易过热，这可能是因为设计的问题或者使用了不稳定的能量供应。 当命中检定投出了 91 以上，表示武器过热。然后投1d10 然后对照“武器过热”表查询结果。 | AI10: 链甲外套 | AJ10: 躯干 | AK10: 3 | AL10: 18 | AM10: 50 | AP10: 防弹 | AQ10: 通过使用包含了能够分散和吸收冲击能量的填充物材料，防弹护甲能有效对抗轻武器，榴散弹，冲击波。 在对抗具有爆炸特性的武器时，只要穿戴者不是正好位于爆炸中心，防弹护甲视为具有 5 点 AP。
B11: 战锤 | C11: 格斗 | D11: — | E11: 1d10+1 I | F11: 0 | G11: 原始，失衡 | H11: 4 | I11: 10 | AI11: 封建铠甲 | AJ11: 全身 | AK11: 5 | AL11: 30 | AM11: 120
B12: 临时武器 | C12: 格斗 | D12: — | E12: d10−2 I | F12: 0 | G12: 原始，失衡 | H12: — | I12: — | AI12: 异形兽皮 | AJ12: 躯干 | AK12: 6 | AL12: 22 | AM12: 5000
B13: 刀 | C13: 格斗 投掷 | D13: 3m | E13: 1d5 R | F13: 0 | G13: 原始 | H13: 0.5 | I13: 5 | AI13: 防弹头盔 | AJ13: 头部 | AK13: 2 | AL13: 2 | AM13: 25 | AN13: 防弹
B14: 飞刀或手里剑 | C14: 投掷 | D14: 5m | E14: 1d5 R | F14: 0 | G14: 原始 | H14: 0.5 | I14: 5 | AI14: 防弹护臂 | AJ14: 手臂 | AK14: 2 | AL14: 1 | AM14: 50
B15: 盾 | C15: 格斗 | D15: — | E15: 1d5 I | F15: 0 | G15: 原始，防御 | H15: 3 | I15: 25 | AI15: 轻型防弹外套 | AJ15: 手臂 躯干 腿 | AK15: 2 | AL15: 4 | AM15: 80
B16: 矛 | C16: 格斗，投掷† | D16: 10m | E16: 1d10 R | F16: 0 | G16: 原始 | H16: 3 | I16: 15 | K16: 霰弹类 | O16: 手枪 | P16: 手枪是可以单手开火的武器，并且可以在近战中使用 无论如何，使用者都不会在近战中因为瞄准器具或者距离受到奖励或者惩罚。 有散射属性的手枪在近战中射击视为近距离平射（但不会有通常近距离平射提供的 +30 加值） | U16: 柔韧 | V16: 一些武器由大量松散的链接单元组成，像是锁环，兽皮等，比如鞭子。因为这类武器攻击时的灵活柔软，使它无法被格档。 | AA16: 捕捉 | AB16: 拥有这种特性的武器被设计用以捕捉目标。 通过一次成功的命中，目标必须通过敏捷检定否则被困住。一个被困住的目标除了尝试结束束缚状态外不能有其他动作。在他的行动轮，他可以尝试挣脱（进行力量检定）或是脱逃（进行敏捷检定）。除非成功脱出，否则目标被视为无助。 | AI16: 防弹背心 | AJ16: 躯干 | AK16: 3 | AL16: 5 | AM16: 50 | AP16: 甲壳 | AQ16: 甲壳护甲将多层特制塑钢纤维，陶瓷甲片，以及其他耐用材料复合制造。 它穿起来很重并且无法很好的保护例如关节之类的护甲接缝处，但是综合防护效果远比那些更轻型的护甲来的优秀。
B17: 剑 | C17: 格斗 | D17: — | E17: 1d10 R | F17: 0 | G17: 原始，平衡 | H17: 3 | I17: 15 | AI17: 防弹夹克 | AJ17: 手臂 躯干 腿 | AK17: 3 | AL17: 6 | AM17: 100
B18: 杖 | C18: 格斗† | D18: — | E18: 1d10 I | F18: 0 | G18: 原始，平衡 | H18: 3 | I18: 10 | K18: 武器伤害类型 E=能量、I=冲击 X=爆炸、R=劈刺 | AI18: 防弹斗篷 | AJ18: 全身 | AK18: 3 | AL18: 8 | AM18: 80
B19: 链锯剑 | C19: 格斗 | D19: — | E19: 1d10+2 R | F19: 2 | G19: 平衡，撕裂 | H19: 6 | I19: 275 | J19: 链锯 | AI19: 卫队防弹甲 | AJ19: 全身 | AK19: 4 | AL19: 11 | AM19: 300
B20: 链锯斧 | C20: 格斗 | D20: — | E20: 1d10+4 R | F20: 2 | G20: 撕裂 | H20: 13 | I20: 450 | AI20: 甲壳头盔 | AJ20: 头部 | AK20: 4 | AL20: 2 | AM20: 250 | AN20: 甲壳
B21: 能量刃 | C21: 格斗 | D21: — | E21: 1d10+3 E | F21: 6 | G21: 能量 | H21: 1.5 | I21: 1750 | J21: 能量 | AI21: 甲壳臂铠 | AJ21: 手臂 | AK21: 5 | AL21: 2 | AM21: 300
B22: 能量剑 | C22: 格斗 | D22: — | E22: 1d10+5 E | F22: 6 | G22: 能量，平衡 | H22: 3.5 | I22: 2500 | O22: 基础 | P22: 基本武器指一般情况下需要双手持 用的武器，但是也能够以 −20 的惩 罚单手持用。 | U22: 笨重 | V22: 庞大并且极端沉重，笨重武器太沉重以至于无法用来防御。此类武器不能用来格档。 | AA22: 粗劣 | AB22: 拥有这个特性武器不是由于糟糕的设计就是因为制作手段所限，不管多么小心的使用，也无法比单纯凭运气使用得到更好的结果。 这样的武器无法通过瞄准得到任何加值。 | AI22: 甲壳胫甲 | AJ22: 腿 | AK22: 5 | AL22: 3 | AM22: 375 | AP22: 纤维 | AQ22: 通过特殊设计和一些加工，纤维护甲是由数千个细胞状个体链接形成。 因为其蜂窝状表层使得它重量更轻，并且在受到外力冲击或高温射线时，护甲表层能够在瞬间硬化，以分散攻击的能量。
B23: 震击槌 | C23: 格斗 | D23: — | E23: 1d10 I | F23: 0 | G23: 震击 | H23: 2.5 | I23: 150 | J23: 震击 | AI23: 执行者轻甲壳护甲 | AJ23: 手臂 躯干 腿 | AK23: 5 | AL23: 15 | AM23: 575
B24: 电击链枷 | C24: 格斗† | D24: — | E24: 1d10+2 I | F24: 0 | G24: 震击，柔韧 | H24: 4.5 | I24: 375 | AI24: 甲壳胸铠 | AJ24: 躯干 | AK24: 6 | AL24: 7 | AM24: 600
B25: 远程武器 | AI25: 风暴突击甲壳护甲 | AJ25: 全身 | AK25: 6 | AL25: 17 | AM25: 3750
B26: 名称 | C26: 类型 | D26: 射程 | E26: 射速 | F26: 伤害 | G26: 破甲 | H26: 弹夹 | I26: 装填 | J26: 特性 | K26: 重量 | L26: 花费 | M26: 激光 | AI26: 纤维罩帽 | AJ26: 头部 | AK26: 3 | AL26: 0.5 | AM26: 100 | AN26: 纤维
B27: 激光手枪 | C27: 手枪 | D27: 30m | E27: S/–/– | F27: 1d10+2 E | G27: 0 | H27: 30 | I27: 完整 | J27: 可靠 | K27: 1.5 | L27: 50 | AI27: 纤维护臂 | AJ27: 手臂 | AK27: 3 | AL27: 0.5 | AM27: 120
B28: 激光卡宾枪 | C28: 基本 | D28: 60m | E28: S/2/– | F28: 1d10+2 E | G28: 0 | H28: 40 | I28: 完整 | J28: 可靠 | K28: 3 | L28: 75 | O28: 重型 | P28: 重型武器指正常情况下需要双手，且必须被用某些手段固定后使用的武器，一般是用两脚或者三脚的支撑架，不过窗沿，沙包（如果是 RPG的话，肩膀也可以）也可以起到同样效果，这样不会有任何惩罚。使用一件重型武器而没有任何妥善固定会受到 −30 的射击惩罚，并且无法使用半自动或者全自动方式射击。 | U28: 防御 | V28: 一件防御武器，比如盾牌，可以用来阻挡对手的攻击，但是作为攻击手段是非常难以使用的。防御武器在进行格档的时候可以获得+15 的加值，但是在攻击的时候会受到 −10的减值。 | AA28: 易损 | AB28: 某些武器相比其他的更容易出现哑火，可能是因为糟糕的维护或是设计问题。 一件易损的武器在每一次进行半自动或是全自动射击时，如果出现 91 及更高，就会发生故障。 | AI28: 异型纤维甲 | AJ28: 手臂 躯干 腿 | AK28: 4 | AL28: 2 | AM28: 375 | AP28: 动力装甲 | AQ28: 这种最为沉重和精密的护甲拥有自带的动力设备以增加使用者的力量。 动力装甲会使穿着者的力量增加 20 并且体型增大一级（举例：一个体型为中型人类在穿着后会变为大型）。轻型动力装甲使穿着者的力量增加 10 并且体型不变。你必须穿着躯干，手臂和腿部装甲才能得到该力量加成。动力装甲需要穿着者随身携带能量源为其正常运作提供持续补给（一般都是做成背包状）。一个标准的非军用能量源在再次充能或替换之前，至多可以维持动力装甲 1d5 小时正常运作。
B29: 激光步枪 | C29: 基本 | D29: 100m | E29: S/3/– | F29: 1d10+3 E | G29: 0 | H29: 60 | I29: 完整 | J29: 可靠 | K29: 4 | L29: 75 | AI29: 纤维背心 | AJ29: 躯干 | AK29: 4 | AL29: 1 | AM29: 150
B30: 激光长枪 | C30: 基本 | D30: 150m | E30: S/–/– | F30: 1d10+3 E | G30: 1 | H30: 40 | I30: 完整 | J30: 可靠，精准 | K30: 4.5 | L30: 100 | AI30: 纤维作战斗篷 | AJ30: 全身 | AK30: 4 | AL30: 1.5 | AM30: 350
B31: 单兵激光炮 | C31: 重型 | D31: 300m | E31: S/–/– | F31: 5d10+10 E | G31: 10 | H31: 5 | I31: 2完整 | J31: — | K31: 55 | L31: 5000 | AI31: 轻型动力装甲 | AJ31: 全身 | AK31: 7 | AL31: 40 | AM31: 8500 | AN31: 动力
B32: 自动手枪 | C32: 手枪 | D32: 30m | E32: S/–/6 | F32: 1d10+2 I | G32: 0 | H32: 18 | I32: 完整 | J32: — | K32: 2.5 | L32: 75 | M32: 实体弹 | AI32: 动力装甲 | AJ32: 全身 | AK32: 8 | AL32: 65 | AM32: 15000
B33: 短管左轮 | C33: 手枪 | D33: 30m | E33: S/–/– | F33: 1d10+3 I | G33: 0 | H33: 6 | I33: 2完整 | J33: 可靠 | K33: 1 | L33: 40
B34: 短管连发枪 | C34: 手枪 | D34: 30m | E34: S/3/– | F34: 1d10+3 I | G34: 0 | H34: 9 | I34: 完整 | J34: — | K34: 1.5 | L34: 50 | O34: 多次命中 | U34: 平衡 | V34: 一些武器，比如刀剑，在手柄和锋刃部分的重量上进行了特别设计，使它更容易被挥动。具有平衡特性的武器用于格挡时，WS 检定获得 +10 加值。 | AA34: 可靠 | AB34: 基于多次试验和值得信赖的技术。可靠特性的武器很少出现问题。 当此类武器故障的时候，投 1d10，只有出现 10 的时候才会确实发生故障，否则只是正常射失而已。
B35: 手铳 | C35: 手枪 | D35: 35m | E35: S/–/– | F35: 1d10+4 I | G35: 2 | H35: 5 | I35: 2完整 | J35: — | K35: 3 | L35: 65
B36: 自动步枪 | C36: 基本 | D36: 90m | E36: S/3/10 | F36: 1d10+3 I | G36: 0 | H36: 30 | I36: 完整 | J36: — | K36: 3.5 | L36: 100 | O36: 原始位置 | P36: 第二 | Q36: 第三 | R36: 第四 | S36: 第五 | T36: 其余命中
B37: 来复猎枪 | C37: 基本 | D37: 150m | E37: S/–/– | F37: 1d10+3 I | G37: 0 | H37: 5 | I37: 完整 | J37: 精准 | K37: 5 | L37: 100
B38: 霰弹猎枪 | C38: 基本 | D38: 30m | E38: S/–/– | F38: 1d10+4 I | G38: 0 | H38: 2 | I38: 2完整 | J38: 可靠，散射 | K38: 5 | L38: 60 | O38: 头部 | P38: 头部 | Q38: 手臂 | R38: 躯干 | S38: 手臂 | T38: 躯干
B39: 泵动霰弹枪 | C39: 基本 | D39: 30m | E39: S/–/– | F39: 1d10+4 I | G39: 0 | H39: 8 | I39: 2完整 | J39: 散射 | K39: 5 | L39: 75
B40: 战斗霰弹枪 | C40: 基本 | D40: 30m | E40: S/3/– | F40: 1d10+4 I | G40: 0 | H40: 18 | I40: 完整 | J40: 散射 | K40: 6.5 | L40: 150 | O40: 手臂 | P40: 手臂 | Q40: 躯干 | R40: 头部 | S40: 躯干 | T40: 手臂 | U40: 撕裂 | V40: 撕裂武器是一种恶毒的，利用大量快速移动的锯齿撕裂血肉的装置。 这些武器在投伤害时投一个额外伤害骰，之后去掉一个点数最小的骰子。 | AA40: 爆炸 | AB40: 许多导弹，榴弹，以及一些枪械在击中目标的时候会引发爆炸。 当具有爆炸特性的武器发射之后，任何位于武器爆炸半径范围内的目标都会受到伤害。需要为每一个受到爆炸影响的人分别投命中位置和伤害。
B41: 重机枪 | C41: 重型 | D41: 120m | E41: –/–/10 | F41: 1d10+4 I | G41: 3 | H41: 200 | I41: 2完整 | J41: — | K41: 35 | L41: 750
B42: 爆矢手枪 | C42: 手枪 | D42: 30m | E42: S/2/– | F42: 1d10+5 X | G42: 4 | H42: 8 | I42: 完整 | J42: 撕裂 | K42: 3.5 | L42: 250 | M42: 爆矢 | O42: 躯干 | P42: 躯干 | Q42: 手臂 | R42: 头部 | S42: 手臂 | T42: 躯干
B43: 爆矢枪 | C43: 基本 | D43: 90m | E43: S/2/– | F43: 1d10+5 X | G43: 4 | H43: 24 | I43: 完整 | J43: 撕裂 | K43: 7 | L43: 500
B44: 重型爆矢枪 | C44: 重型 | D44: 120m | E44: –/–/10 | F44: 2d10+3 X | G44: 5 | H44: 60 | I44: 2完整 | J44: 撕裂 | K44: 40 | L44: 2000 | O44: 腿 | P44: 腿 | Q44: 躯干 | R44: 手臂 | S44: 头部 | T44: 躯干
B45: 炽热手枪 | C45: 手枪 | D45: 10m | E45: S/–/– | F45: 2d10+4 E | G45: 12 | H45: 3 | I45: 完整 | J45: — | K45: 2.5 | L45: 7500 | M45: 热熔
B46: 热熔枪 | C46: 基本 | D46: 20m | E46: S/–/– | F46: 2d10+4 E | G46: 12 | H46: 5 | I46: 2完整 | J46: — | K46: 8 | L46: 4000 | O46: 武器过热 | U46: 能量 | V46: 这种类型的武器可以产生一个环绕在武器上的能量场，增加伤害和破甲效果。 这些效果已经包括在武器的数据当中。另外，使用这种武器成功格档一件不具有该属性的武器时，你有75%的几率毁坏对方武器。 | AA46: 烟雾 | AB46: 这种武器并非造成伤害，而是产生大量烟雾覆盖一片地区。 当一件有烟雾特性的武器射击之后，会以落点圆心，3d10 米直径范围内产生掩护性的烟雾。这些烟雾最多持续 2d10 轮，之后消散，天气会对烟雾持续时间造成影响。
B47: 等离子手枪 | C47: 手枪 | D47: 30m | E47: S/–/– | F47: 1d10+6 E | G47: 6 | H47: 10 | I47: 4完整 | J47: 充能，过热 | K47: 4 | L47: 4000 | M47: 等离子
B48: 等离子枪 | C48: 基本 | D48: 90m | E48: S/2/– | F48: 1d10+6 E | G48: 6 | H48: 20 | I48: 8完整 | J48: 充能，过热 | K48: 11 | L48: 3000 | O48: d10 | P48: 结果
B49: 火焰手枪 | C49: 手枪 | D49: 10m | E49: S/–/– | F49: 1d10+4 E | G49: 2 | H49: 2 | I49: 2完整 | J49: 火焰 | K49: 3.5 | L49: 200 | M49: 火焰
B50: 火焰喷射器 | C50: 基本 | D50: 20m | E50: S/–/– | F50: 1d10+4 E | G50: 3 | H50: 3 | I50: 2完整 | J50: 火焰 | K50: 6 | L50: 300 | O50: 1–5 | P50: 使用者必须通过坚韧检定否则扔掉武器，武器在 1d10 轮内无法使用。
B51: 绳球套索 | C51: 投掷 | D51: 10m | E51: S/–/– | F51: — | G51: 0 | H51: 1 | I51: — | J51: 原始，捕捉，粗劣 | K51: 1.5 | L51: 10 | M51: 原始
B52: 手弩 | C52: 手枪 | D52: 15m | E52: S/–/– | F52: 1d10 R | G52: 0 | H52: 1 | I52: 完整 | J52: 原始 | K52: 1 | L52: 200 | U52: 震击 | V52: 震击武器可以通过一阵巨大的能量冲击打晕目标。 计算防护和坚韧加值之后，如果目标至少受到震击武器 1 点伤害，那么必须进行坚韧检定，但是被命中位置的每点防护值都会为该检定提供 +10 加值。如果失败，那么目标会眩晕相当于受到伤害值一半的轮数。 | AA52: 淬毒 | AB52: 有的武器依靠毒药造成伤害。 在计算护甲和坚韧加值之后，如果受到淬毒武器的伤害，必须以 -5/每点伤害的惩罚进行坚韧检定。成功表示毒素没有对你造成影响。失败会立刻受到 1d10 点毒素伤害，坚韧和护甲均无法防止此伤害。
B53: 燧发手枪 | C53: 手枪 | D53: 15m | E53: S/–/– | F53: 1d10+2 I | G53: 0 | H53: 1 | I53: 3完整 | J53: 原始，易损，粗劣 | K53: 4 | L53: 10 | O53: 6–8 | P53: 用者受到 1d10+2 的能量伤害并且扔掉武器。武器太热以至于在 1d10轮内无法使用，任何尝试的人受到1d10+1 能量伤害。
B54: 滑膛枪 | C54: 基本 | D54: 30m | E54: S/–/– | F54: 1d10+2 I | G54: 0 | H54: 1 | I54: 5完整 | J54: 原始，易损，粗劣 | K54: 7 | L54: 30
B55: 弓 | C55: 基本 | D55: 30m | E55: S/–/– | F55: 1d10 R | G55: 0 | H55: 1 | I55: 部分 | J55: 原始，可靠 | K55: 2 | L55: 10
B56: 投石索 | C56: 基本 | D56: 15m | E56: S/–/– | F56: 1d10−2 I | G56: 0 | H56: 1 | I56: 完整 | J56: 原始 | K56: 0.5 | L56: 10 | O56: 9–10 | P56: 武器爆炸并且损坏。 使用者以及任何位于他 4 米内的人受到等同于该武器一次攻击的伤害。
B57: 十字弩 | C57: 基本 | D57: 30m | E57: S/–/– | F57: 1d10 R | G57: 0 | H57: 1 | I57: 2完整 | J57: 原始 | K57: 3 | L57: 10
B58: 榴弹发射器 | C58: 基本 | D58: 60m | E58: S/–/– | F58: † | G58: † | H58: 6 | I58: 完整 | J58: † | K58: 9 | L58: 500 | M58: 掷弹筒 | U58: 可靠 | V58: 基于多次试验和值得信赖的技术。可靠特性的武器很少出现问题。 当此类武器故障的时候，投 1d10，只有出现 10 的时候才会确实发生故障，否则只是正常射失而已。 | AA58: 火焰 | AB58: 火焰特性的武器能够向射程内的物体喷射一道锥形火焰。和其他武器不同，火焰武器只有一种射程类型，并且当开火的时候，在攻击范围内喷射炽热的死亡。 使用具有火焰特性武器的人并不需要进行射击技能检定，开火就好了。任何处在火焰喷射路径上，一个顶角 30度，半径为标准射程的锥形范围内的所有目标，必须进行敏捷检定躲避否则受到火焰的正常伤害。如果受伤，那么需要进行第二次敏捷检定以扑灭身上的火。 掩蔽无法保护角色不受到火焰武器的攻击。因为火焰武器不需要进行攻击检定，他们总是能够击中范围内的家伙，所以当投伤害时出现９，视为武器故障。如果没有相应的天赋，或者没有支撑使用重型武器，使用者的命中检定会受到−20/−30 减值。火焰武器由于不需进行命中检定，则发生上述情况时，改为被攻击者的敏捷检定得到 +20/+30 加值。
B59: 火箭推进器 | C59: 重型 | D59: 120m | E59: S/–/– | F59: † | G59: † | H59: 1 | I59: 完整 | J59: † | K59: 15 | L59: 1200 | O59: 爆炸事故表
B60: 毒针手枪 | C60: 手枪 | D60: 30m | E60: S/–/– | F60: 1d10 R | G60: 0 | H60: 6 | I60: 完整 | J60: 精准，淬毒 | K60: 1.5 | L60: 1250 | M60: 特种
B61: 捕网手枪 | C61: 手枪 | D61: 30m | E61: S/–/– | F61: — | G61: 0 | H61: 1 | I61: 完整 | J61: 捕捉 | K61: 3.5 | L61: 1200 | O61: d10 | P61: 结果
B62: 毒针来复枪 | C62: 基本 | D62: 180m | E62: S/–/– | F62: 1d10 R | G62: 0 | H62: 6 | I62: 2完整 | J62: 精准，淬毒 | K62: 2 | L62: 1000
B63: 网枪 | C63: 基本 | D63: 50m | E63: S/–/– | F63: — | G63: 0 | H63: 1 | I63: 完整 | J63: 爆炸(5)，捕捉 | K63: 8 | L63: 1800 | O63: 1–5 | P63: 哑弹。榴弹没有爆炸,如果是用掷弹筒发射,武器在下次开火之前必须重新装填。
B64: 弹药和榴弹 | U64: 精准 | V64: 一些武器在被拥有冷静头脑和灵巧双手的人操作会产生更好的效果。 当进行瞄准射击时，BS 检定获得额外 +10 加值。注意该加值只在瞄准射击时有效。另外，瞄准之后进行单发射击的话，命中检定每得到两个成功度，该次射击的伤害 +1d10 ，最多 +2d10 。
B65: 名称 | C65: 类型/数量 | D65: 伤害 | E65: 破甲 | F65: 特性/适配 | G65: 重量 | H65: 花费 | I65: 榴弹
B66: 破片榴弹 | C66: 投掷 | D66: 2d10 X | E66: 0 | F66: 爆炸(4) | G66: 0.5 | H66: 10 | O66: 6–8 | P66: 看起来应该没事......。什么都没有发生,下一轮再投一次 1d10 决定结果。
B67: 穿甲榴弹 | C67: 投掷 | D67: 2d10+4 X | E67: 6 | F67: — | G67: 0.5 | H67: 50
B68: 烟幕榴弹 | C68: 投掷 | D68: 特殊 | E68: 0 | F68: 烟雾 | G68: 0.5 | H68: 25
B69: 致幻榴弹 | C69: 投掷 | D69: 特殊 | E69: 0 | F69: — | G69: 0.5 | H69: 40 | O69: 9–10 | P69: 轰!榴弹立刻以角色为中心爆炸。如果是由掷弹筒发射,那么会在弹舱内爆炸,这种情况下也会导致武器损坏。
B70: 燃烧榴弹 | C70: 投掷 | D70: 1d10+3 E | E70: 6 | F70: 爆炸(3) | G70: 0.5 | H70: 5 | U70: 散射 | V70: 这种武器的标准弹药在射击之后会分裂，进行多次打击。 如果命中一个射程内敌人，每两个成功度会造成一次额外命中（命中位置见“多次命中”表）。因为这些分裂后的射弹减小了冲击效力。所有的护甲在这些武器的远距离和超远距离射击时防护值加倍。
B71: 闪光榴弹 | C71: 投掷 | D71: 特殊 | E71: 0 | F71: — | G71: 0.5 | H71: 60
B72: 箭/矢 | C72: 20 | D72: — | E72: — | F72: 弓弩，原始武器 | G72: 0 | H72: 1 | I72: 弹药
B73: 弹丸 | C73: 20 | D73: — | E73: — | F73: 燧发、滑膛，原始武器 | G73: 0 | H73: 1
B74: 子弹 | C74: 20 | D74: — | E74: — | F74: 实体武器 | G74: 0 | H74: 1
B75: 霰弹 | C75: 20 | D75: — | E75: — | F75: 霰弹，实体武器 | G75: 0 | H75: 1
B76: 达姆弹 | C76: 6 | D76: — | E76: — | F76: 非自动手枪、手枪，实体武器 | G76: 0 | H76: 5
B77: 大威力杀伤弹 | C77: 6 | D77: — | E77: — | F77: 非霰弹、重型，实体武器 | G77: 0 | H77: 5
B78: 充能匣（手枪） | C78: 满仓 | D78: — | E78: — | F78: 手枪，激光武器 | G78: 0 | H78: 10
B79: 充能匣（基础） | C79: 满仓 | D79: — | E79: — | F79: 基础，激光武器 | G79: 0 | H79: 15
B80: 充能匣（重型） | C80: 满仓 | D80: — | E80: — | F80: 重型，激光武器 | G80: 0 | H80: 30
B81: 过载充能匣 | C81: 满仓 | D81: — | E81: — | F81: 基本、手枪，激光武器 | G81: 0 | H81: 15
B82: 放射性充能匣 | C82: 1 | D82: — | E82: — | F82: 非重型，激光武器 | G82: 0 | H82: 15
B83: 燃料罐（手枪） | C83: 满仓 | D83: — | E83: — | F83: 手枪，火焰武器 | G83: 0 | H83: 8
B84: 燃料罐（基础） | C84: 满仓 | D84: — | E84: — | F84: 基础，火焰武器 | G84: 0 | H84: 10
B85: 爆矢弹 | C85: 1 | D85: — | E85: — | F85: 爆矢武器 | G85: 0 | H85: 16
B86: 炽热弹 | C86: 1 | D86: — | E86: — | F86: 霰弹与爆矢武器 | G86: 0 | H86: 18
B87: 热熔筒（手枪） | C87: 满仓 | D87: — | E87: — | F87: 手枪，热熔武器 | G87: 0 | H87: 20
B88: 热熔筒（基础） | C88: 满仓 | D88: — | E88: — | F88: 基础，热熔武器 | G88: 0 | H88: 15
B89: 等离子瓶（手枪） | C89: 满仓 | D89: — | E89: — | F89: 手枪，等离子武器 | G89: 0 | H89: 24
B90: 等离子瓶（基础） | C90: 满仓 | D90: — | E90: — | F90: 基础，等离子武器 | G90: 0 | H90: 18
B91: 特种 | C91: 1 | D91: — | E91: — | F91: 特种武器 | G91: 0 | H91: 20

Sheet 详情速查
B2: 物品详细信息查找处 | L2: 技能具体详情速查处 | W2: 名称 | X2: 购买物物品简要信息（购买精简，详细去查找处） | Y2: 重量 | Z2: 花费 | AA2: 稀有度 | AB2: 类型
W3: 背包 | X3: 大口袋背包，承重最多50kg | Y3: 1 | Z3: 10 | AA3: 丰富 | AB3: 服装
B4: 名称 | D4: 详细信息 | L4: 天赋名称 | O4: 详细信息 | W4: 卡梅莱林斗篷 | X4: 躲藏+20，不动时被射击的话视为双倍距离外 | Y4: 0.5 | Z4: 500 | AA4: 稀有 | AB4: 服装
D5: =_xlfn.IFNA(IF(B5=0,"",VLOOKUP(B5,附表!AC2:AH70,2,FALSE)),"") | O5: =_xlfn.IFNA(IF(L5=0,"",VLOOKUP(L5,附表!AQ5:附表!AT52,4,FALSE)),"") | W5: 护身符 | X5: 可以为佩戴者带来帝皇慈悲指引的小饰物 | Y5: — | Z5: 特殊 | AA5: 一般 | AB5: 服装
W6: 计时器 | X6: 手持或手腕上的时间记录装置 | Y6: — | Z6: 40 | AA6: 充裕 | AB6: 服装
B7: 重量 | C7: 花费 | W7: 缆线盒 | X7: 在垂直表面攀爬获+30，检定失败也不会掉落 | Y7: 2 | Z7: 25 | AA7: 普及 | AB7: 服装
B8: =_xlfn.IFNA(IF(B5=0,"",VLOOKUP(B5,附表!AC2:AH70,3,FALSE)),"") | C8: =_xlfn.IFNA(IF(B5=0,"",VLOOKUP(B5,附表!AC2:AH70,4,FALSE)),"") | L8: 描述 | W8: 服装 | X8: 各种各样的服装服饰 | Y8: — | Z8: 特殊 | AA8: 充裕 | AB8: 服装
B9: 稀有度 | L9: =_xlfn.IFNA(IF(L5=0,"",VLOOKUP(L5,附表!AQ5:附表!AT52,2,FALSE)),"") | W9: 爆破项圈 | X9: 爆炸时佩戴者死亡且产生半径3m1d10爆炸伤害 | Y9: 1 | Z9: 55 | AA9: 稀有 | AB9: 服装
B10: =_xlfn.IFNA(IF(B5=0,"",VLOOKUP(B5,附表!AC2:AH70,5,FALSE)),"") | W10: 过滤塞 | X10: 塞鼻孔后对抗毒气的坚韧+20 | Y10: — | Z10: 15 | AA10: 普及 | AB10: 服装
B11: 类型 | W11: 红外目镜 | X11: 温血动物热量可视化，不怕黑暗，夜晚视力+20 | Y11: 0.5 | Z11: 275 | AA11: 稀有 | AB11: 服装
B12: =_xlfn.IFNA(IF(B5=0,"",VLOOKUP(B5,附表!AC2:AH70,6,FALSE)),"") | L12: 属性 | W12: 成像面罩 | X12: 获得黑暗视觉特性，优秀品质免疫闪光弹 | Y12: 0.5 | Z12: 100 | AA12: 匮乏 | AB12: 服装
L13: =_xlfn.IFNA(IF(L5=0,"",VLOOKUP(L5,附表!AQ5:附表!AT52,3,FALSE)),"") | W13: 循环呼吸器 | X13: 免除毒气，水下存活，滤毒罐1h后需完整动作更换（滤毒罐一个25g，重量可忽略） | Y13: 1 | Z13: 50 | AA13: 匮乏 | AB13: 服装
W14: 缓冲手套 | X14: 单手使用基础武器不承受−20的减值 | Y14: 0.5 | Z14: 85 | AA14: 稀有 | AB14: 服装
W15: 防毒面具 | X15: 对抗毒气的坚韧+30，失败可重投 | Y15: 0.5 | Z15: 25 | AA15: 一般 | AB15: 服装
W16: 太空服 | X16: 可对抗有害环境，内置循环呼吸器，可真空存活 | Y16: 8 | Z16: 100 | AA16: 丰富 | AB16: 服装
W17: 生化皮肤 | X17: 无甲时+2甲，潜行躲避+10，红外/黑暗视觉不可见 | Y17: 2 | Z17: 2500 | AA17: 罕见 | AB17: 服装
W18: 占卜盒/扫描仪 | X18: 警觉+20，可使用技术应用扫描肉眼不可见的东西， 会被50cm+ 的墙壁或防护阻挡侦测 | Y18: 0.5 | Z18: 145 | AA18: 匮乏 | AB18: 消耗品
W19: 自动书写笔 | X19: 精准快速的复制文本，生计（抄写员） +10 | Y19: — | Z19: 55 | AA19: 匮乏 | AB19: 药物
W20: 组合工具 | X20: 一套通用工具，技术应用 +10 | Y20: 1 | Z20: 200 | AA20: 稀有 | AB20: 药物
B21: 天赋具体详情速查处 | W21: 数据板 | X21: 被广泛使用，用来记录和读取编辑完成的文本或是其他的音频和视频数据 | Y21: 0.5 | Z21: 25 | AA21: 普及 | AB21: 消耗品
W22: 爆破药 | X22: 造成 3d10 加每公斤 2 点的爆炸伤害，范围每公斤5米。 | Y22: 1 | Z22: 250 | AA22: 匮乏 | AB22: 消耗品
B23: 天赋名称 | D23: 详细信息 | W23: 刑讯工具 | X23: 一套花样百出的刑具，审讯+20 | Y23: 1 | Z23: 375 | AA23: 罕见 | AB23: 消耗品
D24: =_xlfn.IFNA(IF(B24=0,"",VLOOKUP(B24,附表!W3:附表!X126,2,FALSE)),"") | W24: 照明球/发光器 | X24: 照亮 12 米的距离。可以持续工作1d5h | Y24: 0.5 | Z24: 15 | AA24: 充裕 | AB24: 药物
W25: 抓钩 | X25: 钩中目标后，可徒手攀爬或通过绞盘把自己拉上去 | Y25: 2 | Z25: 30 | AA25: 普及 | AB25: 消耗品
W26: 激光切割刀 | X26: 切割，焊枪，每轮可处理 10cm 的金属（根据材质稍有不同） | Y26: 4 | Z26: 65 | AA26: 一般 | AB26: 消耗品
B27: 先决条件 | W27: 多功能望远镜 | X27: 放大观察远距离目标 | Y27: 0.5 | Z27: 55 | AA27: 一般 | AB27: 消耗品
B28: =_xlfn.IFNA(IF(B24=0,"",VLOOKUP(B24,附表!W3:附表!Y126,3,FALSE)),"") | W28: 镣铐 | X28: 一种枷锁，用来禁锢他人 | Y28: 1 | Z28: 35 | AA28: 丰富 | AB28: 消耗品
W29: 微型通讯器 | X29: 短距离通讯，可在一公里之内清晰的传递讯息。 | Y29: — | Z29: 20 | AA29: 一般 | AB29: 药物
W30: 万能钥匙 | X30: 对开锁时的侵入+30 | Y30: — | Z30: 150 | AA30: 匮乏 | AB30: 药物
L31: 生化义肢 | W31: 图像记录仪 | X31: 简易记录装置，可将储存的信息重放 | Y31: 1 | Z31: 100 | AA31: 一般 | AB31: 药物
W32: 灵能法器 | X32: 灵能者使用法器进行专注时，检定 +10 | Y32: — | Z32: 100 | AA32: 稀有 | AB32: 工具
L33: 生化义肢被假定具有与同它们连接的身体相当的力量和敏捷（而不会出现过度用力就被从身上扯下来的情况），但由于它们的机械化构造，使得在抵抗针对该部位的伤害时，角色的坚韧加值视为 +2 。对于生化义肢的伤害视同作用于角色本身，致命效果照常计算，但撕裂武器导致的失血效果对生化义肢无效。对生化义肢造成足够的伤害同样能导致角色死亡，可以视为义肢炸裂的碎片，高温，或者贮存的能量外泄等对角色造成了致命的伤害。义肢和额外肢体（例如机械附肢）功能的充分发挥依赖于角色的知识。举例而言，只有具有医疗技能的角色才能得到医疗附肢的好处。注意生化义肢的奖励和惩罚都仅在你使用它时生效。移植了两条同样的生化义肢不会使奖励翻倍。 #机械附肢是技术神甫常用的强化设备，通常装在肩部或胸部。一名技术神甫能安装的机械附肢数量不超过他的坚韧加值。 | W33: 尖叫报警器 | X33: 使用须GM暗投技术应用并成功，尖叫报警器感知属性75点，声音传播范围一公里 | Y33: 2 | Z33: 140 | AA33: 匮乏 | AB33: 工具
D34: 药物使用过量 | W34: 声波干扰器 | X34: 潜行+30，可以维持 20 分钟，之后须充能1h | Y34: 2 | Z34: 25 | AA34: 一般 | AB34: 工具
W35: 收发报机 | X35: 使用需进行+10的技术应用。 | Y35: 4 | Z35: 300 | AA35: 匮乏 | AB35: 工具
D36: 频繁服用同一种药物，尤其是在短时间内这样，会有一定几率导致药物无法正常起效。这表现为侍僧的身体开始对药物产生一定的耐药性。如果想要在 24 小时之内重复服用同一种药物，角色必须以−20的减值（反复服药减值累加）通过一次坚韧检定，如果失败，24小时之内服用同样药物不会对角色产生任何影响。 | W36: 书写工具组 | X36: 纸张，墨水，羽毛笔 | Y36: 2 | Z36: 20 | AA36: 普及 | AB36: 工具
W37: 蒸馏酒 | X37: 一种由葡萄酒蒸馏出来的酒精流行饮料 | Y37: — | Z37: 50 | AA37: 匮乏 | AB37: 工具
W38: 解毒剂（药物） | X38: 立刻终止药品毒素空气的任何影响，无论好坏，但有特例 | Y38: — | Z38: 65 | AA38: 稀有 | AB38: 工具
W39: 暴怒（药物） | X39: 1d10min狂暴天赋和无视恐惧 | Y39: — | Z39: 95 | AA39: 罕见 | AB39: 工具
W40: 注射器 | X40: 消耗完整动作储存药物 | Y40: — | Z40: 5 | AA40: 充裕 | AB40: 工具
W41: 卷烟 | X41: 具有特殊香气，微量麻醉（和上瘾）性物质 | Y41: — | Z41: 10 | AA41: 普及 | AB41: 工具
W42: 医疗箱 | X42: 消耗品，每次医疗+20，内含6个兴奋剂 | Y42: 2 | Z42: 150 | AA42: 普及 | AB42: 工具
W43: 愚民粉（药物） | X43: 使用后梦游般1d5h，战斗中使用如制幻榴弹 | Y43: — | Z43: 28 | AA43: 稀有 | AB43: 工具
W44: 压缩食物 | X44: 是经过加工后密封包装，看外表难推测出里面是啥 | Y44: — | Z44: 10 | AA44: 丰富 | AB44: 工具
W45: 雷诺咖啡 | X45: 由植物叶片或花瓣粉碎酿造，热饮，提神醒脑 | Y45: — | Z45: 5 | AA45: 充裕 | AB45: 工具
W46: 劣质烈酒 | X46: 一种经过发酵的液体，低档饮料 | Y46: — | Z46: 10 | AA46: 充裕 | AB46: 工具
W47: 祝福机油 | X47: 完整动作涂抹武器空弹前免疫干扰或终止干扰 | Y47: — | Z47: 150 | AA47: 罕见 | AB47: 工具
W48: 屠杀（药物） | X48: 2d10min内敏捷感知+3，药效结束后过坚韧 | Y48: — | Z48: 75 | AA48: 匮乏 | AB48: 工具
W49: 鬼灵（药物） | X49: 暂时赋予灵能或增强灵能（详见“随机灵能”表） | Y49: — | Z49: 395 | AA49: 稀有 | AB49: 工具
W50: 兴奋剂（药物） | X50: 3d10轮内角色忽视伤害重击不良结果，无法被眩晕，药效结束后1h内力量，坚韧，敏捷−20 | Y50: — | Z50: 20 | AA50: 一般 | AB50: 工具
W51: 生化手臂 | X51: 粗糙：与部位相关的快速反应动作时敏捷减半，持械时 WS/BS−10 。极品：与部位相关的快速反应动作时敏捷+10 ，力量+10。 | Y51: — | Z51: 1000 | AA51: 匮乏 | AB51: 生化义肢
W52: 生化移动装置（腿，臀部，骨盆等） | X52: 粗糙：移动速率减半（向上取整），且在尝试奔跑时需进行敏捷检定，否则会在移动终点跌倒。极品：赋予角色飞跑天赋，跳跃时运动+20 。 | Y52: — | Z52: 1500 | AA52: 匮乏 | AB52: 生化义肢
W54: 生化呼吸系统 | X54: 毒气和缺氧环境坚韧+20。粗糙：使用时潜行−20 。剧烈运动相关鉴定难度提高一级。极品：视为一套独立的生命维持系统。 | Y54: — | Z54: 800 | AA54: 稀有 | AB54: 生化义肢
W56: 螺旋传感阵列 | X56: 使用花费一个部分动作。普通=标准占卜盒。粗糙只有一种探测能力：热，辐射，或电磁，且有效距离20 米。极品允许重投使用时进行的基于感知属性的检定。 | Y56: — | Z56: 1000 | AA56: 稀有 | AB56: 植入物
... W83: 格斗附件 | X83: 近战附件可以加装在几乎所有的远程武器上，加装了格斗附件的武器在近战中视为矛。 | Y83: +2kg | Z83: 25 | AA83: 丰富 | AB83: 武器 改装/升级
W85: 单分子 | X85: 武器必须有刃才能适用此种改装，单分子武器破甲+2，且不视为原始武器。 | Y85: 0 | Z85: 40 | AA85: 匮乏 | AB85: 武器 改装/升级
W87: 激光指示器 | X87: 加装了激光指示器的武器在进行单发射击时 BS+10。 | Y87: +0.5kg | Z87: 50 | AA87: 匮乏 | AB87: 武器 改装/升级
W89: 消声器 | X89: 想要通过警觉检定发现消音武器开火的声音需要受到-20的惩罚，并且有效警觉距离也要减半。 | Y89: +0.5kg | Z89: 15 | AA89: 丰富 | AB89: 武器 改装/升级
W91: 高倍瞄准镜 | X91: 在进行完整动作瞄准后可以忽视远距离和超远距离射击惩罚。 | Y91: +1kg | Z91: 35 | AA91: 一般 | AB91: 武器 改装/升级
W93: 每种武器改装的适用范围详见物品详细信息查找处

Sheet 车卡指南
B2: 1 .选择出生地 | P2: DH车卡战斗入门指南 指南制作者们：晨星、IAN、五三点九 引言：论扩展与规则书与本指南的使用指南 关于扩展内容是什么？ 扩展旨在丰富核心规则外的游玩体验（如新增出身、NPC及装备等），在使用扩展之前，需提前咨询你的GM。 本指南仅引用《【CBR】黑暗异端1版核心规则书》部分内容。 旨在提供一份仅供参考的DH车卡战斗流程入门指南，而非黑暗异端圣典。 强烈建议搭配“规则书本体”使用。若指南内容与规则书或 GM 的裁定有冲突，请以规则书原文或GM为准。 对于指南中未提及且无标注的扩展数据，请自行查阅对应资料文件或询问GM。 规则资料查找链接如下 黑暗异端不全书项目地址：https://github.com/VolEurr0Se/DH1e_chm/releases 使用github需要一定的灵能使用知识（懂得都懂）。 在上述地址中你可以获得规则，资源，及自动卡。 如果无法使用github↓ 翻译：译辞修会圣杯分部 【战锤40K TRPG《黑暗异端》全出身世界整合】网页地址：https://b23.tv/EmRikwu 【战锤40K TRPG《黑暗异端》全背景包整合-哔哩哔哩】网页地址： https://b23.tv/byypIYv 另外，如想交流战锤跑团相关，可以加入qq群 963502363
B4: 在四个核心规则、或扩展规则的出生地中任选其一。
B6: 它决定了你的侍僧的基础技能、属性加减值及独特特性等（详见《核心规则书》第15 页，扩展见https://b23.tv/EmRikwu）。
B8: 生涯（职业）选择范围
B10: 出生地直接限制了可选的职业（生涯）范围。如“蛮荒世界”无法选择“技术神甫”。
B12: （详见附页“出身世界和对应可选职业”）
B14: 2 .投掷属性骰
B16: 侍僧在基本生理、心理、格斗射击上的强弱。共9 项：格斗能力、射击能力、力量、坚韧、敏捷、智力、感知、意志、交际。
B18: 投掷属性
B20: 投掷2d10（网团：r9#2d10）得出属性基本值。
B22: 属性基本值+对应出身世界调整值=侍僧的基础属性值。
B24: （详见附页“出身世界和对应初始属性加成”）
B26: 一次重投机会
... B30: 属性加值
P31: =_xlfn.DISPIMG("ID_4EBE80AC15F543A096196B1DBCE013B0",1) -> =DISPIMG("ID_4EBE80AC15F543A096196B1DBCE013B0",1)
B32: 属性加值=最终属性值÷10（向下取整）。
B34: 示例：45 坚韧=坚韧+4；36 交际=交际+3。
B36: 格斗技巧（WS）
B38: 影响使用近战时的近战命中率。
B40: 远程技巧（BS）
B42: 影响使用远程、投掷时的远程命中率。
B44: 力量（S）：肌肉、力量的强度。
B46: 进行近战攻击时，伤害骰会额外加上力量加值，影响最终近战伤害。
B48: 坚韧（T）：对创伤、环境的忍耐力。
B50: 受到攻击时，需减去等同于坚韧加值的伤害，影响最终承伤。
B52: 示例：伤害7 -坚韧4 =真实伤害3。
B54: 敏捷（Ag）：速度、反应与平衡。
... B66: 意志（WP）：我是罗格·多恩。
P67: 出身世界和对应可选职业（可自由选择与出身世界相对应的可选职业，也可投掷d100随机职业）
B68: 直接决定灵能使用及灵能相关技能的成功率；同时也是恐惧判定是否成功的依据。
P69: 出身 | R69: 文员 | S69: 法务官 | T69: 杀手 | U69: 修女会 | V69: 牧师 | W69: 卫队士兵 | X69: 帝国灵能者 | Y69: 流氓 | Z69: 技术神甫
B70: 交际（Fel）：社交手腕、魅力与领导力。 | P70: 帝国世界 | R70: 01~11 | S70: 12~23 | T70: 24~33 | U70: 34~42 | V70: 43~54 | W70: 55~65 | X70: 66~77 | Y70: 78~89 | Z70: 90~100
P71: 巢都世界 | R71: 不可选 | S71: 01~17 | T71: 18~20 | U71: 不可选 | V71: 21~25 | W71: 26~35 | X71: 36~40 | Y71: 41~79 | Z71: 80~100
B72: 影响与NPC 互动时社交技能的投骰结果，影响侍僧的人际交往能力。 | P72: 蛮荒世界 | R72: 不可选 | S72: 不可选 | T72: 01~30 | U72: 不可选 | V72: 不可选 | W72: 31~80 | X72: 81~90 | Y72: 91~100 | Z72: 不可选
P73: 虚空生人 | R73: 01~10 | S73: 11~20 | T73: 21~25 | U73: 不可选 | V73: 26~35 | W73: 不可选 | X73: 36~75 | Y73: 76~85 | Z73: 86~100
B74: 属性与技能间的关系 | P74: 忠嗣学院 | R74: 01~20 | S74: 21~40 | T74: 不可选 | U74: 41~60 | V74: 61~80 | W74: 81~100 | X74: 不可选 | Y74: 不可选 | Z74: 不可选
P75: 铸造世界 | R75: 01~25 | S75: 不可选 | T75: 26~35 | U75: 不可选 | V75: 图兰舒什限定 | W75: 36~60 | X75: 伊杜梅亚限定 | Y75: 61~70 | Z75: 71~100
B76: 技能分为基础和高级两类，属性高低会直接决定对应技能的技能值，具体如下有三种情况： | P76: 贵族生人 | R76: 01~18 | S76: 19~30 | T76: 31~40 | U76: 不可选 | V76: 41~56 | W76: 57~75 | X76: 76~85 | Y76: 86~100 | Z76: 不可选
P77: 思维洗涤 | R77: 不可选 | S77: 01~15 | T77: 16~50 | U77: 不可选 | V77: 51~60 | W77: 61~80 | X77: 81~90 | Y77: 不可选 | Z77: 91~100
B78: 已受训的技能 | P78: 圣殿世界 | R78: 01~10 | S78: 11~18 | T78: 19~30 | U78: 31~55 | V78: 56~80 | W78: 81~100 | X78: 不可选 | Y78: 不可选 | Z78: 不可选
P79: 役从门生 | R79: 01~20 | S79: 21~32 | T79: 不可选 | U79: 不可选 | V79: 33~60 | W79: 不可选 | X79: 61~80 | Y79: 81~100 | Z79: 不可选
B80: 如果你已经学习过某项技能（即“已受训”），那么，该技能的技能值将完全等同于你对应的属性值。 | P80: 修院栽培 | R80: 01~25 | S80: 不可选 | T80: 26~50 | U80: 51~60 | V80: 61~85 | W80: 85~95 | X80: 不可选 | Y80: 96~100 | Z80: 不可选
B82: •未受训的基础技能
P83: 出身世界和对应初始属性的加成
B84: 对于基础技能，即使你没有专门学习过（未受训），依然可以使用，但能力会打折扣，只会按对应属性值的一半来计算。 | P84: 侍僧的属性数值由投掷2d10 + 以下九个属性的具体调整值而得出。 | X84: 蓝底 | Y84: 额外增加 | Z84: 橙底 | AA84: 额外减少
P85: 出身 | Q85: 类型 | S85: WS | T85: BS | U85: S | V85: T | W85: AG | X85: INT | Y85: PER | Z85: WP | AA85: FEL
B86: •未受训的高级技能 | P86: 帝国世界 | Q86: 核心内容 | S86: 20 | T86: 20 | U86: 20 | V86: 20 | W86: 20 | X86: 20 | Y86: 20 | Z86: 20+3 | AA86: 20
P87: 马卡贝斯五号 | Q87: 帝国世界的扩展 | S87: 20 | T87: 20 | U87: 20 | V87: 20-3 | W87: 20 | X87: 20 | Y87: 20 | Z87: 20 | AA87: 20
B88: 高级技能门槛较高，通常情况下，如果你没有经过专门训练（未受训），是无法使用的。 | P88: 锡诺菲亚 | Q88: 帝国世界的扩展 | S88: 20 | T88: 20 | U88: 20 | V88: 20 | W88: 20 | X88: 20 | Y88: 20+5 | Z88: 20-3 | AA88: 20-3
P89: 巢都世界 | Q89: 核心内容 | S89: 20 | T89: 20 | U89: 20 | V89: 15 | W89: 20 | X89: 20 | Y89: 20 | Z89: 20 | AA89: 25
B90: 示例：你的敏捷属性为60，“闪避”属于敏捷基础技能。 | P90: 巢都变种人 | Q90: 巢都世界的扩展 | S90: 20 | T90: 20 | U90: 20 | V90: 15+10 | W90: 20 | X90: 20 | Y90: 20 | Z90: 20 | AA90: 25-10
P91: 枪灰城 | Q91: 巢都世界的扩展 | S91: 20 | T91: 20+5 | U91: 20 | V91: 15 | W91: 20 | X91: 20 | Y91: 20 | Z91: 20 | AA91: 25
B92: 若已受训：你的闪避技能值就是60。 | P92: 沃格巢都 | Q92: 巢都世界的扩展 | S92: 20 | T92: 20 | U92: 20 | V92: 15+10 | W92: 20 | X92: 20 | Y92: 20 | Z92: 20 | AA92: 25-10
P93: 蛮荒世界 | Q93: 核心内容 | S93: 20 | T93: 20 | U93: 25 | V93: 25 | W93: 20 | X93: 20 | Y93: 20 | Z93: 15 | AA93: 15
B94: 若未受训：你的闪避技能值则是属性的一半，即30。 | P94: 黄昏星 | Q94: 蛮荒世界的扩展 | S94: 20 | T94: 20 | U94: 25 | V94: 25 | W94: 20 | X94: 20 | Y94: 20+3 | Z94: 15+3 | AA94: 15
P95: 虚空生人 | Q95: 核心内容 | S95: 20 | T95: 20 | U95: 15 | V95: 20 | W95: 20 | X95: 20 | Y95: 20 | Z95: 25 | AA95: 20
P96: 卡利西斯舰队 | Q96: 虚空生人的扩展 | S96: 20 | T96: 20 | U96: 15+5 | V96: 20 | W96: 20 | X96: 20 | Y96: 20 | Z96: 25 | AA96: 20
B97: 3 .生涯选择（职业） | P97: 黑暗舰舱人 | Q97: 虚空生人的扩展 | S97: 20 | T97: 20 | U97: 15 | V97: 20+5 | W97: 20 | X97: 20-5 | Y97: 20 | Z97: 25+5 | AA97: 20-5
P98: 忠嗣学院 | Q98: 扩展内容 | S98: 20 | T98: 20 | U98: 20 | V98: 20 | W98: 20 | X98: 20 | Y98: 20 | Z98: 20 | AA98: 20
B99: 可从生涯中自选一详可选生涯，确保属于出生地中‘可选’的职业。 | P99: 枯萎学院 | Q99: 忠嗣学院的扩展 | S99: 20 | T99: 20 | U99: 20 | V99: 20+5 | W99: 20 | X99: 20 | Y99: 20 | Z99: 20 | AA99: 20
P100: 铸造世界 | Q100: 扩展内容 | S100: 15 | T100: 20 | U100: 20 | V100: 20 | W100: 20 | X100: 25 | Y100: 20 | Z100: 20 | AA100: 20
B101: 或投d100 随机决定，若随机决定，需对照（附页“出身世界和对应可选职业”）。 | P101: 遗失的数据板 | Q101: 铸造世界的扩展 | S101: 取决于选择《遗失的数据板》17种出身中的哪一个，可选如图兰舒什、伊杜梅亚、探索舰队、机械神教研究站等。
P102: 贵族生人 | Q102: 扩展内容 | S102: 20 | T102: 20 | U102: 20 | V102: 20 | W102: 20 | X102: 20 | Y102: 20 | Z102: 15 | AA102: 25
B103: 各生涯起始资金与XP | P103: 马尔菲污血 | Q103: 贵族生人的扩展 | S103: 20 | T103: 20 | U103: 20 | V103: 20 | W103: 20 | X103: 20+10 | Y103: 20 | Z103: 15 | AA103: 25
P104: 思维洗涤 | Q104: 扩展内容 | S104: 20 | T104: 20 | U104: 20 | V104: 20 | W104: 20 | X104: 20 | Y104: 20 | Z104: 25 | AA104: 15
B105: 不同生涯提供不同的‘免费’默认初始装备、能力及对应启动资金，确认并填写进你的自动卡中（详见《核心规则书》第23 页）。 | P105: 圣殿世界 | Q105: 扩展内容 | S105: 20 | T105: 20 | U105: 20 | V105: 20 | W105: 20 | X105: 15 | Y105: 15 | Z105: 25 | AA105: 25
P106: 役从门生 | Q106: 扩展内容 | S106: 20 | T106: 15 | U106: 20 | V106: 20 | W106: 20 | X106: 25 | Y106: 20 | Z106: 15 | AA106: 25
B107: 如无意外，统一给予400 XP，用于购买技能和天赋，以及与生涯类型对应的启动资金。 | P107: 修院栽培 | Q107: 扩展内容 | S107: 20 | T107: 20 | U107: 20 | V107: 20 | W107: 20 | X107: 20 | Y107: 20 | Z107: 20 | AA107: 20
P108: 注意：扩展出生地也会给予侍僧不同的技能、属性加值或减值，基础技能，独特的特性等，详见对应的扩展规则书。
B109: 各个生涯的起始资金如下
B110: 各个生涯的起始资金如下 | P110: 出身世界和对应的承伤加值
B111: 文研员 | D111: 100 +1d10
B112: 执法者 | D112: 50 +2d10 | P112: 侍僧的承伤数值由对应世界的投掷基础值 + 具体调整值而得出。
B113: 杀手 | D113: 120 +3d10 | P113: 类型 | R113: 出身 | T113: 基本值 | U113: 调整值
B114: 牧师 | D114: 300 +5d10 | P114: 核心内容 | R114: 帝国世界 | T114: 1d5+ | U114: 8
B115: 卫队士兵 | D115: 70 +1d10 | P115: 帝国世界的扩展 | R115: 马卡贝斯五号 | T115: 1d5+ | U115: 8（同帝国世界）
B116: 帝国灵能者 | D116: 50 +1d5 | P116: 帝国世界的扩展 | R116: 锡诺菲亚 | T116: 1d5+ | U116: 8（同帝国世界）
B117: 流氓 | D117: 10 +1d5 | P117: 核心内容 | R117: 巢都世界 | T117: 1d5+ | U117: 8
B118: 技术神甫 | D118: 150 +1d10 | P118: 巢都世界的扩展 | R118: 巢都变种人 | T118: 1d5+ | U118: 8（同巢都世界）
P119: 巢都世界的扩展 | R119: 枪灰城 | T119: 1d5+ | U119: 8（同巢都世界）
P120: 巢都世界的扩展 | R120: 沃格巢都 | T120: 1d5+ | U120: 8（同巢都世界）
B121: 生涯阶级晋升 | P121: 核心内容 | R121: 蛮荒世界 | T121: 1d5+ | U121: 9
P122: 蛮荒世界的扩展 | R122: 黄昏星 | T122: 1d5+ | U122: 9（同蛮荒世界）
B123: 视已经花费经验值（XP）总数而定，只要花费的总数达到要求，立即自动晋升到下一阶级。 | P123: 核心内容 | R123: 虚空生人 | T123: 1d5+ | U123: 6
P124: 虚空生人的扩展 | R124: 卡利西斯舰队 | T124: 1d5+ | U124: 6（同虚空生人）
B125: 高阶阶级将开放更多可学习的技能与天赋，晋升后仍可继续学习前一阶级的技能与天赋。 | P125: 虚空生人的扩展 | R125: 黑暗舰舱人 | T125: 1d5+ | U125: 6（同虚空生人）
P126: 扩展内容 | R126: 忠嗣学院 | T126: 1d5+ | U126: 8
B127: （详见《核心规则书》第35 页） | P127: 忠嗣学院的扩展 | R127: 枯萎学院 | T127: 1d5+ | U127: 8（同忠嗣学院）
P128: 扩展内容 | R128: 铸造世界 | T128: 1d5+ | U128: 7
B129: 4 .投掷命运点 | P129: 铸造世界的扩展 | R129: 遗失的数据板 | T129: 1d5+ | U129: 取决于选择《遗失的数据板》17种出身中的哪一个，可选如图兰舒什、伊杜梅亚、探索舰队、机械神教研究站等。
B131: 侍僧并非常人，其注定为帝皇服务，命运点反映了命运对你的青睐。 | P131: 扩展内容 | R131: 贵族生人 | T131: 1d5+ | U131: 8
P132: 贵族生人的扩展 | R132: 马尔菲污血 | T132: 1d5+ | U132: 8（同贵族生人）
B133: 投掷1d10，对比“出生世界”的随机范围确定起始点数（详见附页“出身世界和对应的命运点范围”）。 | P133: 扩展内容 | R133: 思维洗涤 | T133: 1d5+ | U133: 8
P134: 扩展内容 | R134: 圣殿世界 | T134: 1d5+ | U134: 8
B135: 如何使用命运点 | P135: 扩展内容 | R135: 役从门生 | T135: 1d5+ | U135: 8
P136: 扩展内容 | R136: 修院栽培 | T136: 1d5+ | U136: 8
B137: 你可以在任何时候以一个自由动作来使用1 点命运点获得如下效果：
B139: •重投任何一次检定。重投的结果作为最终值。 | P139: 出身世界和对应的命运点范围
B140: •本场战斗的先攻权检定取10。
B141: •让一次检定获得额外的成功。 | P141: 投掷 1d10 ，对比下表的随机范围决定起始命运点。
...

Sheet 机械神甫（晋升表）
C3: 表 2.15: 技术神甫属性提升 | I3: 阶级简介 | J3: 提升 | K3: 花费 | L3: 种类 | M3: 先决条件 | O3: 阶级简介 | P3: 提升 | Q3: 花费 | R3: 种类 | S3: 先决条件 | U3: 阶级简介 | V3: 提升 | W3: 花费 | X3: 种类 | Y3: 先决条件 | AA3: 阶级简介 | AB3: 提升 | AC3: 花费 | AD3: 种类 | AE3: 先决条件
I4: 仪表技工 | J4: 常识（机械教） | K4: 100 | L4: 技能 | M4: — | O4: 技术工匠 | P4: 常识(科技)+10 | Q4: 100 | R4: 技能 | S4: 常识(科技) | U4: 电子修士 | V4: 常识(机械教)+10 | W4: 100 | X4: 技能 | Y4: 常识(机械教) | AA4: 技术神甫 | AB4: 常识(内政部) | AC4: 100 | AD4: 技能 | AE4: —
C5: 属性 | D5: 初级 | E5: 中等 | F5: 熟练 | G5: 专家 | J5: 常识（科技） | K5: 100 | L5: 技能 | M5: — | P5: 爆破 | Q5: 100 | R5: 技能 | S5: — | V5: 常识(帝国国教) | W5: 100 | X5: 技能 | Y5: - | AB5: 常识(帝国国教)+10 | AC5: 100 | AD5: 技能 | AE5: 常识(帝国国教)
C6: 格斗能力 WS | D6: 250 | E6: 500 | F6: 750 | G6: 1000 | I6: “如果你发现了任何莫莫名其妙的故障，就交给仪表技工去办。他会把毛病找出来的。” | J6: 驾驶（地面载具） | K6: 100 | L6: 技能 | M6: — | O6: “滑车底部爆炸……卜兹兹兹……五具支架倒塌……喀兹兹兹……任务不能失败……兹喀喀喀……技工小队立即行动!” | P6: 暗号(侍僧) | Q6: 100 | R6: 技能 | S6: — | U6: “我听不懂他在说什么,但那个电子修士头巾下面开始有红光闪动,之后它碰了他一下,然后随着一声巨响,他就飞过了屋子另一头!要不是这样就让皇帝弄瞎我的眼睛!我就知道他们严密看守发电机神殿是有原因的!” | V6: 常识(帝国国教) | W6: 100 | X6: 技能 | Y6: - | AA6: “他站在扇叶前,看起来懦弱又谦卑。用技术神甫的话说,他在启动引擎,好让巢都能呼吸顺畅。他用靴子反复敲出神圣的节奏,之后看哪!风扇开始转动了。” | AB6: 常识(帝国)+10 | AC6: 100 | AD6: 技能 | AE6: 常识(帝国)
C7: 射击能力 BS | D7: 250 | E7: 500 | F7: 750 | G7: 1000 | J7: 估价 | K7: 100 | L7: 技能 | M7: — | P7: 驾驶(地面载具)+10 | Q7: 100 | R7: 技能 | S7: 驾驶(地面载具) | V7: 驾驶(地面载具)+20 | W7: 100 | X7: 技能 | Y7: 驾驶(地面载具)+10 | AB7: 常识(科技)+20 | AC7: 100 | AD7: 技能 | AE7: 常识(科技)+10
C8: 力量 S | D8: 500 | E8: 750 | F8: 1000 | G8: 2500 | J8: 禁忌知识（机械神教） | K8: 100 | L8: 技能 | M8: — | P8: 驾驶(步行载具) | Q8: 100 | R8: 技能 | S8: — | V8: 驾驶(悬浮载具) | W8: 100 | X8: 技能 | Y8: - | AB8: 驾驶(悬浮载具)+20 | AC8: 100 | AD8: 技能 | AE8: 驾驶(悬浮载具)+10
C9: 坚韧 T | D9: 100 | E9: 250 | F9: 500 | G9: 750 | J9: 阅读 | K9: 100 | L9: 技能 | M9: — | P9: 医疗 | Q9: 100 | R9: 技能 | S9: — | V9: 驾驶(步行载具)+10 | W9: 100 | X9: 技能 | Y9: 驾驶(步行载具) | AB9: 禁忌知识(古代科技) | AC9: 100 | AD9: 技能 | AE9: —
C10: 敏捷 Ag | D10: 500 | E10: 750 | F10: 1000 | G10: 2500 | J10: 阅读+10 | K10: 100 | L10: 技能 | M10: 阅读 | P10: 学术知识(化学) | Q10: 100 | R10: 技能 | S10: — | V10: 禁忌知识 | W10: 100 | X10: 技能 | Y10: 禁忌知识(机械神教) | AB10: 禁忌知识(机械神教)+20 | AC10: 100 | AD10: 技能 | AE10: 禁忌知识(机械神教)+10
C11: 智力 Int | D11: 100 | E11: 250 | F11: 500 | G11: 750 | I11: 为了更好地理解机械神欧姆尼塞亚,仪表技工需要学习各种型号,产品,以及形式。他们可以轻易编目与检索任何科技产品。 | J11: 逻辑 | K11: 100 | L11: 技能 | M11: — | P11: 入侵 | Q11: 100 | R11: 技能 | S11: — | V11: (机械神教)+10 | AA11: 技术神甫开始发掘深层次的科技奥秘,并通晓很多维持仪式,发动仪式,重新启动仪式等等。从简单的机械门到从废墟中发掘出来的远古科技,技术神甫都能在它们身上发现机械神的形象,并为将更多的知识添加到机械神教的数据室中。 | AB11: 逻辑+20 | AC11: 100 | AD11: 技能 | AE11: 逻辑+10
C12: 感知 Per | D12: 250 | E12: 500 | F12: 750 | G12: 1000 | J12: 航行(民用飞行器) | K12: 100 | L12: 技能 | M12: — | O12: 技术工匠了解各种材料的性质。他们负责大规模修理工作,维护危险的制造程序。 | P12: 技术应用+10 | Q12: 100 | R12: 技能 | S12: 技术应用 | U12: 对形态和材料配比了如指掌之后,电子修士开始投身于能源的研究。自此他们钻研机械本灵的活动法则,以及安抚它们的方法。 | V12: 阅读+20 | W12: 100 | X12: 技能 | Y12: 阅读+10 | AB12: 学术知识(古代史) | AC12: 100 | AD12: 技能 | AE12: —
C13: 意志 WP | D13: 100 | E13: 250 | F13: 500 | G13: 750 | J13: 密语(科技) | K13: 100 | L13: 技能 | M13: — | P13: 生计(矿工) | Q13: 100 | R13: 技能 | S13: — | V13: 逻辑+10 | W13: 100 | X13: 技能 | Y13: 逻辑 | AB13: 学术知识(化学)+20 | AC13: 100 | AD13: 技能 | AE13: 学术知识(化学)+10
C14: 交际 Fel | D14: N/A | E14: N/A | F14: N/A | G14: N/A | J14: 生计(抄写员) | K14: 100 | L14: 技能 | M14: — | P14: 生计(铁匠) | Q14: 100 | R14: 技能 | S14: — | V14: 学术知识(数字学) | W14: 100 | X14: 技能 | Y14: - | AB14: 学术知识(帝国国教) | AC14: 100 | AD14: 技能 | AE14: —
J15: 生计(雕刻师) | K15: 100 | L15: 技能 | M15: — | P15: 生计(技师) | Q15: 100 | R15: 技能 | S15: — | V15: 听说语言(高歌特语) | W15: 100 | X15: 技能 | Y15: - | AB15: 学术知识(帝国战术) | AC15: 100 | AD15: 技能 | AE15: —
D16: 仪表技工 | J16: 技术应用 | K16: 100 | L16: 技能 | M16: — | P16: 生计(军械师) | Q16: 100 | R16: 技能 | S16: - | V16: 密语(科技)+10 | W16: 100 | X16: 技能 | Y16: 密语(科技) | AB16: 入侵+20 | AC16: 100 | AD16: 技能 | AE16: 入侵+10
D17: xp level | E17: 0-499 | J17: 基础武器训练(原始) | K17: 100 | L17: 天赋 | M17: — | P17: 武器熟悉 | Q17: 100 | R17: 天赋 | S17: BS 30,基本武器训练(任意两种) | V17: 生计(设计师) | W17: 100 | X17: 技能 | Y17: - | AB17: 听说语言 | AC17: 100 | AD17: 技能 | AE17: 听说语言
D18: 技术工匠 | J18: 基础武器训练(激光) | K18: 100 | L18: 天赋 | M18: — | P18: 准确射击 | Q18: 100 | R18: 天赋 | S18: BS 30 | V18: 致命射击 | W18: 100 | X18: 天赋 | Y18: BS 40 | AB18: (高歌特语)+10 | AE18: (高歌特语)
D19: xp level | E19: 500-999 | J19: 基础武器训练(实体弹) | K19: 100 | L19: 天赋 | M19: — | P19: 强化五感(视觉) | Q19: 100 | R19: 天赋 | S19: - | V19: 电子援助 | W19: 100 | X19: 天赋 | Y19: 技术神甫 | AB19: 密语(科技)+20 | AC19: 100 | AD19: 技能 | AE19: 密语(科技)+10
D20: 电子修士 | J20: 机械语言者 | K20: 100 | L20: 天赋 | M20: — | P20: 铁头 | Q20: 100 | R20: 天赋 | S20: T 40 | V20: 强化五感(听觉) | W20: 100 | X20: 天赋 | Y20: - | AB20: 技术应用+20 | AC20: 100 | AD20: 技能 | AE20: 技术应用+10
D21: xp level | E21: 1000-2999 | J21: 生化阉割 | K21: 100 | L21: 天赋 | M21: — | P21: 线圈充能 | Q21: 100 | R21: 天赋 | S21: 技术神甫 | V21: 强化五感(触觉) | W21: 100 | X21: 天赋 | Y21: - | AB21: 生计(技师)+20 | AC21: 100 | AD21: 技能 | AE21: 生计(技师)+10
D22: 工程师 | J22: 电子接口应用 | K22: 100 | L22: 天赋 | M22: — | P22: 拟声高手 | Q22: 100 | R22: 天赋 | S22: - | V22: 鲤鱼打挺 | W22: 100 | X22: 天赋 | Y22: Ag 30 | AB22: 生计(设计师)+20 | AC22: 100 | AD22: 技能 | AE22: 生计(设计师)+10
D23: xp level | E23: 2000-2999 | J23: 尖锐噪音 | K23: 100 | L23: 天赋 | M23: 技术神甫 | P23: 平等待遇(机械神教) | Q23: 100 | R23: 天赋 | S23: Fel 30 | V23: 机械附肢(多功能) | W23: 100 | X23: 天赋 | Y23: 技术神甫 | AB23: 生计(军械师)+20 | AC23: 100 | AD23: 技能 | AE23: 生计(军械师)+10
D24: 技术神甫 | J24: 轻度睡眠 | K24: 100 | L24: 天赋 | M24: Per 30 | P24: 即时备战 | Q24: 100 | R24: 天赋 | S24: - | V24: 悍不畏死 | W24: 100 | X24: 天赋 | Y24: - | AB24: 剑术大师 | AC24: 100 | AD24: 天赋 | AE24: WS 30,格斗武器训练(任意)
D25: xp level | E25: 3000-5999 | J25: 格斗武器训练(原始) | K25: 100 | L25: 天赋 | M25: — | P25: 健壮体格 | Q25: 100 | R25: 天赋 | S25: - | V25: 健壮体格 | W25: 100 | X25: 天赋 | Y25: - | AB25: 格斗专家 | AC25: 100 | AD25: 天赋 | AE25: WS 30
B26: 技术巫师 | F26: 机械执事 | J26: 手枪训练(原始) | K26: 100 | L26: 天赋 | M26: — | P26: 盲斗 | Q26: 200 | R26: 天赋 | S26: Per 30 | V26: 植入电脑 | W26: 100 | X26: 天赋 | Y26: — | AB26: 恼人嗓音 | AC26: 100 | AD26: 天赋 | AE26: —
B27: xp level | C27: 6000-7999 | F27: xp level | G27: 6000-7999 | J27: 手枪训练(激光) | K27: 100 | L27: 天赋 | M27: — | P27: 线圈放电 | Q27: 200 | R27: 天赋 | S27: 技术神甫 | V27: 密语（侍僧） | W27: 200 | X27: 技能 | Y27: — | AB27: 能量缓冲 | AC27: 100 | AD27: 天赋 | AE27: 技术神甫
B28: 运算先知 | F28: 机械神教传教士 | J28: 手枪训练(实体弹) | K28: 100 | L28: 天赋 | M28: — | V28: 基础武器训练（爆矢） | W28: 200 | X28: 天赋 | Y28: — | AB28: 独立目标 | AC28: 100 | AD28: 天赋 | AE28: BS 40
B29: xp level | C29: 8000-9999 | F29: xp level | G29: 8000-9999 | J29: 快速上膛 | K29: 100 | L29: 天赋 | M29: — | V29: 基础武器训练（榴弹） | W29: 200 | X29: 天赋 | Y29: — | AB29: 敬畏仪式 | AC29: 100 | AD29: 天赋 | AE29: 技术神甫
B30: 铸造者 | F30: 漫游锻师 | J30: 健壮体格† | K30: 100 | L30: 天赋 | M30: — | V30: 线圈冲击 | W30: 200 | X30: 天赋 | Y30: 技术神甫 | AB30: 健壮体格 | AC30: 100 | AD30: 天赋 | AE30: —
B31: xp level | C31: 10000-14999 | F31: xp level | G31: 10000-14999 | J31: 一敲就好 | K31: 100 | L31: 天赋 | M31: — | V31: 机械附肢（医疗） | W31: 200 | X31: 天赋 | Y31: 技术神甫 | AB31: 迅捷攻击 | AC31: 100 | AD31: 天赋 | AE31: WS 35
J32: 投掷武器训练(原始) | K32: 300 | L32: 天赋 | M32: — | V32: 格斗武器训练（震击） | W32: 200 | X32: 天赋 | Y32: — | AB32: 航行(宇宙飞船) | AC32: 200 | AD32: 技能 | AE32: —
J33: 可重复选择,当前阶级最多两次 | V33: 手枪训练（爆矢） | W33: 200 | X33: 天赋 | Y33: — | AB33: 基础武器训练(热熔) | AC33: 200 | AD33: 天赋 | AE33: —
AB34: 基础武器训练(等离子) | AC34: 200 | AD34: 天赋 | AE34: —
I35: 阶级简介 | J35: 提升 | K35: 花费 | L35: 种类 | M35: 先决条件 | O35: 阶级简介 | P35: 提升 | Q35: 花费 | R35: 种类 | S35: 先决条件 | U35: 阶级简介 | V35: 提升 | W35: 花费 | X35: 种类 | Y35: 先决条件 | AB35: 重型武器训练(爆矢) | AC35: 200 | AD35: 天赋 | AE35: —
I36: 技术巫师 | J36: 暗号(秘会) | K36: 100 | L36: 技能 | M36: 暗号(秘会) | O36: 运算先知 | P36: 常识(法务部)+10 | Q36: 100 | R36: 技能 | S36: 常识(法务部) | U36: 铸造者 | V36: 禁忌知识 | W36: 100 | X36: 技能 | Y36: 禁忌知识 | AB36: 磁力优雅 | AC36: 200 | AD36: 天赋 | AE36: 技术神甫
J37: 常识(法务部) | K37: 100 | L37: 技能 | M37: — | P37: 常识(国教教义)+10 | Q37: 100 | R37: 技能 | S37: 常识(国教教义) | V37: (古代科技)+20 | Y37: (古代科技)+10 | AB37: 格斗武器训练(能量) | AC37: 200 | AD37: 天赋 | AE37: —
I38: “他们意志犀利如匕首,又知道如何与内政部打交道。记住,别惹技术巫师,尤其当你在飞船上工作时。否则你会被分配到一个漏气的舱室,甚至来不及在胸前划个双头鹰。” | J38: 常识(国教教义) | K38: 100 | L38: 技能 | M38: — | O38: “他们已经很难再算是人类了。我是说,他们比技术神甫们更进一步。没人愿意把那些......你知道......危险的零件整天装在脑袋上。” | P38: 禁忌知识(古代科技)+10 | Q38: 100 | R38: 技能 | S38: 禁忌知识(古代科技) | U38: “机械神教铸造者的知识范围不广,但极有深度。每一个都是某一领域的领头专家,大多以其睿智和执着著称。” | V38: 禁忌知识(恶魔) | W38: 100 | X38: 技能 | Y38: - | AB38: 机械附肢(枪械) | AC38: 200 | AD38: 天赋 | AE38: 技术神甫
J39: 常识(帝国国教)+20 | K39: 100 | L39: 技能 | M39: 常识(帝国国教)+10 | P39: 禁忌知识(亚空间) | Q39: 100 | R39: 技能 | S39: - | V39: 禁忌知识(异端) | W39: 100 | X39: 技能 | Y39: - | AB39: 闪避 | AC39: 300 | AD39: 技能 | AE39: —
J40: 常识(帝国)+20 | K40: 100 | L40: 技能 | M40: 常识(帝国)+10 | P40: 学术知识(行政)+10 | Q40: 100 | R40: 技能 | S40: 学术知识(行政) | V40: 禁忌知识(审判庭) | W40: 100 | X40: 技能 | Y40: - | AB40: 指挥 | AC40: 300 | AD40: 技能 | AE40: —
J41: 估价+20 | K41: 100 | L41: 技能 | M41: 估价+10 | P41: 学术知识(法律)+10 | Q41: 100 | R41: 技能 | S41: 学术知识(法律) | V41: 禁忌知识(灵能者) | W41: 100 | X41: 技能 | Y41: - | AB41: 搜集信息 | AC41: 300 | AD41: 技能 | AE41: —
J42: 审讯 | K42: 100 | L42: 技能 | M42: — | P42: 学术知识(传说) | Q42: 100 | R42: 技能 | S42: - | V42: 禁忌知识(亚空间)+10 | W42: 100 | X42: 技能 | Y42: 禁忌知识(亚空间) | AB42: 恐吓 | AC42: 300 | AD42: 技能 | AE42: —
I43: 技术巫师将他们的全部精力都放在吸收可能对机械教有用的知识上。从取悦国教教会的修理工到外星人审问的参与者,技术巫师以一种无情的,机械的效率四处搜集信息。 | J43: 医疗+10 | K43: 100 | L43: 技能 | M43: 医疗 | O43: 运算先知以一种战斗的狂热钻研那些禁忌的神秘设备。从超自然的异族到亚空间疾病,运算先知坚持不懈地藐视自己探索之路上的种种危险。 | P43: 学术知识(神秘学) | Q43: 100 | R43: 技能 | S43: - | U43: 铸造者对它们领域内的事物有着完美而精确的了解,这使他们成为特定领域的大师。从研究肉体的生物学铸造者,到狩猎外星生物的异形学铸造者,这些贤明的人们以其大量的知识储备服侍机械神教。 | V43: 学术知识(行政)+20 | W43: 100 | X43: 技能 | Y43: 学术知识(行政)+10
J44: 学术知识(行政) | K44: 100 | L44: 技能 | M44: — | P44: 搜索+10 | Q44: 100 | R44: 技能 | S44: 搜索 | V44: 学术知识(法律)+20 | W44: 100 | X44: 技能 | Y44: 学术知识(法律)+10
J45: 学术知识(法律) | K45: 100 | L45: 技能 | M45: — | P45: 双重射击 | Q45: 100 | R45: 天赋 | S45: Ag 40,双武器射击 | V45: 学术知识(传说)+10 | W45: 100 | X45: 技能 | Y45: 学术知识(传说) | AA45: 阶级简介 | AB45: 提升 | AC45: 花费 | AD45: 种类 | AE45: 先决条件
J46: 搜索 | K46: 100 | L46: 技能 | M46: — | P46: 深谋远虑 | Q46: 100 | R46: 天赋 | S46: Int 30 | V46: 学术知识(神秘学)+10 | W46: 100 | X46: 技能 | Y46: 学术知识(神秘学) | AA46: 工程师 | AB46: 化学应用 | AC46: 100 | AD46: 技能 | AE46: —
J47: 听说语言 | K47: 100 | L47: 技能 | M47: 听说语言 | P47: 闪电反射 | Q47: 100 | R47: 天赋 | S47: - | V47: 学术知识(哲学) | W47: 100 | X47: 技能 | Y47: - | AB47: 常识(机械教)+20 | AC47: 100 | AD47: 技能 | AE47: 常识(机械教)+10
J48: (高歌特语)+20 | M48: (高歌特语)+10 | P48: 神射手 | Q48: 100 | R48: 天赋 | S48: BS 35 | V48: 双重打击 | W48: 100 | X48: 天赋 | Y48: Ag 40,双武器格斗 | AA48: “是,长官,我知道不该打扰工程师,但我们必须打开机壳......是,但如果我们没有进行应急操舵,那辆奇美拉很可能就毁掉了......什么?......需要忏悔?在前线,您的意思是?黄金王座啊......好吧,如果这是皇帝的命令......” | AB48: 常识(战争) | AC48: 100 | AD48: 技能 | AE48: —
J49: 傲慢护甲 | K49: 100 | L49: 天赋 | M49: WP 40 | P49: 意志壁垒 | Q49: 100 | R49: 天赋 | S49: WP 50,顽强意志 | V49: 棘手目标 | W49: 100 | X49: 天赋 | Y49: Ag 40 | AB49: 爆破+10 | AC49: 100 | AD49: 技能 | AE49: 爆破
J50: 自动止血 | K50: 100 | L50: 天赋 | M50: — | P50: 快速反应 | Q50: 100 | R50: 天赋 | S50: Ag 40 | V50: 军纪严明 | W50: 100 | X50: 天赋 | Y50: WP 30,指挥 | AB50: 驾驶(悬浮载具)+10 | AC50: 100 | AD50: 技能 | AE50: 驾驶(悬浮载具)
J51: 无所畏惧 | K51: 100 | L51: 天赋 | M51: — | P51: 抵抗(灵能) | Q51: 100 | R51: 天赋 | S51: - | V51: 闪电攻击 | W51: 100 | X51: 天赋 | Y51: 迅捷攻击 | AB51: 驾驶(步行载具)+20 | AC51: 100 | AD51: 技能 | AE51: 驾驶(步行载具)+10
J52: 枪械祝福 | K52: 100 | L52: 天赋 | M52: 技术神甫 | P52: 灵活侧步 | Q52: 100 | R52: 天赋 | S52: Ag 40,闪避 | V52: 医疗+20 | W52: 200 | X52: 技能 | Y52: 医疗+10 | AB52: 估价+10 | AC52: 100 | AD52: 技能 | AE52: 估价
J53: 见惯不惊 | K53: 100 | L53: 天赋 | M53: WP 30 | P53: 顽强意志 | Q53: 100 | R53: 天赋 | S53: WP 30,抵抗(灵能) | V53: 搜索+20 | W53: 200 | X53: 技能 | Y53: 搜索+10 | AA53: 工程师综合运用他的知识来维护复杂的机械设备。通过仪式和祈祷的魔力,他们能唤醒任何机械的本灵,寻找瑕疵并更正错误。 | AB53: 导航(太空导航) | AC53: 100 | AD53: 技能 | AE53: —
J54: 外科专家 | K54: 100 | L54: 天赋 | M54: 医疗+10 | P54: 欺诈+10 | Q54: 200 | R54: 技能 | S54: 欺诈 | V54: 审讯+20 | W54: 200 | X54: 技能 | Y54: 审讯+10 | AB54: 导航(地面导航) | AC54: 100 | AD54: 技能 | AE54: —
J55: 无辜人格 | K55: 100 | L55: 天赋 | M55: — | P55: 审讯+10 | Q55: 200 | R55: 技能 | S55: 审讯 | V55: 平等待遇(帝国国教) | W55: 200 | X55: 天赋 | Y55: Fel 30 | AB55: 航行(军用飞行器) | AC55: 100 | AD55: 技能 | AE55: —
J56: 手枪训练(等离子) | K56: 100 | L56: 天赋 | M56: — | P56: 学术知识(数字学)+20 | Q56: 200 | R56: 技能 | S56: 学术知识(数字学)+10 | V56: 平等待遇(审判庭) | W56: 200 | X56: 天赋 | Y56: Fel 30 | AB56: 入侵+10 | AC56: 100 | AD56: 技能 | AE56: 入侵
J57: 欺诈 | K57: 200 | L57: 技能 | M57: — | P57: 黑暗灵魂 | Q57: 200 | R57: 天赋 | S57: - | V57: 纯净思维仪式 | W57: 200 | X57: 天赋 | Y57: 技术神甫 | AB57: 学术知识(占星术) | AC57: 100 | AD57: 技能 | AE57: —
J58: 特种武器训练(毒针手枪) | K58: 200 | L58: 天赋 | M58: — | P58: 金属召唤 | Q58: 200 | R58: 天赋 | S58: 技术神甫,金属引力 | V58: 健壮体格 | W58: 200 | X58: 天赋 | Y58: — | AB58: 学术知识(化学)+10 | AC58: 100 | AD58: 技能 | AE58: 学术知识(化学)
J59: 健壮体格 | K59: 200 | L59: 天赋 | M59: — | P59: 磁力飞跃 | Q59: 200 | R59: 天赋 | S59: 技术神甫,磁力优雅 | V59: 手枪训练(热熔) | W59: 300 | X59: 天赋 | Y59: — | AB59: 学术知识(数字学)+10 | AC59: 100 | AD59: 技能 | AE59: 学术知识(数字学)
J60: 投掷武器训练(震击) | K60: 300 | L60: 天赋 | M60: — | P60: 平等待遇(内政部) | Q60: 200 | R60: 天赋 | S60: Fel 30 | V60: 投掷武器训练(能量) | W60: 400 | X60: 天赋 | Y60: — | AB60: 生计(技师)+10 | AC60: 100 | AD60: 技能 | AE60: 生计(技师)
P61: 加速循环 | Q61: 200 | R61: 天赋 | S61: 自动止血 | AB61: 生计(设计师)+10 | AC61: 100 | AD61: 技能 | AE61: 生计(设计师)
P62: 健壮体格 | Q62: 200 | R62: 天赋 | S62: - | AB62: 生计(军械师)+10 | AC62: 100 | AD62: 技能 | AE62: 生计(军械师)
P63: 投掷武器训练(链锯) | Q63: 300 | R63: 天赋 | S63: - | AB63: 双巧手 | AC63: 100 | AD63: 天赋 | AE63: Ag 30
AB64: 基础武器训练(火焰) | AC64: 100 | AD64: 天赋 | AE64: —
I65: 阶级简介 | J65: 提升 | K65: 花费 | L65: 种类 | M65: 先决条件 | O65: 阶级简介 | P65: 提升 | Q65: 花费 | R65: 种类 | S65: 先决条件 | U65: 阶级简介 | V65: 提升 | W65: 花费 | X65: 种类 | Y65: 先决条件 | AB65: 藏物暗袋 | AC65: 100 | AD65: 天赋 | AE65: —
I66: 机械执事 | J66: 常识(下层社会) | K66: 100 | L66: 技能 | M66: — | O66: 机械神传教士 | P66: 暗号(战场) | Q66: 100 | R66: 技能 | S66: - | U66: 漫游锻师 | V66: 暗号(下层社会) | W66: 100 | X66: 技能 | Y66: — | AB66: 极限打击 | AC66: 100 | AD66: 天赋 | AE66: WS 50
J67: 爆破+20 | K67: 100 | L67: 技能 | M67: 爆破+10 | P67: 常识(国教教义) | Q67: 100 | R67: 技能 | S67: - | V67: 常识(法务部) | W67: 100 | X67: 技能 | Y67: — | AB67: 金属引力 | AC67: 100 | AD67: 天赋 | AE67: 技术神甫
I68: “这里是机械执事。全能者改变了铸造样式,以及引擎边齿,还有蒸馏设备。我们按照之后的计划执行两遍。全能者无所不知。” | J68: 估价+20 | K68: 100 | L68: 技能 | M68: 估价+10 | O68: “听啊,听从这名机械神传教士!弯曲你们的膝盖,感谢他维持空气循环。你们肺里的每一口气都是他的恩赐!祈祷吧,在我们把你当作异教徒赶出矿井之前。” | P68: 学术知识(纹章学) | Q68: 100 | R68: 技能 | S68: - | U68: “我们对于阿詹提的血液发光生物的了解是源于阿比那图斯,一名搭乘商浪人飞船的漫游锻师的工作。相关资料已经因为机械神教的关系而被删除了,但我们还是能从剩下来的东西中推断出很多情报。” | V68: 禁忌知识(古代科技)+10 | W68: 100 | X68: 技能 | Y68: 禁忌知识(古代科技) | AB68: 重型武器训练(实体弹) | AC68: 100 | AD68: 天赋 | AE68: —
J69: 学术知识(古代史)+10 | K69: 100 | L69: 技能 | M69: 学术知识(古代史) | P69: 学术知识(帝国战术)+10 | Q69: 100 | R69: 技能 | S69: 学术知识(帝国战术) | V69: 禁忌知识(异型) | W69: 100 | X69: 技能 | Y69: — | AB69: 强化五感(嗅觉) | AC69: 100 | AD69: 天赋 | AE69: —
J70: 搜索 | K70: 100 | L70: 技能 | M70: — | P70: 密语(内政部) | Q70: 100 | R70: 技能 | S70: - | V70: 赌博 | W70: 100 | X70: 技能 | Y70: — | AB70: 机械附肢(起重) | AC70: 100 | AD70: 天赋 | AE70: 技术神甫
J71: 密语(军队) | K71: 100 | L71: 技能 | M71: — | P71: 密语(帝国国教) | Q71: 100 | R71: 技能 | S71: - | V71: 审讯 | W71: 100 | X71: 技能 | Y71: — | AB71: 机械附肢(光学) | AC71: 100 | AD71: 天赋 | AE71: 技术神甫
J72: 手上功夫 | K72: 100 | L72: 技能 | M72: — | P72: 手上功夫+10 | Q72: 100 | R72: 技能 | S72: 手上功夫 | V72: 学术知识(古代史)+20 | W72: 100 | X72: 技能 | Y72: 学术知识(古代史)+10 | AB72: 手枪训练(火焰) | AC72: 100 | AD72: 天赋 | AE72: —
I73: 机械执事为寻求知识而四处游荡,知道如何与不了解机械神的人打交道。机械执事的能力足以自卫,以保证他的探索之路畅通。 | J73: 生计(药剂师) | K73: 100 | L73: 技能 | M73: — | O73: 机械神传教士与帝国里各种人打交道,从穿金戴银的富商到衣衫褴褛的殖民地居民。他传播机械教之道,并搜集任何火星的机械神甫们可能感兴趣的东西。 | P73: 追迹 | Q73: 100 | R73: 技能 | S73: - | U73: 漫游锻师精通各种技巧,希望能在机械神教之上更进一步,发掘新的领域,世界,以及技术。由于通晓各种秘密,漫游锻师能在任何情况下应对自如。 | V73: 学术知识(动物学) | W73: 100 | X73: 技能 | Y73: — | AB73: 抵抗(毒素) | AC73: 100 | AD73: 天赋 | AE73: —
J74: 生计(殡葬师) | K74: 100 | L74: 技能 | M74: — | P74: 生计(探矿者) | Q74: 100 | R74: 技能 | S74: - | V74: 学术知识(传说) | W74: 100 | X74: 技能 | Y74: — | AB74: 完整回忆 | AC74: 100 | AD74: 天赋 | AE74: Int 30
J75: 生计(泥瓦匠) | K75: 100 | L75: 技能 | M75: — | P75: 傲慢护甲 | Q75: 100 | R75: 天赋 | S75: WP 40 | V75: 学术知识(神秘学) | W75: 100 | X75: 技能 | Y75: — | AB75: 双武器射击 | AC75: 100 | AD75: 天赋 | AE75: BS 35, Ag 35
J76: 生计(皮匠) | K76: 100 | L76: 技能 | M76: — | P76: 颓废者 | Q76: 100 | R76: 天赋 | S76: T 30 | V76: 拨挡飞箭 | W76: 100 | X76: 天赋 | Y76: Ag 50 | AB76: 双武器格斗 | AC76: 100 | AD76: 天赋 | AE76: WS 35, Ag 35
J77: 自动止血 | K77: 100 | L77: 天赋 | M77: — | P77: 狂热袭击 | Q77: 100 | R77: 天赋 | S77: WS 35 | V77: 命硬 | W77: 100 | X77: 天赋 | Y77: WP 40 | AB77: 警觉 | AC77: 200 | AD77: 技能 | AE77: —
J78: 稳健肌肉 | K78: 100 | L78: 天赋 | M78: S 45 | P78: 见惯不惊 | Q78: 100 | R78: 天赋 | S78: WP 30 | V78: 无所畏惧 | W78: 100 | X78: 天赋 | Y78: — | AB78: 常识(帝国卫队) | AC78: 200 | AD78: 技能 | AE78: —
J79: 净化之火 | K79: 100 | L79: 天赋 | M79: 基本武器训练(火焰) | P79: 神射手 | Q79: 100 | R79: 天赋 | S79: BS 35 | V79: 外科专家 | W79: 100 | X79: 天赋 | Y79: 医疗+10 | AB79: 密语(侍僧)+10 | AC79: 200 | AD79: 技能 | AE79: 密语(侍僧)
J80: 双重射击 | K80: 100 | L80: 天赋 | M80: Ag 40,双武器射击 | P80: 灵活侧步 | Q80: 100 | R80: 天赋 | S80: Ag 40,闪避 | V80: 无辜人格 | W80: 100 | X80: 天赋 | Y80: — | AB80: 格斗武器训练(链锯) | AC80: 200 | AD80: 天赋 | AE80: —
J81: 双重打击 | K81: 100 | L81: 天赋 | M81: Ag 40,双武器格斗 | P81: 交易 | Q81: 200 | R81: 技能 | S81: - | V81: 抵抗(灵能) | W81: 100 | X81: 天赋 | Y81: — | AB81: 抵抗(恐惧) | AC81: 200 | AD81: 天赋 | AE81: —
J82: 枪械祝福 | K82: 100 | L82: 天赋 | M82: 技术神甫 | P82: 欺诈+10 | Q82: 200 | R82: 技能 | S82: 欺诈 | V82: 顽强意志 | W82: 100 | X82: 天赋 | Y82: WP 30,抵抗(灵能) | AB82: 健壮体格 | AC82: 200 | AD82: 天赋 | AE82: —
J83: 棘手目标 | K83: 100 | L83: 天赋 | M83: Ag 40 | P83: 生计(商人) | Q83: 200 | R83: 技能 | S83: - | V83: 生计(占卜者) | W83: 200 | X83: 技能 | Y83: —
J84: 欺诈 | K84: 200 | L84: 技能 | M84: — | P84: 金属召唤 | Q84: 200 | R84: 天赋 | S84: 技术神甫,金属引力 | V84: 出生入死 | W84: 200 | X84: 天赋 | Y84: 军纪严明
J85: 医疗+10 | K85: 200 | L85: 技能 | M85: 医疗 | P85: 重型武器训练(热熔) | Q85: 200 | R85: 天赋 | S85: - | V85: 平等待遇(下层社会) | W85: 200 | X85: 天赋 | Y85: Fel 30
J86: 搜集信息+10 | K86: 200 | L86: 技能 | M86: 搜集信息 | P86: 重型武器训练(等离子) | Q86: 200 | R86: 天赋 | S86: - | V86: 加速循环 | W86: 200 | X86: 天赋 | Y86: 自动止血
J87: 察言观色 | K87: 200 | L87: 技能 | M87: — | P87: 磁力飞跃 | Q87: 200 | R87: 天赋 | S87: 技术神甫,磁力优雅 | V87: 恐惧仪式 | W87: 200 | X87: 天赋 | Y87: 技术神甫
J88: 重型武器训练(激光) | K88: 200 | L88: 天赋 | M88: — | P88: 平等待遇(帝国海军) | Q88: 200 | R88: 天赋 | S88: Fel 30 | V88: 健壮体格 | W88: 200 | X88: 天赋 | Y88: —
J89: 重型武器训练(榴弹) | K89: 200 | L89: 天赋 | M89: — | P89: 健壮体格 | Q89: 200 | R89: 天赋 | S89: - | V89: 交易+10 | W89: 300 | X89: 技能 | Y89: 交易
J90: 重型武器训练(原始) | K90: 200 | L90: 天赋 | M90: — | V90: 欺诈+20 | W90: 300 | X90: 技能 | Y90: 欺诈+10
J91: 军纪严明 | K91: 200 | L91: 天赋 | M91: WP 30,指挥 | V91: 表演(乐师) | W91: 300 | X91: 技能 | Y91: —
J92: 健壮体格 | K92: 200 | L92: 天赋 | M92: —

Sheet 自填扩展
A1: 自填并入自动化 近战武器（当前版本生效） | J1: 自填并入自动化 远程武器（当前版本生效） | V1: 自填并入自动化 天赋记录（当前版本生效）
A2: 名称 | B2: 类型 | C2: 射程 | D2: 伤害 | E2: 破甲 | F2: 特性 | G2: 重量 | H2: 花费 | J2: 名称 | K2: 类型 | L2: 射程 | M2: 射速 | N2: 伤害 | O2: 破甲 | P2: 弹容 | Q2: 装填 | R2: 特性 | S2: 重量 | T2: 花费 | V2: 名称 | W2: 具体

Sheet 职业数据
A1: 生涯职业 | B1: 起始资金 | C1: 骰点倍数 | D1: 骰点范围 | E1: 社会阶级 | F1: 王座币/月 | G1: 等级提升 | J1: 生涯职业 | K1: 文研员 | L1: 法务官 | M1: 杀手 | N1: 牧师 | O1: 卫队士兵 | P1: 帝国灵能者 | Q1: 流氓 | R1: 技术神甫 | S1: 战斗修女 | U1: =IF(人物!D3="","",IF(人物!Q4>=10000,8,IF(人物!Q4>=8000,7,IF(人物!Q4>=6000,6,IF(人物!Q4>=3000,5,IF(人物!Q4>=2000,4,IF(人物!Q4>=1000,3,IF(人物!Q4>=500,2,IF(人物!Q4>=1,1,"")))))))))
A2: 文研员 | B2: 100 | C2: 1 | D2: D10 | E2: 行伍（卫队士兵） | F2: 50 | G2: 5 | J2: 文研员 | K2: 档案员 | L2: 警员 | M2: 雇佣打手 | N2: 新信徒 | O2: 动员兵 | P2: 净化者 | Q2: 人渣 | R2: 仪表技工
A3: 执法者/法务官 | B3: 50 | C3: 2 | D3: D10 | E3: 仆役（法务官、灵能者） | F3: 70 | G3: 7 | J3: 执法者 | K3: 公证人 | L3: 治安队员 | M3: 潜行者 | N3: 入信者 | O3: 护卫队 | P3: 新生者 | Q3: 无赖 | R3: 技术工匠
A4: 杀手 | B4: 120 | C4: 3 | D4: D10 | E4: 学者（文研员） | F4: 100 | G4: 10 | J4: 杀手 | K4: 著述者 | L4: 探员 | M4: 夜鹰 | N4: 僧侣 | O4: 常备军 | P4: 候选人 | Q4: 不法分子 | R4: 电子修士
A5: 牧师 | B5: 300 | C5: 5 | D5: D10 | E5: 商人（杀手） | F5: 120 | G5: 12 | J5: 牧师 | K5: 作者 | L5: 调查员 | M5: 独行客 | N5: 传教士 | O5: 军士 | P5: 战斗术士 | Q5: 叛逆者 | R5: 工程师
A6: 卫队士兵 | B6: 70 | C6: 1 | D6: D10 | E6: 技术（技术神甫） | F6: 150 | G6: 15 | J6: 卫队士兵 | K6: 医师 | L6: 执法者 | M6: 刺客 | N6: 牧师 | O6: 老兵 | P6: 授权术士 | Q6: 浪人 | R6: 技术神甫
A7: 帝国灵能者 | B7: 50 | C7: 1 | D7: D5 | E7: 宗教（牧师） | F7: 200 | G7: 20 | J7: 帝国灵能者 | K7: 学者 | L7: 督战员 | M7: 刽子手 | N7: 告解神父 | O7: 突击队老兵 | P7: 术士中尉 | Q7: 歹徒 | R7: 技术巫师
A8: 流氓 | B8: 10 | C8: 1 | D8: D5 | E8: 贵族 | F8: 500 | G8: 50 | J8: 流氓 | K8: 律法编撰人 | L8: 司法官 | M8: 虚无者 | N8: 主教 | O8: 闪电战士 | P8: 辅战术士 | Q8: 劫匪 | R8: 运算先知
A9: 技术神甫 | B9: 150 | C9: 1 | D9: D10 | J9: 技术神甫 | K9: 学术专家 | L9: 司法长 | M9: 死亡君主 | N9: 圣师 | O9: 暴风突击队员 | P9: 参谋术士 | Q9: 龙头老大 | R9: 铸造者
A10: 战斗修女 | B10: 50 | C10: 0 | D10: 0 | J10: 战斗修女 | K10: 师范 | L10: 情报员 | M10: 自由之刃 | N10: 驱魔师 | O10: 中尉 | P10: 元素学者 | Q10: 仲介人 | R10: 机械执事
K11: 审计员 | L11: 治安官 | M11: 执照刺客 | N11: 狂信者 | O11: 队长 | P11: 生体学者 | Q11: 老油条 | R11: 机械神传教士
K12: 分析员 | L12: 审判长 | M12: 刺客统领 | N12: 赎罪者 | O12: 指挥官 | P12: 奥秘学者 | Q12: 诈骗高手 | R12: 漫游锻师
K13: 贤者 | O13: 侦察兵 | P13: 禁忌学者
O14: 射手 | P14: 至高学者
O15: 狙击手
J18: 文研员背景包 | K18: 法务官背景包 | L18: 杀手背景包 | M18: 牧师背景包 | N18: 卫队士兵背景包 | O18: 帝国灵能者背景包 | P18: 流氓背景包 | Q18: 技术神甫背景包 | R18: 战斗修女背景包
J19: 军务部军需官 | K19: 卡利西斯型谋杀 | L19: 星海锋刃 | M19: 塔苏斯至圣经院 | N19: 玛拉登陆点大屠杀 | O19: 魂覆暗影 | P19: 野兽屋奴商 | Q19: 图勒门徒 | R19: 戴罪之身
J20: 言究学社学者 | K20: 大锡诺菲亚空心人 | L20: 谋杀歌者 | M20: 托钵传教士 | N20: 边际远征军 | O20: 神皇之光指引 | P20: 冷行会情报员 | Q20: 索雷克斯圣光教 | R20: 赎罪者
J21: 虚空商贸员 | K21: 卢格南的红窟 | L21: 冥父之子 | M21: 救赎教派布焰使 | N21: 特伦奇战争老兵 | O21: 活梦魇 | P21: 托罗斯联盟 | Q21: 玛琉格利斯技术异端 | R21: 不可接触者
J22: 赎罪者 | K22: 正义，而非法律 | L22: 赎罪者 | M22: 异端教派 | N22: 赎罪者 | O22: 赎罪者 | P22: 赎罪者 | Q22: 赎罪者 | R22: 蒙福降生
J23: 持尔真名 | K23: 赎罪者 | L23: 不可接触者 | M23: 赎罪者 | N23: 不可接触者 | O23: 亚空间侵染 | P23: 不可接触者 | Q23: 不可接触者 | R23: 皈依者
J24: 不可接触者 | K24: 不可接触者 | L24: 亚空间侵染 | M24: 不可接触者 | N24: 亚空间侵染 | O24: 皈依者 | P24: 亚空间侵染 | Q24: 亚空间侵染 | R24: 朝圣者
J25: 亚空间侵染 | K25: 亚空间侵染 | L25: 命线缠绕 | M25: 亚空间侵染 | N25: 命线缠绕 | O25: 朝圣者 | P25: 命线缠绕 | Q25: 皈依者 | R25: 血肉圣化
J26: 命线缠绕 | K26: 命线缠绕 | L26: 皈依者 | M26: 命线缠绕 | N26: 皈依者 | O26: 血肉圣化 | P26: 皈依者 | Q26: 背弃万机神之人 | R26: 降魔者
J27: 皈依者 | K27: 皈依者 | L27: 朝圣者 | M27: 蒙福降生 | N27: 朝圣者 | O27: 降魔者 | P27: 朝圣者 | Q27: 血肉圣化 | R27: 宿命噬者
J28: 朝圣者 | K28: 朝圣者 | L28: 血肉圣化 | M28: 皈依者 | N28: 得见神迹 | O28: 宿命噬者 | P28: 血肉圣化 | Q28: 降魔者 | R28: 宿主备身
J29: 血肉圣化 | K29: 血肉圣化 | L29: 降魔者 | M29: 朝圣者 | N29: 血肉圣化 | O29: 巢都马仔 | P29: 降魔者 | Q29: 宿命噬者 | R29: 冒充者
J30: 降魔者 | K30: 降魔者 | L30: 宿命噬者 | M30: 血肉圣化 | N30: 降魔者 | O30: 冒充者 | P30: 宿命噬者 | Q30: 冷贸易商 | R30: 无罪证明
J31: 宿命噬者 | K31: 宿命噬者 | L31: 宿主备身 | M31: 降魔者 | N31: 宿命噬者 | O31: 无罪证明 | P31: 宿主备身 | Q31: 冒充者
J32: 宿主备身 | K32: 宿主备身 | L32: 冷贸易商 | M32: 宿命噬者 | N32: 宿主备身 | P32: 冷贸易商 | Q32: 无罪证明
J33: 冷贸易商 | K33: 执法者 | L33: 执法者 | M33: 宿主备身 | N33: 巢都马仔 | P33: 执法者 | Q33: 西贝柳斯拾荒者
J34: 执法者 | K34: 冒充者 | L34: 巢都马仔 | M34: 冷贸易商 | N34: 冒充者 | P34: 巢都马仔 | Q34: 底巢商人
J35: 冒充者 | K35: 无罪证明 | L35: 冒充者 | M35: 冒充者 | N35: 无罪证明 | P35: 冒充者
J36: 卡斯巴利卡“贵族” | K36: 西贝柳斯拾荒者 | L36: 无罪证明 | M36: 无罪证明 | N36: 西贝柳斯拾荒者 | P36: 卡斯巴利卡“贵族”
J37: 无罪证明 | K37: 底巢商人 | M37: 底巢商人 | N37: 底巢商人 | P37: 无罪证明
J38: 西贝柳斯拾荒者 | P38: 西贝柳斯拾荒者
J39: 底巢商人 | P39: 底巢商人

Sheet 人物数据
A1: 出目 | B1: 预言 | C1: 影响 | D1: SB+TB | E1: 携带 | F1: 举起 | G1: 拖拽 | H1: 缩写 | I1: AB | J1: 部分移动 | K1: 完整移动 | L1: 冲刺 | M1: 奔跑 | N1: 每分钟 | O1: 每小时 | P1: 每天 | Q1: 体型 | R1: 检定调整 | S1: 起源 | T1: {=_xlfn.UNIQUE(灵能表[灵能类别])} -> 次级灵能 | U1: {=IFERROR(_xlfn._xlws.FILTER(灵能表[灵能名称],灵能表[灵能类别]=灵能!E11),"")} | V1: {=_xlfn.UNIQUE(_xlfn._xlws.FILTER(_xlfn.VSTACK(武器与防具与弹药!B6:I24,自填扩展!A3:H60),INDEX(_xlfn.VSTACK(武器与防具与弹药!B6:I24,自填扩展!A3:H60),,1)<>""))} -> 斧 | W1: 格斗 | X1: — | Y1: 1d10+1 R | Z1: 0 | AA1: 原始，失衡 | AB1: 4 | AC1: 20 | AE1: {=_xlfn.UNIQUE(_xlfn._xlws.FILTER(_xlfn.VSTACK(武器与防具与弹药!B27:L63,自填扩展!J3:T60),INDEX(_xlfn.VSTACK(武器与防具与弹药!B27:L63,自填扩展!J3:T60),,1)<>""))} -> 激光手枪 | AF1: 手枪 | AG1: 30m | AH1: S/–/– | AI1: 1d10+2 E | AJ1: 0 | AK1: 30 | AL1: 完整 | AM1: 可靠 | AN1: 1.5 | AO1: 50 | AQ1: {=_xlfn.UNIQUE(_xlfn._xlws.FILTER(_xlfn.VSTACK(附表!W3:X126,自填扩展!V3:W60),INDEX(_xlfn.VSTACK(附表!W3:X126,自填扩展!V3:W60),,1)<>""))} -> 傲慢护甲 | AR1: 你将自己包裹在由轻蔑与憎恶织就的护甲里。每次得到堕落点时，你都可以抵抗掉1点。另外，作为一个自由动作，你可以进行一个意志检定以尝试在一轮之内忽略你积累的堕落的影响。 | AW1: =_xlfn.IFNA(IF(人物!B98=0,"",VLOOKUP(人物!B98,人物数据!$AQ$1:人物数据!$AR$300,2,FALSE)),"") | BB1: =_xlfn.IFNA(IF(武备!B20=0,"",VLOOKUP(武备!B20,武器与防具与弹药!$B$66:武器与防具与弹药!$H$91,2,FALSE)),"") | BC1: =_xlfn.IFNA(IF(武备!B20=0,"",VLOOKUP(武备!B20,武器与防具与弹药!$B$66:武器与防具与弹药!$H$91,3,FALSE)),"") | BD1: =_xlfn.IFNA(IF(武备!B20=0,"",VLOOKUP(武备!B20,武器与防具与弹药!$B$66:武器与防具与弹药!$H$91,4,FALSE)),"") | BE1: =_xlfn.IFNA(IF(武备!B20=0,"",VLOOKUP(武备!B20,武器与防具与弹药!$B$66:武器与防具与弹药!$H$91,5,FALSE)),"") | BF1: =_xlfn.IFNA(IF(武备!B20=0,"",VLOOKUP(武备!B20,武器与防具与弹药!$B$66:武器与防具与弹药!$H$91,6,FALSE)),"") | BG1: =_xlfn.IFNA(IF(武备!B20=0,"",VLOOKUP(武备!B20,武器与防具与弹药!$B$66:武器与防具与弹药!$H$91,7,FALSE)),"") | BI1: =_xlfn.IFNA(IF(武备!B35=0,"",VLOOKUP(武备!B35,武器与防具与弹药!$AI$6:武器与防具与弹药!$AM$32,2,FALSE)),"") | BJ1: =_xlfn.IFNA(IF(武备!B35=0,"",VLOOKUP(武备!B35,武器与防具与弹药!$AI$6:武器与防具与弹药!$AM$32,3,FALSE)),"") | BK1: =_xlfn.IFNA(IF(武备!B35=0,"",VLOOKUP(武备!B35,武器与防具与弹药!$AI$6:武器与防具与弹药!$AM$32,4,FALSE)),"") | BL1: =_xlfn.IFNA(IF(武备!B35=0,"",VLOOKUP(武备!B35,武器与防具与弹药!$AI$6:武器与防具与弹药!$AM$32,5,FALSE)),"") | BN1: =_xlfn.IFNA(IF(武备!C43=0,"",VLOOKUP(武备!C43,附表!AC2:附表!AF61,2,FALSE)),"") | BO1: =_xlfn.IFNA(IF(武备!C43=0,"",VLOOKUP(武备!C43,附表!$AC$2:附表!$AF$61,3,FALSE)),"") | BP1: =_xlfn.IFNA(IF(武备!C43=0,"",VLOOKUP(武备!C43,附表!$AC$2:附表!$AF$61,4,FALSE)),"") | BR1: =_xlfn.IFNA(IF(武备!K75=0,"",VLOOKUP(武备!K75,附表!$AJ$53:附表!$AM$64,2,FALSE)),"") | BU1: {=_xlfn.IFNA(IF(武备!B4=0,"",VLOOKUP(武备!B4,人物数据!$V$1:$AC$300,{1,2,3,4,5,6,7,8},FALSE)),"")} | CD1: {=_xlfn.IFNA(IF(武备!B10=0,"",VLOOKUP(武备!B10,人物数据!$AE$1:$AO$300,{1,2,3,4,5,6,7,8,9,10,11},FALSE)),"")} | CP1: {=_xlfn.IFNA(IF(人物!T65=0,"",VLOOKUP(人物!T65,附表!$B$70:$D$118,{1,2,3},FALSE)),"")}
A2: 1 | B2: 外表的变异，揭示着内心的腐化。 | C2: 以一个次级变异状态开始游戏。 | D2: 0 | E2: 0.9 | F2: 2.25 | G2: 4.5 | H2: 格 | I2: 0 | J2: 0 | K2: 0 | L2: 0 | M2: =6*I2 -> 0 | N2: 12m | O2: 0.75km | P2: 7km | Q2: 微小 | R2: -30 | S2: 帝国世界 | T2: 生化学科 | V2: 黄铜指虎 | W2: 格斗 | X2: — | Y2: 1d5−1 I | Z2: 0 | AA2: 原始 | AB2: 0.5 | AC2: 5 | AE2: 激光卡宾枪 | AF2: 基本 | AG2: 60m | AH2: S/2/– | AI2: 1d10+2 E | AJ2: 0 | AK2: 40 | AL2: 完整 | AM2: 可靠 | AN2: 3 | AO2: 75 | AQ2: 拨挡飞箭 | AR2: 你可以格挡投掷武器或原始远程武器。 | AW2: =_xlfn.IFNA(IF(人物!B99=0,"",VLOOKUP(人物!B99,人物数据!$AQ$1:人物数据!$AR$300,2,FALSE)),"") | BB2: =_xlfn.IFNA(IF(武备!B21=0,"",VLOOKUP(武备!B21,武器与防具与弹药!$B$66:武器与防具与弹药!$H$91,2,FALSE)),"") | BC2: =_xlfn.IFNA(IF(武备!B21=0,"",VLOOKUP(武备!B21,武器与防具与弹药!$B$66:武器与防具与弹药!$H$91,3,FALSE)),"") | BD2: =_xlfn.IFNA(IF(武备!B21=0,"",VLOOKUP(武备!B21,武器与防具与弹药!$B$66:武器与防具与弹药!$H$91,4,FALSE)),"") | BE2: =_xlfn.IFNA(IF(武备!B21=0,"",VLOOKUP(武备!B21,武器与防具与弹药!$B$66:武器与防具与弹药!$H$91,5,FALSE)),"") | BF2: =_xlfn.IFNA(IF(武备!B21=0,"",VLOOKUP(武备!B21,武器与防具与弹药!$B$66:武器与防具与弹药!$H$91,6,FALSE)),"") | BG2: =_xlfn.IFNA(IF(武备!B21=0,"",VLOOKUP(武备!B21,武器与防具与弹药!$B$66:武器与防具与弹药!$H$91,7,FALSE)),"") | BI2: =_xlfn.IFNA(IF(武备!B36=0,"",VLOOKUP(武备!B36,武器与防具与弹药!$AI$6:武器与防具与弹药!$AM$32,2,FALSE)),"") | BJ2: =_xlfn.IFNA(IF(武备!B36=0,"",VLOOKUP(武备!B36,武器与防具与弹药!$AI$6:武器与防具与弹药!$AM$32,3,FALSE)),"") | BK2: =_xlfn.IFNA(IF(武备!B36=0,"",VLOOKUP(武备!B36,武器与防具与弹药!$AI$6:武器与防具与弹药!$AM$32,4,FALSE)),"") | BL2: =_xlfn.IFNA(IF(武备!B36=0,"",VLOOKUP(武备!B36,武器与防具与弹药!$AI$6:武器与防具与弹药!$AM$32,5,FALSE)),"") | BN2: =_xlfn.IFNA(IF(武备!C44=0,"",VLOOKUP(武备!C44,附表!$AC$2:附表!$AF$61,2,FALSE)),"") | BO2: =_xlfn.IFNA(IF(武备!C44=0,"",VLOOKUP(武备!C44,附表!$AC$2:附表!$AF$61,3,FALSE)),"") | BP2: =_xlfn.IFNA(IF(武备!C44=0,"",VLOOKUP(武备!C44,附表!$AC$2:附表!$AF$61,4,FALSE)),"") | BR2: =_xlfn.IFNA(IF(武备!K76=0,"",VLOOKUP(武备!K76,附表!$AJ$53:附表!$AM$64,2,FALSE)),"") | BU2: {=_xlfn.IFNA(IF(武备!B5=0,"",VLOOKUP(武备!B5,人物数据!$V$1:$AC$300,{1,2,3,4,5,6,7,8},FALSE)),"")} | CD2: {=_xlfn.IFNA(IF(武备!B12=0,"",VLOOKUP(武备!B12,人物数据!$AE$1:$AO$300,{1,2,3,4,5,6,7,8,9,10,11},FALSE)),"")} | CP2: {=_xlfn.IFNA(IF(人物!T78=0,"",VLOOKUP(人物!T78,附表!$B$70:$D$118,{1,2,3},FALSE)),"")}
A3: 2 | B3: 只有疯狂者才有成功所需的力量，只有成功者才有权定义何为理智。 | C3: 以2点失心点数状态开始游戏。 | D3: 1 | E3: 2.25 | F3: 4.5 | G3: 9 | H3: 射 | I3: 1 | J3: 1 | K3: 2 | L3: 3 | M3: =6*I3 -> 6 | N3: 24m | O3: 1.5km | P3: 15km | Q3: 超小 | R3: -20 | S3: 马卡贝斯五号 | T3: 预言学科 | V3: 棍棒 | W3: 格斗 | X3: — | Y3: 1d10 I | Z3: 0 | AA3: 原始 | AB3: 2 | AC3: 5 | AE3: 激光步枪 | AF3: 基本 | AG3: 100m | AH3: S/3/– | AI3: 1d10+3 E | AJ3: 0 | AK3: 60 | AL3: 完整 | AM3: 可靠 | AN3: 4 | AO3: 75 | AQ3: 藏物暗袋 | AR3: 你身上有个用于藏匿不超过巴掌大小的物件的秘密隔间，可能是某个嵌入你体内的小袋，或是半机械移植物的一部分。一个困难（−10 ）程度的搜索检定可以发现被藏起来的物品。如果搜身者借助于医学扫描仪，生化嗅探器等设备，检定变为普通（ +10 ）。你身上有个用于藏匿不超过巴掌大小的物件的秘密隔间，可能是某个嵌入你体内的小袋，或是半机械移植物的一部分。一个困难（−10 ）程度的搜索检定可以发现被藏起来的物品。如果搜身者借助于医学扫描仪，生化嗅探器等设备，检定变为普通（ +10 ）。 | AW3: =_xlfn.IFNA(IF(人物!B100=0,"",VLOOKUP(人物!B100,人物数据!$AQ$1:人物数据!$AR$300,2,FALSE)),"") | BB3: =_xlfn.IFNA(IF(武备!B22=0,"",VLOOKUP(武备!B22,武器与防具与弹药!$B$66:武器与防具与弹药!$H$91,2,FALSE)),"") | BC3: =_xlfn.IFNA(IF(武备!B22=0,"",VLOOKUP(武备!B22,武器与防具与弹药!$B$66:武器与防具与弹药!$H$91,3,FALSE)),"") | BD3: =_xlfn.IFNA(IF(武备!B22=0,"",VLOOKUP(武备!B22,武器与防具与弹药!$B$66:武器与防具与弹药!$H$91,4,FALSE)),"") | BE3: =_xlfn.IFNA(IF(武备!B22=0,"",VLOOKUP(武备!B22,武器与防具与弹药!$B$66:武器与防具与弹药!$H$91,5,FALSE)),"") | BF3: =_xlfn.IFNA(IF(武备!B22=0,"",VLOOKUP(武备!B22,武器与防具与弹药!$B$66:武器与防具与弹药!$H$91,6,FALSE)),"") | BG3: =_xlfn.IFNA(IF(武备!B22=0,"",VLOOKUP(武备!B22,武器与防具与弹药!$B$66:武器与防具与弹药!$H$91,7,FALSE)),"") | BI3: =_xlfn.IFNA(IF(武备!B37=0,"",VLOOKUP(武备!B37,武器与防具与弹药!$AI$6:武器与防具与弹药!$AM$32,2,FALSE)),"") | BJ3: =_xlfn.IFNA(IF(武备!B37=0,"",VLOOKUP(武备!B37,武器与防具与弹药!$AI$6:武器与防具与弹药!$AM$32,3,FALSE)),"") | BK3: =_xlfn.IFNA(IF(武备!B37=0,"",VLOOKUP(武备!B37,武器与防具与弹药!$AI$6:武器与防具与弹药!$AM$32,4,FALSE)),"") | BL3: =_xlfn.IFNA(IF(武备!B37=0,"",VLOOKUP(武备!B37,武器与防具与弹药!$AI$6:武器与防具与弹药!$AM$32,5,FALSE)),"") | BN3: =_xlfn.IFNA(IF(武备!C45=0,"",VLOOKUP(武备!C45,附表!$AC$2:附表!$AF$61,2,FALSE)),"") | BO3: =_xlfn.IFNA(IF(武备!C45=0,"",VLOOKUP(武备!C45,附表!$AC$2:附表!$AF$61,3,FALSE)),"") | BP3: =_xlfn.IFNA(IF(武备!C45=0,"",VLOOKUP(武备!C45,附表!$AC$2:附表!$AF$61,4,FALSE)),"") | BR3: =_xlfn.IFNA(IF(武备!K77=0,"",VLOOKUP(武备!K77,附表!$AJ$53:附表!$AM$64,2,FALSE)),"") | BU3: {=_xlfn.IFNA(IF(武备!B6=0,"",VLOOKUP(武备!B6,人物数据!$V$1:$AC$300,{1,2,3,4,5,6,7,8},FALSE)),"")} | CD3: {=_xlfn.IFNA(IF(武备!B14=0,"",VLOOKUP(武备!B14,人物数据!$AE$1:$AO$300,{1,2,3,4,5,6,7,8,9,10,11},FALSE)),"")}
A4: 3 | B4: 只有疯狂者才有成功所需的力量，只有成功者才有权定义何为理智。 | C4: 以2点失心点数状态开始游戏。 | D4: 2 | E4: 4.5 | F4: 9 | G4: 18 | H4: 力 | I4: 2 | J4: 2 | K4: 4 | L4: 6 | M4: =6*I4 -> 12 | N4: 48m | O4: 3km | P4: 30km | Q4: 小型 | R4: -10 | S4: 锡诺菲亚 | T4: 操火学科 | V4: 链枷 | W4: 格斗† | X4: — | Y4: 1d10+2 I | Z4: 0 | AA4: 原始，柔韧 | AB4: 4 | AC4: 20 | AE4: 激光长枪 | AF4: 基本 | AG4: 150m | AH4: S/–/– | AI4: 1d10+3 E | AJ4: 1 | AK4: 40 | AL4: 完整 | AM4: 可靠，精准 | AN4: 4.5 | AO4: 100 | AQ4: 出生入死 | AR4: 只要看到你，你的下属免受恐惧和压制。 | AW4: =_xlfn.IFNA(IF(人物!B101=0,"",VLOOKUP(人物!B101,人物数据!$AQ$1:人物数据!$AR$300,2,FALSE)),"") | BB4: =_xlfn.IFNA(IF(武备!B23=0,"",VLOOKUP(武备!B23,武器与防具与弹药!$B$66:武器与防具与弹药!$H$91,2,FALSE)),"") | BC4: =_xlfn.IFNA(IF(武备!B23=0,"",VLOOKUP(武备!B23,武器与防具与弹药!$B$66:武器与防具与弹药!$H$91,3,FALSE)),"") | BD4: =_xlfn.IFNA(IF(武备!B23=0,"",VLOOKUP(武备!B23,武器与防具与弹药!$B$66:武器与防具与弹药!$H$91,4,FALSE)),"") | BE4: =_xlfn.IFNA(IF(武备!B23=0,"",VLOOKUP(武备!B23,武器与防具与弹药!$B$66:武器与防具与弹药!$H$91,5,FALSE)),"") | BF4: =_xlfn.IFNA(IF(武备!B23=0,"",VLOOKUP(武备!B23,武器与防具与弹药!$B$66:武器与防具与弹药!$H$91,6,FALSE)),"") | BG4: =_xlfn.IFNA(IF(武备!B23=0,"",VLOOKUP(武备!B23,武器与防具与弹药!$B$66:武器与防具与弹药!$H$91,7,FALSE)),"") | BI4: =_xlfn.IFNA(IF(武备!B38=0,"",VLOOKUP(武备!B38,武器与防具与弹药!$AI$6:武器与防具与弹药!$AM$32,2,FALSE)),"") | BJ4: =_xlfn.IFNA(IF(武备!B38=0,"",VLOOKUP(武备!B38,武器与防具与弹药!$AI$6:武器与防具与弹药!$AM$32,3,FALSE)),"") | BK4: =_xlfn.IFNA(IF(武备!B38=0,"",VLOOKUP(武备!B38,武器与防具与弹药!$AI$6:武器与防具与弹药!$AM$32,4,FALSE)),"") | BL4: =_xlfn.IFNA(IF(武备!B38=0,"",VLOOKUP(武备!B38,武器与防具与弹药!$AI$6:武器与防具与弹药!$AM$32,5,FALSE)),"") | BN4: =_xlfn.IFNA(IF(武备!C46=0,"",VLOOKUP(武备!C46,附表!$AC$2:附表!$AF$61,2,FALSE)),"") | BO4: =_xlfn.IFNA(IF(武备!C46=0,"",VLOOKUP(武备!C46,附表!$AC$2:附表!$AF$61,3,FALSE)),"") | BP4: =_xlfn.IFNA(IF(武备!C46=0,"",VLOOKUP(武备!C46,附表!$AC$2:附表!$AF$61,4,FALSE)),"") | BR4: =_xlfn.IFNA(IF(武备!K78=0,"",VLOOKUP(武备!K78,附表!$AJ$53:附表!$AM$64,2,FALSE)),"") | BU4: {=_xlfn.IFNA(IF(武备!B7=0,"",VLOOKUP(武备!B7,人物数据!$V$1:$AC$300,{1,2,3,4,5,6,7,8},FALSE)),"")} | CD4: {=_xlfn.IFNA(IF(武备!B16=0,"",VLOOKUP(武备!B16,人物数据!$AE$1:$AO$300,{1,2,3,4,5,6,7,8,9,10,11},FALSE)),"")}
A5: 4 | B5: 罪恶越是深藏于内心，越是能够腐化人的一切。 | C5: 以3点堕落点数开始游戏。 | D5: 3 | E5: 9 | F5: =2*E5 -> 18 | G5: =2*F5 -> 36 | H5: 坚 | I5: 3 | J5: 3 | K5: 6 | L5: 9 | M5: =6*I5 -> 18 | N5: 72m | O5: 4km | P5: 40km | Q5: 中型 | R5: 0 | S5: 巢都世界 | T5: 遥感学科 | V5: 加重武器 | W5: 格斗† | X5: — | Y5: 2d10 R | Z5: 2 | AA5: 原始，笨重 | AB5: 7 | AC5: 70 | AE5: 单兵激光炮 | AF5: 重型 | AG5: 300m | AH5: S/–/– | AI5: 5d10+10 E | AJ5: 10 | AK5: 5 | AL5: 2完整 | AM5: — | AN5: 55 | AO5: 5000 | AQ5: 纯净思维仪式 | AR5: 你将自己的右脑切除，代之以思考电路。你变得沉默寡言，不再感受到任何情绪，脑中只有冰冷纯粹的逻辑。你免疫恐惧，压制，以及任何基于情绪的效果。GM可以把不再适用于你的精神失常去除，代之以相等程度的其它精神失常加重。 | AW5: =_xlfn.IFNA(IF(人物!B102=0,"",VLOOKUP(人物!B102,人物数据!$AQ$1:人物数据!$AR$300,2,FALSE)),"") | BB5: =_xlfn.IFNA(IF(武备!B24=0,"",VLOOKUP(武备!B24,武器与防具与弹药!$B$66:武器与防具与弹药!$H$91,2,FALSE)),"") | BC5: =_xlfn.IFNA(IF(武备!B24=0,"",VLOOKUP(武备!B24,武器与防具与弹药!$B$66:武器与防具与弹药!$H$91,3,FALSE)),"") | BD5: =_xlfn.IFNA(IF(武备!B24=0,"",VLOOKUP(武备!B24,武器与防具与弹药!$B$66:武器与防具与弹药!$H$91,4,FALSE)),"") | BE5: =_xlfn.IFNA(IF(武备!B24=0,"",VLOOKUP(武备!B24,武器与防具与弹药!$B$66:武器与防具与弹药!$H$91,5,FALSE)),"") | BF5: =_xlfn.IFNA(IF(武备!B24=0,"",VLOOKUP(武备!B24,武器与防具与弹药!$B$66:武器与防具与弹药!$H$91,6,FALSE)),"") | BG5: =_xlfn.IFNA(IF(武备!B24=0,"",VLOOKUP(武备!B24,武器与防具与弹药!$B$66:武器与防具与弹药!$H$91,7,FALSE)),"") | BI5: =_xlfn.IFNA(IF(武备!B39=0,"",VLOOKUP(武备!B39,武器与防具与弹药!$AI$6:武器与防具与弹药!$AM$32,2,FALSE)),"") | BJ5: =_xlfn.IFNA(IF(武备!B39=0,"",VLOOKUP(武备!B39,武器与防具与弹药!$AI$6:武器与防具与弹药!$AM$32,3,FALSE)),"") | BK5: =_xlfn.IFNA(IF(武备!B39=0,"",VLOOKUP(武备!B39,武器与防具与弹药!$AI$6:武器与防具与弹药!$AM$32,4,FALSE)),"") | BL5: =_xlfn.IFNA(IF(武备!B39=0,"",VLOOKUP(武备!B39,武器与防具与弹药!$AI$6:武器与防具与弹药!$AM$32,5,FALSE)),"") | BN5: =_xlfn.IFNA(IF(武备!C47=0,"",VLOOKUP(武备!C47,附表!$AC$2:附表!$AF$61,2,FALSE)),"") | BO5: =_xlfn.IFNA(IF(武备!C47=0,"",VLOOKUP(武备!C47,附表!$AC$2:附表!$AF$61,3,FALSE)),"") | BP5: =_xlfn.IFNA(IF(武备!C47=0,"",VLOOKUP(武备!C47,附表!$AC$2:附表!$AF$61,4,FALSE)),"") | BR5: =_xlfn.IFNA(IF(武备!K79=0,"",VLOOKUP(武备!K79,附表!$AJ$53:附表!$AM$64,2,FALSE)),"") | BU5: {=_xlfn.IFNA(IF(武备!B8=0,"",VLOOKUP(武备!B8,人物数据!$V$1:$AC$300,{1,2,3,4,5,6,7,8},FALSE)),"")}
A6: 5 | B6: 罪恶越是深藏于内心，越是能够腐化人的一切。 | C6: 以3点堕落点数开始游戏。 | D6: 4 | E6: 18 | F6: 36 | G6: 72 | H6: 敏 | I6: 4 | J6: 4 | K6: 8 | L6: 12 | M6: =6*I6 -> 24 | N6: 96m | O6: 6km | P6: 60km | Q6: 大型 | R6: 10 | S6: 巢都变种人 | T6: 传心学科 | V6: 战锤 | W6: 格斗 | X6: — | Y6: 1d10+1 I | Z6: 0 | AA6: 原始，失衡 | AB6: 4 | AC6: 10 | AE6: 自动手枪 | AF6: 手枪 | AG6: 30m | AH6: S/–/6 | AI6: 1d10+2 I | AJ6: 0 | AK6: 18 | AL6: 完整 | AM6: — | AN6: 2.5 | AO6: 75 | AQ6: 磁力飞跃 | AR6: 与磁力优雅效果相同，除了以下几点：持续时间变为2d10+TB分钟；可以完全抵消坠落伤害；每十二小时可使用两次。 | AW6: =_xlfn.IFNA(IF(人物!B103=0,"",VLOOKUP(人物!B103,人物数据!$AQ$1:人物数据!$AR$300,2,FALSE)),"") | BB6: =_xlfn.IFNA(IF(武备!B25=0,"",VLOOKUP(武备!B25,武器与防具与弹药!$B$66:武器与防具与弹药!$H$91,2,FALSE)),"") | BC6: =_xlfn.IFNA(IF(武备!B25=0,"",VLOOKUP(武备!B25,武器与防具与弹药!$B$66:武器与防具与弹药!$H$91,3,FALSE)),"") | BD6: =_xlfn.IFNA(IF(武备!B25=0,"",VLOOKUP(武备!B25,武器与防具与弹药!$B$66:武器与防具与弹药!$H$91,4,FALSE)),"") | BE6: =_xlfn.IFNA(IF(武备!B25=0,"",VLOOKUP(武备!B25,武器与防具与弹药!$B$66:武器与防具与弹药!$H$91,5,FALSE)),"") | BF6: =_xlfn.IFNA(IF(武备!B25=0,"",VLOOKUP(武备!B25,武器与防具与弹药!$B$66:武器与防具与弹药!$H$91,6,FALSE)),"") | BG6: =_xlfn.IFNA(IF(武备!B25=0,"",VLOOKUP(武备!B25,武器与防具与弹药!$B$66:武器与防具与弹药!$H$91,7,FALSE)),"") | BI6: =_xlfn.IFNA(IF(武备!B40=0,"",VLOOKUP(武备!B40,武器与防具与弹药!$AI$6:武器与防具与弹药!$AM$32,2,FALSE)),"") | BJ6: =_xlfn.IFNA(IF(武备!B40=0,"",VLOOKUP(武备!B40,武器与防具与弹药!$AI$6:武器与防具与弹药!$AM$32,3,FALSE)),"") | BK6: =_xlfn.IFNA(IF(武备!B40=0,"",VLOOKUP(武备!B40,武器与防具与弹药!$AI$6:武器与防具与弹药!$AM$32,4,FALSE)),"") | BL6: =_xlfn.IFNA(IF(武备!B40=0,"",VLOOKUP(武备!B40,武器与防具与弹药!$AI$6:武器与防具与弹药!$AM$32,5,FALSE)),"") | BN6: =_xlfn.IFNA(IF(武备!C48=0,"",VLOOKUP(武备!C48,附表!$AC$2:附表!$AF$61,2,FALSE)),"") | BO6: =_xlfn.IFNA(IF(武备!C48=0,"",VLOOKUP(武备!C48,附表!$AC$2:附表!$AF$61,3,FALSE)),"") | BP6: =_xlfn.IFNA(IF(武备!C48=0,"",VLOOKUP(武备!C48,附表!$AC$2:附表!$AF$61,4,FALSE)),"") | BU6: {=_xlfn.IFNA(IF(武备!B9=0,"",VLOOKUP(武备!B9,人物数据!$V$1:$AC$300,{1,2,3,4,5,6,7,8},FALSE)),"")} | CD6: {=_xlfn.IFNA(IF(武备!B15=0,"",VLOOKUP(武备!B15,人物数据!$AE$1:$AO$300,{1,2,3,4,5,6,7,8,9,10,11},FALSE)),"")}
A7: 6 | B7: 罪恶越是深藏于内心，越是能够腐化人的一切。 | C7: 以3点堕落点数开始游戏。 | D7: 5 | E7: 27 | F7: 54 | G7: 108 | H7: 智 | I7: 5 | J7: 5 | K7: 10 | L7: 15 | M7: =6*I7 -> 30 | N7: 120m | O7: 7km | P7: 70km | Q7: 超大 | R7: 20 | S7: 枪灰城 | T7: 次级秘仪 | V7: 临时武器 | W7: 格斗 | X7: — | Y7: d10−2 I | Z7: 0 | AA7: 原始，失衡 | AB7: — | AC7: — | AE7: 短管左轮 | AF7: 手枪 | AG7: 30m | AH7: S/–/– | AI7: 1d10+3 I | AJ7: 0 | AK7: 6 | AL7: 2完整 | AM7: 可靠 | AN7: 1 | AO7: 40 | AQ7: 磁力优雅 | AR7: 长时间的辛苦钻研让你掌握了机械神无尽秘密中的一个。花费一个部分动作，你可以在距地面 20–30 米处悬浮，持续时间等于1d10+TB 分钟。你能以正常步行速度移动，但必须保持移动，或者花费部分动作盘旋以保持悬浮状态。你可以在坠落时使用该能力以抵消坠落伤害，这样的话，你的坠落伤害变为固定的 1d10+3 。磁力优雅会消耗储压线圈能量，因此每十二小时只能使用一次。 | AW7: =_xlfn.IFNA(IF(人物!B104=0,"",VLOOKUP(人物!B104,人物数据!$AQ$1:人物数据!$AR$300,2,FALSE)),"") | BN7: =_xlfn.IFNA(IF(武备!C49=0,"",VLOOKUP(武备!C49,附表!$AC$2:附表!$AF$61,2,FALSE)),"") | BO7: =_xlfn.IFNA(IF(武备!C49=0,"",VLOOKUP(武备!C49,附表!$AC$2:附表!$AF$61,3,FALSE)),"") | BP7: =_xlfn.IFNA(IF(武备!C49=0,"",VLOOKUP(武备!C49,附表!$AC$2:附表!$AF$61,4,FALSE)),"") | BU7: {=_xlfn.IFNA(IF(武备!B10=0,"",VLOOKUP(武备!B10,人物数据!$V$1:$AC$300,{1,2,3,4,5,6,7,8},FALSE)),"")}
A8: 7 | B8: 罪恶越是深藏于内心，越是能够腐化人的一切。 | C8: 以3点堕落点数开始游戏。 | D8: 6 | E8: 36 | F8: 72 | G8: 144 | H8: 感 | I8: 6 | J8: 6 | K8: 12 | L8: 18 | M8: =6*I8 -> 36 | N8: 144m | O8: 9km | P8: 90km | Q8: 巨大 | R8: 30 | S8: 沃格巢都 | T8: 高阶秘仪 | V8: 刀 | W8: 格斗 投掷 | X8: 3m | Y8: 1d5 R | Z8: 0 | AA8: 原始 | AB8: 0.5 | AC8: 5 | AE8: 短管连发枪 | AF8: 手枪 | AG8: 30m | AH8: S/3/– | AI8: 1d10+3 I | AJ8: 0 | AK8: 9 | AL8: 完整 | AM8: — | AN8: 1.5 | AO8: 50 | AQ8: 抵抗* | AR8: 子项：低温，恐惧，高热，毒素，灵能抵抗特定状态的检定+10。 | AW8: =_xlfn.IFNA(IF(人物!B105=0,"",VLOOKUP(人物!B105,人物数据!$AQ$1:人物数据!$AR$300,2,FALSE)),"") | BN8: =_xlfn.IFNA(IF(武备!C50=0,"",VLOOKUP(武备!C50,附表!$AC$2:附表!$AF$61,2,FALSE)),"") | BO8: =_xlfn.IFNA(IF(武备!C50=0,"",VLOOKUP(武备!C50,附表!$AC$2:附表!$AF$61,3,FALSE)),"") | BP8: =_xlfn.IFNA(IF(武备!C50=0,"",VLOOKUP(武备!C50,附表!$AC$2:附表!$AF$61,4,FALSE)),"") | BU8: {=_xlfn.IFNA(IF(武备!B11=0,"",VLOOKUP(武备!B11,人物数据!$V$1:$AC$300,{1,2,3,4,5,6,7,8},FALSE)),"")} | CD8: {=_xlfn.IFNA(IF(武备!B17=0,"",VLOOKUP(武备!B17,人物数据!$AE$1:$AO$300,{1,2,3,4,5,6,7,8,9,10,11},FALSE)),"")}
A9: 8 | B9: 所谓清白无辜，只是虚妄的假象。 | C9: 以1点失心点和1点堕落点状态开始游戏。 | D9: 7 | E9: 45 | F9: 90 | G9: 180 | H9: 意 | I9: 7 | J9: 7 | K9: 14 | L9: 21 | M9: =6*I9 -> 42 | N9: 168m | O9: 10km | P9: 100km | S9: 蛮荒世界 | T9: 其他灵能 | V9: 飞刀或手里剑 | W9: 投掷 | X9: 5m | Y9: 1d5 R | Z9: 0 | AA9: 原始 | AB9: 0.5 | AC9: 5 | AE9: 手铳 | AF9: 手枪 | AG9: 35m | AH9: S/–/– | AI9: 1d10+4 I | AJ9: 2 | AK9: 5 | AL9: 2完整 | AM9: — | AN9: 3 | AO9: 65 | AQ9: 电子接口 | AR9: 你能使用电子接口访问数据点和联系机魂。当你连接到数据点时，搜集信息，技术应用，和常识检定可以获得+10加值。 | AW9: =_xlfn.IFNA(IF(人物!B106=0,"",VLOOKUP(人物!B106,人物数据!$AQ$1:人物数据!$AR$300,2,FALSE)),"") | BN9: =_xlfn.IFNA(IF(武备!C51=0,"",VLOOKUP(武备!C51,附表!$AC$2:附表!$AF$61,2,FALSE)),"") | BO9: =_xlfn.IFNA(IF(武备!C51=0,"",VLOOKUP(武备!C51,附表!$AC$2:附表!$AF$61,3,FALSE)),"") | BP9: =_xlfn.IFNA(IF(武备!C51=0,"",VLOOKUP(武备!C51,附表!$AC$2:附表!$AF$61,4,FALSE)),"") | BU9: {=_xlfn.IFNA(IF(武备!B12=0,"",VLOOKUP(武备!B12,人物数据!$V$1:$AC$300,{1,2,3,4,5,6,7,8},FALSE)),"")} | CD9: {=_xlfn.IFNA(IF(武备!B18=0,"",VLOOKUP(武备!B18,人物数据!$AE$1:$AO$300,{1,2,3,4,5,6,7,8,9,10,11},FALSE)),"")}
A10: 9 | B10: 黑暗的迷梦徘徊在心门之内。 | C10: 以2点堕落点数开始游戏。 | D10: 8 | E10: 56 | F10: 112 | G10: 224 | H10: 交 | I10: 8 | J10: 8 | K10: 16 | L10: 24 | M10: =6*I10 -> 48 | N10: 192m | O10: 12km | P10: 120km | S10: 黄昏星 | V10: 盾 | W10: 格斗 | X10: — | Y10: 1d5 I | Z10: 0 | AA10: 原始，防御 | AB10: 3 | AC10: 25 | AE10: 自动步枪 | AF10: 基本 | AG10: 90m | AH10: S/3/10 | AI10: 1d10+3 I | AJ10: 0 | AK10: 30 | AL10: 完整 | AM10: — | AN10: 3.5 | AO10: 100 | AQ10: 电子援助 | AR10: 你可以召唤神圣的能量来治愈你虚弱的肉体。每当你接触一个发电机，电动机，或者充满的电池时，你可以进行一个普通（+10）的坚韧检定，成功可以恢复1点虚弱，每成功度再加1点。这需要1分钟的冥思与祷告。 | AW10: =_xlfn.IFNA(IF(人物!B107=0,"",VLOOKUP(人物!B107,人物数据!$AQ$1:人物数据!$AR$300,2,FALSE)),"") | BN10: =_xlfn.IFNA(IF(武备!C52=0,"",VLOOKUP(武备!C52,附表!$AC$2:附表!$AF$61,2,FALSE)),"") | BO10: =_xlfn.IFNA(IF(武备!C52=0,"",VLOOKUP(武备!C52,附表!$AC$2:附表!$AF$61,3,FALSE)),"") | BP10: =_xlfn.IFNA(IF(武备!C52=0,"",VLOOKUP(武备!C52,附表!$AC$2:附表!$AF$61,4,FALSE)),"") | BU10: {=_xlfn.IFNA(IF(武备!B13=0,"",VLOOKUP(武备!B13,人物数据!$V$1:$AC$300,{1,2,3,4,5,6,7,8},FALSE)),"")} | CD10: {=_xlfn.IFNA(IF(武备!B19=0,"",VLOOKUP(武备!B19,人物数据!$AE$1:$AO$300,{1,2,3,4,5,6,7,8,9,10,11},FALSE)),"")}
A11: 10 | B11: 黑暗的迷梦徘徊在心门之内。 | C11: 以2点堕落点数开始游戏。 | D11: 9 | E11: 67 | F11: 134 | G11: 268 | I11: 9 | J11: 9 | K11: 18 | L11: 27 | M11: =6*I11 -> 54 | N11: 216m | O11: 13km | P11: 130km | S11: 虚空生人 | V11: 矛 | W11: 格斗，投掷† | X11: 10m | Y11: 1d10 R | Z11: 0 | AA11: 原始 | AB11: 3 | AC11: 15 | AE11: 来复猎枪 | AF11: 基本 | AG11: 150m | AH11: S/–/– | AI11: 1d10+3 I | AJ11: 0 | AK11: 5 | AL11: 完整 | AM11: 精准 | AN11: 5 | AO11: 100 | AQ11: 独立目标 | AR11: 同时使用两把武器射击时，你可以攻击间距超过10米的多个目标。 | AW11: =_xlfn.IFNA(IF(人物!B108=0,"",VLOOKUP(人物!B108,人物数据!$AQ$1:人物数据!$AR$300,2,FALSE)),"") | BN11: =_xlfn.IFNA(IF(武备!C53=0,"",VLOOKUP(武备!C53,附表!$AC$2:附表!$AF$61,2,FALSE)),"") | BO11: =_xlfn.IFNA(IF(武备!C53=0,"",VLOOKUP(武备!C53,附表!$AC$2:附表!$AF$61,3,FALSE)),"") | BP11: =_xlfn.IFNA(IF(武备!C53=0,"",VLOOKUP(武备!C53,附表!$AC$2:附表!$AF$61,4,FALSE)),"") | BU11: {=_xlfn.IFNA(IF(武备!B14=0,"",VLOOKUP(武备!B14,人物数据!$V$1:$AC$300,{1,2,3,4,5,6,7,8},FALSE)),"")}
A12: 11 | B12: 黑暗的迷梦徘徊在心门之内。 | C12: 以2点堕落点数开始游戏。 | D12: 10 | E12: 78 | F12: 156 | G12: 312 | I12: 10 | J12: 10 | K12: 20 | L12: 30 | M12: =6*I12 -> 60 | N12: 240m | O12: 14km | P12: 140km | S12: 卡利西斯舰队 | V12: 剑 | W12: 格斗 | X12: — | Y12: 1d10 R | Z12: 0 | AA12: 原始，平衡 | AB12: 3 | AC12: 15 | AE12: 霰弹猎枪 | AF12: 基本 | AG12: 30m | AH12: S/–/– | AI12: 1d10+4 I | AJ12: 0 | AK12: 2 | AL12: 2完整 | AM12: 可靠，散射 | AN12: 5 | AO12: 60 | AQ12: 额外次级灵能* | AR12: 你获得一项次级灵能。 | AW12: =_xlfn.IFNA(IF(人物!B109=0,"",VLOOKUP(人物!B109,人物数据!$AQ$1:人物数据!$AR$300,2,FALSE)),"") | BN12: =_xlfn.IFNA(IF(武备!C54=0,"",VLOOKUP(武备!C54,附表!$AC$2:附表!$AF$61,2,FALSE)),"") | BO12: =_xlfn.IFNA(IF(武备!C54=0,"",VLOOKUP(武备!C54,附表!$AC$2:附表!$AF$61,3,FALSE)),"") | BP12: =_xlfn.IFNA(IF(武备!C54=0,"",VLOOKUP(武备!C54,附表!$AC$2:附表!$AF$61,4,FALSE)),"") | BU12: {=_xlfn.IFNA(IF(武备!B15=0,"",VLOOKUP(武备!B15,人物数据!$V$1:$AC$300,{1,2,3,4,5,6,7,8},FALSE)),"")} | CD12: {=_xlfn.IFNA(IF(武备!B21=0,"",VLOOKUP(武备!B21,人物数据!$AE$1:$AO$300,{1,2,3,4,5,6,7,8,9,10,11},FALSE)),"")}
A13: 12 | B13: 与天谴之堕落相比，子弹带来的痛苦无异极乐。 | C13: 坚韧+1。 | D13: 11 | E13: 90 | F13: 180 | G13: 360 | S13: 黑暗舰舱人 | V13: 杖 | W13: 格斗† | X13: — | Y13: 1d10 I | Z13: 0 | AA13: 原始，平衡 | AB13: 3 | AC13: 10 | AE13: 泵动霰弹枪 | AF13: 基本 | AG13: 30m | AH13: S/–/– | AI13: 1d10+4 I | AJ13: 0 | AK13: 8 | AL13: 2完整 | AM13: 散射 | AN13: 5 | AO13: 75 | AQ13: 额外灵能* | AR13: 从你已知的学科中获得一项额外灵能。 | AW13: =_xlfn.IFNA(IF(人物!B110=0,"",VLOOKUP(人物!B110,人物数据!$AQ$1:人物数据!$AR$300,2,FALSE)),"") | BN13: =_xlfn.IFNA(IF(武备!C55=0,"",VLOOKUP(武备!C55,附表!$AC$2:附表!$AF$61,2,FALSE)),"") | BO13: =_xlfn.IFNA(IF(武备!C55=0,"",VLOOKUP(武备!C55,附表!$AC$2:附表!$AF$61,3,FALSE)),"") | BP13: =_xlfn.IFNA(IF(武备!C55=0,"",VLOOKUP(武备!C55,附表!$AC$2:附表!$AF$61,4,FALSE)),"") | BU13: {=_xlfn.IFNA(IF(武备!B16=0,"",VLOOKUP(武备!B16,人物数据!$V$1:$AC$300,{1,2,3,4,5,6,7,8},FALSE)),"")} | CD13: {=_xlfn.IFNA(IF(武备!B22=0,"",VLOOKUP(武备!B22,人物数据!$AE$1:$AO$300,{1,2,3,4,5,6,7,8,9,10,11},FALSE)),"")}
A14: 13 | B14: 与天谴之堕落相比，子弹带来的痛苦无异极乐。 | C14: 坚韧+1。 | D14: 12 | E14: 112 | F14: 224 | G14: 448 | S14: 忠嗣学院 | V14: 链锯剑 | W14: 格斗 | X14: — | Y14: 1d10+2 R | Z14: 2 | AA14: 平衡，撕裂 | AB14: 6 | AC14: 275 | AE14: 战斗霰弹枪 | AF14: 基本 | AG14: 30m | AH14: S/3/– | AI14: 1d10+4 I | AJ14: 0 | AK14: 18 | AL14: 完整 | AM14: 散射 | AN14: 6.5 | AO14: 150 | AQ14: 反戈一击 | AR14: 成功进行格档之后，你可以用格档所用的武器立刻对攻击你的目标进行一次攻击，但攻击检定−20。 | AW14: =_xlfn.IFNA(IF(人物!B111=0,"",VLOOKUP(人物!B111,人物数据!$AQ$1:人物数据!$AR$300,2,FALSE)),"") | BN14: =_xlfn.IFNA(IF(武备!C56=0,"",VLOOKUP(武备!C56,附表!$AC$2:附表!$AF$61,2,FALSE)),"") | BO14: =_xlfn.IFNA(IF(武备!C56=0,"",VLOOKUP(武备!C56,附表!$AC$2:附表!$AF$61,3,FALSE)),"") | BP14: =_xlfn.IFNA(IF(武备!C56=0,"",VLOOKUP(武备!C56,附表!$AC$2:附表!$AF$61,4,FALSE)),"") | BU14: {=_xlfn.IFNA(IF(武备!B17=0,"",VLOOKUP(武备!B17,人物数据!$V$1:$AC$300,{1,2,3,4,5,6,7,8},FALSE)),"")} | CD14: {=_xlfn.IFNA(IF(武备!B23=0,"",VLOOKUP(武备!B23,人物数据!$AE$1:$AO$300,{1,2,3,4,5,6,7,8,9,10,11},FALSE)),"")}
A15: 14 | B15: 与天谴之堕落相比，子弹带来的痛苦无异极乐。 | C15: 坚韧+1。 | D15: 13 | E15: 225 | F15: 450 | G15: 900 | S15: 枯萎学院 | V15: 链锯斧 | W15: 格斗 | X15: — | Y15: 1d10+4 R | Z15: 2 | AA15: 撕裂 | AB15: 13 | AC15: 450 | AE15: 重机枪 | AF15: 重型 | AG15: 120m | AH15: –/–/10 | AI15: 1d10+4 I | AJ15: 3 | AK15: 200 | AL15: 2完整 | AM15: — | AN15: 35 | AO15: 750 | AQ15: 飞跑 | AR15: 你能够以突然爆发的速度来摆脱——或是一头扎入——麻烦。你进行完整移动时可多移动等于敏捷加值的米数。另外，你的奔跑速度翻倍，持续一轮。如果连续两次使用该天赋奔跑，你会得到1级虚弱。 | AW15: =_xlfn.IFNA(IF(人物!B112=0,"",VLOOKUP(人物!B112,人物数据!$AQ$1:人物数据!$AR$300,2,FALSE)),"") | BU15: {=_xlfn.IFNA(IF(武备!B18=0,"",VLOOKUP(武备!B18,人物数据!$V$1:$AC$300,{1,2,3,4,5,6,7,8},FALSE)),"")}
A16: 15 | B16: 与天谴之堕落相比，子弹带来的痛苦无异极乐。 | C16: 坚韧+1。 | D16: 14 | E16: 337 | F16: 674 | G16: 1348 | S16: 铸造世界 | V16: 能量刃 | W16: 格斗 | X16: — | Y16: 1d10+3 E | Z16: 6 | AA16: 能量 | AB16: 1.5 | AC16: 1750 | AE16: 爆矢手枪 | AF16: 手枪 | AG16: 30m | AH16: S/2/– | AI16: 1d10+5 X | AJ16: 4 | AK16: 8 | AL16: 完整 | AM16: 撕裂 | AN16: 3.5 | AO16: 250 | AQ16: 格斗武器训练* | AR16: 子项：原始武器，链锯武器，震击武器，能量武器无减值地使用你选择的格斗武器。 | AW16: =_xlfn.IFNA(IF(人物!B113=0,"",VLOOKUP(人物!B113,人物数据!$AQ$1:人物数据!$AR$300,2,FALSE)),"") | BR16: =_xlfn.IFNA(IF(BN16=0,"",VLOOKUP(BN16,附表!#REF!:附表!#REF!,2,FALSE)),"") | BU16: {=_xlfn.IFNA(IF(武备!B19=0,"",VLOOKUP(武备!B19,人物数据!$V$1:$AC$300,{1,2,3,4,5,6,7,8},FALSE)),"")} | CD16: {=_xlfn.IFNA(IF(武备!B25=0,"",VLOOKUP(武备!B25,人物数据!$AE$1:$AO$300,{1,2,3,4,5,6,7,8,9,10,11},FALSE)),"")}
A17: 16 | B17: 在外种族异形得以开口欺骗之前将其处死。 | C17: 敏捷+2。 | D17: 15 | E17: 450 | F17: 900 | G17: 1800 | S17: 遗失的数据板 | V17: 能量剑 | W17: 格斗 | X17: — | Y17: 1d10+5 E | Z17: 6 | AA17: 能量，平衡 | AB17: 3.5 | AC17: 2500 | AE17: 爆矢枪 | AF17: 基本 | AG17: 90m | AH17: S/2/– | AI17: 1d10+5 X | AJ17: 4 | AK17: 24 | AL17: 完整 | AM17: 撕裂 | AN17: 7 | AO17: 500 | AQ17: 格斗专家 | AR17: 你擅长应付以寡敌众的肉搏战，在近战格斗中包围你的对手不会得到任何加值。 | AW17: =_xlfn.IFNA(IF(人物!B114=0,"",VLOOKUP(人物!B114,人物数据!$AQ$1:人物数据!$AR$300,2,FALSE)),"") | BU17: {=_xlfn.IFNA(IF(武备!B20=0,"",VLOOKUP(武备!B20,人物数据!$V$1:$AC$300,{1,2,3,4,5,6,7,8},FALSE)),"")} | CD17: {=_xlfn.IFNA(IF(武备!B26=0,"",VLOOKUP(武备!B26,人物数据!$AE$1:$AO$300,{1,2,3,4,5,6,7,8,9,10,11},FALSE)),"")}
A18: 17 | B18: 在外种族异形得以开口欺骗之前将其处死。 | C18: 敏捷+2。 | D18: 16 | E18: 675 | F18: 1350 | G18: 2700 | S18: 贵族生人 | V18: 震击槌 | W18: 格斗 | X18: — | Y18: 1d10 I | Z18: 0 | AA18: 震击 | AB18: 2.5 | AC18: 150 | AE18: 重型爆矢枪 | AF18: 重型 | AG18: 120m | AH18: –/–/10 | AI18: 2d10+3 X | AJ18: 5 | AK18: 60 | AL18: 2完整 | AM18: 撕裂 | AN18: 40 | AO18: 2000 | AQ18: 悍不畏死 | AR18: 可重投失败的压制检定。 | AW18: =_xlfn.IFNA(IF(人物!B115=0,"",VLOOKUP(人物!B115,人物数据!$AQ$1:人物数据!$AR$300,2,FALSE)),"") | BU18: {=_xlfn.IFNA(IF(武备!B21=0,"",VLOOKUP(武备!B21,人物数据!$V$1:$AC$300,{1,2,3,4,5,6,7,8},FALSE)),"")}
A19: 18 | B19: 在外种族异形得以开口欺骗之前将其处死。 | C19: 敏捷+2。 | D19: 17 | E19: 900 | F19: 1800 | G19: 3600 | S19: 马尔菲污血 | V19: 电击链枷 | W19: 格斗† | X19: — | Y19: 1d10+2 I | Z19: 0 | AA19: 震击，柔韧 | AB19: 4.5 | AC19: 375 | AE19: 炽热手枪 | AF19: 手枪 | AG19: 10m | AH19: S/–/– | AI19: 2d10+4 E | AJ19: 12 | AK19: 3 | AL19: 完整 | AM19: — | AN19: 2.5 | AO19: 7500 | AQ19: 黑暗灵魂 | AR19: 你的灵魂被黑暗污染，使得你能够抵抗堕落。每当你需要进行恶化检定，该检定所受减值减半。详见第256页堕落规则。 | AW19: =_xlfn.IFNA(IF(人物!B116=0,"",VLOOKUP(人物!B116,人物数据!$AQ$1:人物数据!$AR$300,2,FALSE)),"") | BU19: {=_xlfn.IFNA(IF(武备!B22=0,"",VLOOKUP(武备!B22,人物数据!$V$1:$AC$300,{1,2,3,4,5,6,7,8},FALSE)),"")} | CD19: {=_xlfn.IFNA(IF(武备!B28=0,"",VLOOKUP(武备!B28,人物数据!$AE$1:$AO$300,{1,2,3,4,5,6,7,8,9,10,11},FALSE)),"")}
A20: 19 | B20: 所谓事实，不过是一种主观虚饰。 | C20: 智力+3，以3点堕落点数开始游戏。 | D20: 18 | E20: 1350 | F20: 2700 | G20: 5400 | S20: 思维洗涤 | AE20: 热熔枪 | AF20: 基本 | AG20: 20m | AH20: S/–/– | AI20: 2d10+4 E | AJ20: 12 | AK20: 5 | AL20: 2完整 | AM20: — | AN20: 8 | AO20: 4000 | AQ20: 击昏 | AR20: 花费一个部分动作进行一次攻击，在检定之前声明要击昏目标。如果这次攻击命中并造成了至少1点伤害，则该伤害被忽略，目标进行坚韧检定，失败就会昏迷1轮。 | AW20: =_xlfn.IFNA(IF(人物!B117=0,"",VLOOKUP(人物!B117,人物数据!$AQ$1:人物数据!$AR$300,2,FALSE)),"")
A21: 20 | B21: 所谓事实，不过是一种主观虚饰。 | C21: 智力+3，以3点堕落点数开始游戏。 | D21: 19 | E21: 1800 | F21: 3600 | G21: 7200 | S21: 圣殿世界 | AE21: 等离子手枪 | AF21: 手枪 | AG21: 30m | AH21: S/–/– | AI21: 1d10+6 E | AJ21: 6 | AK21: 10 | AL21: 4完整 | AM21: 充能，过热 | AN21: 4 | AO21: 4000 | AQ21: 机械附肢* | AR21: 子项：枪械附肢，起重附肢，医疗附肢，光学附肢，多功能附肢能够使用选择的机械附肢。 | AW21: =_xlfn.IFNA(IF(人物!B118=0,"",VLOOKUP(人物!B118,人物数据!$AQ$1:人物数据!$AR$300,2,FALSE)),"")
A22: 21 | B22: 所谓事实，不过是一种主观虚饰。 | C22: 智力+3，以3点堕落点数开始游戏。 | D22: 20 | E22: 2250 | F22: 4500 | G22: 9000 | S22: 役从门生 | AE22: 等离子枪 | AF22: 基本 | AG22: 90m | AH22: S/2/– | AI22: 1d10+6 E | AJ22: 6 | AK22: 20 | AL22: 8完整 | AM22: 充能，过热 | AN22: 11 | AO22: 3000 | AQ22: 机械语者 | AR22: 对机械仆役进行命令，编程，询问等行为的检定+10。 | AW22: =_xlfn.IFNA(IF(人物!B119=0,"",VLOOKUP(人物!B119,人物数据!$AQ$1:人物数据!$AR$300,2,FALSE)),"")
A23: 22 | B23: 了解变异者；消灭变异者。 | C23: 感知+2。 | S23: 修院栽培 | AE23: 火焰手枪 | AF23: 手枪 | AG23: 10m | AH23: S/–/– | AI23: 1d10+4 E | AJ23: 2 | AK23: 2 | AL23: 2完整 | AM23: 火焰 | AN23: 3.5 | AO23: 200 | AQ23: 基本武器训练 | AR23: 子项：矢弹武器，火焰武器，激光武器，榴弹武器，热熔武器，等离子武器，原始武器，实体弹武器.无减值地使用你选择的武器。 | AW23: =_xlfn.IFNA(IF(人物!B120=0,"",VLOOKUP(人物!B120,人物数据!$AQ$1:人物数据!$AR$300,2,FALSE)),"")
A24: 23 | B24: 了解变异者；消灭变异者。 | C24: 感知+2。 | S24: 自定义起源 | AE24: 火焰喷射器 | AF24: 基本 | AG24: 20m | AH24: S/–/– | AI24: 1d10+4 E | AJ24: 3 | AK24: 3 | AL24: 2完整 | AM24: 火焰 | AN24: 6 | AO24: 300 | AQ24: 极限打击 | AR24: 如果你的格斗武器对目标造成了致命伤害，它将增加1d5−1点。 | AW24: =_xlfn.IFNA(IF(人物!B121=0,"",VLOOKUP(人物!B121,人物数据!$AQ$1:人物数据!$AR$300,2,FALSE)),"")
A25: 24 | B25: 了解变异者；消灭变异者。 | C25: 感知+2。 | AE25: 绳球套索 | AF25: 投掷 | AG25: 10m | AH25: S/–/– | AI25: — | AJ25: 0 | AK25: 1 | AL25: — | AM25: 原始，捕捉，粗劣 | AN25: 1.5 | AO25: 10 | AQ25: 即时备战 | AR25: 当你只装备着一把手枪或基本射击武器，或单手执用格斗武器时，你可以用一个自由动作进行准备动作。 | AW25: =_xlfn.IFNA(IF(人物!B122=0,"",VLOOKUP(人物!B122,人物数据!$AQ$1:人物数据!$AR$300,2,FALSE)),"")
A26: 25 | B26: 了解变异者；消灭变异者。 | C26: 感知+2。 | AE26: 手弩 | AF26: 手枪 | AG26: 15m | AH26: S/–/– | AI26: 1d10 R | AJ26: 0 | AK26: 1 | AL26: 完整 | AM26: 原始 | AN26: 1 | AO26: 200 | AQ26: 棘手目标 | AR26: 奔跑或冲锋时对手的BS检定−20。 | AW26: =_xlfn.IFNA(IF(人物!B123=0,"",VLOOKUP(人物!B123,人物数据!$AQ$1:人物数据!$AR$300,2,FALSE)),"")
A27: 26 | B27: 了解变异者；消灭变异者。 | C27: 感知+2。 | AE27: 燧发手枪 | AF27: 手枪 | AG27: 15m | AH27: S/–/– | AI27: 1d10+2 I | AJ27: 0 | AK27: 1 | AL27: 3完整 | AM27: 原始，易损，粗劣 | AN27: 4 | AO27: 10 | AQ27: 加速循环 | AR27: 你可以主动让你血液中的移植物加速工作。每十二小时可用一次，你进行一次技术应用检定，成功的话可立刻恢复1d5点伤害。如果检定投出96―100视为自动失败，且你的血液移植物过载，它们将罢工一周。一周之内，你失去自动止血和加速循环两个天赋的效果。一周之后两个天赋效果恢复。启动加速循环天赋需要10分钟的冥想与祈祷。 | AW27: =_xlfn.IFNA(IF(人物!B124=0,"",VLOOKUP(人物!B124,人物数据!$AQ$1:人物数据!$AR$300,2,FALSE)),"")
A28: 27 | B28: 即使是一无所有的人，依然可以贡献自己的生命。 | C28: 力量+2。 | AE28: 滑膛枪 | AF28: 基本 | AG28: 30m | AH28: S/–/– | AI28: 1d10+2 I | AJ28: 0 | AK28: 1 | AL28: 5完整 | AM28: 原始，易损，粗劣 | AN28: 7 | AO28: 30 | AQ28: 尖锐噪音 | AR28: 用呼吸面罩的声音合成系统发出一阵尖锐的噪音，不分敌我影响四周的生物。30米半径内恶魔和机械类单位之外的生物必须进行意志检定，否则接下来的回合由于战栗，颤抖，堵住耳朵等行为而失去部分动作。使用尖锐噪音是一个完整动作，之后要让音频电路休息1d5轮才可以再次使用。 | AW28: =_xlfn.IFNA(IF(人物!B125=0,"",VLOOKUP(人物!B125,人物数据!$AQ$1:人物数据!$AR$300,2,FALSE)),"")
A29: 28 | B29: 即使是一无所有的人，依然可以贡献自己的生命。 | C29: 力量+2。 | AE29: 弓 | AF29: 基本 | AG29: 30m | AH29: S/–/– | AI29: 1d10 R | AJ29: 0 | AK29: 1 | AL29: 部分 | AM29: 原始，可靠 | AN29: 2 | AO29: 10 | AQ29: 坚忍体魄 | AR29: 计算伤害恢复时总是视为轻伤状态。 | AW29: =_xlfn.IFNA(IF(人物!B127=0,"",VLOOKUP(人物!B127,人物数据!$AQ$1:人物数据!$AR$300,2,FALSE)),"")
A30: 29 | B30: 即使是一无所有的人，依然可以贡献自己的生命。 | C30: 力量+2。 | AE30: 投石索 | AF30: 基本 | AG30: 15m | AH30: S/–/– | AI30: 1d10−2 I | AJ30: 0 | AK30: 1 | AL30: 完整 | AM30: 原始 | AN30: 0.5 | AO30: 10 | AQ30: 见惯不惊 | AR30: 你已经见识过银河系中最糟糕的场面，对于死亡，鲜血，大屠杀等等世间的恐怖都已经见惯不惊，这些场面不会让你得到失心点。但超自然的恐怖会正常影响你。 | AW30: =_xlfn.IFNA(IF(人物!B128=0,"",VLOOKUP(人物!B128,人物数据!$AQ$1:人物数据!$AR$300,2,FALSE)),"")
A31: 30 | B31: 即使是一无所有的人，依然可以贡献自己的生命。 | C31: 力量+2。 | AE31: 十字弩 | AF31: 基本 | AG31: 30m | AH31: S/–/– | AI31: 1d10 R | AJ31: 0 | AK31: 1 | AL31: 2完整 | AM31: 原始 | AN31: 3 | AO31: 10 | AQ31: 剑术大师 | AR31: 使用任何种类的刀或剑——包括链锯剑和能量剑——时，每轮一次，你可以重掷没有命中的攻击骰。 | AW31: =_xlfn.IFNA(IF(人物!B129=0,"",VLOOKUP(人物!B129,人物数据!$AQ$1:人物数据!$AR$300,2,FALSE)),"")
A32: 31 | B32: 如果一项任务值得做，它值得你付出生命。 | C32: 得到狂暴天赋。 | AE32: 榴弹发射器 | AF32: 基本 | AG32: 60m | AH32: S/–/– | AI32: † | AJ32: † | AK32: 6 | AL32: 完整 | AM32: † | AN32: 9 | AO32: 500 | AQ32: 健壮体格 | AR32: 获得1点额外承伤
A33: 32 | B33: 如果一项任务值得做，它值得你付出生命。 | C33: 得到狂暴天赋。 | AE33: 火箭推进器 | AF33: 重型 | AG33: 120m | AH33: S/–/– | AI33: † | AJ33: † | AK33: 1 | AL33: 完整 | AM33: † | AN33: 15 | AO33: 1200 | AQ33: 街道斗殴 | AR33: 当使用小刀或徒手对目标造成致命伤害时，该伤害+2。
A34: 33 | B34: 如果一项任务值得做，它值得你付出生命。 | C34: 得到狂暴天赋。 | AE34: 毒针手枪 | AF34: 手枪 | AG34: 30m | AH34: S/–/– | AI34: 1d10 R | AJ34: 0 | AK34: 6 | AL34: 完整 | AM34: 精准，淬毒 | AN34: 1.5 | AO34: 1250 | AQ34: 金属引力 | AR34: 花费一个完整动作进行WP检定，你可以将20米半径内，一个未固定的金属制品吸引到你手里，该物品重量不超过1kg/WB。
A35: 34 | B35: 只有死亡才是职责终结之时。 | C35: 承伤+1。 | AE35: 捕网手枪 | AF35: 手枪 | AG35: 30m | AH35: S/–/– | AI35: — | AJ35: 0 | AK35: 1 | AL35: 完整 | AM35: 捕捉 | AN35: 3.5 | AO35: 1200 | AQ35: 金属召唤 | AR35: 花费一个完整动作进行WP检定，你可以将40米半径内，一个未固定的金属制品吸引到你手里，该物品重量不超过2kg/WB。
A36: 35 | B36: 只有死亡才是职责终结之时。 | C36: 承伤+1。 | AE36: 毒针来复枪 | AF36: 基本 | AG36: 180m | AH36: S/–/– | AI36: 1d10 R | AJ36: 0 | AK36: 6 | AL36: 2完整 | AM36: 精准，淬毒 | AN36: 2 | AO36: 1000 | AQ36: 谨小慎微 | AR36: 你总是疑神疑鬼，紧张地东张西望。你的先攻权+2。另外，只要附近有危险存在，你可以自动进行感知检定（GM暗投）。
A37: 36 | B37: 只有死亡才是职责终结之时。 | C37: 承伤+1。 | AE37: 网枪 | AF37: 基本 | AG37: 50m | AH37: S/–/– | AI37: — | AJ37: 0 | AK37: 1 | AL37: 完整 | AM37: 爆炸(5)，捕捉 | AN37: 8 | AO37: 1800 | AQ37: 精确击打 | AR37: 近战攻击特定部位无减值。
A38: 37 | B38: 只有死亡才是职责终结之时。 | C38: 承伤+1。 | AQ38: 精确射击 | AR38: 瞄准特定部位射击无减值。
A39: 38 | B39: 只有死亡才是职责终结之时。 | C39: 承伤+1。 | AQ39: 净化之火 | AR39: 烧！烧！烧！无人能逃过你的怒火！尝试躲避你的火焰喷射器的检定有−20减值。
A40: 39 | B40: 没有使命的灵魂将在黑暗之中游荡。 | C40: 命运点+1。 | AQ40: 敬畏仪式 | AR40: 你可以吟诵引发敬畏与恐怖的次声波祷文。50米范围内的人类，无论听力是否健全，都会感到畏惧和罪恶感。由于这种情绪影响，他们接下来的技能检定承受−10减值。成功的意志检定可以摆脱此效果。吟诵祷文时，你不能用其它频率发声。仪式持续2分钟，由于任何原因中断仪式都是很严重的亵渎行为。注意，除非安装了特殊的接收装置，否则一般人是听不到次声波的，因此也不会认为你在讲话。
A41: 40 | B41: 没有使命的灵魂将在黑暗之中游荡。 | C41: 命运点+1。 | AQ41: 军纪严明 | AR41: 只要你的下属能看到你，他们可以重投失败的恐惧和压制检定。该能力可影响的目标数等于你的WB，且这些人必须处于你的指挥之下。如果你是官方指派的侍僧小队的领导，则其他PC也可从该天赋中获益。
A42: 41 | B42: 没有使命的灵魂将在黑暗之中游荡。 | C42: 命运点+1。 | AQ42: 恐惧仪式 | AR42: 你可以吟唱引发恐惧与虚弱的次声波挽歌。50米范围内的人类，无论听力是否健全，都会对你怀有等级1的恐惧。吟唱挽歌时，你不能用其它频率发声。仪式持续2分钟，由于任何原因中断仪式都是很严重的亵渎行为。注意，除非安装了特殊的接收装置，否则一般人是听不到次声波的，因此也不会认为你在讲话。
A43: 42 | B43: 没有使命的灵魂将在黑暗之中游荡。 | C43: 命运点+1。 | AQ43: 苦修者 | AR43: 每天，你都要进行一个为时12分钟的祈祷并鞭笞自己造成1点伤害，你不能让这个伤害被抵抗或治疗。鞭策自己的肉体之后，你抵抗精神控制和恶化的WP检定+10。另外，如果你有狂暴天赋，你可以用一个自由动作开始狂暴。任何一天，如果你没有进行自我鞭笞，就会由于羞愧和罪恶感而使所有检定有−5减值。
A44: 43 | B44: 生存的战争之中，没有可以划分在外的平民。 | C44: 坚韧+2，承伤+1。 | AQ44: 快速反应 | AR44: 被突袭或埋伏时，可进行一次敏捷检定，通过即可正常行动。
A45: 44 | B45: 生存的战争之中，没有可以划分在外的平民。 | C45: 坚韧+2，承伤+1。 | AQ45: 快速装填 | AR45: 装填所有武器的时间缩短为正常的一半（向下取整）。例如，部分动作变为自由动作，完整动作变为部分动作。
A46: 45 | B46: 生存的战争之中，没有可以划分在外的平民。 | C46: 坚韧+2，承伤+1。 | AQ46: 狂暴 | AR46: 将你自己完全投入战斗狂怒中。你要花费一轮时间来使自己进入状态（嚎叫，抽打自己，嗑药等等）。下一轮你将失去控制并陷入完全的疯狂，你的格斗能力，力量，坚韧，和意志属性+10，射击能力和智力−20。你必须尽可能靠近距你最近的敌人并进行近战攻击，但你不会做出明显的自杀行为，例如，跳下高楼以攻击敌人。狂暴时，你免疫恐惧，眩晕效果，不受虚弱造成的减值，但你无法脱离，撤退，和格挡。只要可能，你就要进行全力攻击。狂暴状态持续整场战斗。如果没有特定天赋，你无法在狂暴时施展灵能。
A47: 46 | B47: 生存的战争之中，没有可以划分在外的平民。 | C47: 坚韧+2，承伤+1。 | AQ47: 狂热袭击 | AR47: 用全力攻击命中一个目标之后，你可以用你本轮的反射动作进行一次额外攻击，攻击检定难度与原始攻击检定相同。
A48: 47 | B48: 暴力可以解决所有问题。 | C48: 格斗能力+3。 | AQ48: 狂热信仰 | AR48: 信仰保护你免于疯狂。决定震惊效果时，投两次百分骰并取较好者。
A49: 48 | B49: 暴力可以解决所有问题。 | C49: 格斗能力+3。 | AQ49: 狂野灵魂 | AR49: 狂暴状态下可以使用灵能
... A101: 100 | B101: 不要问为什么尽职，只问怎样去做。 | C101: 格斗能力+2，射击能力+2。 | AQ101: 无所畏惧 | AR101: 免疫恐惧和压制，视为检定自动成功。但如果试图从近战脱离或者撤离战场，你必须先通过意志检定。
AQ102: 武器熟悉 | AR102: 以−10减值使用不熟悉的武器。
AQ103: 武器卸除 | AR103: 近战中，你可以用一个完整动作卸除对手的格斗武器。你们进行WS对抗检定，如果你胜出，则对手武器落在他脚下；如果你得到三个或以上成功度，你可以将对手的武器夺过来。
AQ104: 线圈冲能 | AR104: 进行一次坚韧检定，成功的话你可以用你的生物电流为机械设备提供能量。需要一分钟的准备与仪式来启动该天赋。坚韧检定难度视需要充电的设备种类而定，注意有些神秘的，损坏的，或者耗电量过大的设备，GM可能裁定不适用此天赋。使用该天赋需要进行另一次标准难度的坚韧检定，否则承受1级虚弱。
AQ105: 线圈冲击 | AR105: 凭借你的电子设备和适当的仪式，你可以创造出一支由生物电流构成，噼啪作响的能量球并将它投向敌人。能量球可以攻击10米之内的单个目标，花费部分动作并视为一次标准攻击，BS检定成功可以造成1d10+WB的能量伤害。使用该天赋需要进行坚韧检定，否则承受1级虚弱。
AQ106: 线圈放电 | AR106: 用你的生物电能伤害接触的对手。你需要进行WS或擒抱检定来传递这股伤害性的能量，这花费部分动作并视为一次标准攻击。每次放电可造成1d10+3点能量伤害。使用该天赋需要进行坚韧检定，否则承受1级虚弱。信仰坚定重投失败的恐惧检定。
AQ107: 信仰坚定 | AR107: 重投失败的恐惧检定。
AQ108: 学科专攻* | AR108: 子项：生物，预言，操火，遥感，传心施展选定学科的灵能时灵能检定+2。
AQ109: 迅捷攻击 | AR109: 以一个完整动作近战攻击两次。如果你具有双武器攻击天赋，且两手各执一把近战武器，则只有一把武器受该天赋影响，另一把只能攻击一次。如果你具有双武器攻击天赋，且装备一把近战武器和一把手枪，则只有近战武器受该天赋影响，手枪只能攻击一次。
AQ110: 亚空间选民 | AR110: 引发灵能现象时，掷两次灵能现象并取较好者。
AQ111: 演说大师 | AR111: 基于交际属性的检定可以影响10倍数量的目标。
AQ112: 野蛮冲锋 | AR112: 冲锋时的WS检定变为+20，取代原本的+10。
AQ113: 一敲就好 | AR113: 花费一个部分动作，用仪式手法接触一把故障枪支，即可排除故障。一次仪式只能接触一把武器，否则是对机魂十分失礼的行为。
... AQ124: 自动止血 | AR124: 你的血液由远古的受祝福科技透析。你体内的移植物可以帮你修复较小的伤口。在计算伤害恢复时，你总是被视为轻伤状态。另外，你每天可以自然恢复2点伤害。移植物还可以缓解疼痛，让你性格变得较为温和（无游戏影响）

Sheet 附表
B1: 技能 | U1: 天赋 | AC1: 购买物品（速查用） | AE1: 重量 | AF1: 花费 | AG1: 稀有度 | AH1: 类型 | AJ1: 服装与个人物品（精简，武备自动用） | AQ1: 技能 | AV1: 近战名称 | AW1: 类型 | AX1: 射程 | AY1: 伤害 | AZ1: 破甲 | BA1: 特性 | BB1: 重量 | BC1: 花费 | BE1: 名称 | BF1: 类型 | BG1: 射程 | BH1: 射速 | BI1: 伤害 | BJ1: 破甲 | BK1: 弹夹 | BL1: 装填 | BM1: 特性 | BN1: 重量 | BO1: 花费
T2: 天赋名称 | U2: 说明 | W2: 详细描述 | AB2: 服 装 | AC2: 背包 | AD2: 能够存放很多物品，并且一般有固定用的皮带方便携带的口袋状单人储物装置。一个背包一般认为能够负载50公斤的重量。 | AE2: 1 | AF2: 10 | AG2: 丰富 | AH2: 服装 | AV2: 斧 | AW2: 格斗 | AX2: — | AY2: 1d10+1 R | AZ2: 0 | BA2: 原始，失衡 | BB2: 4 | BC2: 20 | BE2: 激光手枪 | BF2: 手枪 | BG2: 30m | BH2: S/–/– | BI2: 1d10+2 E | BJ2: 0 | BK2: 30 | BL2: 完整 | BM2: 可靠 | BN2: 1.5 | BO2: 50 | CE2: 种类 | CF2: 花费 | CG2: 稀有度 | CI2: 种类 | CJ2: 花费 | CK2: 稀有度 | CL2: 效果
T3: 傲慢护甲 | U3: 可以抵抗堕落 | W3: 傲慢护甲 | X3: 你将自己包裹在由轻蔑与憎恶织就的护甲里。每次得到堕落点时，你都可以抵抗掉1点。另外，作为一个自由动作，你可以进行一个意志检定以尝试在一轮之内忽略你积累的堕落的影响。 | Y3: 先决条件：WP30 | AC3: 卡梅莱林斗篷 | AD3: 卡梅莱林是由一种拟态纤维缝制而成的特殊材料，可以随着周围环境而改变颜色。穿着卡梅莱林斗篷的角色可以在躲藏检定上获得 +20 的加值。如果穿着者站定不动，敌人射击他时视为他在实际距离加一倍标准射程之外（见第七章：进行游戏）。 | AE3: 0.5 | AF3: 500 | AG3: 稀有 | AH3: 服装 | AU3: √ | AV3: 黄铜指虎 | AW3: 格斗 | AX3: — | AY3: 1d5−1 I | AZ3: 0 | BA3: 原始 | BB3: 0.5 | BC3: 5 | BE3: 激光卡宾枪 | BF3: 基本 | BG3: 60m | BH3: S/2/– | BI3: 1d10+2 E | BJ3: 0 | BK3: 40 | BL3: 完整 | BM3: 可靠 | BN3: 3 | BO3: 75 | CE3: 住宿 | CI3: 简陋
B4: 技能名称 | C4: 类型 | D4: 属性 | F4: 技能名称 | G4: 类型 | H4: 属性 | J4: 技能名称 | K4: 类型 | L4: 属性 | N4: 技能名称 | O4: 类型 | P4: 属性 | T4: 拨挡飞箭 | U4: 你可格挡投掷武器或原始远程武器 | W4: 拨挡飞箭 | X4: 你可以格挡投掷武器或原始远程武器。 | Y4: 先决条件：Ag50 | AC4: 护身符 | AD4: 护身符是某种纪念品，神圣遗物，好运符咒，以及其它类似可以为佩戴者带来帝皇慈悲指引的小饰物。它们可以由很多种东西制造，像是圣人的指骨，被祝福的爆矢弹壳，圣河中的水，甚至是圣袍上的一缕纺线。遍布整个帝国，有不计其数的人会向侍僧出售类似的东西，虽然想要分辨其中的真伪基本上是不可能的事情（护身符的价格一般由 GM 或者销售者与侍僧的讨价还价决定）。虽然护身符并没有什么切实的用处。不过当任何角色发生任何糟糕的事情的话，GM 可以决定使携带了护身符的角色免除惩罚。如果所有的角色都携带了护身符（就如同每一个敬仰帝皇的公民应该做的），那么 GM 可以选择一个携带最有效护身符的角色免除惩罚。 | AE4: — | AF4: 特殊 | AG4: 一般 | AH4: 服装 | AJ4: 名称 | AK4: 物品简要信息（购买精简，详细去查找处） | AL4: 重量 | AM4: 花费 | AN4: 稀有度 | AO4: 类型 | AQ4: 技能名称 | AR4: 描述 | AS4: 属性 | AT4: 详细描述 | AV4: 棍棒 | AW4: 格斗 | AX4: — | AY4: 1d10 I | AZ4: 0 | BA4: 原始 | BB4: 2 | BC4: 5 | BE4: 激光步枪 | BF4: 基本 | BG4: 100m | BH4: S/3/– | BI4: 1d10+3 E | BJ4: 0 | BK4: 60 | BL4: 完整 | BM4: 可靠 | BN4: 4 | BO4: 75 | CE4: 低档次（密封睡袋，戈洛兽皮帐篷，底舱铺位） | CF4: 5 | CG4: 丰富 | CI4: (萨满) | CJ4: 50 | CK4: 一般 | CL4: Int 30医疗技能
B5: 察言观色 | C5: 基础 | D5: 感知 | F5: 暗号子项 | J5: 听说语言子项 | N5: 爆破 | O5: 高级 | P5: 智力 | T5: 藏物暗袋 | U5: 你有个秘密的藏匿物品之处 | W5: 藏物暗袋 | X5: 你身上有个用于藏匿不超过巴掌大小的物件的秘密隔间，可能是某个嵌入你体内的小袋，或是半机械移植物的一部分。一个困难（−10 ）程度的搜索检定可以发现被藏起来的物品。如果搜身者借助于医学扫描仪，生化嗅探器等设备，检定变为普通（ +10 ）。你身上有个用于藏匿不超过巴掌大小的物件的秘密隔间，可能是某个嵌入你体内的小袋，或是半机械移植物的一部分。一个困难（−10 ）程度的搜索检定可以发现被藏起来的物品。如果搜身者借助于医学扫描仪，生化嗅探器等设备，检定变为普通（ +10 ）。 | Y5: — | AC5: 计时器 | AD5: 计时器是一种手持或手腕上的时间记录装置，一般都是可靠且使用简单的。 | AE5: — | AF5: 40 | AG5: 充裕 | AH5: 服装 | AJ5: 背包 | AK5: 大口袋背包，承重最多50kg | AL5: 1 | AM5: 10 | AN5: 丰富 | AO5: 服装 | AQ5: 暗号* | AR5: —— | AS5: 智力 Int | AT5: 子项：侍僧，战场，秘会，神秘，下层社会 暗号技能是指理解和记录那些在特定群体内使用的，用于传递基本信息，示警，或显示区域情报的暗号。暗号通常是一个手势，或者一个记号——通常画在不起眼的地方。暗号一般不会表达很复杂的信息。阅读暗号的基础含义不需要进行检定。仅当需要解密过于复杂的，残缺的，或者过时的暗号时才进行检定。 进行暗号检定时，画出或抄写一个正确的符号需要一个完整动作，理解一个暗号则是个自由动作。 侍僧： 在侍僧团体内部传递私人信息的符号。注意每个侍僧团体的暗号都是不同的。 战场： 在军队中用于传递指令的手势，肢体语言，或声音代码。 秘密组织： 在特定秘密组织或教派内部，用于识别成员与传递简短信息的暗号。注意每个秘密组织使用的暗号都是不同的。 神秘： 咒语中用到的神秘姿势，用于识别同行，召唤或驱赶恶魔。 下层社会： 犯罪团伙中用于交流关键信息的手势，衣着，记号或其它花招。 | AV5: 链枷 | AW5: 格斗† | AX5: — | AY5: 1d10+2 I | AZ5: 0 | BA5: 原始，柔韧 | BB5: 4 | BC5: 20 | BE5: 激光长枪 | BF5: 基本 | BG5: 150m | BH5: S/–/– | BI5: 1d10+3 E | BJ5: 1 | BK5: 40 | BL5: 完整 | BM5: 可靠，精准 | BN5: 4.5 | BO5: 100 | CE5: 中档次（下层房间，旅店单间，中档舱位） | CF5: 20 | CG5: 普及 | CI5: 普通
B6: 赌博 | C6: 基础 | D6: 智力 | F6: 侍僧 | G6: 高级 | H6: 智力 | J6: 高哥特语 | K6: 高级 | L6: 智力 | N6: 扯淡 | O6: 高级 | P6: 交际 | T6: 出生入死 | U6: 只要能看到你，你的下属免疫恐惧和压制 | W6: 出生入死 | X6: 只要看到你，你的下属免受恐惧和压制。 | Y6: 先决条件：军纪严明 | AC6: 缆线盒 | AD6: 小型的利用磁力或是挂钩装置的安全绳。这是一个安全攀爬屋顶或是滑降的好主意。使用缆线盒的角色在垂直表面进行攀爬检定可以获得 +30 的加值，并且检定失败也不会掉落。 | AE6: 2 | AF6: 25 | AG6: 普及 | AH6: 服装 | AJ6: 卡梅莱林斗篷 | AK6: 躲藏+20，不动时被射击的话视为双倍距离外 | AL6: 0.5 | AM6: 500 | AN6: 稀有 | AO6: 服装 | AQ6: 爆破 | AR6: 制造 | AS6: 智力 Int | AT6: 爆破技能用于在爆破物体时避免将自己炸飞。这个技能包括正确地安装，拆卸，处理，和制作爆炸物，而与对着敌人扔手雷一类的事情无关。 制作爆炸物：只要有足够的时间和原料，爆破技能可以让你制作任何种类的爆炸物。检定难度视时间和产品而定。组装一个碎片手雷是个轻松的活计，但制作一个触发式热熔炸弹就难得多。这个技能也遵循第 107 页于制造物品的规则。 安装爆炸物：爆破技能还可以让你将炸药、热熔炸弹、热熔手雷等装到某个目标上。检定成功意味着你将爆炸物和你选择的控制器一起安装到了你选择的目标上。可能的控制器包括计时器、保险丝、动态传感器，或微型遥控器。检定失败意味着你以为安装成功，但其实设备无法如你所想的启动。如果失败度达到 5 或以上，就会当场引爆。 你可以主动提高检定的难度，例如提高装弹所用时间，选择一个更有价值的安装位置。检定难度每提高一级，或者每多花费1分钟用来安装炸弹，爆炸伤害都会额外 +2 。 检定的每一点成功度都使炸弹更难以被发现和拆除。记得要把安装炸弹的爆破检定结果记下来，他人发现和拆除你的炸弹时需要和该检定结果做对抗检定。 拆除炸弹：拆除炸弹需要和安装炸弹的目标进行爆破技能对抗检定。检定成功意味着炸弹被及时排除，失败的话还可以重试——只要还有时间的话。如果失败度达到 5 或以上，表示你不幸引爆了炸弹。 拆除和安装爆炸物都是完整动作。制作炸弹至少需要 1 分钟，但考虑到产品的复杂性，通常需要更长时间。 | AV6: 加重武器 | AW6: 格斗† | AX6: — | AY6: 2d10 R | AZ6: 2 | BA6: 原始，笨重 | BB6: 7 | BC6: 70 | BE6: 单兵激光炮 | BF6: 重型 | BG6: 300m | BH6: S/–/– | BI6: 5d10+10 E | BJ6: 10 | BK6: 5 | BL6: 2完整 | BM6: — | BN6: 55 | BO6: 5000 | CE6: 高档次（头等舱，宽敞豪华的房间） | CF6: 100 | CG6: 匮乏 | CI6: (实习医生) | CJ6: 75 | CK6: 匮乏 | CL6: Int 40医疗技能
B7: 躲藏 | C7: 基础 | D7: 敏捷 | F7: 战场 | G7: 高级 | H7: 智力 | J7: 巢都方言 | K7: 高级 | L7: 智力 | N7: 读唇 | O7: 高级 | P7: 感知 | T7: 纯净思维仪式 | U7: 免疫一切情绪波动 | W7: 纯净思维仪式 | X7: 你将自己的右脑切除，代之以思考电路。你变得沉默寡言，不再感受到任何情绪，脑中只有冰冷纯粹的逻辑。你免疫恐惧，压制，以及任何基于情绪的效果。GM可以把不再适用于你的精神失常去除，代之以相等程度的其它精神失常加重。 | Y7: 先决条件：技术神甫（颅腔电路） | AC7: 服装 | AD7: 帝国内的居民都会穿着风格各异的服饰，重要人物的着装总会引领着时代的潮流。对于侍僧来说，服装意味着实用的街头装束，统一的制服，或是僧侣长袍。服装的花费取决于侍僧选择怎么样的衣服，从不值钱的褴褛衣衫到价值数千的昂贵服饰都有可能。 | AE7: — | AF7: 特殊 | AG7: 充裕 | AH7: 服装 | AJ7: 护身符 | AK7: 可以为佩戴者带来帝皇慈悲指引的小饰物 | AL7: — | AM7: 特殊 | AN7: 一般 | AO7: 服装 | AQ7: 表演* | AR7: —— | AS7: 交际 Fel | AT7: 子项：舞者，乐师，歌手，说书人，或其它GM开放的项目。 用演技来娱乐或迷惑观众，也可以如同生计技能一样赚取收入。另外，在特殊情况下，表演技能可以代替其他技能。 视表演内容不同——从朗诵一首短诗到表演冗长的歌剧——表演检定所需时间也随之变化。 吸引观众：用于使他人变得更加友好时，表演（歌手）或表演（说书人）可以代替吸引力检定，但有−10 减值。 迷惑观众：用于迷惑目标时，表演（乐师）或表演（歌手）可以代替扯淡技能，同样有 −10 减值。其它规则与扯淡技能相同。 | AV7: 战锤 | AW7: 格斗 | AX7: — | AY7: 1d10+1 I | AZ7: 0 | BA7: 原始，失衡 | BB7: 4 | BC7: 10 | BE7: 自动手枪 | BF7: 手枪 | BG7: 30m | BH7: S/–/6 | BI7: 1d10+2 I | BJ7: 0 | BK7: 18 | BL7: 完整 | BM7: — | BN7: 2.5 | BO7: 75 | CE7: 供给 | CI7: 出色
B8: 估价 | C8: 基础 | D8: 智力 | F8: 秘密组织 | G8: 高级 | H8: 智力 | J8: 低哥特语 | K8: 高级 | L8: 智力 | N8: 跟踪 | O8: 高级 | P8: 敏捷 | T8: 磁力飞跃 | U8: 悬浮2d10+TB分钟，每天两次 | W8: 磁力飞跃 | X8: 与磁力优雅效果相同，除了以下几点：持续时间变为2d10+TB分钟；可以完全抵消坠落伤害；每十二小时可使用两次。 | Y8: 先决条件：技术神甫（储压线圈），磁力优雅 | AC8: 爆破项圈 | AD8: 这些令人不快的装置经常被使用在触犯刑事罪士兵身上，以给予他们额外的激励为帝皇而战。项圈一般都会有一个远程遥控装置可以用来引爆，或者有某些条件，例如 1000 米远。当项圈爆炸的时候会炸死佩戴者并且对周围三米之内的所有人造成 1d10 爆炸伤害。控制装置也可以用来移除项圈。如果没有控制器则需要一个艰难（−20）的技术应用检定。一个严重或是比较严重的失败会立刻引爆项圈。该项圈只能被戴到一个顺从的或者被束缚的目标身上，花费两个完整动作。 | AE8: 1 | AF8: 55 | AG8: 稀有 | AH8: 服装 | AJ8: 计时器 | AK8: 手持或手腕上的时间记录装置 | AL8: — | AM8: 40 | AN8: 充裕 | AO8: 服装 | AQ8: 察言观色 | AR8: —— | AS8: 感知 Per | AT8: 察言观色检定用于评估你遇到的人，看对方是否对你说谎，了解对方的情绪，或大体估计对方的身份地位。注意这个技能无法揭示对 方的所有秘密，也不是心灵感应。它通常用于对抗吸引力，欺诈，恐吓等社交技能。如果成功对抗了目标的欺诈检定，你会察觉对方的话语里有不对劲的地方。 | AV8: 临时武器 | AW8: 格斗 | AX8: — | AY8: d10−2 I | AZ8: 0 | BA8: 原始，失衡 | BB8: — | BC8: — | BE8: 短管左轮 | BF8: 手枪 | BG8: 30m | BH8: S/–/– | BI8: 1d10+3 I | BJ8: 0 | BK8: 6 | BL8: 2完整 | BM8: 可靠 | BN8: 1 | BO8: 40 | CE8: 低档次（虫豸，液态菌类，浑浊的啤酒） | CF8: 1 | CG8: 丰富 | CI8: (受训医生, 医疗仆役) | CJ8: 150 | CK8: 稀少 | CL8: Int 50 医疗技能+10
B9: 交易 | C9: 基础 | D9: 交际 | F9: 神秘 | G9: 高级 | H9: 智力 | J9: 舰船方言 | K9: 高级 | L9: 智力 | N9: 化学应用 | O9: 高级 | P9: 智力 | T9: 磁力优雅 | U9: 悬浮1d10+TB分钟，每天一次 | W9: 磁力优雅 | X9: 长时间的辛苦钻研让你掌握了机械神无尽秘密中的一个。花费一个部分动作，你可以在距地面 20–30 米处悬浮，持续时间等于1d10+TB 分钟。你能以正常步行速度移动，但必须保持移动，或者花费部分动作盘旋以保持悬浮状态。你可以在坠落时使用该能力以抵消坠落伤害，这样的话，你的坠落伤害变为固定的 1d10+3 。磁力优雅会消耗储压线圈能量，因此每十二小时只能使用一次。 | Y9: 先决条件：技术神甫（储压线圈） | AC9: 过滤塞 | AD9: 这个简单的塞子可以放在鼻孔内用来隔离有害及污染气体。使用了过滤塞的角色在对抗毒气的坚韧检定中可以获得 +20 的加值。 | AE9: — | AF9: 15 | AG9: 普及 | AH9: 服装 | AJ9: 缆线盒 | AK9: 在垂直表面攀爬获+30，检定失败也不会掉落 | AL9: 2 | AM9: 25 | AN9: 普及 | AO9: 服装 | AQ9: 常识 | AR9: 调查 | AS9: 智力 Int | AT9: 子项：法务部，机械教，内政部，帝国国教，国教教义，帝国卫队，帝国，技术，下层社会，战争，及其它 GM自定项。 常识是你成长或旅行中了解到的一般性知识。检定成功意味着你回忆起了相关信息。每点成功度都可以得到更多信息，由 GM 决定。 进行常识检定不需花费时间。 法务部： 关于法务部下属的各种军事力量，次级部门，包括它们的等级结构和一般办公程序。 机械教： 机械教的符号与仪式的大致意义，以及外交礼节和等级识别一类的知识。 内政部： 有关内政部内部大体上的工作，规章和守则的知识。 帝国国教： 帝国国教的等级的意义，礼仪和行为习惯方面的知识。 国教教义： 帝国国教的仪式和礼节，有关皇帝的常见仪式，以及广为人知的圣徒。 帝国卫队： 帝国卫队编制，军阶，和指挥体系的基本信息，包括常见的战术和战略行为。 帝国： 帝国的主要部门，以及广为人知的世界的情况。 技术： 对于安抚机魂的典礼和连祷文的理解。 下层社会： 帝国下层社会的犯罪和煽动组织的情况。 战争： 关于伟大战役，知名（以及不太知名）的指挥官和英雄，以及著名战略的知识。 | AV9: 刀 | AW9: 格斗 投掷 | AX9: 3m | AY9: 1d5 R | AZ9: 0 | BA9: 原始 | BB9: 0.5 | BC9: 5 | BE9: 短管连发枪 | BF9: 手枪 | BG9: 30m | BH9: S/3/– | BI9: 1d10+3 I | BJ9: 0 | BK9: 9 | BL9: 完整 | BM9: — | BN9: 1.5 | BO9: 50 | CE9: 中档次（面食，戈洛兽肋骨，蒸馏酒） | CF9: 5 | CG9: 普及 | CI9: 完美 | CJ9: 500
B10: 警觉 | C10: 基础 | D10: 感知 | F10: 下层社会 | G10: 高级 | H10: 智力 | J10: 部落方言 | K10: 高级 | L10: 智力 | N10: 技术应用 | O10: 高级 | P10: 智力 | T10: 抵抗* | U10: 抵抗特定状态的检定+10 | W10: 抵抗* | X10: 子项：低温，恐惧，高热，毒素，灵能抵抗特定状态的检定+10。 | Y10: — | AC10: 红外目镜 | AD10: 相对简单装置，红外线护目镜允许佩戴者看到温血动物发出的热量，可以在晚上更好地发现敌人。一个佩戴了红外护目镜的角色不会受到黑暗影响，并且在夜晚基于视力的感知检定可以获得 +20 的加值。更高级的版本可以将自己伪装成一个普通的眼镜状。 | AE10: 0.5 | AF10: 275 | AG10: 稀有 | AH10: 服装 | AJ10: 服装 | AK10: 各种各样的服装服饰 | AL10: — | AM10: 特殊 | AN10: 充裕 | AO10: 服装 | AQ10: 扯淡 | AR10: 社交 | AS10: 交际 Fel | AT10: 你原地站定，开始胡说八道以迷惑或妨碍对手。扯淡检定通常需要对抗对方的意志（或察言观色）检定。如果你胜出，则对手被迷惑一轮，无法进行任何行动，只能愣在原地思索你究竟抽了什么疯。每点成功度可以多冻住对手一轮。如果对手胜出，或者你们两个全都失败，则扯淡无效。 你可以对一组敌人扯淡，只要他们看起来是一个模子刻出来的（例如，邪教徒甲，邪教徒乙，和邪教徒丙），GM 只需进行一次检定，玩家胜出则这一组敌人被迷惑。这一组敌人的数目不能超过你的交际加值。 如果对方处于显而易见的险境，则扯淡的效果结束。如果双方语言不通，扯淡检定自动失败。 扯淡是一个完整动作。 | AV10: 飞刀或手里剑 | AW10: 投掷 | AX10: 5m | AY10: 1d5 R | AZ10: 0 | BA10: 原始 | BB10: 0.5 | BC10: 5 | BE10: 手铳 | BF10: 手枪 | BG10: 35m | BH10: S/–/– | BI10: 1d10+4 I | BJ10: 2 | BK10: 5 | BL10: 2完整 | BM10: — | BN10: 3 | BO10: 65 | CE10: 高档次（珍馔，琥珀色的液体） | CF10: 40 | CG10: 匮乏 | CI10: (熟练医师) | CJ10: 500 | CK10: 罕见 | CL10: Int 60 医疗技能+20 外科专家
B11: 恐吓 | C11: 基础 | D11: 力量 | F11: 密语子项 | J11: 禁忌知识子项 | N11: 灵能感应 | O11: 高级 | P11: 感知 | T11: 电子接口 | U11: 搜集信息，技术应用，常识检定+10 | W11: 电子接口 | X11: 你能使用电子接口访问数据点和联系机魂。当你连接到数据点时，搜集信息，技术应用，和常识检定可以获得+10加值。 | Y11: — | AC11: 成像面罩 | AD11: 这种更高级的透镜装置可以在最阴暗的夜晚都无视低光的影响。使用者即使在最黑暗的地方都能够像在日光下一样观察事物。穿戴者获得黑暗视觉特性（见268页）。而其中优秀品质的甚至可以压制闪光榴弹的效果，使穿戴者免除其影响。 | AE11: 0.5 | AF11: 100 | AG11: 匮乏 | AH11: 服装 | AJ11: 爆破项圈 | AK11: 爆炸时佩戴者死亡且产生半径3m1d10爆炸伤害 | AL11: 1 | AM11: 55 | AN11: 稀有 | AO11: 服装 | AQ11: 导航* | AR11: —— | AS11: 智力 Int | AT11: 当你使用地图，导航仪，或者记忆来避免迷路时，都需要进行导航检定。检定成功的话，你还可以根据地理或星系情况，时令，天气等因素估算出旅行所用时间。正常情况下，每天一次成功的导航检定可以让你不至迷路。如果遇到特殊情况，例如大陆板块起伏，等离子漩涡，或是猛烈的风暴等等，GM可以要求角色进行额外的导航检定。 进行导航检定通常需要好几个小时来阅读图纸，标记线路。但如果只是用地图或导航设备找到自己现在的位置，则至多需要 1 分钟。 地面导航 使用逻辑圆规，地图仪等设备以及地理学知识在行星表面进行旅行。 星际导航 使用星图和占卜仪式进行星际旅行。 | AV11: 盾 | AW11: 格斗 | AX11: — | AY11: 1d5 I | AZ11: 0 | BA11: 原始，防御 | BB11: 3 | BC11: 25 | BE11: 自动步枪 | BF11: 基本 | BG11: 90m | BH11: S/3/10 | BI11: 1d10+3 I | BJ11: 0 | BK11: 30 | BL11: 完整 | BM11: — | BN11: 3.5 | BO11: 100 | CE11: 交通
B12: 狂饮 | C12: 基础 | D12: 坚韧 | F12: 侍僧 | G12: 高级 | H12: 智力 | J12: 黑图书馆 | K12: 高级 | L12: 智力 | N12: 入侵 | O12: 高级 | P12: 敏捷 | T12: 电子援助 | U12: 移除虚弱的坚韧检定+10 | W12: 电子援助 | X12: 你可以召唤神圣的能量来治愈你虚弱的肉体。每当你接触一个发电机，电动机，或者充满的电池时，你可以进行一个普通（+10）的坚韧检定，成功可以恢复1点虚弱，每成功度再加1点。这需要1分钟的冥思与祷告。 | Y12: 先决条件：技术神甫（电感组织/储压线圈） | AC12: 循环呼吸器 | AD12: 包括了一个面罩或是头盔，呼吸器以及自带的循环补给是为了在有毒大气中为使用者提供空气设计的。装备了呼吸器的角色可以免除有毒气体的影响，并且可以在水下存活。作为呼吸器的特色，空气滤毒罐最多可以维持一个小时的使用，之后必须进行更换，更换滤毒罐是一个完整动作。更换用滤毒罐需要花费25帝国币，并且属于匮乏物品。 | AE12: 1 | AF12: 50 | AG12: 匮乏 | AH12: 服装 | AJ12: 过滤塞 | AK12: 塞鼻孔后对抗毒气的坚韧+20 | AL12: — | AM12: 15 | AN12: 普及 | AO12: 服装 | AQ12: 读唇 | AR12: —— | AS12: 感知 Per | AT12: 观察目标嘴唇的活动以了解对方在说什么。使用该检定，你必须能够清楚地看到对方的嘴唇，且能够理解对方使用的语言。距离影响检定难度的主要因素。基本难度为挑战(+0) ，与目标每距离 10 米难度提高一级。如果使用适当的观察设备（译注：例如望远镜）可以忽视距离因素，还会为检定提供加值。 检定成功可以让你了解对方谈论的大致内容，例如天气如何，空港关税几何等。每点成功度都会使内容更具体。 进行读唇检定是一个完整动作，但读唇过程会一直持续到目标谈话结束。 | AV12: 矛 | AW12: 格斗，投掷† | AX12: 10m | AY12: 1d10 R | AZ12: 0 | BA12: 原始 | BB12: 3 | BC12: 15 | BE12: 来复猎枪 | BF12: 基本 | BG12: 150m | BH12: S/–/– | BI12: 1d10+3 I | BJ12: 0 | BK12: 5 | BL12: 完整 | BM12: 精准 | BN12: 5 | BO12: 100 | CE12: 低档次（沙漠犬，低档运输机，破旧的驳船） | CF12: 5 | CG12: 丰富 | CI12: 种类 | CJ12: 医疗护理的水平，从简陋到完美。
B13: 逻辑 | C13: 基础 | D13: 智力 | F13: 内政部 | G13: 高级 | H13: 智力 | J13: 邪教 | K13: 高级 | L13: 智力 | N13: 审讯 | O13: 高级 | P13: 意志 | T13: 独立目标 | U13: 对相距10米内的多个目标射击 | W13: 独立目标 | X13: 同时使用两把武器射击时，你可以攻击间距超过10米的多个目标。 | Y13: 先决条件：BS40 | AC13: 缓冲手套 | AD13: 这些手套拥有使用记忆金属线连接的铁片咬合而成。当持用武器时，铁片的咬合锁会围绕着使用者的手和手腕硬化，以化解武器产生的后座力引发的伤害。当使用缓冲手套时，角色可以正常单手使用基础类武器而不用承受标准情况下 −20 的减值。需要双手使用的手枪类武器也可以依此法单手使用而不受减值。 | AE13: 0.5 | AF13: 85 | AG13: 稀有 | AH13: 服装 | AJ13: 红外目镜 | AK13: 温血动物热量可视化，不怕黑暗，夜晚视力+20 | AL13: 0.5 | AM13: 275 | AN13: 稀有 | AO13: 服装 | AQ13: 赌博 | AR13: —— | AS13: 智力 Int | AT13: 任何形式的赌博活动（例如纸牌或骰子游戏）都需要双方进行赌博技能对抗检定。你可以自动放弃检定，视为检定失败。 对抗之前你可以先进行手上功夫技能检定来尝试出老千，成功的话随后的赌博检定有+20 加值。如果手上功夫检定的失败度达到 5或以上，意味着你拙劣的手法被人发现了。 随游戏的种类不同，赌博检定所需时间亦不同，从几秒钟到一整天不等。 | AV13: 剑 | AW13: 格斗 | AX13: — | AY13: 1d10 R | AZ13: 0 | BA13: 原始，平衡 | BB13: 3 | BC13: 15 | BE13: 霰弹猎枪 | BF13: 基本 | BG13: 30m | BH13: S/–/– | BI13: 1d10+4 I | BJ13: 0 | BK13: 2 | BL13: 2完整 | BM13: 可靠，散射 | BN13: 5 | BO13: 60 | CE13: 中档次（民用飞行器，大气层内飞行） | CF13: 20 | CG13: 普及 | CI13: 花费 | CJ13: 一次医疗处理的花费。如果是长期护理，则此处为每天的花费，不包括食宿。这里的标准没有考虑那些自视过高的庸医，也没有考虑那些志愿救死扶伤的高贵的灵魂。因此gm在调整花费时应该有很大的余地。
B14: 攀爬 | C14: 基础 | D14: 力量 | F14: 帝国国教 | G14: 高级 | H14: 智力 | J14: 恶魔学 | K14: 高级 | L14: 智力 | N14: 生存 | O14: 高级 | P14: 智力 | T14: 额外次级灵能* | U14: 你获得一项次级灵能 | W14: 额外次级灵能* | X14: 你获得一项次级灵能。 | Y14: — | AC14: 防毒面具 | AD14: 这是一个能够覆盖使用者口鼻或整个脸部的呼吸面具，并且在各种层面上来说都要远胜于过滤塞。防毒面具可以使角色在对抗毒气的坚韧检定中获得 +30 的加值，并且允许重投失败检定。 | AE14: 0.5 | AF14: 25 | AG14: 一般 | AH14: 服装 | AJ14: 成像面罩 | AK14: 获得黑暗视觉特性，优秀品质免疫闪光弹 | AL14: 0.5 | AM14: 100 | AN14: 匮乏 | AO14: 服装 | AQ14: 躲藏 | AR14: —— | AS14: 敏捷 Ag | AT14: 花费一个部分动作躲起来。周围必须有合适的掩蔽物，或者黑暗、大雾一类的环境，否则检定自动失败。躲藏本身不需要检定，仅当有人注意到你时，对方用警觉（或者感知属性的一半）检定对抗你的躲藏检定。 如果你保持静止不动，躲藏检定 +10 。 | AV14: 杖 | AW14: 格斗† | AX14: — | AY14: 1d10 I | AZ14: 0 | BA14: 原始，平衡 | BB14: 3 | BC14: 10 | BE14: 泵动霰弹枪 | BF14: 基本 | BG14: 30m | BH14: S/–/– | BI14: 1d10+4 I | BJ14: 0 | BK14: 8 | BL14: 2完整 | BM14: 散射 | BN14: 5 | BO14: 75 | CE14: 高档次（低轨道飞行器，私人轿车） | CF14: 150 | CG14: 匮乏 | CI14: 稀有度 | CJ14: 好医生可很难找到。侍僧在求医问药的时候也要考虑稀有度的因素。见第139页表5.4。
B15: 欺诈 | C15: 基础 | D15: 交际 | F15: 下层社会 | G15: 高级 | H15: 智力 | J15: 异端 | K15: 高级 | L15: 智力 | N15: 手上功夫 | O15: 高级 | P15: 敏捷 | T15: 额外灵能* | U15: 从你已知的学科中获得一项额外灵能 | W15: 额外灵能* | X15: 从你已知的学科中获得一项额外灵能。 | Y15: — | AC15: 太空服 | AD15: 这种密封的服装可以使穿戴者对抗几乎所有的有害环境。一件太空服包括了一个循环呼吸器并且可以使穿戴者在真空中存活。 | AE15: 8 | AF15: 100 | AG15: 丰富 | AH15: 服装 | AJ15: 循环呼吸器 | AK15: 免除毒气，水下存活，滤毒罐1h后需完整动作更换（滤毒罐一个25g，重量可忽略） | AL15: 1 | AM15: 50 | AN15: 匮乏 | AO15: 服装 | AQ15: 跟踪 | AR15: —— | AS15: 敏捷 Ag | AT15: 跟踪技能用于尾随生物或车辆而不被对方发现。跟踪与躲藏不同，前者需要在移动中保持隐蔽。跟踪通常需要你由一个掩蔽物移动到另一个。 如果没有这种条件，就装作是在做别的事情——例如正在阅读一块数据板，检查一张悬赏海报，或是诸如此类的事情。跟踪技能用于对抗目标的警觉技能，一次检定成功可以让你不被发现地跟踪目标 1 分钟。 | AV15: 链锯剑 | AW15: 格斗 | AX15: — | AY15: 1d10+2 R | AZ15: 2 | BA15: 平衡，撕裂 | BB15: 6 | BC15: 275 | BE15: 战斗霰弹枪 | BF15: 基本 | BG15: 30m | BH15: S/3/– | BI15: 1d10+4 I | BJ15: 0 | BK15: 18 | BL15: 完整 | BM15: 散射 | BN15: 6.5 | BO15: 150 | CI15: 效果 | CJ15: 医生的医疗水平以及进行医疗检定的效果。具体技能检定的运作方式见第三章：技能，医疗部分。
B16: 潜行 | C16: 基础 | D16: 敏捷 | F16: 军队 | G16: 高级 | H16: 智力 | J16: 审判庭 | K16: 高级 | L16: 智力 | N16: 特技 | O16: 高级 | P16: 敏捷 | T16: 反戈一击 | U16: 成功的格挡检定可以进行一次自由攻击 | W16: 反戈一击 | X16: 成功进行格档之后，你可以用格档所用的武器立刻对攻击你的目标进行一次攻击，但攻击检定−20。 | Y16: 先决条件：WS40 | AC16: 生化皮肤 | AD16: 生化皮肤是一种能够覆盖在使用者身体表面的惰性生物反应防护装置。生化皮肤为使用者全身提供2点护甲防护，不可与其它护甲叠加。只要穿戴者不穿着其它护甲，他在潜行和躲藏检定上可获得 +10 的加值。对于红外护目镜以及黑暗视觉来说，生化皮肤穿戴者是不可见的，除非他穿着动力护甲。 | AE16: 2 | AF16: 2500 | AG16: 罕见 | AH16: 服装 | AJ16: 缓冲手套 | AK16: 单手使用基础武器不承受−20的减值 | AL16: 0.5 | AM16: 85 | AN16: 稀有 | AO16: 服装 | AQ16: 估价 | AR16: 调查 | AS16: 智力 Int | AT16: 用于确定日用品或贵重物品的大致价值。成功的检定可以揭示物品的市场价格，以及少量关于物品本身的信息。检定失败会得到错误的信息，因此这个检定是由GM暗投的。 估价检定至少需要1分钟，视花费时间的长短可以有一定的加值或减值，由GM决定。 | AV16: 链锯斧 | AW16: 格斗 | AX16: — | AY16: 1d10+4 R | AZ16: 2 | BA16: 撕裂 | BB16: 13 | BC16: 450 | BE16: 重机枪 | BF16: 重型 | BG16: 120m | BH16: –/–/10 | BI16: 1d10+4 I | BJ16: 3 | BK16: 200 | BL16: 2完整 | BM16: — | BN16: 35 | BO16: 750
B17: 柔术 | C17: 基础 | D17: 敏捷 | F17: 科技 | G17: 高级 | H17: 智力 | J17: 古代科技 | K17: 高级 | L17: 智力 | N17: 驯养动物 | O17: 高级 | P17: 智力 | T17: 飞跑 | U17: 战斗中移动得更快 | W17: 飞跑 | X17: 你能够以突然爆发的速度来摆脱——或是一头扎入——麻烦。你进行完整移动时可多移动等于敏捷加值的米数。另外，你的奔跑速度翻倍，持续一轮。如果连续两次使用该天赋奔跑，你会得到1级虚弱。 | Y17: — | AB17: 药 物 和 消 耗 品 | AC17: 蒸馏酒 | AD17: 是一种由葡萄酒蒸馏出来的酒精流行饮料。它们其中既有简陋私家作坊酿造的，几乎能够作成燃烧弹使用的品种，也有经过精心制作并且有着知名商标，只有帝国忠仆内的高贵人物才可以享用的佳酿。 | AE17: — | AF17: 50 | AG17: 匮乏 | AH17: 消耗品 | AJ17: 防毒面具 | AK17: 对抗毒气的坚韧+30，失败可重投 | AL17: 0.5 | AM17: 25 | AN17: 一般 | AO17: 服装 | AQ17: 航行* | AR17: 操作 | AS17: 敏捷 Ag | AT17: 航行技能用于操作任何类型的飞行器，从小型飞行器到大型战舰。检定规则与驾驶技能相同。 | AV17: 能量刃 | AW17: 格斗 | AX17: — | AY17: 1d10+3 E | AZ17: 6 | BA17: 能量 | BB17: 1.5 | BC17: 1750 | BE17: 爆矢手枪 | BF17: 手枪 | BG17: 30m | BH17: S/2/– | BI17: 1d10+5 X | BJ17: 4 | BK17: 8 | BL17: 完整 | BM17: 撕裂 | BN17: 3.5 | BO17: 250 | CE17: 住宿 | CF17: 包括各种旅店和出租床位，从某个中世纪的简陋小酒馆到供帝国贵族使用的豪华套房。
B18: 闪避 | C18: 基础 | D18: 敏捷 | F18: 表演子项 | J18: 变种人 | K18: 高级 | L18: 智力 | N18: 医疗 | O18: 高级 | P18: 智力 | T18: 格斗武器训练* | U18: 熟练地使用你选择的格斗武器 | W18: 格斗武器训练* | X18: 子项：原始武器，链锯武器，震击武器，能量武器无减值地使用你选择的格斗武器。 | Y18: — | AC18: 解毒剂（药物） | AD18: 这种药品可以免除大部分有害气体影响，使用及时甚至可以中和毒素。使用解毒剂可以立刻终止来源于药品，毒素，空气的影响，无论是积极的还是消极的（除非有特殊说明该影响无法使用解毒剂进行对抗）。 | AE18: — | AF18: 65 | AG18: 稀有 | AH18: 药物 | AJ18: 太空服 | AK18: 可对抗有害环境，内置循环呼吸器，可真空存活 | AL18: 8 | AM18: 100 | AN18: 丰富 | AO18: 服装 | AQ18: 化学应用 | AR18: 制造，调查 | AS18: 智力 Int | AT18: 化学应用包括正确地处理，制备，和鉴别化学品——尤其是有毒，有害物质及麻醉品。 配制或使用化学品时，必须进行化学应用检定，难度由GM调整。检定失败则药品被浪费。失败度达5以上意味着你受沾染或摄入过量药物。具体化学品的作用见第五章：武装。 使用毒素探针或解毒剂时，一个成功的化学检定可以让所需时间减半。 合成化学品的相关规则书见第 107 页制造技能部分。 | AV18: 能量剑 | AW18: 格斗 | AX18: — | AY18: 1d10+5 E | AZ18: 6 | BA18: 能量，平衡 | BB18: 3.5 | BC18: 2500 | BE18: 爆矢枪 | BF18: 基本 | BG18: 90m | BH18: S/2/– | BI18: 1d10+5 X | BJ18: 4 | BK18: 24 | BL18: 完整 | BM18: 撕裂 | BN18: 7 | BO18: 500 | CE18: 供给 | CF18: 包括各种消耗品，例如食物和饮料。
B19: 搜集信息 | C19: 基础 | D19: 交际 | F19: 舞者 | G19: 高级 | H19: 交际 | J19: 修会 | K19: 高级 | L19: 智力 | N19: 阅读 | O19: 高级 | P19: 智力 | T19: 格斗专家 | U19: 包围你的对手不会得到任何加值 | W19: 格斗专家 | X19: 你擅长应付以寡敌众的肉搏战，在近战格斗中包围你的对手不会得到任何加值。 | Y19: 先决条件：WS30 | AC19: 暴怒（药物） | AD19: 这种特殊类型的战斗药物在刑事犯军团中被大量使用。一旦服用，人在战斗中会变得疯狂且无所畏惧。任何服用暴怒药的角色获得狂暴天赋并且无视任何恐惧影响，一剂暴怒的效力最多可以维持 1d10分钟。 | AE19: — | AF19: 95 | AG19: 罕见 | AH19: 药物 | AJ19: 生化皮肤 | AK19: 无甲时+2甲，潜行躲避+10，红外/黑暗视觉不可见 | AL19: 2 | AM19: 2500 | AN19: 罕见 | AO19: 服装 | AQ19: 技术应用 | AR19: —— | AS19: 智力 Int | AT19: 可用于修理机械或探索那些不寻常的机械设备如何运转。在通常情况下使用话筒或占卜盒一类常见机械不需检定。技术应用检定仅在使用罕见的设备，故障机械，或者恶劣条件下——例如在电子风暴中使用占卜盒，或者让一台废置了上千年的亚空间引擎重新运转——才需要进行。修理故障或损坏的设备时，检定难度视物品复杂程度和损坏情况而定。 技术应用技能也可用于根据图纸制造物品，尽管这种情况通常使用相关的生计技能。 用于确定物品功用的技术应用检定通常需要 1 分钟，视物品的复杂程度而变。用于修理物品的技术应用检定通常需要1小时，每点成功度减少10 分钟。 | AV19: 震击槌 | AW19: 格斗 | AX19: — | AY19: 1d10 I | AZ19: 0 | BA19: 震击 | BB19: 2.5 | BC19: 150 | BE19: 重型爆矢枪 | BF19: 重型 | BG19: 120m | BH19: –/–/10 | BI19: 2d10+3 X | BJ19: 5 | BK19: 60 | BL19: 2完整 | BM19: 撕裂 | BN19: 40 | BO19: 2000 | CE19: 交通 | CF19: 包括各种运输工具。注意这里所列的是在某个固定地点（例如，一个世界）之内的旅行，而不包括行星之间乃至太阳系间的旅行。
B20: 搜索 | C20: 基础 | D20: 感知 | F20: 乐师 | G20: 高级 | H20: 交际 | J20: 机械神教 | K20: 高级 | L20: 智力 | N20: 专注 | O20: 高级 | P20: 意志 | T20: 悍不畏死 | U20: 压制检定失败可重投 | W20: 悍不畏死 | X20: 可重投失败的压制检定。 | Y20: — | AC20: 注射器 | AD20: 来自低技术世界的廉价注射器拥有多种形式，从压力注射器到皮下注射器不一而足。一个注射器可以储存一剂任意种类的药物，这样的行为需要角色的一个完整动作。 | AE20: — | AF20: 5 | AG20: 充裕 | AH20: 消耗品 | AJ20: 占卜盒/扫描仪 | AK20: 警觉+20，可使用技术应用扫描肉眼不可见的东西， 会被50cm+ 的墙壁或防护阻挡侦测 | AL20: 0.5 | AM20: 145 | AN20: 匮乏 | AO20: 消耗品 | AQ20: 驾驶* | AR20: 操作 | AS20: 敏捷 Ag | AT20: 子项：地面载具，悬浮载具，步行载具 驾驶技能是用来操作汽车，卡车，兰德速攻艇或其它地面以及悬浮载具。通常驾驶不需要检定，只有在通过困难地形、超速飙车，或进行危险动作时可能需要检定。驾车追逐时，追赶和被追赶双方驾驶员进行驾驶技能对抗检定。 驾驶检定通常是一个部分动作，但特定载具可能需要更多或更少的时间。 帝国的代步工具 帝国充满了令人眼花缭乱的载具，从摇晃的手推车到帝王级战舰。下面列举几种侍僧可能会用到的。 骑乘动物：被驯化的生物坐骑，最常见的是马，尤其是在那些野蛮世界和科技水平较低的农业世界。 摩托：帝国中常见的载具之一，包括一些加了装甲和武器的战斗型号。每驾摩托可以容纳一名驾驶员和他的装备，如果后座空间允许还可以加上一名乘客。 机枪艇：机枪艇是一种轻型飞行器，能够达到低轨道。它装备有重武器，随时可以投入战斗，总是出现在危险的场合。大部分机枪艇只能承载一名船员和有限的乘员。 奇美拉：奇美拉装甲运兵车是一种常见的轻型支援载具，广泛应用于帝国的军事和准军事组织。它有结实的装甲，能搭载多种重武器，可以运载十二名乘员加三名车组人员。 雷鹰登陆艇：帝国海军需要运送要员到停泊在轨道上的飞船上时，通常会使用雷鹰登陆艇。这种飞行器因为机身和机翼上的帝国双头鹰浮雕而得名。雷鹰登陆艇不具备行星间航行的能力，只是一种出色的轻型穿梭机，内部典雅舒适，可以轻松承载七名乘客和一名导航者。 | AV20: 电击链枷 | AW20: 格斗† | AX20: — | AY20: 1d10+2 I | AZ20: 0 | BA20: 震击，柔韧 | BB20: 4.5 | BC20: 375 | BE20: 炽热手枪 | BF20: 手枪 | BG20: 10m | BH20: S/–/– | BI20: 2d10+4 E | BJ20: 12 | BK20: 3 | BL20: 完整 | BM20: — | BN20: 2.5 | BO20: 7500 | CE20: 服务的花费以帝国币为单位，表示一个晚上的住宿费用或一顿饭的开销。至于交通，如果旅行路程很长或目的地十分危险，GM可适当调整花费。
B21: 伪装 | C21: 基础 | D21: 交际 | F21: 歌手 | G21: 高级 | H21: 交际 | J21: 灵能者 | K21: 高级 | L21: 智力 | N21: 追迹 | O21: 高级 | P21: 智力 | T21: 黑暗灵魂 | U21: 恶化检定所受减值减半 | W21: 黑暗灵魂 | X21: 你的灵魂被黑暗污染，使得你能够抵抗堕落。每当你需要进行恶化检定，该检定所受减值减半。详见第256页堕落规则。 | Y21: — | AC21: 卷烟 | AD21: 卷烟能够在很多帝国卫军战士和仆役工人手中发现。被包成管状的纸质外壳内，存有某些具有特殊香气，微量麻醉（和上瘾）性物质，当被点燃的时候，烟雾就通过纸管被吸入使用者体内。 | AE21: — | AF21: 10 | AG21: 普及 | AH21: 消耗品 | AJ21: 自动书写笔 | AK21: 精准快速的复制文本，生计（抄写员） +10 | AL21: — | AM21: 55 | AN21: 匮乏 | AO21: 药物 | AQ21: 交易 | AR21: —— | AS21: 交际 Fel | AT21: 用于杀价。日常集市只需要进行交易技能检定，但如果遇到交易的某一方要承担风险，交易环境危险，或者涉及大量金钱等情况，则进行交易技能对抗检定。无论是哪种情况，检定成功减价 10% ，每个成功度再减 5% 。砍价通常历时5分钟，但如果进行复杂的磋商则需要更多时间，具体由GM决定。 | BE21: 热熔枪 | BF21: 基本 | BG21: 20m | BH21: S/–/– | BI21: 2d10+4 E | BJ21: 12 | BK21: 5 | BL21: 2完整 | BM21: — | BN21: 8 | BO21: 4000
B22: 吸引力 | C22: 基础 | D22: 交际 | F22: 说书人 | G22: 高级 | H22: 交际 | J22: 亚空间 | K22: 高级 | L22: 智力 | T22: 击昏 | U22: 用一个特殊的攻击打昏对手 | W22: 击昏 | X22: 花费一个部分动作进行一次攻击，在检定之前声明要击昏目标。如果这次攻击命中并造成了至少1点伤害，则该伤害被忽略，目标进行坚韧检定，失败就会昏迷1轮。 | Y22: — | AC22: 医疗箱 | AD22: 这是一个对任何医生来说都至关重要的设备。一个典型的医药箱包含了各式药膏，抗生素，合成皮肤。一个拥有医疗箱的角色可以在进行医疗技能检定时获得 +20 的加值。医疗箱还含有6份兴奋剂，当使用之后必须进行替换。 | AE22: 2 | AF22: 150 | AG22: 普及 | AH22: 消耗品 | AJ22: 组合工具 | AK22: 一套通用工具，技术应用 +10 | AL22: 1 | AM22: 200 | AN22: 稀有 | AO22: 药物 | AQ22: 禁忌知识* | AR22: 调查 | AS22: 智力 Int | AT22: 子项：黑图书馆，邪教，恶魔学，异端，审判庭，古代科技，变种人，修会，机械神教，灵能者，亚空间，异族 禁忌知识是那些危险且带有异端色彩的知识，角色在这方面的知识通常一部分靠文献，一部分靠实践。仅仅是掌握这些知识就足 以成为审判庭除掉此人的充分理由，因此一定要谨慎对待。 禁忌知识检定成功意味着你回忆起了相关信息。每点成功度都可以得到更多信息，由GM决定。 如果角色试图学习禁忌知识，或者尝试以这种知识发掘群星深处的秘密，都可能得到一定的堕落或失心点数，具体多少取决于知识的危险程度，详见 GM部分。 进行禁忌知识检定不需要花费时间，尽管了解这些知识的后果可能伴随你一生…… 黑图书馆： 关于黑图书馆的秘密知识，那禁忌的内容，诡异的机械，以及高墙内那些肤色苍白，没有毛发，无法言语的奴工。 邪教： 有关帝国境内大部分声名狼藉的教派的知识，包括其分支教派和部分阴谋。 恶魔学： 有关那些进入过亚空间的人，以及他们表现出的不同症状的恐怖知识。 异端： 对于被帝国认定为异端的行为的可耻了解。 审判庭： 有关审判庭那些恐怖的秘密部门的大致了解（通常源于异端言论与道听途说）。 古代科技： 关于远古时代伟大机械设备的知识，及探索这些设备功能与目的的线索。 变种人： 对于稳定和不稳定的突变异种的研究，以及部分变种人最终的不幸下场。 修会： 对于审判庭下属的恶魔，异端，和异族猎手修会内情的些许了解。 机械神教： 对于机械神追随者的了解，包括他们的礼仪，观念与核心信条。 灵能者： 辨识灵能者标记，了解灵能的特征与威力。 亚空间： 知道亚空间的道路，以及亚空间航行的原理。 异族： 了解帝国附近常见外星人的情况。 | BE22: 等离子手枪 | BF22: 手枪 | BG22: 30m | BH22: S/–/– | BI22: 1d10+6 E | BJ22: 6 | BK22: 10 | BL22: 4完整 | BM22: 充能，过热 | BN22: 4 | BO22: 4000
B23: 游泳 | C23: 基础 | D23: 力量 | F23: 导航子项 | J23: 异族 | K23: 高级 | L23: 智力 | T23: 机械附肢（多功能） | U23: 能够使用多功能机械附肢 | W23: 机械附肢* | X23: 子项：枪械附肢，起重附肢，医疗附肢，光学附肢，多功能附肢能够使用选择的机械附肢。 | Y23: 先决条件：技术神甫（机械外壳/颅腔电路） | AC23: 愚民粉（药物） | AD23: 做为一种在帝国内广泛流传的神经麻醉类药物，愚民在相当多的地区都是被禁止流通并且严密监控的。但是走私者经常通过和当地重要人物的良好关系获得私下将这种药物向各个阶层的市民以及军事组织成员兜售的权利。使用愚民粉会导致进入类似梦游状态大约 1d5 小时（如果在此过程中进入战斗状态，则使用者会受到类似致幻榴弹的影响）。经过1d10小时，随着药物效力的逐渐消散，除非能够获得另一剂愚民，否则他们会陷入深深的沮丧情绪中。 | AE23: — | AF23: 28 | AG23: 稀有 | AH23: 药物 | AJ23: 数据板 | AK23: 被广泛使用，用来记录和读取编辑完成的文本或是其他的音频和视频数据 | AL23: 0.5 | AM23: 25 | AN23: 普及 | AO23: 消耗品 | AQ23: 警觉 | AR23: —— | AS23: 感知 Per | AT23: 你可以用警觉技能来发现伏兵，侦查陷阱，或注意到其它威胁。这个技能综合了你的全部感知能力。 使用警觉技能通常是一个自由动作，注意到埋伏一般进行对抗检定，其它情况的话检定难度视物体隐蔽程度而定。 | BE23: 等离子枪 | BF23: 基本 | BG23: 90m | BH23: S/2/– | BI23: 1d10+6 E | BJ23: 6 | BK23: 20 | BL23: 8完整 | BM23: 充能，过热 | BN23: 11 | BO23: 3000
B24: 指挥 | C24: 基础 | D24: 交际 | F24: 地面 | G24: 高级 | H24: 智力 | J24: 学术知识子项 | T24: 机械附肢（医疗） | U24: 能够使用医疗机械附肢 | W24: 机械语者 | X24: 对机械仆役进行命令，编程，询问等行为的检定+10。 | Y24: — | AC24: 压缩食物 | AD24: 帝国内几乎所有的食物都是经过加工后密封包装，并且从外表看起来完全不知道是哪种东西制成的。压缩食物的品质多种多样，从简单廉价的生物淀粉搭配人工养殖的食用藻到经过特殊烹饪富含营养的戈洛兽肉条。 | AE24: — | AF24: 10 | AG24: 丰富 | AH24: 消耗品 | AJ24: 爆破药 | AK24: 造成 3d10 加每公斤 2 点的爆炸伤害，范围每公斤5米。 | AL24: 1 | AM24: 250 | AN24: 匮乏 | AO24: 消耗品 | AQ24: 恐吓 | AR24: 社交 | AS24: 力量 S | AT24: 使人因畏惧而服从你，并非只要恐吓对方就需要检定。通常基于力量，但采用恐吓信一类的方式也可以改用交际或智力属性。 恐吓可对个体或一群人使用，但人数上限不超过你的力量（或者智力，或者交际，取决于你检定时用的属性）加值。目标必须能够看到你，清楚地听到你的声音，且能理解你的意思。 恐吓检定是一个完整动作。 | BE24: 火焰手枪 | BF24: 手枪 | BG24: 10m | BH24: S/–/– | BI24: 1d10+4 E | BJ24: 2 | BK24: 2 | BL24: 2完整 | BM24: 火焰 | BN24: 3.5 | BO24: 200
F25: 星际 | G25: 高级 | H25: 智力 | J25: 古代史 | K25: 高级 | L25: 智力 | T25: 机械附肢（起重） | U25: 能够使用起重机械附肢 | W25: 基本武器训练 | X25: 子项：矢弹武器，火焰武器，激光武器，榴弹武器，热熔武器，等离子武器，原始武器，实体弹武器.无减值地使用你选择的武器。 | Y25: — | AC25: 雷诺咖啡 | AD25: 雷诺咖啡是一种在帝国内十分流行，由植物叶片或花瓣粉碎酿造制成的热饮。它的成分因植物来源不同而多种多样，但是几乎所有的都混合了一些刺激性的成分，例如咖啡因或是茶碱。 | AE25: — | AF25: 5 | AG25: 充裕 | AH25: 消耗品 | AJ25: 刑讯工具 | AK25: 一套花样百出的刑具，审讯+20 | AL25: 1 | AM25: 375 | AN25: 罕见 | AO25: 消耗品 | AQ25: 狂饮 | AR25: —— | AS25: 坚韧 T | AT25: 这个技能可以帮助你抵抗乙醇或其它麻醉品的效果。每次摄入麻醉品（译注：书上没有注明剂量，GM 看着合适罢），进行一次狂饮检定，失败则承受 1 级虚弱。因此而失去意识会维持 1d10 减去坚韧加值的小时数（至少一小时）。清醒之后角色可能会受到一些宿醉减值，GM可以视情况灵活决定。 进行狂饮检定是一个自由动作。 | BE25: 火焰喷射器 | BF25: 基本 | BG25: 20m | BH25: S/–/– | BI25: 1d10+4 E | BJ25: 3 | BK25: 3 | BL25: 2完整 | BM25: 火焰 | BN25: 6 | BO25: 300
F26: 航行子项 | J26: 气象学 | K26: 高级 | L26: 智力 | T26: 机械附肢（光学） | U26: 能够使用光学机械附肢 | W26: 极限打击 | X26: 如果你的格斗武器对目标造成了致命伤害，它将增加1d5−1点。 | Y26: 先决条件：WS50 | AC26: 劣质烈酒 | AD26: 各式各样的酒精饮料遍布整个帝国，在几乎所有文明的记录中，它属于一种经过发酵的液体。在这些不同品质的饮料中，劣质烈酒算是其中较为低档的（尤其对于旅行者来说）。 | AE26: — | AF26: 10 | AG26: 充裕 | AH26: 消耗品 | AJ26: 照明球/发光器 | AK26: 照亮 12 米的距离。可以持续工作1d5h | AL26: 0.5 | AM26: 15 | AN26: 充裕 | AO26: 药物 | AQ26: 灵能感应 | AR26: —— | AS26: 感知 Per | AT26: 你可以感应并追踪亚空间波动，通常用于侦测恶魔或其它灵能者的动向。这样做需要进行灵能感应检定，成功的话可以侦测 1d10 加感知加值的米数半径区域内的情况，每点成功度都让你的侦测半径增加 1d10 + PB 米。 灵能感应技能也可以侦测不寻常的灵能现象，真实空间出现的扰动，以及非物质空间被阻隔的区域等等。灵能检定由GM暗投。 进行灵能感应是一个完整动作。 检定结果与了解到的信息如下： 成功度 结果 标准 察觉到非物质空间出现扰动 一 灵能现象源头的大致位置 二或以上 引导或阻隔非物质空间个体的精确位置 | BE26: 绳球套索 | BF26: 投掷 | BG26: 10m | BH26: S/–/– | BI26: — | BJ26: 0 | BK26: 1 | BL26: — | BM26: 原始，捕捉，粗劣 | BN26: 1.5 | BO26: 10
F27: 民用飞行器 | G27: 高级 | H27: 敏捷 | J27: 动物学 | K27: 高级 | L27: 智力 | T27: 机械附肢（枪械） | U27: 能够使用枪械机械附肢 | W27: 即时备战 | X27: 当你只装备着一把手枪或基本射击武器，或单手执用格斗武器时，你可以用一个自由动作进行准备动作。 | Y27: — | AC27: 祝福机油 | AD27: 这些被机械神祝福的礼物能够通过作用于机械而展现它们的神秘力量。如果将圣油涂抹在一件武器上（需要一个完整动作）会使其免疫干扰，效果维持到使用完相当于一个满载弹夹的弹药量为止。如果将它涂抹在已被干扰的武器上，可以立刻终止干扰，但不会有其它效果。 | AE27: — | AF27: 150 | AG27: 罕见 | AH27: 消耗品 | AJ27: 抓钩 | AK27: 钩中目标后，可徒手攀爬或通过绞盘把自己拉上去 | AL27: 2 | AM27: 30 | AN27: 普及 | AO27: 消耗品 | AQ27: 逻辑 | AR27: 调查 | AS27: 智力 Int | AT27: 数学推理与解决问题的技能。逻辑检定可用于破译密码或解开复杂的方程式。机械神甫还可以用它来对机械进行数字仪式。注意逻辑是一个纯理论技能，而技术应用则提供实践方面的补充。 逻辑检定需要 1 分钟时间来推算和思考，有些特别复杂的问题可能需要更长时间。 | BE27: 手弩 | BF27: 手枪 | BG27: 15m | BH27: S/–/– | BI27: 1d10 R | BJ27: 0 | BK27: 1 | BL27: 完整 | BM27: 原始 | BN27: 1 | BO27: 200
F28: 军用飞行器 | G28: 高级 | H28: 敏捷 | J28: 行政 | K28: 高级 | L28: 智力 | T28: 机械语者 | U28: 控制自动仆役时有+10加值 | W28: 棘手目标 | X28: 奔跑或冲锋时对手的BS检定−20。 | Y28: 先决条件：Ag40 | AC28: 屠杀（药物） | AD28: 作为一种能够明显改善使用者的反应时间和速度的药物，持续使用屠杀会引发疲劳和神经系统伤害。屠杀能够在 2d10 分钟内使服用者的敏捷和感知加值 +3 。当药效结束时，除非通过一个坚韧检定，否则在之后的1d5小时中，使用者的敏捷和感知检定会受到 −20 的减值。 | AE28: — | AF28: 75 | AG28: 匮乏 | AH28: 药物 | AJ28: 激光切割刀 | AK28: 切割，焊枪，每轮可处理 10cm 的金属（根据材质稍有不同） | AL28: 4 | AM28: 65 | AN28: 一般 | AO28: 消耗品 | AQ28: 密语* | AR28: —— | AS28: 智力 Int | AT28: 子项：侍僧，内政部，帝国国教，下层社会，军队，科技，或其它GM开放的项目。 密语是特定群体内部使用的一种更接近于代码的秘密语言，通常一个单词可以表达非常丰富的含义，可用于快速隐秘地交流信息。通常情况下，用密语交流不需要检定（但必须双方都懂得这种密语），只有在特别喧闹的环境或混乱的战场上才需要密语检定。参加游戏的侍僧们可能希望设计一种仅用于玩家间交流的暗语，这包括在密语（侍僧）技能里。 密语检定通常是一个自由动作。 侍僧： 一系列预先约定好的被赋予特殊意义的短语，仅用于伙伴成员间的交流。注意不同侍僧团体间使用着不同版本的密语。 内政部： 内政部使用的各种缩略语，行话，以及标准用语的集合。注意这是一种极其复杂冗长的语言。 帝国国教： 一种虔诚而圆滑的寓言式的语言，充满了隐喻和专业性极强的高哥特语。 下层社会： 帝国最下层社会使用的低哥特语的混合，是各种各样的俚语，粗话的大杂烩。 军队： 参考了远古战场使用的密语而挑选出来的加密短语，隐语，以及数量惊人的描述死亡的词汇。 科技： 机械神教的发声技术，由各种术语，二进制编码，以及高频和低频声波组成。 | BE28: 燧发手枪 | BF28: 手枪 | BG28: 15m | BH28: S/–/– | BI28: 1d10+2 I | BJ28: 0 | BK28: 1 | BL28: 3完整 | BM28: 原始，易损，粗劣 | BN28: 4 | BO28: 10
F29: 宇宙飞船 | G29: 高级 | H29: 敏捷 | J29: 化学 | K29: 高级 | L29: 智力 | T29: 基本武器训练* | U29: 无减值地使用你选择的武器 | W29: 加速循环 | X29: 你可以主动让你血液中的移植物加速工作。每十二小时可用一次，你进行一次技术应用检定，成功的话可立刻恢复1d5点伤害。如果检定投出96―100视为自动失败，且你的血液移植物过载，它们将罢工一周。一周之内，你失去自动止血和加速循环两个天赋的效果。一周之后两个天赋效果恢复。启动加速循环天赋需要10分钟的冥想与祈祷。 | Y29: 先决条件：自动止血 | AC29: 鬼灵（药物） | AD29: 这种药物可以在短时间内增加使用者的灵能。如果一个没有灵能级别的角色使用鬼灵，它必须通过一个意志检定或是得到1d5的失心点数，就如同他刚刚瞥见恐怖亚空间波动的一角一样。如果成功，使用者会获得一种随机灵能（具体见表5.22：随机灵能，灵能具体效果见第六章：灵能）。该能力会维持 1d5 小时，在这期间角色可以任意施展该灵能。如果该角色没有聚焦能量的技巧，则进行一个−20的意志检定以施展灵能。 如果角色已经具有灵能等级1或更高，则需要进行一个意志检定，失败仅会得到 1 点失心而不会有其它结果。如果成功，角色在之后的一个小时中使用灵能会获得 2 点能量聚焦加成。作为代价，此时所有的灵能现象结果都会得到 +25% 的结果（最高 100，详见第178页，灵能现象）。 | AE29: — | AF29: 395 | AG29: 稀有 | AH29: 药物 | AJ29: 多功能望远镜 | AK29: 放大观察远距离目标 | AL29: 0.5 | AM29: 55 | AN29: 一般 | AO29: 消耗品 | AQ29: 攀爬 | AR29: —— | AS29: 力量 S | AT29: 详见规则书第七章：进行游戏，移动部分。 | BE29: 滑膛枪 | BF29: 基本 | BG29: 30m | BH29: S/–/– | BI29: 1d10+2 I | BJ29: 0 | BK29: 1 | BL29: 5完整 | BM29: 原始，易损，粗劣 | BN29: 7 | BO29: 30
F30: 驾驶子项 | J30: 密码学 | K30: 高级 | L30: 智力 | T30: 即时备战 | U30: 以自由动作准备武器或物品 | W30: 尖锐噪音 | X30: 用呼吸面罩的声音合成系统发出一阵尖锐的噪音，不分敌我影响四周的生物。30米半径内恶魔和机械类单位之外的生物必须进行意志检定，否则接下来的回合由于战栗，颤抖，堵住耳朵等行为而失去部分动作。使用尖锐噪音是一个完整动作，之后要让音频电路休息1d5轮才可以再次使用。 | Y30: 先决条件：技术神甫（呼吸面罩） | AC30: 兴奋剂（药物） | AD30: 兴奋剂是一种效力猛烈的药物，能够抑制痛苦并且驱使角色在身体超过极限的情况下依然坚持战斗。一剂兴奋剂可以最多维持3d10 轮。在此期间，角色忽视任何伤害，重击引发的不良结果并且不会被眩晕。药效结束后，角色在一个小时之内的力量，坚韧，敏捷都会受到 −20 的减值。 | AE30: — | AF30: 20 | AG30: 一般 | AH30: 药物 | AJ30: 镣铐 | AK30: 一种枷锁，用来禁锢他人 | AL30: 1 | AM30: 35 | AN30: 丰富 | AO30: 消耗品 | AQ30: 欺诈 | AR30: 社交 | AS30: 交际 Fel | AT30: 用于欺骗或误导他人。你不需要每次对NPC 说谎都进行检定，仅当你试图改变对方想法或使其信服某事时才进行欺诈检定。欺诈检定通常用于对抗对方的察言观色检定。 欺诈可对个体或一群人使用，但人数上限不超过你的交际加值。目标必须能够看到你，清楚地听到你的声音，且能理解你的意思。 欺诈检定通常需要一分钟。 | BE30: 弓 | BF30: 基本 | BG30: 30m | BH30: S/–/– | BI30: 1d10 R | BJ30: 0 | BK30: 1 | BL30: 部分 | BM30: 原始，可靠 | BN30: 2 | BO30: 10
F31: 地面载具 | G31: 高级 | H31: 敏捷 | J31: 纹章学 | K31: 高级 | L31: 智力 | T31: 极限打击 | U31: 使用格斗武器造成+1d5−1致命伤害 | W31: 坚忍体魄 | X31: 计算伤害恢复时总是视为轻伤状态。 | Y31: 先决条件：T40 | AB31: 工 具 | AC31: 占卜盒/扫描仪 | AD31: 这些装置被用于侦测能量射线，波动，以及生物活动信号。使用扫描仪的角色可以在警觉检定上获得 +20 的加值，而且通过一个成功的技术应用检定，可以利用扫描发现只用肉眼无法发现的东西，例如不可见的气体，生物信号，以及放射线。占卜盒的侦测范围大约50米，超过 50cm 的墙壁或是某些防护金属会阻挡侦测。 | AE31: 0.5 | AF31: 145 | AG31: 匮乏 | AH31: 工具 | AJ31: 微型通讯器 | AK31: 短距离通讯，可在一公里之内清晰的传递讯息。 | AL31: — | AM31: 20 | AN31: 一般 | AO31: 药物 | AQ31: 潜行 | AR31: —— | AS31: 敏捷 Ag | AT31: 用于悄无声息的移动，难度与行走的地面状况有关。潜行检定通常用于对抗警觉检定。 潜行检定作为移动动作的一部分，视为一个自由动作。 | BE31: 投石索 | BF31: 基本 | BG31: 15m | BH31: S/–/– | BI31: 1d10−2 I | BJ31: 0 | BK31: 1 | BL31: 完整 | BM31: 原始 | BN31: 0.5 | BO31: 10
F32: 悬浮载具 | G32: 高级 | H32: 敏捷 | J32: 国教教义 | K32: 高级 | L32: 智力 | T32: 棘手目标 | U32: 奔跑或冲锋时对手的BS检定−20 | W32: 见惯不惊 | X32: 你已经见识过银河系中最糟糕的场面，对于死亡，鲜血，大屠杀等等世间的恐怖都已经见惯不惊，这些场面不会让你得到失心点。但超自然的恐怖会正常影响你。 | Y32: 先决条件：WP30 | AC32: 自动书写笔 | AD32: 这些看起来不可思议的划线工具可以使角色以近乎不可能的速度和精确性复制文本。一个角色使用自动书写笔时，可以在他的生计（抄写员）检定中获得 +10 的加值。 | AE32: — | AF32: 55 | AG32: 匮乏 | AH32: 工具 | AJ32: 万能钥匙 | AK32: 对开锁时的侵入+30 | AL32: — | AM32: 150 | AN32: 匮乏 | AO32: 药物 | AQ32: 柔术 | AR32: 移动 | AS32: 敏捷 Ag | AT32: 用于脱离束缚或挤过狭缝。 通常柔术检定需要1分钟，每点成功度减10秒。脱离擒抱的柔术检定是一个完整动作。 逃脱束缚：从任何种类的束缚中逃脱都需要柔术检定。如果束缚你的人的智力属性高于你的敏捷属性，该检定为艰难（ −20 ）。其它会影响检定难度的情况包括：束缚你的工具——简单的手铐还是复杂的防逃爆破项圈；束缚你所用的时间——对方是在匆忙中将你关起来，还是有充足的时间确定你不会逃跑。 脱离擒抱：遭受擒抱时，你可以用柔术检定对抗对方的力量检定，胜出则可脱离擒抱状态。 挤过狭窄空间：进行柔术检定以尝试通过狭窄空间，例如挤过牢房的铁条，通过被巨石堵住的洞口，爬过通风口等等。难度视空间的狭窄程度而定，GM 应靠常识判断有些狭缝是不可能通过的。检定成功即可顺利无阻地通过，失败则无法通过。如果失败度达到 5 或以上，则会被卡住，脱困需要他人协助，或者尝试再次进行柔术检定，直到成功为止。 | BE32: 十字弩 | BF32: 基本 | BG32: 30m | BH32: S/–/– | BI32: 1d10 R | BJ32: 0 | BK32: 1 | BL32: 2完整 | BM32: 原始 | BN32: 3 | BO32: 10
F33: 步行载具 | G33: 高级 | H33: 敏捷 | J33: 法律 | K33: 高级 | L33: 智力 | T33: 加速循环 | U33: 每天恢复1d5伤害 | W33: 剑术大师 | X33: 使用任何种类的刀或剑——包括链锯剑和能量剑——时，每轮一次，你可以重掷没有命中的攻击骰。 | Y33: 先决条件：WS30，格斗武器训练（任意） | AC33: 组合工具 | AD33: 组合工具作为一种通用的奇异工具经常在机械教徒的手中发现。使用组合工具的角色可以在进行技术应用检定时获得 +10 的加值。 | AE33: 1 | AF33: 200 | AG33: 稀有 | AH33: 工具 | AJ33: 图像记录仪 | AK33: 简易记录装置，可将储存的信息重放 | AL33: 1 | AM33: 100 | AN33: 一般 | AO33: 药物 | AQ33: 入侵 | AR33: —— | AS33: 敏捷 Ag | AT33: 这个技能可以让你绕过保险锁或其它安全措施，检定难度取决于防御措施的质量。通常只需进行一次检定，但多重安全措施可能需要多次检定或更高的成功度。如果手头没有万用钥匙一类适当的工具，则检定受 -20 减值。 进行入侵检定需要1分钟，每点成功度减10 秒。 | BE33: 榴弹发射器 | BF33: 基本 | BG33: 60m | BH33: S/–/– | BI33: † | BJ33: † | BK33: 6 | BL33: 完整 | BM33: † | BN33: 9 | BO33: 500
F34: 生计子项 | J34: 传说 | K34: 高级 | L34: 智力 | T34: 尖锐噪音 | U34: 30米半径，进行意志检定否则失去部分动作 | W34: 健壮体格 | X34: 获得1点额外承伤 | Y34: — | AC34: 数据板 | AD34: 数据板是一种在帝国很常见的工具，它被广泛使用来记录和读取编辑完成的文本或是其他的音频和视频数据。它们是如此廉价和易于制造，以至于很多的数据板都整合了简单的多媒体读取功能，并且还能进行一定程度的文本处理。另一些则可以更新资料，并且和其他装置进行资料的传输和接收。 | AE34: 0.5 | AF34: 25 | AG34: 普及 | AH34: 工具 | AJ34: 灵能法器 | AK34: 灵能者使用法器进行专注时，检定 +10 | AL34: — | AM34: 100 | AN34: 稀有 | AO34: 工具 | AQ34: 闪避 | AR34: 战斗 | AS34: 敏捷 Ag | AT34: 详见规则书第七章：进行游戏，战斗部分。 | BE34: 火箭推进器 | BF34: 重型 | BG34: 120m | BH34: S/–/– | BI34: † | BJ34: † | BK34: 1 | BL34: 完整 | BM34: † | BN34: 15 | BO34: 1200
F35: 农民 | G35: 高级 | H35: （S） | J35: 数字学 | K35: 高级 | L35: 智力 | T35: 坚忍体魄 | U35: 计算伤害恢复时总是视为轻伤状态 | W35: 街道斗殴 | X35: 当使用小刀或徒手对目标造成致命伤害时，该伤害+2。 | Y35: — | AC35: 爆破药 | AD35: 爆破药是一种简单的爆炸装置，可以用来轰开密封门，炸穿墙壁，破坏桥梁。这里的花费指的是每公斤当量炸药所需花费，尽管你可以通过加装其他装置或是将其贴在墙或门上提高爆炸效果。当爆破药爆炸时，任何位于爆破范围的人或物体会受到 3d10 点外加每公斤 2 点的爆炸伤害。爆炸的范围则为每公斤 5米。安置和使用爆破药通过爆破技能完成（见第三章：技能）。 | AE35: 1 | AF35: 250 | AG35: 匮乏 | AH35: 工具 | AJ35: 尖叫报警器 | AK35: 使用须GM暗投技术应用并成功，尖叫报警器感知属性75点，声音传播范围一公里 | AL35: 2 | AM35: 140 | AN35: 匮乏 | AO35: 工具 | AQ35: 审讯 | AR35: 调查 | AS35: 意志 WP | AT35: 通过精神和肉体双方面的施压以撬开一个不合作目标的嘴。注意审讯和酷刑还是有区别的，后者的目标只会说出施刑者想听的东西，而一个熟练的审讯者则会利用各种设备、药物，和技术来发掘目标最黑暗的秘密。 设备，环境，和双方背景等因素都会影响审讯难度。审讯目标时，用你的审讯技能检定对抗目标的意志检定，如果你胜出，可以得到一个问题的答案，每点成功度多得到一个问题的答案。如果败掉，就什么回答也得不到。一次严重失败意味着你把审讯程序搞得一团糟，还对目标造成了 1d10 加上你意志加值的伤害。如果失败度达到 5 或以上，你在造成伤害的同时还让目标对抗审讯的意志检定得到+30 加值。 每次审讯检定需要消耗1d5小时，且对目标造成1 级虚弱。 | BE35: 毒针手枪 | BF35: 手枪 | BG35: 30m | BH35: S/–/– | BI35: 1d10 R | BJ35: 0 | BK35: 6 | BL35: 完整 | BM35: 精准，淬毒 | BN35: 1.5 | BO35: 1250
F36: 药剂师 | G36: 高级 | H36: （Int） | J36: 神秘学 | K36: 高级 | L36: 智力 | T36: 见惯不惊 | U36: 一般的恐怖景象不会造成失心点 | W36: 金属引力 | X36: 花费一个完整动作进行WP检定，你可以将20米半径内，一个未固定的金属制品吸引到你手里，该物品重量不超过1kg/WB。 | Y36: 先决条件：技术神甫（电感组织/储压线圈） | AC36: 刑讯工具 | AD36: 这个装置经常用于对被帝国俘获的敌人进行问讯，或是揭示那些背离帝王之人的堕落本质。这里面包罗了大量令人眼花缭乱的刃，针，化学品，药物，烙铁，神经链以及其它很多不便解说的东西。一个使用刑讯工具的角色可以在审讯检定上获得 +20 的加值。 | AE36: 1 | AF36: 375 | AG36: 罕见 | AH36: 工具 | AJ36: 声波干扰器 | AK36: 潜行+30，可以维持 20 分钟，之后须充能1h | AL36: 2 | AM36: 25 | AN36: 一般 | AO36: 工具 | AQ36: 生存 | AR36: —— | AS36: 智力 Int | AT36: 这个技能用于野外生存，包括捕鱼，狩猎，取火，寻找食物，搭建栖身之处，寻找安全的储物场所等等。难度与自然环境有关。 检定失败意味着你没能找到所寻找的东西。失败度达到5或以上表示你的失败得十分华丽，通常会为自己惹上麻烦，例如引发了山体滑坡，惊动了一打愤怒的沼泽熊，或是愚蠢的误食了有毒浆果。 生存检定通常需要1小时，每点成功度减少 10 分钟。在某些情况下，例如在砸向地面 的流星风暴中寻找掩蔽物，检定难度提高，而检定时间缩短到 1分钟。 | BE36: 捕网手枪 | BF36: 手枪 | BG36: 30m | BH36: S/–/– | BI36: — | BJ36: 0 | BK36: 1 | BL36: 完整 | BM36: 捕捉 | BN36: 3.5 | BO36: 1200
F37: 军械士 | G37: 高级 | H37: （S） | J37: 哲学 | K37: 高级 | L37: 智力 | T37: 剑术大师 | U37: 每轮一次，重掷失败的格斗检定 | W37: 金属召唤 | X37: 花费一个完整动作进行WP检定，你可以将40米半径内，一个未固定的金属制品吸引到你手里，该物品重量不超过2kg/WB。 | Y37: 先决条件：技术神甫（电感组织/储压线圈），金属引力 | AC37: 照明球/发光器 | AD37: 一个经常用于夜晚和黑暗地区的照明工具，这些手持装置可以照亮 12 米或者更远半径的距离。一个照明球/发光器可以持续工作1d5个小时，之后需要进行充能或更换电池。 | AE37: 0.5 | AF37: 15 | AG37: 充裕 | AH37: 工具 | AJ37: 收发报机 | AK37: 使用需进行+10的技术应用。 | AL37: 4 | AM37: 300 | AN37: 匮乏 | AO37: 工具 | AQ37: 生计* | AR37: 制造 | AS37: 多种 | AT37: 子项：农民（S），药剂师（Int），军械士（S），艺术家（ .Ag ），绘图师（Ag），厨师（Int），抄写员（Int），殡仪师（Int），泥瓦匠（ (Ag) ），商人（Fel），矿工（S），探矿者（S），雕刻师 (Ag) ），铁匠（S），占卜者（Fel），皮匠（S），技师（Int），仆人（Fel），设计师（Int），以及其它GM开放的项目。 用于制造物品，进行相关知识检定，或者辨认特定同行的作品。生计检定通常需要一整天。辨认同行的作品则是一个完整动作。 | BE37: 毒针来复枪 | BF37: 基本 | BG37: 180m | BH37: S/–/– | BI37: 1d10 R | BJ37: 0 | BK37: 6 | BL37: 2完整 | BM37: 精准，淬毒 | BN37: 2 | BO37: 1000
F38: 艺术家 | G38: 高级 | H38: （ Ag ） | J38: 帝国战术 | K38: 高级 | L38: 智力 | T38: 健壮体格 | U38: 获得1点额外承伤 | W38: 谨小慎微 | X38: 你总是疑神疑鬼，紧张地东张西望。你的先攻权+2。另外，只要附近有危险存在，你可以自动进行感知检定（GM暗投）。 | Y38: — | AC38: 抓钩 | AD38: 抓钩通过一个小的弹射器或是枪将一个钩子或是磁力锚发射出去，并且使用了纤细但是坚韧的金属线连接（100米）。当抓钩命中了一个理想的目标，例如屋顶，使用者就可以徒手攀爬或是通过绞盘把自己拉上去。不过必要的时候，他们也可以使用一些原始的弹射武器来使用抓钩（例如通过十字弩）。 | AE38: 2 | AF38: 30 | AG38: 普及 | AH38: 工具 | AJ38: 书写工具组 | AK38: 纸张，墨水，羽毛笔 | AL38: 2 | AM38: 20 | AN38: 普及 | AO38: 工具 | AQ38: 手上功夫 | AR38: —— | AS38: 敏捷 Ag | AT38: 手上功夫技能用于将小物件藏在手中，偷窃，或是在硬币或纸牌游戏中作弊。物件越小，越容易动手脚。手上功夫检定通常需要对抗目标的警觉检定。 进行手上功夫检定是一个部分动作。你也可以尝试用一个自由动作进行检定，但难度提高一级（−10）。 | BE38: 网枪 | BF38: 基本 | BG38: 50m | BH38: S/–/– | BI38: — | BJ38: 0 | BK38: 1 | BL38: 完整 | BM38: 爆炸(5)，捕捉 | BN38: 8 | BO38: 1800
F39: 绘图师 | G39: 高级 | H39: （Ag） | J39: 常识子项 | T39: 街道斗殴 | U39: 徒手或使用小刀攻击可造成+2致命伤害 | W39: 精确击打 | X39: 近战攻击特定部位无减值。 | Y39: 先决条件：WS40，稳健一击 | AC39: 激光切割刀 | AD39: 当一扇门（或是防水隔墙）无法正常打开的时候，激光切割刀就派上用场了。最早由矿工使用，这些短射程的装置发射一道猛烈的能量束，就像特别锋利的刀刃一样，可以轻松将金属，石头，钢铁，乃至装甲板切开。当然，它可以切割，也可以当作焊枪使用，每轮可以处理 10cm 的金属（确切地数值会随着金属的材质和厚度而稍有不同）。激光切割刀因为过于笨重而不能在战斗中使用。 | AE39: 4 | AF39: 65 | AG39: 一般 | AH39: 工具 | AJ39: 蒸馏酒 | AK39: 一种由葡萄酒蒸馏出来的酒精流行饮料 | AL39: — | AM39: 50 | AN39: 匮乏 | AO39: 工具 | AQ39: 搜集信息 | AR39: 调查 | AS39: 交际 Fel | AT39: 了解流言，秘密，隐情等的技能，你可以对 NPC 威逼利诱旁敲侧击，也可以伸长耳朵四处乱转，通常前一种方法更常用。检定成功可以得到想要的基本信息，每点成功度可以得到更高质量的情报。 搜集信息技能可作为一项调查技能来使用，详见第七章：进行游戏，调查部分。 有效的进行搜集信息检定需要至少一小时，视环境情况而增减。
F40: 厨师 | G40: 高级 | H40: （Int） | J40: 法务部 | K40: 高级 | L40: 智力 | T40: 金属引力 | U40: 进行WP检定以吸引1kg/WB的金属 | W40: 精确射击 | X40: 瞄准特定部位射击无减值。 | Y40: 先决条件：BS40，准确射击 | AC40: 多功能望远镜 | AD40: 这是一种能够放大远距离目标的强大视觉辅助设施。更先进的是，高级版本的多功能望远镜可以远程读取，显示热源信号，目标坐标定位，甚至可以进行拍照以便日后进行分析。 | AE40: 0.5 | AF40: 55 | AG40: 一般 | AH40: 工具 | AJ40: 解毒剂（药物） | AK40: 立刻终止药品毒素空气的任何影响，无论好坏，但有特例 | AL40: — | AM40: 65 | AN40: 稀有 | AO40: 工具 | AQ40: 搜索 | AR40: —— | AS40: 感知 Per | AT40: 搜索技能用于检查一个区域以发现不引人注目的物品，线索，或任何隐蔽的事物。它与警觉技能的区别在于警觉是一个被动检定，在进入可能存在危险的区域时自动进行，而搜索则是由角色主动提出对某区域进行的检查。 一次搜索检定足以覆盖一个小房间或空地。如果有蓄意藏匿的目标，则用你的搜索检定对抗对方的躲藏检定。 一次搜索检定至少需要5分钟，搜索更大的区域需要更多时间。
F41: 抄写员 | G41: 高级 | H41: （Int） | J41: 机械教 | K41: 高级 | L41: 智力 | T41: 金属召唤 | U41: 进行WP检定以吸引2kg/WB的金属 | W41: 净化之火 | X41: 烧！烧！烧！无人能逃过你的怒火！尝试躲避你的火焰喷射器的检定有−20减值。 | Y41: 先决条件：基本武器训练（火焰） | AC41: 镣铐 | AD41: 这些坚固的装置经常被赏金猎人和执法者使用，当然这些东西也会被某些更加凶恶的家伙出于不可告人的黑暗目的使用在赏金猎人和执法者身上。 | AE41: 1 | AF41: 35 | AG41: 丰富 | AH41: 工具 | AJ41: 暴怒（药物） | AK41: 1d10min狂暴天赋和无视恐惧 | AL41: — | AM41: 95 | AN41: 罕见 | AO41: 工具 | AQ41: 特技 | AR41: 移动 | AS41: 敏捷 Ag | AT41: 特技技能可以让你选择凌空跃或翻筋斗一类大胆的移动方式。你进行的动作越复杂——例如翻滚过一群包围着你的邪教徒，抓住一驾正在起飞的雷鹰的起落架——检定难度越高。检定成功度越高，你的动作完成得越漂亮。该技能还有两种特殊用法： 脱离： 你可以尝试进行一个特技检定以一个部分动作完成脱离动作。 跳高和跳远： 进行这两种动作时，你可以用特技检定代替敏捷检定和力量检定。
F42: 殡仪师 | G42: 高级 | H42: （Int） | J42: 内政部 | K42: 高级 | L42: 智力 | T42: 谨小慎微 | U42: 你对危险各外警觉 | W42: 敬畏仪式 | X42: 你可以吟诵引发敬畏与恐怖的次声波祷文。50米范围内的人类，无论听力是否健全，都会感到畏惧和罪恶感。由于这种情绪影响，他们接下来的技能检定承受−10减值。成功的意志检定可以摆脱此效果。吟诵祷文时，你不能用其它频率发声。仪式持续2分钟，由于任何原因中断仪式都是很严重的亵渎行为。注意，除非安装了特殊的接收装置，否则一般人是听不到次声波的，因此也不会认为你在讲话。 | Y42: 先决条件：技术神甫（颅腔电路） | AC42: 微型通讯器 | AD42: 微型通讯器或普通通讯器是一种置于耳内的短距离通讯装置，可以在一公里之内清晰的传递讯息。但是糟糕的天气，复杂地形，以致石头和塑料都会极大地影响通讯距离。 | AE42: — | AF42: 20 | AG42: 一般 | AH42: 工具 | AJ42: 注射器 | AK42: 消耗完整动作储存药物 | AL42: — | AM42: 5 | AN42: 充裕 | AO42: 工具 | AQ42: 听说语言* | AR42: —— | AS42: 智力 Int | AT42: 听说语言 （高级） 智力 子项：高哥特语，巢都方言，低哥特语，舰船方言，部落方言 可与持相同语言的人交流，通常不需要检定。帝国的各个世界的语言混杂变化成了低哥特语。而各个地区也有其独特的方言。 听说语言检定通常是个自由动作。 语言不通时的交流：在遇到和你语言不通的生物—例如灵族或者道星异形时，在你用爆矢枪轰掉对方的脑袋之前，也许还有些时间沟通一下。你可以尝试使用肢体语言或类似的手段表达一些简单的信息，诸如”当心后面！”。这时发出信息一方进行交际检定，而接受信息一方进行智力检定。交际检定的每点成功度都可以为对方的智力检定提供 +10 加值，以便对方理解你的意思。交际检定失败意味着你传出的信息无法理解。智力检定失败意味着对方误解了你的意思，而这很可能导致悲剧性的后果。 高哥特语： 贵族阶级，法律条文，以及帝国国教仪式上使用的语言。 巢都方言： 巢都内通用的低哥特语变体。 低哥特语： 帝国通用语。 舰船方言： 在特定舰队内使用的独特代码，俚语，和方言。 部落方言： 特定行星上的部落使用的原始而粗糙的语言。
F43: 泥瓦匠 | G43: 高级 | H43: (Ag) | J43: 帝国国教 | K43: 高级 | L43: 智力 | T43: 精确击打 | U43: 攻击特定部位无减值 | W43: 军纪严明 | X43: 只要你的下属能看到你，他们可以重投失败的恐惧和压制检定。该能力可影响的目标数等于你的WB，且这些人必须处于你的指挥之下。如果你是官方指派的侍僧小队的领导，则其他PC也可从该天赋中获益。 | Y43: 先决条件：WP30，指挥 | AC43: 万能钥匙 | AD43: 作为一种能够打开大部分帝国制式锁的工具，万能钥匙在几乎所有的城市都不是一种可以正常搞到的商品。基于同样的原因，它广泛的被罪犯或是声名狼藉的家伙使用。一个拥有万能钥匙的角色可以在开锁的侵入检定上获得 +30 的加值。 | AE43: — | AF43: 150 | AG43: 匮乏 | AH43: 工具 | AJ43: 卷烟 | AK43: 具有特殊香气，微量麻醉（和上瘾）性物质 | AL43: — | AM43: 10 | AN43: 普及 | AO43: 工具 | AQ43: 伪装 | AR43: —— | AS43: 交际 Fel | AT43: 伪装成不同的身份，性别，种族，甚至是某个特定的人。合适的衣着，道具，捏造的身份以及易容术都是伪装成功的关键。更为激进的做法包括整形手术，仿生移植物，或变形药。 伪装检定通常是与对手的察言观色检定对抗。进行简单的伪装至少需要 1 分钟，复杂一些的需要更长时间。
F44: 商人 | G44: 高级 | H44: （Fel） | J44: 国教教义 | K44: 高级 | L44: 智力 | T44: 精确射击 | U44: 瞄准特定部位射击无减值 | W44: 恐惧仪式 | X44: 你可以吟唱引发恐惧与虚弱的次声波挽歌。50米范围内的人类，无论听力是否健全，都会对你怀有等级1的恐惧。吟唱挽歌时，你不能用其它频率发声。仪式持续2分钟，由于任何原因中断仪式都是很严重的亵渎行为。注意，除非安装了特殊的接收装置，否则一般人是听不到次声波的，因此也不会认为你在讲话。 | Y44: 先决条件：技术神甫（颅腔电路） | AC44: 图像记录仪 | AD44: 图像记录仪是一种简易的生物媒介记录装置，有些还具有全息成像功能。几乎所有的记录仪都能够将储存的信息完整的重放。它们经常被安装在特殊的仆役里，这样就可以使它们进行考古发掘工作，武器测试，异端审问等等其他可能有危险的工作。 | AE44: 1 | AF44: 100 | AG44: 一般 | AH44: 工具 | AJ44: 医疗箱 | AK44: 消耗品，每次医疗+20，内含6个兴奋剂 | AL44: 2 | AM44: 150 | AN44: 普及 | AO44: 工具 | AQ44: 吸引力 | AR44: 社交 | AS44: 交际 Fel | AT44: 使他人变得友好，用于祈使或引诱，仅当你希望改变 NPC 的态度或让对方为你做某事时才需要进行吸引力检定。可对个体或一群人使用，但人数上限不超过你的交际加值。目标必须能够看到你，清楚地听到你的声音，且能理解你的意思。 吸引力检定通常需要一分钟。
F45: 矿工 | G45: 高级 | H45: （S） | J45: 帝国卫队 | K45: 高级 | L45: 智力 | T45: 净化之火 | U45: 你的火焰武器变得更难躲避 | W45: 苦修者 | X45: 每天，你都要进行一个为时12分钟的祈祷并鞭笞自己造成1点伤害，你不能让这个伤害被抵抗或治疗。鞭策自己的肉体之后，你抵抗精神控制和恶化的WP检定+10。另外，如果你有狂暴天赋，你可以用一个自由动作开始狂暴。任何一天，如果你没有进行自我鞭笞，就会由于羞愧和罪恶感而使所有检定有−5减值。 | Y45: — | AC45: 灵能法器 | AD45: 灵能者经常用来帮助自己进行聚焦能量的装置。一个灵能法器可能是由骨头，雕琢过的短棒，被祝福过的圣像，或是水晶球。当一个灵能者使用灵能法器进行专注检定时，可以获得 +10 的加值。 | AE45: — | AF45: 100 | AG45: 稀有 | AH45: 工具 | AJ45: 愚民粉（药物） | AK45: 使用后梦游般1d5h，战斗中使用如制幻榴弹 | AL45: — | AM45: 28 | AN45: 稀有 | AO45: 工具 | AQ45: 学术知识* | AR45: 调查 | AS45: 智力 Int | AT45: 子项：古代史，气象学，动物学，行政，化学，密码学，纹章学，国教教义，法律，传说，数字学，神秘学，哲学，帝国战术 学术知识是专业性很强的知识技能，比常识更深入，是通过长期学习研究得到的技能。学术知识检定用于研究属于你专业领域内的客体，具体效果如下： 成功度 结果 标准 你学术圈内的常识性信息 一 你同行不见得了解的情报 二 该领域少数学者掌握的知识 三或以上 只有少数专家了解的信息 学术知识的某些子项可能与常识或禁忌知识重叠，但学术知识的研究比前两者更具体而深入。例如，一个具有常识（国教教义）的角色可能由于生活在教会的教导之下而知道国教教会的日常仪式，而一个具有学术知识（国教教义）的人能够解释这些仪式的产生，以及在数千年过程中的变化。 回忆起某条信息所需的学术知识检定不用花费时间，但进行深入研究——假设你有合适的资料和设备的情况下——需要每 1d10 小时进行一次检定，详见第七章：进行游戏。 古代史： 了解帝国的黑暗过去，以及逝去的那些千年如何改变了人类。 气象学： 了解恒星，天体，以及各个世界的自然面貌，同时也知道望远镜，星盘一类工具的应用理论。 动物学： 了解野生动物的分类及特点，包括多种半智能生物的情况。 行政： 知道如何与政府部门打交道，尤其了解帝国内政部以及其下属的各个分支部门的结构和政策。 化学： 关于化学品的性质及制备，以及其在帝国内的应用情况的知识。 密码学： 关于各种密码，代码，密语以及数字密匙的知识。这个技能可以用于加密和解密。 纹章学： 掌握各种纹章的使用规则，包括帝国内常见的制服款式，私人印记，以及身份识别设备。 国教教义： 熟悉国教福音书，教堂结构，以及礼拜仪式的神圣含义。可用于向他人传教。 法律： 对帝国法律条文的熟悉。 传说： 关于古代的伟大历史故事的知识，例如恐怖的何露斯之乱，以及科技的黑暗年代。 数字学： 有关数字的神秘性质的知识，从突变理论到数字连祷。 神秘学： 关于神秘仪式，理论和迷信的知识，以及对神秘物品用途的了解。 哲学： 涉及观念，信仰与批判的知识。可用于辩论或制造哲学难题。 帝国战术： 了解帝国军事基础，以及其它战争理论，队形，和战斗技巧。可用于规划战斗或推演战争进程。
F46: 探矿者 | G46: 高级 | H46: （S） | J46: 帝国 | K46: 高级 | L46: 智力 | T46: 敬畏仪式 | U46: 50米半径内，所有人的技能检定−10 | W46: 快速反应 | X46: 被突袭或埋伏时，可进行一次敏捷检定，通过即可正常行动。 | Y46: 先决条件：Ag40 | AC46: 尖叫报警器 | AD46: 尖叫报警器能够侦测周围声音或动作（依照设置方式不同），并且爆发出可怕的响声以警告使用者危险靠近。想要使用一个尖叫报警器必须通过一个成功的技术应用检定。GM 应暗投该检定，所以使用者并不清楚是否正确设置了工作状态。每一个尖叫报警器侦测声音的动作时的感知属性为 75 点。当侦测到入侵者时，它发出的警报声能够在一公里范围内的任何地方听到。门，墙壁，或是其他阻挡物会缩短传播的距离。 | AE46: 2 | AF46: 140 | AG46: 匮乏 | AH46: 工具 | AJ46: 压缩食物 | AK46: 是经过加工后密封包装，看外表难推测出里面是啥 | AL46: — | AM46: 10 | AN46: 丰富 | AO46: 工具 | AQ46: 驯养动物 | AR46: —— | AS46: 智力 Int | AT46: 用于命令或驾驭被已被驯化的动物。常规护理与饲喂不需要检定。通常在治疗动物的疾病，缓解不适，或进行其它特殊任务（例如为动物制作一副鞍具）时才进行驯养动物检定。 你可以教导被驯化的动物一些把戏，例如守卫，取物，攻击等。你需要教导动物整整一周，并在周末进行驯养动物检定。一个简单的 把戏只需一个成功即可让动物学会；复杂一些的需要三次成功；十分困难的需要十次成功。 你也可以用该检定让野生动物对你友善（驯化的动物总是对你很友善），或者让受指令攻击你的动物平静下来。如果目标是攻击性很强的野生生物，或者对主人十分忠诚的攻击动物，检定难度会提高。这么做需要一个完整动作。 该技能对半机器的动物无效。
F47: 雕刻师 | G47: 高级 | H47: (Ag) | J47: 技术 | K47: 高级 | L47: 智力 | T47: 军纪严明 | U47: 下属可以重投恐惧和压制检定，只要他们能看到你 | W47: 快速装填 | X47: 装填所有武器的时间缩短为正常的一半（向下取整）。例如，部分动作变为自由动作，完整动作变为部分动作。 | Y47: — | AC47: 声波干扰器 | AD47: 和尖叫报警器恰恰相反，声波干扰器会在小范围内释放出声波覆盖使用者移动时发出的声音和噪声。一个使用了声波干扰器的角色可以在潜行检定中获得 +30 的加值。一个声波干扰器储存的能量可以维持 20 分钟的工作，之后必须通过充能（大约一个小时）才可以继续使用。 | AE47: 2 | AF47: 25 | AG47: 一般 | AH47: 工具 | AJ47: 雷诺咖啡 | AK47: 由植物叶片或花瓣粉碎酿造，热饮，提神醒脑 | AL47: — | AM47: 5 | AN47: 充裕 | AO47: 工具 | AQ47: 医疗 | AR47: —— | AS47: 智力 Int | AT47: 医疗技能用来处理和恢复伤势，稳定士兵的情绪。这个技能有两种用法：急救和长期护理。 急救： 进行医疗检定对受伤的角色进行急救。检定成功可以让轻伤的目标恢复等于你智力加值的伤害；重伤的目标恢复 1 点伤害；受致命伤的目标恢复1点致命伤。检定失败则无法稳定伤势。如果失败度达到 3 或以上，会对轻伤或重伤目标造成1点伤害，承伤到0的目标必须进行坚韧检定，否则死亡。 急救检定需要施救者和受治疗者都花费一个完整动作。 长期护理：你可以同时护理等于你智力加值的受伤目标，每超过一人检定受到 −10 减值。护理轻伤患者需要每天结束时进行一次医疗检定，护理重伤或致命伤患者则需每周结束时进行检定。检定成功可以加速伤者的恢复速率，详见第七章：进行游戏：伤害与恢复部分。检定失败则无法帮助伤者。如果失败度达到 3 或以上，会对轻伤或重伤目标造成 1 点伤害，致命伤患者使用猝死规则。失败度达到 5以上，全部由你护理的患者受到1d10伤害，致命伤患者同样适用猝死规则。 特殊：有外科专家天赋的角色可以更好的发挥医疗检定，详见第133页。
F48: 铁匠 | G48: 高级 | H48: （S） | J48: 下层社会 | K48: 高级 | L48: 智力 | T48: 恐惧仪式 | U48: 50米半径内，造成恐惧等级1，持续2分钟 | W48: 狂暴 | X48: 将你自己完全投入战斗狂怒中。你要花费一轮时间来使自己进入状态（嚎叫，抽打自己，嗑药等等）。下一轮你将失去控制并陷入完全的疯狂，你的格斗能力，力量，坚韧，和意志属性+10，射击能力和智力−20。你必须尽可能靠近距你最近的敌人并进行近战攻击，但你不会做出明显的自杀行为，例如，跳下高楼以攻击敌人。狂暴时，你免疫恐惧，眩晕效果，不受虚弱造成的减值，但你无法脱离，撤退，和格挡。只要可能，你就要进行全力攻击。狂暴状态持续整场战斗。如果没有特定天赋，你无法在狂暴时施展灵能。 | Y48: — | AC48: 收发报机 | AD48: 收发报机是一种简单的长距离通讯装置，能够将信号发往极其遥远的地方，包括从星球表面发往太空轨道上的飞船。使用收发报机接收或发送信号需要进行一个普通（ (+10) ）的技术应用检定。 | AE48: 4 | AF48: 300 | AG48: 匮乏 | AH48: 工具 | AJ48: 劣质烈酒 | AK48: 一种经过发酵的液体，低档饮料 | AL48: — | AM48: 10 | AN48: 充裕 | AO48: 工具 | AQ48: 游泳 | AR48: 移动 | AS48: 力量 S | AT48: 详见规则书第七章：进行游戏，游泳部分。
F49: 占卜者 | G49: 高级 | H49: （Fel） | J49: 战争 | K49: 高级 | L49: 智力 | T49: 苦修者 | U49: 伤害自己以使意志坚定 | W49: 狂热袭击 | X49: 用全力攻击命中一个目标之后，你可以用你本轮的反射动作进行一次额外攻击，攻击检定难度与原始攻击检定相同。 | Y49: 先决条件：WS35 | AC49: 书写工具组 | AD49: 书写工具组包括了纸张，墨水，羽毛笔。 | AE49: 2 | AF49: 20 | AG49: 普及 | AH49: 工具 | AJ49: 祝福机油 | AK49: 完整动作涂抹武器空弹前免疫干扰或终止干扰 | AL49: — | AM49: 150 | AN49: 罕见 | AO49: 工具 | AQ49: 阅读 | AR49: —— | AS49: 智力 Int | AT49: 你可以阅读任何用自己会说的语言写下的文字。通常不需检定，但在阅读过于复杂或专业性很强的文件，部分残缺或错别字过多的文章时可能需要检定。 阅读一页文章——大约 750 个单词——大约需要 1 分钟。
F50: 皮匠 | G50: 高级 | H50: （S） | T50: 快速反应 | U50: 进行Ag检定以避免措手不及 | W50: 狂热信仰 | X50: 信仰保护你免于疯狂。决定震惊效果时，投两次百分骰并取较好者。 | Y50: — | AB50: 神 经 反 馈 设 备 | AC50: 生化手臂 | AD50: 普通型号的生化手臂能精确再现人类臂和手的功能，包括力量，反应速度和触觉。粗糙质量生化手臂使角色在进行与该部位相关的快速反应动作时，敏捷值视为减半。用该肢体持械会使 WS 和 BS 检定 −10 。极品质量生化手臂使角色在进行与该部位相关的快速反应动作（如手上功夫）时，敏捷检定 +10 。使用该手臂时力量检定 +10。 | AE50: — | AF50: 1000 | AG50: 匮乏 | AH50: 生化义肢 | AJ50: 屠杀（药物） | AK50: 2d10min内敏捷感知+3，药效结束后过坚韧 | AL50: — | AM50: 75 | AN50: 匮乏 | AO50: 工具 | AQ50: 指挥 | AR50: 社交 | AS50: 交际 Fel | AT50: 让你的下级服从你的指示。检定成功意味着你的命令被执行，失败则表示你的命令被曲解或拒绝执行。如果失败度达到 5 或以上，则命令被完全相反的执行。 一次性可以指挥的目标最多不超过你的交际加值。目标必须能够看到你，清楚地听到你的声音，且能理解你的意思。 进行指挥检定为一个部分动作。如果指令过于复杂则需要一个完整动作。
F51: 技师 | G51: 高级 | H51: （Int） | T51: 快速装填 | U51: 减少装填时间 | W51: 狂野灵魂 | X51: 狂暴状态下可以使用灵能 | Y51: 狂暴 | AC51: 生化移动装置（腿，臀部，骨盆等） | AD51: 普通型号的生化移动装置必须完全与脊椎末端和神经系统结为一体才能正常作用。基本包括了常人的双腿能做到的全部功能。粗糙质量的生化移动装置使角色的移动速率减半（向上取整），且角色在尝试奔跑时需要进行敏捷检定，否则会在移动终点跌倒。极品质量的生化移动装置赋予角色飞跑天赋，跳跃时的运动检定 +20 。 | AE51: — | AF51: 1500 | AG51: 匮乏 | AH51: 生化义肢 | AJ51: 鬼灵（药物） | AK51: 暂时赋予灵能或增强灵能（详见“随机灵能”表） | AL51: — | AM51: 395 | AN51: 稀有 | AO51: 工具 | AQ51: 专注 | AR51: —— | AS51: 意志 WP | AT51: 专注检定可以让你在使用灵能时将灵能骰提高等于你意志加值的数目。专注检定是一个完整动作。在此期间，你清除脑中的杂念，专心聚焦能量。检定成功意味着你的思维已经准备好接触亚空间了，下一回合，你可以将意志加值加到灵能骰中，与其它加值累加。 范例： 多克准备施展“次级致痛”灵能。他先花费了一轮时间舒展筋骨，恶毒地对目标低语， 这些都作为专注过程的一部分。他进行专注检定且成功。下一轮，多克开始施展致痛灵能，他的灵能骰掷出了4，并按照灵能规则惯例加上自己的意志加值 3。由于他上一轮专注检定成功，多克可以在刚才的基础上再加一次意志加值 3，最终结果为 10 (4 + 3 + 3 = 10) 。聚焦能量成功。 专注检定失败意味着你没能进入状态，不会得到任何加值。如果检定成功，但下一轮没有施展灵能，则加值作废，没有副作用（除了让你看起来有点蠢）。
F52: 仆人 | G52: 高级 | H52: （Fel） | T52: 狂暴 | U52: 进入疯狂的愤怒状态以换取格斗加值 | W52: 鲤鱼打挺 | X52: 倒地后可以用自由动作起身。 | Y52: 先决条件：Ag30 | AC52: 生化呼吸系统 | AD52: 普通型号的生化肺和植入呼吸系统可以模拟正常人的肺脏，保证人体的供氧。植入生化呼吸系统的角色在抵抗毒气和缺氧环境的坚韧检定有 +20 加值。粗糙的生化呼吸系统可以提供与普通型号同样的保护措施。但是，它工作起来发出大量噪音，使角色的所有潜行检定 −20 。低下的供氧效率是角色进行任何剧烈运动所作的检定难度提高一级。极品生化呼吸系统视为一套独立的生命维持系统（这样一来，如果你自己原装的呼吸系统出于某些原因挂掉了，这套设备可以保证你血液的含氧量）。这种设备可以被设计得毫不引人注目。 | AE52: — | AF52: 800 | AG52: 稀有 | AH52: 生化义肢 | AJ52: 兴奋剂（药物） | AK52: 3d10轮内角色忽视伤害重击不良结果，无法被眩晕，药效结束后1h内力量，坚韧，敏捷−20 | AL52: — | AM52: 20 | AN52: 一般 | AO52: 工具 | AQ52: 追迹 | AR52: —— | AS52: 智力 Int | AT52: 追迹技能用于循着踪迹追猎目标——可能是动物，也可能是别的什么。追踪显而易见的痕迹不用检定，也不需要放慢速度。但如果气候恶劣，光照不足，或者地形复杂时，就需要追迹检定。例如，新近下的一场雪会让检定变得困难 (−10)甚至艰难 (−20)。追踪模糊的痕迹需要追踪者移动速度减半。 如果对方有意掩盖自己的行踪，就要用追迹检定与目标躲藏检定对抗。 成功的追迹检定还可以让你了解目标数量，种族，并推断出和你的大致距离。 追迹检定是移动动作的一部分，视为一个自由动作。
F53: 设计师 | G53: 高级 | H53: （Int） | T53: 狂热袭击 | U53: 成功的WS检定可以换取一次额外命中 | W53: 灵活侧步 | X53: 每轮可以多进行一次闪避。 | Y53: 先决条件：Ag40，闪避 | AC53: 螺旋传感阵列 | AD53: 这种植入物是两个特殊的传感器。使用它需要精神集中并花费一个部分动作。普通系统的功能如同一台标准的占卜盒。粗糙系统只有一种探测能力（热，辐射，或电磁），且有效距离只有 20 米。极品系统的功能如同一台完整的占卜盒，还允许重投使用时进行的任何基于感知属性的检定。 | AE53: — | AF53: 1000 | AG53: 稀有 | AH53: 植入物 | AJ53: 生化手臂 | AK53: 粗糙：与部位相关的快速反应动作时敏捷减半，持械时 WS/BS−10 。极品：与部位相关的快速反应动作时敏捷+10 ，力量+10。 | AL53: — | AM53: 1000 | AN53: 匮乏 | AO53: 生化义肢
T54: 狂热信仰 | U54: 对抗震击效果时，投两次检定并取较好者 | W54: 灵能等级1 | X54: 你解放了你的灵能力量。选择一定数量的次级灵能，该数目等于你意志加值的一半（向上取整）。你的灵能等级达到1，显能时投一枚骰子并加上意志加值。特殊：如果日后你的意志加值提高了，你不能根据该天赋得到额外的灵能。 | Y54: — | AC54: 枪械附肢 | AD54: 这种坚固的肩架式附肢是为自卫而设计的。两米长的附肢末端装着一把机械神教设计的外观圆滑的激光手枪。该武器视为一把装有改良能量匣的激光手枪。技术神甫可以在他的回合用部分动作进行射击，也可以在他的回合之外用反射动作进行射击，但无论如何，该武器一轮只能攻击一次。使用该武器应用正常的射击能力属性而没有特殊的减值。注意这把武器上没有安装任何光学瞄准零件。你必须有相应的机械附肢天赋才能使用它。 | AE54: — | AF54: 600 | AG54: 仅机械神教 | AH54: 附肢 | AJ54: 生化移动装置（腿，臀部，骨盆等） | AK54: 粗糙：移动速率减半（向上取整），且在尝试奔跑时需进行敏捷检定，否则会在移动终点跌倒。极品：赋予角色飞跑天赋，跳跃时运动+20 。 | AL54: — | AM54: 1500 | AN54: 匮乏 | AO54: 生化义肢
T55: 狂野灵魂 | U55: 狂暴状态下可以使用灵能 | W55: 灵能等级2 | X55: 选择等于你意志加值数量一半（向上取整）的次级灵能。你的灵能等级达到2，显能时投两枚骰子并加上意志加值。特殊：如果日后你的意志加值提高了，你不能根据该天赋得到额外的灵能。 | Y55: 先决条件：灵能等级1 | AC55: 脑皮层植入物 | AD55: 这一系统用于拯救受到严重损坏的大脑，或者强化其能力。普通的脑皮层植入物可以让瘫痪或脑损伤患者恢复表面上的正常。这种设备能做到的最好情形是让受术者永久失去 1d10 点格斗能力，射击能力，敏捷，智力，和交际，并得到1d10 失心点。粗糙质量的脑皮层植入物可恢复大脑机能，但会破坏目标的个性和记忆，有效地将受术者变成一个生化仆役，显然不适合玩家角色。极品脑皮层植入物甚至在机械神教内部都极其稀有，其制造工艺已经失传（因此价格是通常稀有物品的十倍）。这一设备具有一台思考系统的全部功能，并赋予受术者超自然智力 (∗2) 特性（见第265页）。但受术者仍会得到1d10 失心点。 | AE55: — | AF55: 5000 | AG55: 罕见 | AH55: 植入物 | AJ55: 生化呼吸系统 | AK55: 毒气和缺氧环境坚韧+20。粗糙：使用时潜行−20 。剧烈运动相关鉴定难度提高一级。极品：视为一套独立的生命维持系统。 | AL55: — | AM55: 800 | AN55: 稀有 | AO55: 生化义肢
T56: 鲤鱼打挺 | U56: 以自由动作起身 | W56: 灵能等级3 | X56: 选择一个学科，并获取该学科的一种灵能。获得等于你意志加值数目一半（向上取整）的次级灵能。你的灵能等级达到3，显能时投三枚骰子并加上意志加值。特殊：如果日后你的意志加值提高了，你不能根据该天赋得到额外的灵能。 | Y56: 先决条件：灵能等级2 | AC56: 感觉计算机 | AD56: 视觉，听觉，甚至触觉与嗅觉都可以被人工强化，某些更神秘的感觉也可以通过这种手段添加。普通感觉计算机安装后有着很明显的人工痕迹，且通常体积过大。它可以适当提升人类的感官，并无进一步的游戏影响。粗糙感觉计算机只是对肉体感觉的拙劣模仿（听觉系统出现静电噪音，视觉系统频闪或只有低分辨率单色影像，等等）。任何基于该人工感觉的检定 −20 。极品感觉计算机赋予使用者相应的增强五感天赋，且抵抗针对此项感官的攻击（例如致聋噪音，致盲闪光等）时有 +20 加值。视觉计算机可以整合高倍瞄准镜，成像仪，以及任何具有黑暗视觉特性的设备。同样的，听觉计算机也可以内部整合微型通讯器。所有这些“额外组件”在计算花费时视为一件单独的设备。 | AE56: — | AF56: 2250 | AG56: 稀有 | AH56: 植入物 | AJ56: 螺旋传感阵列 | AK56: 使用花费一个部分动作。普通=标准占卜盒。粗糙只有一种探测能力：热，辐射，或电磁，且有效距离20 米。极品允许重投使用时进行的基于感知属性的检定。 | AL56: — | AM56: 1000 | AN56: 稀有 | AO56: 植入物
T57: 灵活侧步 | U57: 每轮可以多进行一次闪避 | W57: 灵能等级4 | X57: 从任何你已知的学科中获取总数等于你意志加值数目一半（向上取整）的灵能，并获得相同数目的次级灵能。或者，你也可以放弃上述好处，改为选择一个新学科，并获取该学科的一种灵能。不论如何，你的灵能等级达到4，显能时投四枚骰子并加上意志加值。特殊：如果日后你的意志加值提高了，你不能根据该天赋得到额外的灵能。 | Y57: 先决条件：灵能等级3 | AC57: 起重附肢 | AD57: 这种有力的肩架式附肢被设计用来提举重物和操作工业设备。起重附肢由钢铁和高温烧硬的陶瓷制成，可伸展 1.5m 。使用此机械臂的角色力量检定 +20 。机械臂的末端有两套机械爪和压力钳，花费一个自由动作可以将它们固定在周围的某一点，让技术神甫能安全地待滑轨或高支架上。这套设备也可以当作棍子使用，攻击时被视为原始武器，可造成1d5 + 2 的冲击伤害。起重附肢无法进行精密操作（敲击键盘，抓握易碎品，打包裹等）。你必须有相应的机械附肢天赋才能使用它。 | AE57: — | AF57: 500 | AG57: 仅机械神教 | AH57: 附肢 | AJ57: 枪械附肢 | AK57: 视为装有改良能量匣的激光手枪，使用需具备对应天赋。适用正常射击能力属性，无特殊减值；每轮限攻击1次。 | AL57: — | AM57: 600 | AN57: 仅机械神教 | AO57: 附肢
B58: 格斗 | C58: 手枪 | T58: 灵能等级1 | U58: 获得能力，灵能检定1d10+WB | W58: 灵能等级5 | X58: 你能称得上帝国最强的那一级灵能者了。你可以从任何已知的学科中获取总数等于你意志加值数目一半（向上取整）的灵能，或者改为选择一个新学科并获取该学科的一种灵能。不论如何，你的灵能等级达到5，显能时投五枚骰子并加上意志加值。特殊：如果日后你的意志加值提高了，你不能根据该天赋得到额外的灵能。 | Y58: 先决条件：灵能等级4 | AC58: 医疗附肢 | AD58: 这个两米长，伸缩灵活的附肢被设计用来进行战地救援和实施外科手术。它具有医疗检定 +10 。这个附肢内置七个注射活塞，每一个都可装满某种药剂。这些注射器的装填与替换必须分别进行。除了实施急救外，这个附肢的肌肉缝合器可以用一个部分动作阻止失血。一个小型链锯手术刀让截肢手术的难度变为挑战（ +0 ）。这把手术刀也可作为一件临时武器，造成 1d5 劈刺伤害。最后，这套设备还能用来让你的审讯检定 +10 。医疗附肢可以被安装在肩部或胸部。你必须有相应的机械附肢天赋才能正确操作它。 | AE58: — | AF58: 500 | AG58: 仅机械神教 | AH58: 附肢 | AJ58: 脑皮层植入物 | AK58: 受术者永久失去 1d10 点格斗、射击、敏捷、智力及交际能力，并获得 1d10 点失心点。粗糙会使其沦为生化仆役，极品赋予“超自然智力 (∗2) | AL58: — | AM58: 5000 | AN58: 罕见 | AO58: 植入物
B59: 投掷 | C59: 基本 | T59: 灵能等级2 | U59: 获得能力，灵能检定2d10+WB | W59: 灵能等级6 | X59: 或许你已经发掘出了人类在灵能方面的最大潜力，只有极少数灵能者可匹敌你的技术。从任何你已知的学科中获取总数等于你意志加值数目一半（向上取整）的灵能，并获得相同数目的次级灵能。或者改为选择一个新学科，并获取该学科的一种灵能。不论如何，你的灵能等级达到6，显能时投六枚骰子并加上意志加值。特殊：如果日后你的意志加值提高了，你不能根据该天赋得到额外的灵能。 | Y59: 先决条件：灵能等级5 | AC59: 思维刺激设备(MIU) | AD59: 这一设备也被称为神经链接，可以让使用者的思维直接接触机械或科技设备。这一设备在机械神教广泛流行，被视为用于神圣交流的媒介。基础或简易 MIU 只有一套神经或脑皮层接口，而高级MIU除了神经拴之外还装备了腕部链接探针（如果条件允许，还有附肢链接探针）。普通的 MIU 不会影响你与机魂交流的检定，但在使用有 MIU 接口的设备时，你的技术应用，驾驶，航行技能 +10 。使用粗糙 MIU 需要进行意志检定，失败的话与机魂的交流承受 −10 减值。优质 MIU 可以让你与机魂的交流得到+10 加值，在使用有 MIU 接口的设备时，你的技术应用，驾驶，航行，逻辑，搜集信息技能以及射击能力 +10 。 | AE59: — | AF59: 1750 | AG59: 稀有 | AH59: 植入物 | AJ59: 感觉计算机 | AK59: 粗糙：任何与部位相关的检定−20。极品：赋予使用者“增强五感”天赋；且在抵抗针对该感官的攻击时+20。 | AL59: — | AM59: 2250 | AN59: 稀有 | AO59: 植入物
B60: 格斗，投掷 | C60: 重型 | T60: 灵能等级3 | U60: 获得能力，灵能检定3d10+WB | W60: 灵肉转化 | X60: 自由动作，自发承受伤害以提高灵能力量。灵能者永久性牺牲1点坚韧属性，使接下来的一次灵能检定+1d10。一轮之内，灵能者最多可牺牲等于WB的坚韧，使一次灵能检定增加相等数目的d10。 | Y60: 先决条件：灵能等级2 | AC60: 光学附肢 | AD60: 这种具有高度灵活性，装有摄像机的附肢被设计用于辅助探测和侦查。这种附肢可延展至多三米，且可将自身宽度缩减到铅笔粗细。它赋予使用者任何基于感知的检定 +10 加值。光学灵敏触头可以让使用者对表面进行微观检查，也可用作高倍瞄准镜。该附肢还装有红外照明设备和红外传感器。使用光学附肢的角色不会因黑暗承受任何减值，且在夜间，任何基于视觉的感知检定 +20 。光学附肢会发出微光，颜色随控制者心意而定。光学附肢可以被安装在肩部或胸部。你必须有相应的机械附肢天赋才能正确操作它。 | AE60: — | AF60: 400 | AG60: 仅机械神教 | AH60: 附肢 | AJ60: 起重附肢 | AK60: 使用需具备对应天赋，可伸展1.5米，力量+20，伤害 1d5+2I。消耗一个自由动作可固定机械爪至支点提供支撑，无法进行精密操作。 | AL60: — | AM60: 500 | AN60: 仅机械神教 | AO60: 附肢
C61: 投掷 | T61: 灵能等级4 | U61: 获得能力，灵能检定4d10+WB | W61: 盲斗 | X61: 长期的特殊训练使你无需看到目标即可命中，在非明亮环境中作战时的减值变为原来的一半。 | Y61: 先决条件：Per30 | AC61: 多功能附肢 | AD61: 这条两米长的附肢内置了种类齐全的大量工具，以辅助技术神甫们完成它们的神圣使命。多功能附肢视为一套组合工具，使用者在进行技术应用检定时获得 +10 的加值。这个附肢还内置七个装满祝福机油的注射活塞。这些注射器的装填与替换必须分别进行。除此之外，多功能附肢还安装了一个电动香炉，当发现某些显著故障时它就会冒出一阵浓烟。这个香炉装置还可以“爆发”出一阵浓烟，这是个部分动作，每十五分钟可用一次。在格斗中，这一功能可用于阻碍和干扰对手，让两米以内的任何生物在一轮以内格斗能力 −5 。除非香炉关闭，否则任何尝试以嗅觉侦测技术神甫的感知检定 +10 。最后，多功能附肢上还有一把切割刀，这被视为一把有防御特性的单分子小刀。你必须有相应的机械附肢天赋才能正确使用多功能附肢。 | AE61: — | AF61: 500 | AG61: 仅机械神教 | AH61: 附肢 | AJ61: 医疗附肢 | AK61: 使用需具备对应天赋，医疗+10，审讯+10，截肢手术+0，伤害1d5R 。内置七个注射活塞可分别装满各种药剂，可用一个部分动作阻止失血。 | AL61: — | AM61: 500 | AN61: 仅机械神教 | AO61: 附肢
T62: 灵能等级5 | U62: 获得能力，灵能检定5d10+WB | W62: 貌不惊人 | X62: 试图在人群中注意到你或者回忆你的相貌的检定−20。 | Y62: — | AB62: 改 装 | AC62: 轻量化 | AD62: 轻量化可以使手枪类和基础类武器变的更加小巧，这种强化在要求隐蔽性胜于杀伤力的人中十分流行。轻量化武器的重量，载弹量，射程都变为标准武器的一半，并且武器伤害减少1点。如果这种武器被藏在身上，对方搜出这种武器的检定-20。 | AE62: ∗1/2 | AF62: 50 | AG62: 一般 | AH62: 强化类型：任何手枪类和基本类激光，实弹，火焰，爆矢或等离子武器 | AJ62: 思维刺激设备(MIU) | AK62: 技术应用、驾驶、航行技能+10。粗糙：使用时需进行意志检定，失败机魂的交流−10。优质：机魂交流+10，额外逻辑，搜集信息技能以及射击能力+10。 | AL62: — | AM62: 1750 | AN62: 稀有 | AO62: 植入物
T63: 灵能等级6 | U63: 获得能力，灵能检定6d10+WB | W63: 猛力打击 | X63: 格斗武器能造成的伤害加2。 | Y63: 先决条件：S40 | AC63: 根除者 | AD63: 在帝国内，很多更加狂热的宗教战士都会将一个根除者弹药筒加装在他们的标准武器上。这是一个小型装置，其中包含了可以喷射出一片火焰的单发火焰武器。加装了这种装置的武器开火的时候几乎和同时使用火焰武器攻击一样的效果，使它比标准武器更具威力。根除者是种一次性武器，每次使用之后都需要进行更换。安装了根除者的武器将失去原有的“平衡”特性。 | AE63: +1kg | AF63: 35 | AG63: 普及 | AH63: 强化类型：任何武器，除了具有柔韧属性的武器，基本伤害为 d5 的武器，或手枪 | AJ63: 光学附肢 | AK63: 使用需具备对应天赋，可伸展3米，基于感知的检定+10，夜间中基于视觉的感知检定 +20。具有显微/高倍瞄准镜，红外照明/传感器功能，且不会因黑暗承受减值。 | AL63: — | AM63: 400 | AN63: 仅机械神教 | AO63: 附肢
T64: 灵肉转化 | U64: 承受伤害以提高灵能检定 | W64: 命硬 | X64: 重投由失血引起的死亡几率。 | Y64: 先决条件：WP40 | AC64: 改良枪柄 | AD64: 就像已知的手枪枪柄，这个强化允许单手使用基础武器而不必承受正常情况下的-20惩罚。但在单手持用时，该武器难以瞄准因此射程减为正常的一半。你可以选择双手使用该武器，则不会造成射程下降。 | AE64: ∗1/3 | AF64: 25 | AG64: 丰富 | AH64: 强化类型：任何基本远程武器。 | AJ64: 多功能附肢 | AK64: 使用需具备对应天赋，技术应用+10，内置七个装满祝福机油的注射活塞，一把防御特性的单分子小刀，可花费一个部分动作引爆香炉，冷却十五分钟，两米内生物下一轮格斗-5，嗅觉侦测神甫感知+10。 | AL64: — | AM64: 500 | AN64: 仅机械神教 | AO64: 附肢
T65: 盲斗 | U65: 视线受阻时的减值减半 | W65: 恼人嗓音 | X65: 你的声音听起来十分阴险，令人不安。这可能是由于你使用了电子合成发声器官，或受过专门的审讯训练，也可能你天生如此。你的恐吓与审讯检定+10。但和那些容易因你的声音而受惊的生物（灵能者，小孩，紧张的戈洛兽等等）打交道时，交际检定−10。 | Y65: 先决条件：技术神甫（呼吸面罩） | AC65: 分弹器 | AD65: 一些武器由于能装载不同种类的弹药，所以经常需要对其进行变更。一个加装了分弹器的武器最多可以同时携带三个不同类型的额外弹夹。当轮到射击者行动时，他可以利用分弹器选择该轮他需要的弹夹。 | AE65: +0.5kg | AF65: 25 | AG65: 匮乏 | AH65: 强化类型：爆矢或实弹手枪，爆矢或实弹基本武器。 | AJ65: 轻量化 | AK65: 重量、载弹量与射程减半，伤害 -1。被藏匿时，试图搜出这件武器的检定-20。 | AL65: ∗1/2 | AM65: 50 | AN65: 一般 | AO65: 强化类型：任何手枪类和基本类激光，实弹，火焰，爆矢或等离子武器。
T66: 貌不惊人 | U66: 你很容易被遗忘 | W66: 能量缓冲 | X66: 进行线圈冲击，线圈充能，和线圈放电时不会再引起虚弱。 | Y66: 先决条件：技术神甫（储压线圈） | AC66: 格斗附件 | AD66: 刺刀，链锯刃以及其他近战附件可以加装在几乎所有的远程武器上，使它们在攻击中更有效率。加装了格斗附件的武器在近战中视为矛。 | AE66: +2kg | AF66: 25 | AG66: 丰富 | AH66: 强化类型：任何基本远程武器。 | AJ66: 根除者 | AK66: 开火的时候约等于同时使用火焰武器攻击的效果。使用之后需进行更换。安装的武器将失去“平衡”特性。 | AL66: +1kg | AM66: 35 | AN66: 普及 | AO66: 强化类型：任何武器，除了具有柔韧属性的武器，基本伤害为 d5 的武器，或手枪。
T67: 猛力打击 | U67: 使用格斗武器造成+2伤害 | W67: 拟声高手 | X67: 你可以模仿某人的声音。你必须至少听过目标的声音一小时以上，且你能理解目标的语言，你与目标还必须是同一种族（例如，人类无法模仿兽人的声音）。戳穿你的模仿需要一次困难（−10）的察言观色检定。如果你的模仿是基于录音设备或其它介质而不是直接模仿自本人，察言观色检定难度变为挑战（+10）。注意该天赋只能让你模仿声音，而不包括相貌。如果对方能看到你本人，你的模仿自动失败。 | Y67: — | AC67: 单分子 | AD67: 单分子武器使用了特制的锐利锋刃，使得它能够在不损害武器特性的情况下轻易切开护甲。单分子武器不视为原始武器，并且能够获得额外的 +2 破甲。显然，武器必须有个刃才能适用此种强化。但 GM 可以据此设计适用于钝器的强化规则。（钝器也可以强化） | AE67: 0 | AF67: 40 | AG67: 匮乏 | AH67: 强化类型：任何原始近战武器 | AJ67: 改良枪柄 | AK67: 允许单手使用基础武器而不承受惩罚。但在单手持用时该武器射程减半。双手使用则不会造成射程下降。 | AL67: ∗1/3 | AM67: 25 | AN67: 丰富 | AO67: 强化类型：任何基本远程武器。
T68: 命硬 | U68: 重投由失血引起的死亡几率 | W68: 凝神静养 | X68: 进行一次意志检定以进入“入定”状态。在这种状态下每休息10分钟可恢复1级虚弱。 | Y68: — | AC68: 激光指示器 | AD68: 强化类型：手枪类和基本类激光，实弹，爆矢，原始和等离子武器。激光指示器视为瞄准具，一件武器只能装载一件瞄准具。 | AE68: +0.5kg | AF68: 50 | AG68: 匮乏 | AH68: 加装了激光指示器的武器在进行单发射击时 BS+10。 | AJ68: 分弹器 | AK68: 最多可以同时携带三个不同类型的额外弹夹。当轮到射击者行动时，可以利用分弹器选择该轮需要的弹夹。 | AL68: +0.5kg | AM68: 25 | AN68: 匮乏 | AO68: 强化类型：爆矢或实弹手枪，爆矢或实弹基本武器。
B69: 名称 | C69: 花费 | D69: 描述 | T69: 恼人嗓音 | U69: 恐吓与审讯检定+10，交际−10 | W69: 皮糙肉厚 | X69: 一旦受到致命伤害，该伤害减半（向下取整）。 | Y69: 先决条件：T40 | AC69: 消声器 | AD69: 消声器能够有效降低武器开火时的声音和闪光，减少被发现的几率。想通过警觉检定发现消音武器开火的声音需要受到-20的惩罚，并且有效警觉距离也要减半。 | AE69: +0.5kg | AF69: 15 | AG69: 丰富 | AH69: 强化类型：短管左轮，短管连发枪，手铳，自动步枪，来复猎枪。 | AJ69: 格斗附件 | AK69: 近战附件可以加装在几乎所有的远程武器上，加装了格斗附件的武器在近战中视为矛。 | AL69: +2kg | AM69: 25 | AN69: 丰富 | AO69: 强化类型：任何基本远程武器。
B70: 军务部军需官 | C70: 100 | D70: 军务部是个冷酷无情的庞大机构，永不停歇地向帝国军队输送所需的一切物资，大到星际飞船的等离子核心，小到鞋带和子弹。可想而知，这项任务背后的后勤压力有多么沉重，涉及的行政管理过程又多么盘根错杂。正因如此，军务部设有军需官，承担监管之职。他们不但要确保后勤工作井然有序，生产配额得到满足，还必须时刻警惕叛乱与不满的迹象，防微杜渐。然而，军需官要面对的挑战远不止如此，犯罪分子与邪教徒经常将他们列作袭击目标，试图夺走武备，心怀不满的劳工和囚犯也可能蓄意报复他们。种种因素塑造了军需官的对外面貌，让外界普遍认为军需官不近人情、偏执多疑。 军需官生活艰苦，更无安全可言。这样的工作环境磨砺了军需官的观察力与决策力，让他们既能明察秋毫，又能雷厉风行地做出判断。当军需官成为审判庭的仆从时，这两种品质都会派上用场。但很快，这些加入审判庭的军需官就会发现，他们要处理的危险只会比以往更为可怕而棘手。 效果 Effects 将以下所有更改应用到你的角色上： 属性 Characteristics：你的起始意志与交际属性减少 5 点。 技能 Skills：你开局获得指挥，常识（帝国卫队），搜集信息，搜索和入侵 技能。 天赋 Talents：你开局获得谨小慎微天赋。 | T70: 能量缓冲 | U70: 储能线圈充电，爆发，以及电击时不会虚弱 | W70: 平等待遇 | X70: 子项：学者，法务部，机械神教，内政部，导航者，帝国国教，荒蛮世界生人，政府官员，巢都生人，审判庭，中产阶级，军人，贵族，灵能者，下层社会，星海生人，工人对选定组织或人群的交际检定+10。 | Y70: 先决条件：Fel30 | AC70: 高倍瞄准镜 | AD70: 高倍瞄准镜能够放大目标图像，这使得它在进行长距离射击或是精确射击的时候十分有用。使用了高倍瞄准镜的武器在进行完整动作瞄准后可以忽视远距离和超远距离射击惩罚。 | AE70: +1kg | AF70: 35 | AG70: 一般 | AH70: 强化类型：基础类激光，实弹，爆矢，原始和等离子武器。高倍瞄准镜视为瞄准具，一件武器只能装载一件瞄准具。 | AJ70: 单分子 | AK70: 武器必须有刃才能适用此种改装，单分子武器破甲+2，且不视为原始武器。 | AL70: 0 | AM70: 40 | AN70: 匮乏 | AO70: 强化类型：任何原始近战武器
B71: 言究学社学者 | C71: 100 | D71: 要求出身世界为：帝国世界或贵族生人 言究学社（Hetaireia Lexis）是由多个学术机构与私立学院组成的松散组织，致力于学问研究与高等学艺。言究学社的历史曲折坎坷，最早可以追溯到六百年前。星区总督喀拉卡拉（Caracalla）一手创办了言究学社，同时颁布相关宪章，在法律层面确立了学社的独立性，赋予学社罕见的自治权，哪怕其并不受帝国政府管辖。而后，岁月变迁，星区政府几度轮换，言究学社也历经无数磨难，它曾遭国教排斥，深陷丑闻与谋杀的漩涡之中，也曾流出亵渎的黑暗传言，因异端风险而经受审判，甚至有一个下属机构被审判庭全面清洗。然而，这些磨难都未能打垮言究学社。时至今日，整个卡利西斯星区仍有十来个独立机构在言究学社的庇护下运作。这些机构大小不一，小至仅有几十名学生的偏僻缮写院，大至容纳数千学者的“言究大殿”（Lexis Maxima）——这座建筑群规模庞大，如迷宫般复杂，其地理位置更是特殊，就位于西贝柳斯巢都，在星区政府“清宫”的阴影之下。 许多审判官认为，言究学社是滋生危险思想与叛逆者的温床，另有审判官持不同的观点，认为言究学社培育出了大量有识之士，这些人才是宝贵的潜在资源，值得加以利用。而对于那些引起审判庭注意的学者来说，他们所能期望的最好情况，莫过于作为侍僧活下去。 效果 Effects 将以下所有更改应用到你的角色上： 属性 Characteristics：你的智力属性提高 3 点，但你的近战技巧和力量属性减少 5 点。 技能 Skills：你开局获得暗号（秘密组织：言究学社），禁忌知识（任选一项），学术知识（任选一项）技能。 天赋 Talents：你开局获得 平等待遇（学者）天赋。 | T71: 拟声高手 | U71: 你可以模仿声音 | W71: 气势威严 | X71: 你天生就有对人吆五喝六的天赋。成功的命令检定可以影响1d10+FB的目标。可尝试以−10减值进行检定以指挥并非你下属的目标。该天赋对敌对目标无效，且只能影响NPC。 | Y71: 先决条件：Fel30 | AJ71: 激光指示器 | AK71: 加装了激光指示器的武器在进行单发射击时 BS+10。 | AL71: +0.5kg | AM71: 50 | AN71: 匮乏 | AO71: 加装了激光指示器的武器在进行单发射击时 BS+10。
B72: 虚空商贸员 | C72: 200 | D72: 要求出身世界为：虚空生人 卡利西斯星区能有今日的繁荣，全仰赖兴盛的贸易。倘若某日贸易断绝，星区必将凋敝衰亡。保证贸易通达至关重要，但绝非易事，因为星际航行是一项晦涩玄奥、充满危险的工作，甚至还带有些许不祥色彩，能胜任的人少之又少。通常情况下，星际航行的最佳人选便是那些出生星海，适应其叵测本性的人。卡利西斯贸易网络的每个玩家都清楚这点，因此，为了保护自身利益，各个行星商会、企业与贵族门阀都会配备一支训练有素、高度专业化的文员队伍作为代理人，为他们管理星际贸易事务。这些专业人才被称为“虚空商贸员”，通常由内政部签约招募并培训。但某些大型组织可以从内部选拔人才，培养出自己的虚空商贸员。 与多数文员不同，虚空商贸员对星际航行习以为常，同时作为雇主的传话筒，享有优渥的待遇。有时，虚空商贸员的专业能力会引起审判庭的兴趣。审判庭会威逼利诱，将这些虚空商贸员纳入其麾下。而这些新雇主不仅向虚空商贸员下达了截然不同的指示，还要求他们与过去划清界限。从此之后，不再有人考虑他们的感受，他们唯一能依靠的只有自己。 效果 Effects 将以下所有更改应用到你的角色上： 属性 Characteristics：你的近战技巧与坚韧属性减少 5 点。 技能 Skills：你开局获得交易，悦服，常识（帝国），常识（商业），估价，察言观色，密语（你曾效力的组织†）技能。 †比方说，你可以选择塔苏斯巢都商会的“金舌腔（Goldentongue）”或是德瓦恩企业（DeVayne Corporation）的“契心语（Cordcordia）”。 | T72: 凝神静养 | U72: 进入一种假寐状态以移除虚弱 | W72: 轻度睡眠 | X72: 你睡得又浅又轻，即使在睡眠状态下警觉检定也不会有任何减值。你不会因睡眠而被突袭，被惊醒时也不会措手不及。缺点是你在白天通常会觉得疲劳，总是心烦意乱或脾气暴躁。 | Y72: 先决条件：Per30 | AJ72: 消声器 | AK72: 想要通过警觉检定发现消音武器开火的声音需要受到-20的惩罚，并且有效警觉距离也要减半。 | AL72: +0.5kg | AM72: 15 | AN72: 丰富 | AO72: 强化类型：短管左轮，短管连发枪，手铳，自动步枪，来复猎枪。
B73: 卡利西斯型谋杀 | C73: 200 | D73: 单从作案手段来看，卡利西斯型连环凶案除却骇人外，并无其他特别之处：凶手以锐器将受害者割喉或斩首，极端情况下甚至会肢解尸体，摘除器官。此等残忍的暴行在帝国司空见惯，但卡利西斯型连环凶案还隐藏着某种更为黑暗的可怕秘密，它们遵循着同一种犯罪模式，却在时间与空间尺度上跨越极大，犯罪现场间有时能相距数个世界之远。数个世纪以来，无数出类拔萃的预言家与学者试图解开这个谜团，但仅仅是投入心智，便足以将他们逼至疯狂。时至今日，卡利西斯型连环凶案仍未停止，而它的真相也依然隐藏于迷雾之中。 卡利西斯型谋杀的受害者涵盖各个阶层，既有加工厂的底层劳工，也有顶层权贵在家中遇害。所有谋杀案都发生在夜晚，但案发地点却各有不同。有些受害者在光线昏暗的公共场所被杀，其他市民离案发地仅数码之遥，但无人察觉到近在咫尺的犯罪。有些受害者死在封闭的密室里，唯一的出入口是一扇窗户，但窗外并无立足点，只有骇人的万丈深渊。那些曾瞥见凶手的目击者描述了如出一辙的细节，其内容令人不安：一双闪烁的眼睛、宛若在燃烧，行动敏捷，异乎常人，通常伴有一闪而过的黑色斗篷，或手杖反复敲击地面的声音。若有人敢与他（或者说“它”）对峙，下场非死即残。 神圣修会持续跟踪着此类谋杀案的发展，暴君智谋团对此事的关注甚至比其他同僚更为密切。审判庭日复一日地筛选堆积如山的数据，徒劳地挖掘着谋杀背后的黑暗目的。有时，他们会在调查途中碰见一些敏锐的法务官或本地执法者，能自行分辨出卡利西斯型连环凶案。审判庭往往会招募这些人才，为己所用——毕竟，要是将他们的才能浪费在治安琐事上，多少有点暴殄天物。 效果 Effects 将以下所有更改应用到你的角色上： 属性 Characteristics：你的智力或感知属性提升 5 点。 天赋 Talents：你开局获得天赋异禀（搜集信息）天赋。 | T73: 皮糙肉厚 | U73: 减少你所受的致命伤害 | W73: 枪械祝福 | X73: 花费一个完整动作进行智力检定，成功的话可以治愈10米内等于你智力加值数目枪械的机魂，使枪械的故障排除。 | Y73: 先决条件：技术神甫（电感组织/储压线圈） | AJ73: 高倍瞄准镜 | AK73: 在进行完整动作瞄准后可以忽视远距离和超远距离射击惩罚。 | AL73: +1kg | AM73: 35 | AN73: 一般 | AO73: 强化类型：基础类激光，实弹，爆矢，原始和等离子武器。高倍瞄准镜视为瞄准具，一件武器只能装载一件瞄准具。
B74: 大锡诺菲亚空心人 | C74: 100 | D74: 大约三年前，卡利西斯审判庭收到报告，得知巢都城市大锡诺菲亚发生了一系列恐怖而怪异的死亡事件。这些事件造成了大规模伤亡，其形式极为可怕，以至于锡诺菲亚上的愚昧居民都大为惊骇。事件的真相已被彻底封锁，但相关传闻却层出不穷。据说，在这一事件中，法务部仲裁官们自相残杀，甚至有人失去理智，变成了怪物，以非人的力量疯狂撕扯自己的身体，粉碎任何它们够得到的人。 这些传闻背后隐藏着可怕的真相。导致这一灾难事件的罪魁祸首是名为“逻辑学家（Logicians）”的异端科技教派，他们策划阴谋，触犯禁忌，企图用异形生物学玷污神圣的人类形态，以打造由“完美”人类组成的军队。逻辑学者的计划最终失败，但相关调查也惨烈告终：法务部的辖区堡垒遭内部叛徒摧毁，审判庭的部队全面突袭了锡诺菲亚行星防御部队的医疗中心，逻辑学者的异端生物术士正是在那里进行亵渎的跨物种实验。这座设施的地下潜伏着难以想象的恐怖，逻辑学者曾小心地将它们隐藏在人类视线之外。而当真相终于大白天下时，所有见证者都因此留下了永久的创伤。 随后数月里，经历这一事件的忠诚法务官大都被审判庭吸纳。这些幸存者所目睹的恐怖深深烙印于他们的身心。攘外修会的独占派审判官格外重视这些特质，视这些人为保卫人类免受异形腐化与内在邪恶的战士之材。 效果 Effects 将以下所有更改应用到你的角色上。 天赋 Talents：你开局获得宿敌（技术异端）与谨小慎微天赋。 失心点 Insanity Points：你获得 1d5 点失心。 | T74: 平等待遇 | U74: 你对特定群体的交际检定+10 | W74: 枪战能手 | X74: 双手各持一把手枪战斗时，BS减值变为−10。如果你同时具有双巧手天赋，则无减值。 | Y74: 先决条件：BS40，双武器攻击
B75: 卢格南的红窟 | C75: 100 | D75: 异端总在偏僻的边缘地带扎根。矿业世界卢格南无疑是这样的沃土，供异端分子肆意生长。在这个落后的矿业世界上，奥莉亚·格雷女士（Lady Orlea Grey）治下的领地不断流出黑暗传言，同报告一并指责她过于残暴的统治手段。在流言发酵数年后，次星区的法务部指挥部派遣了一支五十人小队，负责调查与镇压这一事件。法务官们本以为自己要面对的不过是在矿道里苦苦挣扎的邪教徒，却不料一头撞进了人间炼狱。地道里布满了致命陷阱，杀戮机仆无情追逐着不幸的工人，渴望用他们的血肉满足口腹。法务部小队的大部分人或死于非命，或精神崩溃，少数逃回地上的幸存者意识到了可怕的事实：整个矿场都已被格雷女士改造成了血腥屠宰场，而她这么做，只是为了娱乐自己和卢格南“铁脊”矿场（Ironback mines）的堕落矿场主。格雷女士在自己的亲信口中还有另一个称呼，“绯红女爵”。事发后，星区法务部和讨逆修会在卢格南发动了全面的惩戒清洗，但真正的秘密直到很久后才被发现：格雷女士只是个幌子，她的真实身份是卡利西斯星区最恶名昭著的异端之一——“瓦萨尼德的血红天使”麦琪拉·辛德菲尔（Myrchella Sinderfell）。在卢格南的惨案发生前，人们以为她已经死了一百多年。尽管格雷女士的庄园修建得如壁垒般森严，但仍挡不住法务部和审判庭的正义制裁。然而，在庄园废墟里，人们并没有找到麦琪拉的尸体，所以在惩戒清洗后，一些人认为她仍逍遥法外。 从“红窖”初步调查中幸存的法务官寥寥无几，那里的恐怖摧残了他们，却也磨砺了他们，审判庭很快便为他们找到了用武之地。这些法务官尤其适合与手段强硬的审判官共事，因为他们已亲眼见过任由异端肆虐的惨痛代价，他们的心已同眼神一般冰冷。相比之下，那些手段不足为道。 效果 Effects 将以下所有更改应用到你的角色上： 属性 Characteristics：你的意志属性提高 3 点。 天赋 Talents：你开局获得见惯不惊天赋。 失心点 Insanity Points：你开局获得 1d5 点失心。 | T75: 气势威严 | U75: 指挥检定可以影响更多目标 | W75: 强化五感* | X75: 子项：视觉，听觉，嗅觉，味觉，触觉进行与选定感觉有关的检定有+10加值。注意该天赋不会影响射击能力检定。 | Y75: —
B76: 星海锋刃 | C76: 200 | D76: 要求出身世界为：虚空生人 作为拜死教派中被帝国取缔的一支，星海锋刃教徒必须对所有人隐瞒自己的信仰，除了最值得信赖的密友。星海锋刃是虚空生人封闭社会内部的秘密结社，自认为肩负着一份神圣使命，即守护人类在亚空间航行时的安全。若航程遭遇险阻、目睹黑暗征兆，或虚空中的危险迫近，星海锋刃便会执行一场献祭仪式，以求得帝皇的庇护。那些最明显“不洁”的目标，例如变种人和灵能者，会被优先选中，但根据仪式预言指引，几乎任何人都可能成为目标。 大约五十年前，卡利西斯审判庭发现毁灭力量的崇拜者已渗入该教派的大片网络，随即将星海锋刃宣布为异端教派，并展开了一场大规模的清剿行动。尽管如此，这个根基深厚、分布广泛的拜死教依然存续至今，尽管其成员已四散各地，人数也远少于从前。 星海锋刃教徒通常出生于教派中，而非后天培养而成。某些虚空家族与该教派有着悠久的渊源，或是亲自担任杀手，又或者暗中提供支持。他们也并非嗜血的杀手。相反，他们被教导认为，他们的谋杀——往往伪装成意外——是一桩糟糕但必要的职责。部分成员会在适当的时候为受害者哀悼，但也有许多人在虚空生人中售卖自己的能力，以此进一步磨练技艺，尤其当目标是“地面佬（dirtside）”或非本船人员时。 审判庭中一些更为激进的势力，在条件允许的情况下，会将幸存且未受腐化的星海锋刃吸纳入麾下，充当技艺娴熟的间谍和杀手；而锋刃方面，他们也迫切希望以此证明自己的信仰。 效果 Effects 将以下所有更改应用到你的角色上： 技能 Skills：你开局获得暗号（秘密组织：星海锋刃）技能。此外，你将禁忌知识（亚空间）和技术应用视作基础技能。 堕落 Corruption：你开局获得 1d5 点堕落。 注意：星海锋刃教徒是被取缔组织的成员。如果此事广为人知，他们很可能会招致法务官、猎巫人以及那些不如他们的主人通情达理的审判官的怒火。 | T76: 轻度睡眠 | U76: 睡眠时的所有检定按清醒时计算 | W76: 强力射击 | X76: 你使用的远程武器伤害+2。 | Y76: 先决条件：BS40
B77: 谋杀歌者 | C77: 300 | D77: 要求出身世界为：蛮荒世界、帝国世界或巢都世界 谋杀歌者是拜死教派之一，其历史远比卡利西斯星区本身更为悠久。有传说称，谋杀歌者是由那些潜藏于安茹远征军中的信众带入卡利西斯的，正是这场远征开辟了卡利西斯星区。也有人宣称，该教派早已在这片土地上埋下种子，静待帝国军到来。无论如何，谋杀歌者都高度依附于帝国教义，尽管其对教义的诠释充满了血腥与神秘色彩。该教派宣扬，唯有通过无情的暴力与死亡，帝国方得以维系，弱者与腐败之徒方能被剔除，帝皇的伟大牺牲方能得到尊崇。在组织结构上，谋杀歌者极难被渗透或锁定，其运作以独立小组为单位，每个小组由一名主祭（master or mistress）领导。这些主祭扎根于底巢、蛮荒世界的荒野以及战区等招募据点。谋杀歌者会挑选那些已被悲剧与血腥“标记”之人来为帝皇效力，向祂的敌人降下死亡。他们将这些人从年幼时带走，将其心中的苦涩与仇怨锻造成武器。谋杀歌者会对新血施以残酷的训练，教授毁灭、欺骗和血腥技艺，同时也向他们灌输其独特版本的帝国信仰以及教派秘辛。那些在严酷训练中幸存下来的谋杀歌者学徒将成为教派的正式成员，并被单独派往更广阔的帝国疆域——他们将这一过程称为“苦旅（travail）”，以此磨练作为刺客、义警和无可匹敌的决斗者的技艺。他们坚信，唯有通过无止境的冲突与血腥的历练，才能在技艺上登峰造极，从而与侍奉帝皇的职责相配。 *译注：moritat是德语地区的一种中世纪街头舞曲，一般记录感官性的犯罪或谋杀，由街头艺人表演。moritat的可能词源为mordtat，意为谋杀/犯罪。 在卡利西斯贵族世家与帝国各机构的高层中，谋杀歌者的存在算是一个公开的秘密，尽管关于该组织的事实信息少之又少。该教派的存在似乎也得到了帝国高层某种程度的默许，这一事实使得有人私下猜测，谋杀歌者背后真正的支持者，正是那遥远而令人畏惧的刺客庭本身。 对一位谋杀歌者刺客而言，能为审判庭效力实属荣幸——不仅能亲手斩杀神皇的敌人，这更是一个试炼场；他们得以在面对最凶险、最强大的对手时检验自身实力。许多审判官都将谋杀歌者刺客视为无价之宝，他们是在面对诸多必须被克服的怪物时，由自己驯养的，能与之相抗的怪物。 效果 Effects 将以下所有更改应用到你的角色上： 属性 Characteristics：你的交际属性减少 5 点。 技能 Skills：你开局获得攀爬、密语（谋杀歌者）、跟踪和潜行技能。 天赋 Talents：你获得见惯不惊天赋。 失心点 Insanity Points：你开局获得 1d5 点失心。 装备 Equipment：用以下装备替换你常规的起始装备：单分子剑、六把飞刀、十字弓（crossbow pistol）及二十发弩矢、抓钩与绳索、装备挂带、三剂兴奋剂，以及一套防护贴身服（为躯干、双臂和双腿提供 2 点原始护甲）。 *译注：没有找到crossbow pistol对应的官方武器数据，疑似误写，可以和游戏主持人沟通后考虑使用十字弩（crossbow）或者弹射弩（Flick Bow）或手弩（hand bow）的数据。 “识别目标。集中火力，排除他物干扰。摧毁目标后，选择下一目标。此乃制胜之道。” 血腥锋刃 The Bloody Edge（特性）：谋杀歌者鄙视许多现代武器，认为其粗陋且无法带来精神满足。他们更青睐刀刃的神圣锋芒。因此，除非显然别无他法，否则他们在战斗中使用任何缺乏“刃”的武器（投掷刀、匕首和箭矢可以）时，必须通过一次艰难（-20）的意志检定。然而，鉴于他们在流血技艺上的致命造诣，当他们使用任何带刃武器攻击活体目标时，该武器均视为具备撕裂特性。 | T77: 枪械祝福 | U77: 瞬间修好10米内等于智力加值数目的枪械 | W77: 轻身坠 | X77: 从高处落下时可以一个自由动作进行敏捷检定，每点成功度可以在计算坠落伤害时少算等于敏捷加值的米数。 | Y77: 先决条件：Ag30
B78: 冥父之子 | C78: 100 | D78: 冥父之子（The Sons of Dispater）只在乎钱。对他们而言，每条命都有其价码，唯有目标的身份地位以及刺杀行动的难易会影响价格。冥父之子最初是一家佣兵集团，参与了星区中爆发的那场残酷贸易战争。它逐渐演变为更现代的形态，也正是在这样的改进中，冥父之子蜕变为一支自由的刺客公会，向任何有能力支付报酬的人提供技艺精湛的杀手、决斗者和毁坏者。多年来，冥父之子凭借其可靠性与致命性赢得了当之无愧的声誉，其势力范围从马尔菲的行动中心向外延伸，几乎覆盖了星区内的每一个重要世界。尽管他们唯一的忠诚只属于收到的酬金，但该组织仍将合约视为不可侵犯之物——他们很早就意识到，一个充斥着背信弃义刺客的组织注定难以为继。因此，任何背弃合约的成员，最好将其行踪掩盖得天衣无缝，否则将面临冥父之子同袍的怒火。 *译注：冥父之子原文的Dispater应当来源于罗马神话中的Dis Pater，意为富有的父亲。他掌管农田与矿产，也是冥王，在40k出现可能是某种古泰拉宗教遗迹。 审判庭并不排斥雇佣由冥父之子训练出来的杀手，因为他们看重这些成员的技能及其可预料的动机。同样地，一名杀手也可能在无意中触怒了审判庭，如今除赎罪之外别无选择——神圣修会的成员是为数不多、连冥父之子也不肯触碰的目标之一。 效果 Effects 将以下所有更改应用到你的角色上： 技能 Skills：你开局获得常识（地下势力），恐吓和入侵技能。 装备 Equipment：将刺杀手职业通常获得的剑替换成一把短管连发手枪、一个消音器以及两份弹匣。 注意：任何冥父之子成员，若其打破或背弃了契约——即便是奉审判庭之命，且让此事走漏了风声，便会引来其原先公会同僚所下达的死亡印记。任何成员一见此印记，将对叛徒格杀勿论。 | T78: 枪战能手 | U78: 承受−10减值用两把手枪战斗 | W78: 杀手之击 | X78: 无论何时，当你接触对手并进行肉搏攻击之后，你可以尝试进行特技检定，成功的话可以用一个自由动作以你的部分移动速度移动。对方无法借机对你进行攻击。 | Y78: 先决条件：Ag40，特技
B79: 塔苏斯至圣经院 | C79: 200 | D79: 要求出身世界：贵族生人、帝国世界或巢都世界 首都世界辛提拉的塔苏斯巢都矗立着国教在卡利西斯星区的权力核心——巍峨壮丽的“启明大教堂”。这座宏伟建筑是帝国信仰的具现，而在它的阴影之下，又坐落着成百上千的小教堂与修院。这些下属机构各司其职，有的服务于礼拜与朝圣，有的则服务于国教那盘根错杂的官僚体系，还有像至圣经院这样的学院组织，致力于培养有潜力成为国教高层的人才（或富人）。大部分至圣经院由某一贵族家族或教义派别资助，这些赞助者试图以此影响下一代国教教士，从而实现自身的目的。许多人批评至圣经院，认为它们会制造信仰分裂，甚至化为滋生异端的温床，让教士们沉溺于世俗享受或个人的野心。尽管反对声众多，但至圣经院已然作为一项传统，在帝国社会根深蒂固，影响深远，它所扮演的角色也得到了帝国社会的普遍认可。 在诸多至圣经院中，德鲁苏斯经院（Drusine）最为古老，也最为神秘。斯科里亚经院（Scoriaen）以狂热祝圣，宣称其在过去培养出了大批的猎巫人。许多贵族把狡狐经院（Vulpine）当作垃圾场，用来打发不听话的子女。而最近成立的伊格纳托经院（Ignatian），只不过是现任高阶主教（high cardinal）伊格纳托巩固权力的工具。 塔苏斯至圣经院培养出的牧师往往比大多数同僚更具政治头脑，也更渴望跻身高位。他们有的只是将审判庭看作出人头地的敲门砖，有的则认为自己的天职正是成为受审判庭认证的猎巫人。无论抱有怎样的目的，这些塔苏斯经院出身的牧师都学识渊博，既通晓灵性事务，又精于世故，熟悉各类政治手腕，是审判庭侍僧的优良候选。 效果 Effects 将以下所有更改应用到你的角色上： 属性 Characteristics：你的智力与交际属性提高 5 点。你的近战技巧，远程技巧和力量属性减少 5 点。 技能 Skills：你开局获得悦服，常识（国教教会），察言观色和听说语言（高哥特语）技能。 天赋 Talents：你开局获得平等待遇（国教教会）天赋。 | T79: 强化五感* | U79: 特定感觉得到+10加值 | W79: 闪电反射 | X79: 将两倍敏捷加值计算入先攻权。 | Y79: —
B80: 托钵传教士 | C80: 100 | D80: 托钵传教团（Mendicantine Fraters）是由帝国传教士和告解神父组成的修会。他们毕生致力于服务帝国信众，并在星海之间守护帝国信徒。作为传教士，他们追随信仰的需求与召唤，前往世界各地，不论那是家喻户晓的朝圣之路，还是几近失落的边陲世界。他们孤身流浪，随遇而安，常将途中偶遇的初信者收为门徒。即使只是萍水相逢的师徒关系，托钵传教士也热忱地将自己的信条尽数传授。这样全凭天意、忽视教规的随性作风，自然引发了某些国教成员的不信任。许多身居高位的枢机主教认为，托钵传教士及其传教方式脱离了国教“正统”，很可能会成为威胁。然而，托钵传教士受古老传统的庇护：相传，托钵传教团由塞巴斯蒂安·托尔（Sebastian Thor）本人创建。因此，他们赢得了普罗大众的尊重，得以延续至今。 一些审判官意识到，托钵传教士身上有着种种优秀品质：独立自主、信仰坚定、善于求生。这些都是审判庭侍僧应有的宝贵品质。若要挑选一名牧师担任审判庭侍僧，托钵传教士将是个不错的选择，尤其是托尔派审判官，往往比其他同僚更看重这些托钵传教士。而托钵传教士大都乐于侍奉审判庭，希望能借机庇护帝皇子民，令其免受灵魂腐化与谎言侵蚀。 效果 Effects 将以下所有更改应用到你的角色上： 技能 Skills：你获得常识（帝国），导航（地面），学术知识（传说）以及生存技能。 装备 Equipment：由于曾发誓甘守清贫，你的起始王座币减半。此外，在确定月收入时，你的社会阶级按弃民（Outcast）标准计算（见《黑暗异端》原文第 124 页）。 | T80: 强力射击 | U80: 使用射击武器造成+2伤害 | W80: 闪电攻击 | X80: 以一个完整动作近战攻击三次，取代迅捷攻击。如果你具有双武器攻击天赋，且两手各执一把近战武器，则只有一把武器受该天赋影响，另一把只能攻击一次。如果你具有双武器攻击天赋，且装备一把近战武器和一把手枪，则只有近战武器受该天赋影响，手枪只能攻击一次。 | Y80: 先决条件：迅捷攻击
B81: 救赎教派布焰使 | C81: 200 | D81: 救赎教派是最为常见的极端组织之一，活跃于国教辖区的边缘，但国教官方从未正式认可过其合法性。救赎教派只关心一件事：消灭邪恶，惩戒罪人，最好能以神圣的火焰来充当媒介。可想而知，救赎教派极大震慑了变种人、异端和巫师。但与此同时，许多人仅是犯了点小错、甚至毫无过错，便被极端狂热的救赎教派送上了火刑架。在卡利西斯星区，救赎教派的势力主要集中于辛提拉底巢以及哈洗录深渊的边境世界，那些地方变种人肆虐，救赎教派也因此兴盛。近期，救赎教派正积极扩张自身势力范围，他们声嘶力竭的布道已吸引了不少皈依者。如今，无论是战火纷飞的特伦奇，还是内乱不断的伊卡索斯，都能找到救赎教派的身影。 救赎教派的成员癫狂偏激、纵火成癖、几乎毫不掩饰自己的暴虐，但他们又确实对人类之敌恨之入骨，狂热敬奉帝国信仰。这两样品质，正好符合神圣修会对侍僧的要求。那些能被审判庭吸纳的救赎者往往比同僚更狡猾、更能干，知道审时度势，不会一见异端便歇斯底里，能够胜任隐秘行动。不过，这不意味着他们的狂热有任何削弱。一旦时机成熟，这些救赎者将不惜代价，竭尽所能地将帝皇之敌连同罪孽一起烧成灰烬。 效果 Effects 将以下所有更改应用到你的角色上： 属性 Characteristics：你的交际属性减少 5 点。 技能 Skills：你开局获得审讯和恐吓技能。 天赋 Talents：你开局获得信仰坚定天赋，并可以在基础武器训练（火焰）或近战武器训练（链锯）中任选其一作为起始天赋。 失心点 Insanity Point：你开局获得 1d5 点失心。 | T81: 轻身坠 | U81: 减少坠落伤害 | W81: 深谋远虑 | X81: 花费10分钟研究你目前的遇到的问题，使下一次基于智力的检定得到+10加值。 | Y81: 先决条件：Int30
B82: 玛拉登陆点大屠杀 | C82: 300 | D82: 玛拉是个苦寒之地，曾建有关押囚犯的殖民地，但早已沉寂多年。没有人会前往玛拉，帝国海军已隔离了周围的空域，不定期巡逻，以防有人靠近。然而，这样的诅咒之地似乎有某种魔力，总能吸引到一些粗心大意的不幸者。由于导航错误加之不明原因的引擎故障，维尔利克斯号（Vervilix）运兵船闯入了玛拉禁区，迫降于星球地表。接下来五天里，地狱般的惨剧降临在了这些受困的不幸之人身上。没人知道这段时间里究竟发生了什么，当帝国海军抵达时，踏上玛拉的五千名帝国卫队士兵仅剩几百人，幸存者个个形销骨立、神情恍惚。随后，大部分幸存者因异端罪而被处决，或因心智崩溃而消失得无影无踪。剩下的幸存者对自己的遭遇闭口不谈，除非走投无路，否则绝不承认自己登上过维尔利克斯号。唯有那些封存的审判庭报告，记录下了发生在玛拉的惨案：战友彼此残杀，噩梦之物在现实行走，令人不适的抓挠声无处不在，似真似幻的低语萦绕耳边，虫翅振鸣声似乎总挥之不去。 玛拉登陆点大屠杀的幸存者很可能会吸引激进派审判官的特别关注。这些审判官认为，在玛拉的经历已让这些幸存者能够直面最恶劣的情况。抛开这样的推论不谈，从那样的炼狱中幸存，就已经证明了他们能力出众。此外，这些幸存者身上或许留有一丝痕迹，可供研究玛拉那不可言说的谜团，这种可能同样值得关注。 效果 Effects 将以下所有更改应用到你的角色上： 属性 Characteristics：你的意志属性提升 5 点。 天赋 Talents：你开局获得抵抗（灵能）天赋。 堕落 Corruption：玛拉大屠杀的经历令你开局获得 1d5 点堕落。 命运点 Fate Points：你获得额外 1 命运点。 失心点 Insanity Points：你的失心程度视作“错乱（Unhinged）”，开局获得 1d10 点失心。 | T82: 杀手之击 | U82: 肉搏攻击后进行特技检定，成功可以用自由动作移动 | W82: 神射手 | X82: 射击远距离或超远距离的目标无减值。 | Y82: 先决条件：BS35
B83: 边际远征军 | C83: 200 | D83: 三十年前，朦胧星域主教议会批准了《科维努斯法令（Lex Corvinus）》，发起了“边际远征（The Margin Crusade）”，意图征服光晕群星。该法令授权色雷斯主星（Thracian Primaris）的高阶告解神父科维努斯发动信仰远征，号召斯卡鲁斯、卡利西斯和伊萨尼亚德这三个星区为战争提供人力与物资。战事连绵数十年，却收效甚微，远征军逐渐耗竭，最终停滞在卡利西斯星区之外、边境世界卡尔夫（Kalf）以远的星域。时至今日，边际远征仍不断向星区总督哈克斯索要兵力支援，后者不情不愿地从卡利西斯各世界调拨部队，并提出了一个附加条件：必须先将服役完毕的幸存老兵送还星区，他才会向这台绞肉机投入新的兵团。边际远征战况复杂，残酷的战场吞噬了成千上万的生命。与此同时，亚空间航行风云难测，指挥层频频战术失误。即使已付出了惨烈的代价，随军指挥的牧师们不断发出警告，远征的战果仍微乎其微。 从科维努斯圣战中归来的士兵，都是身经百战、阅历丰富的战争老兵。他们曾在远离帝皇之光的地方英勇作战，正是这段经历，让他们成为神圣修会的理想仆从。 效果 Effects 将以下所有更改应用到你的角色上： 属性 Characteristics：你的坚韧属性减少 3 点。 技能 Skills：你获得警觉和生存技能。 天赋 Talents：你获得信仰坚定天赋。 | T83: 闪电反射 | U83: 将两倍AB计算入先攻权 | W83: 生化阉割 | X83: 通过大量药物得使用，你能够忽视一些生理需求。对你进行引诱的检定自动失败，针对你的其它吸引力检定难度提高一级。这个天赋还会给你带来1个失心点。 | Y83: —
